Workbook

Sheet Base Libro Banco  
A2: FECHA | B2: MES | C2: AÑO | D2: CONCEPTO | E2: UNIDAD DE NEGOCIO | F2: DETALLE | G2: PROVEEDOR | H2: TIPO | I2: n cheque | J2: DEBE (INGRESO) | K2: HABER (EGRESO) | L2: IVA | M2: FCATURADO A SAS | N2: Fecha ingreso tarjeta | O2: Monto de ingreso | Q2: Concepto | R2: Unidad de negocio | S2: Tipo
A3: 44958 | B3: =MONTH(A3) -> 2 | C3: =YEAR((A3)) -> 2023 | D3: pago cliente | E3: Taller | F3: Miren cipolla casual | H3: Transferencia | J3: 19500 | Q3: ='Base Libro Caja'!Q3 -> Pago cliente | R3: Personal | S3: Cheque de terceros
A4: 45133 | B4: =MONTH(A4) -> 7 | C4: =YEAR((A4)) -> 2023 | D4: Pago cliente | E4: Taller | F4: Alemandi Banina | H4: Transferencia | J4: 54400 | Q4: ='Base Libro Caja'!Q4 -> Impuestos Municipales | R4: Taller | S4: Transferencia
A5: 45134 | B5: =MONTH(A5) -> 7 | C5: =YEAR((A5)) -> 2023 | D5: Pago cliente | E5: Taller | F5: Cele | H5: Transferencia | J5: 73100 | Q5: ='Base Libro Caja'!Q5 -> Saldo inicial | S5: Tarjeta
A6: 45134 | B6: =MONTH(A6) -> 7 | C6: =YEAR((A6)) -> 2023 | D6: Pago cliente | E6: Taller | F6: Sandra carrara | H6: Cheque de terceros | I6: 1575924 | J6: 115000 | Q6: ='Base Libro Caja'!Q6 -> Pago cliente casual | S6: Personal
A7: 45134 | B7: =MONTH(A7) -> 7 | C7: =YEAR((A7)) -> 2023 | D7: Pago cliente | E7: Taller | F7: Bernard abu grillo | H7: Transferencia | J7: 80700 | Q7: ='Base Libro Caja'!Q7 -> Librería | S7: E-cheq
A8: 45135 | B8: =MONTH(A8) -> 7 | C8: =YEAR((A8)) -> 2023 | D8: Pago cliente | E8: Taller | F8: Martin Jose | H8: Transferencia | J8: 68150 | Q8: ='Base Libro Caja'!Q8 -> Articulos de limpieza | S8: Efectivo Personal
A9: 45136 | B9: =MONTH(A9) -> 7 | C9: =YEAR((A9)) -> 2023 | D9: Pago cliente | E9: Taller | F9: Castro Martin | H9: Transferencia | J9: 50500 | Q9: ='Base Libro Caja'!Q9 -> Combustible
A10: 45138 | B10: =MONTH(A10) -> 7 | C10: =YEAR((A10)) -> 2023 | D10: Pago cliente | E10: Taller | F10: Juan Pablo Lang | H10: Transferencia | J10: 124220 | Q10: ='Base Libro Caja'!Q10 -> Ingreso a Caja grande
A11: 45139 | B11: =MONTH(A11) -> 8 | C11: =YEAR((A11)) -> 2023 | D11: Pago cliente | E11: Taller | F11: Cane Emiliano | H11: Cheque de terceros | J11: 100000 | Q11: ='Base Libro Caja'!Q11 -> Ingreso a Caja chica
A12: 45139 | B12: =MONTH(A12) -> 8 | C12: =YEAR((A12)) -> 2023 | D12: Pago cliente | E12: Taller | F12: Cane Emiliano | H12: Cheque de terceros | J12: 18792 | Q12: ='Base Libro Caja'!Q12 -> Pago proveedor
A13: 45141 | B13: =MONTH(A13) -> 8 | C13: =YEAR((A13)) -> 2023 | D13: Pago cliente | E13: Taller | F13: Ana Paula Goico | H13: Transferencia | J13: 50000 | Q13: ='Base Libro Caja'!Q13 -> Personal
A14: 45141 | B14: =MONTH(A14) -> 8 | C14: =YEAR((A14)) -> 2023 | D14: Pago cliente | E14: Taller | F14: Duran | H14: Transferencia | J14: 51600 | Q14: ='Base Libro Caja'!Q14 -> Gastos generales
A15: 45142 | B15: =MONTH(A15) -> 8 | C15: =YEAR((A15)) -> 2023 | D15: Pago cliente | E15: Taller | F15: Isasi | H15: Transferencia | J15: 22000 | Q15: ='Base Libro Caja'!Q15 -> Comisiones
A16: 45142 | B16: =MONTH(A16) -> 8 | C16: =YEAR((A16)) -> 2023 | D16: Pago cliente | E16: Taller | F16: Gimenez | H16: Cheque de terceros | J16: 30000 | Q16: ='Base Libro Caja'!Q16 -> Vuelto cliente
A17: 45146 | B17: =MONTH(A17) -> 8 | C17: =YEAR((A17)) -> 2023 | D17: Personal | E17: Personal | F17: Mutual | H17: Transferencia | K17: 107970 | Q17: Servicios
A18: 45146 | B18: =MONTH(A18) -> 8 | C18: =YEAR((A18)) -> 2023 | D18: Pago cliente | E18: Taller | F18: palloni | H18: Cheque de terceros | J18: 87120 | Q18: Sueldos
A19: 45146 | B19: =MONTH(A19) -> 8 | C19: =YEAR((A19)) -> 2023 | D19: Pago cliente | E19: Taller | F19: palloni | H19: Cheque de terceros | J19: 87120 | Q19: Honorarios
A20: 45146 | B20: =MONTH(A20) -> 8 | C20: =YEAR((A20)) -> 2023 | D20: Pago cliente | E20: Taller | F20: palloni | H20: Cheque de terceros | J20: 87120 | Q20: Sueldo administrativo
A21: 45147 | B21: =MONTH(A21) -> 8 | C21: =YEAR((A21)) -> 2023 | D21: Pago cliente | E21: Taller | F21: Rodriguez | H21: Transferencia | J21: 121900 | Q21: Sueldo mecánicos
A22: 45147 | B22: =MONTH(A22) -> 8 | C22: =YEAR((A22)) -> 2023 | D22: Pago cliente | E22: Taller | F22: Calderón | H22: Transferencia | J22: 17693 | Q22: Herramientas / bienes de uso
A23: 45147 | B23: =MONTH(A23) -> 8 | C23: =YEAR((A23)) -> 2023 | D23: Pago cliente | E23: Taller | F23: mansuino | H23: Transferencia | J23: 10500 | Q23: Servicios de terceros
A24: 45147 | B24: =MONTH(A24) -> 8 | C24: =YEAR((A24)) -> 2023 | D24: Pago cliente | E24: Taller | F24: Manito | H24: Transferencia | J24: 52900 | Q24: Calco
A25: 45148 | B25: =MONTH(A25) -> 8 | C25: =YEAR((A25)) -> 2023 | D25: Pago cliente | E25: Taller | F25: bocha | H25: Transferencia | J25: 21800 | Q25: Monotributo
A26: 45149 | B26: =MONTH(A26) -> 8 | C26: =YEAR((A26)) -> 2023 | D26: Pago cliente | E26: Taller | F26: bertaina | H26: Transferencia | J26: 53762.5 | Q26: Publicidad
A27: 45153 | B27: =MONTH(A27) -> 8 | C27: =YEAR((A27)) -> 2023 | D27: Pago cliente | E27: Taller | F27: irouleguy | H27: Transferencia | J27: 36800 | Q27: Ropa
A28: 45153 | B28: =MONTH(A28) -> 8 | C28: =YEAR((A28)) -> 2023 | D28: Pago cliente | E28: Taller | F28: Cane Emiliano | H28: Cheque de terceros | J28: 35000 | Q28: Impuestos AFIP
A29: 45153 | B29: =MONTH(A29) -> 8 | C29: =YEAR((A29)) -> 2023 | D29: Pago cliente | E29: Taller | F29: Cane Emiliano | H29: Cheque de terceros | J29: 28000 | Q29: Gastos tarjetas
A30: 45153 | B30: =MONTH(A30) -> 8 | C30: =YEAR((A30)) -> 2023 | D30: Pago cliente | E30: Taller | F30: mainero | H30: Transferencia | J30: 76750 | Q30: Gastos bancarios
A31: 45153 | B31: =MONTH(A31) -> 8 | C31: =YEAR((A31)) -> 2023 | D31: Pago cliente | E31: Taller | F31: suarez | H31: Cheque de terceros | J31: 102615
A32: 45154 | B32: =MONTH(A32) -> 8 | C32: =YEAR((A32)) -> 2023 | D32: Pago cliente | E32: Taller | F32: Fiori Martin | H32: Transferencia | J32: 25000
A33: 45155 | B33: =MONTH(A33) -> 8 | C33: =YEAR((A33)) -> 2023 | D33: Pago cliente | E33: Taller | F33: moreti Ani | H33: Cheque de terceros | J33: 75000
A34: 45155 | B34: =MONTH(A34) -> 8 | C34: =YEAR((A34)) -> 2023 | D34: Pago cliente | E34: Taller | F34: moreti Ani | H34: Cheque de terceros | J34: 60000
A35: 45155 | B35: =MONTH(A35) -> 8 | C35: =YEAR((A35)) -> 2023 | D35: Pago cliente | E35: Taller | F35: gigante | H35: Cheque de terceros | J35: 29460
A36: 45155 | B36: =MONTH(A36) -> 8 | C36: =YEAR((A36)) -> 2023 | D36: Pago proveedor | E36: Taller | G36: Repuestos Serrano | H36: Cheque de terceros | K36: 102615
A37: 45155 | B37: =MONTH(A37) -> 8 | C37: =YEAR((A37)) -> 2023 | D37: Pago cliente | E37: Taller | F37: Angeleri | H37: Transferencia | J37: 84580
A38: 45156 | B38: =MONTH(A38) -> 8 | C38: =YEAR((A38)) -> 2023 | D38: Pago cliente | E38: Taller | F38: Fiori Martin | H38: Transferencia | J38: 57600
A39: 45156 | B39: =MONTH(A39) -> 8 | C39: =YEAR((A39)) -> 2023 | D39: Pago cliente | E39: Taller | F39: martina carlos | H39: Cheque de terceros | J39: 7000
A40: 45156 | B40: =MONTH(A40) -> 8 | C40: =YEAR((A40)) -> 2023 | D40: Pago cliente | E40: Taller | F40: martina carlos | H40: Cheque de terceros | J40: 6500
A41: 45160 | B41: =MONTH(A41) -> 8 | C41: =YEAR((A41)) -> 2023 | D41: Pago cliente | E41: Taller | F41: suarez lucas | H41: Transferencia | J41: 95200
A42: 45160 | B42: =MONTH(A42) -> 8 | C42: =YEAR((A42)) -> 2023 | D42: Pago cliente | E42: Taller | F42: silveira | H42: Cheque de terceros | J42: 107000
A43: 45160 | B43: =MONTH(A43) -> 8 | C43: =YEAR((A43)) -> 2023 | D43: Pago cliente | E43: Taller | F43: medic | H43: Cheque de terceros | J43: 30000
A44: 45160 | B44: =MONTH(A44) -> 8 | C44: =YEAR((A44)) -> 2023 | D44: Pago cliente | E44: Taller | F44: medic | H44: Cheque de terceros | J44: 35000
A45: 45160 | B45: =MONTH(A45) -> 8 | C45: =YEAR((A45)) -> 2023 | D45: Pago cliente | E45: Taller | F45: saladino | H45: Cheque de terceros | J45: 46375
A46: 45160 | B46: =MONTH(A46) -> 8 | C46: =YEAR((A46)) -> 2023 | D46: Pago cliente | E46: Taller | F46: saladino | H46: Cheque de terceros | J46: 51000
A47: 45161 | B47: =MONTH(A47) -> 8 | C47: =YEAR((A47)) -> 2023 | D47: Pago proveedor | E47: Taller | G47: Rep Center | H47: Cheque de terceros | K47: 115000
A48: 45161 | B48: =MONTH(A48) -> 8 | C48: =YEAR((A48)) -> 2023 | D48: Pago proveedor | E48: Taller | G48: Rep Center | H48: Cheque de terceros | K48: 28000
A49: 45161 | B49: =MONTH(A49) -> 8 | C49: =YEAR((A49)) -> 2023 | D49: Pago proveedor | E49: Taller | G49: Rep Center | H49: Cheque de terceros | K49: 35000
A50: 45161 | B50: =MONTH(A50) -> 8 | C50: =YEAR((A50)) -> 2023 | D50: Pago proveedor | E50: Taller | G50: Rep Center | H50: Cheque de terceros | K50: 6500
A51: 45161 | B51: =MONTH(A51) -> 8 | C51: =YEAR((A51)) -> 2023 | D51: Pago proveedor | E51: Taller | G51: Rep Center | H51: Cheque de terceros | K51: 7000
A52: 45161 | B52: =MONTH(A52) -> 8 | C52: =YEAR((A52)) -> 2023 | D52: Pago proveedor | E52: Taller | G52: Rep Center | H52: Cheque de terceros | K52: 51000
A53: 45161 | B53: =MONTH(A53) -> 8 | C53: =YEAR((A53)) -> 2023 | D53: Pago proveedor | E53: Taller | G53: Rep Center | H53: Cheque de terceros | K53: 46375
A54: 45161 | B54: =MONTH(A54) -> 8 | C54: =YEAR((A54)) -> 2023 | D54: Pago proveedor | E54: Taller | G54: Rep Center | H54: Cheque de terceros | K54: 30000
A55: 45161 | B55: =MONTH(A55) -> 8 | C55: =YEAR((A55)) -> 2023 | D55: Pago proveedor | E55: Taller | G55: Rep Center | H55: Cheque de terceros | K55: 35000
A56: 45161 | B56: =MONTH(A56) -> 8 | C56: =YEAR((A56)) -> 2023 | D56: Pago cliente | E56: Taller | F56: moretti | H56: Transferencia | J56: 150000
A57: 45166 | B57: =MONTH(A57) -> 8 | C57: =YEAR((A57)) -> 2023 | D57: Pago cliente | E57: Taller | F57: lopez | H57: Cheque de terceros | J57: 10900
A58: 45167 | B58: =MONTH(A58) -> 8 | C58: =YEAR((A58)) -> 2023 | D58: Pago cliente | E58: Taller | F58: weizek | H58: Transferencia | J58: 74690
A59: 45167 | B59: =MONTH(A59) -> 8 | C59: =YEAR((A59)) -> 2023 | D59: Pago cliente | E59: Taller | F59: san jose | H59: Transferencia | J59: 76250
A60: 45167 | B60: =MONTH(A60) -> 8 | C60: =YEAR((A60)) -> 2023 | D60: Pago cliente | E60: Taller | F60: ventura | H60: Transferencia | J60: 50000
A61: 45167 | B61: =MONTH(A61) -> 8 | C61: =YEAR((A61)) -> 2023 | D61: Pago proveedor | E61: Taller | G61: Wurth | H61: Cheque de terceros | K61: 87120
A62: 45167 | B62: =MONTH(A62) -> 8 | C62: =YEAR((A62)) -> 2023 | D62: Pago proveedor | E62: Taller | G62: Wurth | H62: Cheque de terceros | K62: 87120
A63: 45167 | B63: =MONTH(A63) -> 8 | C63: =YEAR((A63)) -> 2023 | D63: Pago proveedor | E63: Taller | G63: Wurth | H63: Cheque de terceros | K63: 107000
A64: 45169 | B64: =MONTH(A64) -> 8 | C64: =YEAR((A64)) -> 2023 | D64: Pago cliente | E64: Taller | F64: Isseta | H64: Cheque de terceros | J64: 50000
A65: 45169 | B65: =MONTH(A65) -> 8 | C65: =YEAR((A65)) -> 2023 | D65: Pago cliente | E65: Taller | F65: Isseta | H65: Cheque de terceros | J65: 63440
A66: 45169 | B66: =MONTH(A66) -> 8 | C66: =YEAR((A66)) -> 2023 | D66: Pago cliente | E66: Taller | F66: Marcos isseta | H66: Transferencia | J66: 50000
A67: 45169 | B67: =MONTH(A67) -> 8 | C67: =YEAR((A67)) -> 2023 | D67: Pago cliente | E67: Taller | F67: Dutto mariano | H67: Cheque de terceros | J67: 42350
A68: 45169 | B68: =MONTH(A68) -> 8 | C68: =YEAR((A68)) -> 2023 | D68: Pago cliente | E68: Taller | F68: Moretti Renato | H68: Transferencia | J68: 213100
A69: 45169 | B69: =MONTH(A69) -> 8 | C69: =YEAR((A69)) -> 2023 | D69: Pago proveedor | E69: Taller | G69: Barotto Marcelo | H69: Cheque de terceros | K69: 213100
A70: 45170 | B70: =MONTH(A70) -> 9 | C70: =YEAR((A70)) -> 2023 | D70: Pago proveedor | E70: Taller | G70: Barotto Marcelo | H70: Cheque de terceros | K70: 42350
A71: 45170 | B71: =MONTH(A71) -> 9 | C71: =YEAR((A71)) -> 2023 | D71: Pago proveedor | E71: Taller | G71: Barotto Marcelo | H71: Cheque de terceros | K71: 50000
A72: 45170 | B72: =MONTH(A72) -> 9 | C72: =YEAR((A72)) -> 2023 | D72: Pago proveedor | E72: Taller | G72: Barotto Marcelo | H72: Cheque de terceros | K72: 63440
A73: 45170 | B73: =MONTH(A73) -> 9 | C73: =YEAR((A73)) -> 2023 | D73: Pago proveedor | E73: Taller | G73: Barotto Marcelo | H73: Cheque de terceros | K73: 10900
A74: 45170 | B74: =MONTH(A74) -> 9 | C74: =YEAR((A74)) -> 2023 | D74: Pago proveedor | E74: Taller | G74: Barotto Marcelo | H74: Cheque de terceros | K74: 60000
A75: 45170 | B75: =MONTH(A75) -> 9 | C75: =YEAR((A75)) -> 2023 | D75: Pago proveedor | E75: Taller | G75: Barotto Marcelo | H75: Cheque de terceros | K75: 29460
A76: 45170 | B76: =MONTH(A76) -> 9 | C76: =YEAR((A76)) -> 2023 | D76: Pago proveedor | E76: Taller | G76: Barotto Marcelo | H76: Cheque de terceros | K76: 75000
A77: 45170 | B77: =MONTH(A77) -> 9 | C77: =YEAR((A77)) -> 2023 | D77: Pago cliente | E77: Taller | F77: moreno | H77: Transferencia | J77: 133750
A78: 45173 | B78: =MONTH(A78) -> 9 | C78: =YEAR((A78)) -> 2023 | D78: servicios | E78: Taller | F78: luz gas tel | K78: 70583.59
A79: 45173 | B79: =MONTH(A79) -> 9 | C79: =YEAR((A79)) -> 2023 | D79: Pago cliente | E79: Taller | F79: Nardin Larisa | H79: Transferencia | J79: 12100
A80: 45174 | B80: =MONTH(A80) -> 9 | C80: =YEAR((A80)) -> 2023 | D80: Pago cliente | E80: Taller | F80: Oviedo | H80: Transferencia | J80: 26800
A81: 45174 | B81: =MONTH(A81) -> 9 | C81: =YEAR((A81)) -> 2023 | D81: Pago cliente | E81: Taller | F81: isasi | H81: Transferencia | J81: 68400
A82: 45175 | B82: =MONTH(A82) -> 9 | C82: =YEAR((A82)) -> 2023 | D82: Gastos generales | E82: Taller | F82: Honorarios | H82: Transferencia | K82: 100000
A83: 45175 | B83: =MONTH(A83) -> 9 | C83: =YEAR((A83)) -> 2023 | D83: Pago cliente | E83: Taller | F83: martina carlos | H83: Cheque de terceros | J83: 15000
A84: 45175 | B84: =MONTH(A84) -> 9 | C84: =YEAR((A84)) -> 2023 | D84: Pago cliente | E84: Taller | F84: martina carlos | H84: Cheque de terceros | J84: 13265.39
A85: 45176 | B85: =MONTH(A85) -> 9 | C85: =YEAR((A85)) -> 2023 | D85: Pago cliente | E85: Taller | F85: Bilinski | H85: Transferencia | J85: 65850
A86: 45176 | B86: =MONTH(A86) -> 9 | C86: =YEAR((A86)) -> 2023 | D86: Pago proveedor | E86: Taller | G86: Barotto Marcelo | H86: Transferencia | K86: 65850
A87: 45176 | B87: =MONTH(A87) -> 9 | C87: =YEAR((A87)) -> 2023 | D87: Pago cliente | E87: Taller | F87: Isseta | H87: Transferencia | J87: 100000
A88: 45177 | B88: =MONTH(A88) -> 9 | C88: =YEAR((A88)) -> 2023 | D88: Pago cliente | E88: Taller | F88: Eracci | H88: Transferencia | J88: 245000
A89: 45177 | B89: =MONTH(A89) -> 9 | C89: =YEAR((A89)) -> 2023 | D89: Pago proveedor | E89: Taller | G89: Barotto Marcelo | H89: Transferencia | K89: 245000
A90: 45177 | B90: =MONTH(A90) -> 9 | C90: =YEAR((A90)) -> 2023 | D90: Pago cliente | E90: Taller | F90: Integral Agropecuaria | H90: Transferencia | J90: 356000
A91: 45177 | B91: =MONTH(A91) -> 9 | C91: =YEAR((A91)) -> 2023 | D91: Pago proveedor | E91: Taller | G91: Barotto Marcelo | H91: Transferencia | K91: 356000
A92: 45178 | B92: =MONTH(A92) -> 9 | C92: =YEAR((A92)) -> 2023 | D92: Pago proveedor | E92: Taller | G92: Wurth | H92: Transferencia | K92: 235800
A93: 45178 | B93: =MONTH(A93) -> 9 | C93: =YEAR((A93)) -> 2023 | D93: Pago proveedor | E93: Taller | G93: Gutierrez | H93: Transferencia | K93: 53562.48
A94: 45180 | B94: =MONTH(A94) -> 9 | C94: =YEAR((A94)) -> 2023 | D94: Pago cliente | E94: Taller | F94: Transporte Palloni | H94: Cheque de terceros | J94: 117571.63
A95: 45180 | B95: =MONTH(A95) -> 9 | C95: =YEAR((A95)) -> 2023 | D95: Pago cliente | E95: Taller | F95: Transporte Palloni | H95: Cheque de terceros | J95: 117571.63
A96: 45180 | B96: =MONTH(A96) -> 9 | C96: =YEAR((A96)) -> 2023 | D96: Pago cliente | E96: Taller | F96: Transporte Palloni | H96: Cheque de terceros | J96: 117571.63
A97: 45180 | B97: =MONTH(A97) -> 9 | C97: =YEAR((A97)) -> 2023 | D97: Pago cliente | E97: Taller | F97: pini de mainero | H97: Transferencia | J97: 69920
A98: 45180 | B98: =MONTH(A98) -> 9 | C98: =YEAR((A98)) -> 2023 | D98: Pago cliente | E98: Taller | F98: Weizur | H98: Transferencia | J98: 76800
A99: 45180 | B99: =MONTH(A99) -> 9 | C99: =YEAR((A99)) -> 2023 | D99: Pago proveedor | E99: Taller | G99: Barotto Marcelo | H99: Transferencia | K99: 76800
A100: 45181 | B100: =MONTH(A100) -> 9 | C100: =YEAR((A100)) -> 2023 | D100: Pago cliente | E100: Taller | F100: Lang Juan Pablo | H100: Transferencia | J100: 100000
A101: 45181 | B101: =MONTH(A101) -> 9 | C101: =YEAR((A101)) -> 2023 | D101: Pago cliente | E101: Taller | F101: perviu | H101: Cheque de terceros | J101: 281468
...

Sheet Base Libro Caja
A2: FECHA | B2: MES | C2: AÑO | D2: CONCEPTO | E2: UNIDAD DE NEGOCIO | F2: DETALLE | G2: PROVEEDOR | J2: DEBE (INGRESO) | K2: HABER (EGRESO) | L2: SALDO DEUDOR | M2: SALDO ACREEDOR | N2: IVA | O2: FACTURADO A SAS | Q2: Concepto | R2: Unidad de negocio | S2: Proveedor
A3: 45132 | B3: =MONTH(A3) -> 7 | C3: =YEAR(A3) -> 2023 | D3: Saldo inicial | E3: Taller | F3: Pago con transferencia | J3: 3000 | L3: =3000+1950 -> 4950 | M3: 0 | Q3: Pago cliente | R3: Personal | S3: Barotto
A4: 45132 | B4: =MONTH(A4) -> 7 | C4: =YEAR(A4) -> 2023 | L4: =IF((L3+M3+J4-K4)>0,(L3+M3+J4-K4),0) -> 4950 | M4: =IF((L3+M3+J4-K4)<0,(L3+M3+J4-K4),0) -> 0 | Q4: Impuestos Municipales | R4: Taller | S4: Ferrando
A5: 45132 | B5: =MONTH(A5) -> 7 | C5: =YEAR(A5) -> 2023 | D5: Pago cliente | E5: Taller | F5: efectivo | J5: 60000 | L5: =IF((L4+M4+J5-K5)>0,(L4+M4+J5-K5),0) -> 64950 | M5: =IF((L4+M4+J5-K5)<0,(L4+M4+J5-K5),0) -> 0 | Q5: Saldo inicial | S5: Bata rio 4
A6: 45133 | B6: =MONTH(A6) -> 7 | C6: =YEAR(A6) -> 2023 | D6: Gastos generales | E6: Taller | F6: efectivo | K6: 5200 | L6: =IF((L5+M5+J6-K6)>0,(L5+M5+J6-K6),0) -> 59750 | M6: =IF((L5+M5+J6-K6)<0,(L5+M5+J6-K6),0) -> 0 | Q6: Pago cliente casual | S6: Vetaro
A7: 45133 | B7: =MONTH(A7) -> 7 | C7: =YEAR(A7) -> 2023 | D7: Ingreso a Caja chica | E7: Taller | F7: pago Cristian | J7: 64388.86 | L7: =IF((L6+M6+J7-K7)>0,(L6+M6+J7-K7),0) -> 124138.86 | M7: =IF((L6+M6+J7-K7)<0,(L6+M6+J7-K7),0) -> 0 | Q7: Librería | S7: Stabio
A8: 45133 | B8: =MONTH(A8) -> 7 | C8: =YEAR(A8) -> 2023 | D8: Pago proveedor | E8: Taller | F8: pago Cristian | G8: RC distribuciones | K8: 64388.86 | L8: =IF((L7+M7+J8-K8)>0,(L7+M7+J8-K8),0) -> 59750 | M8: =IF((L7+M7+J8-K8)<0,(L7+M7+J8-K8),0) -> 0 | Q8: Articulos de limpieza | S8: Accotto Aldo
A9: 45133 | B9: =MONTH(A9) -> 7 | C9: =YEAR(A9) -> 2023 | D9: Ingreso a Caja chica | E9: Taller | F9: pago Cristian | J9: 38631.07 | L9: =IF((L8+M8+J9-K9)>0,(L8+M8+J9-K9),0) -> 98381.07 | M9: =IF((L8+M8+J9-K9)<0,(L8+M8+J9-K9),0) -> 0 | Q9: Combustible | S9: Color Plus
A10: 45133 | B10: =MONTH(A10) -> 7 | C10: =YEAR(A10) -> 2023 | D10: Pago proveedor | E10: Taller | G10: Rep Center | K10: 38631.07 | L10: =IF((L9+M9+J10-K10)>0,(L9+M9+J10-K10),0) -> 59750 | M10: =IF((L9+M9+J10-K10)<0,(L9+M9+J10-K10),0) -> 0 | Q10: Ingreso a Caja grande | S10: Magliano Metal
A11: 45133 | B11: =MONTH(A11) -> 7 | C11: =YEAR(A11) -> 2023 | D11: Personal | E11: Personal | F11: Mutual Medic | K11: 2800 | L11: =IF((L10+M10+J11-K11)>0,(L10+M10+J11-K11),0) -> 56950 | M11: =IF((L10+M10+J11-K11)<0,(L10+M10+J11-K11),0) -> 0 | Q11: Ingreso a Caja chica | S11: Marglas S.A
A12: 45133 | B12: =MONTH(A12) -> 7 | C12: =YEAR(A12) -> 2023 | D12: Pago cliente | E12: Taller | J12: 8000 | L12: =IF((L11+M11+J12-K12)>0,(L11+M11+J12-K12),0) -> 64950 | M12: =IF((L11+M11+J12-K12)<0,(L11+M11+J12-K12),0) -> 0 | Q12: Pago proveedor | S12: Refiat
A13: 45133 | B13: =MONTH(A13) -> 7 | C13: =YEAR(A13) -> 2023 | D13: Vuelto cliente | E13: Taller | J13: 4500 | L13: =IF((L12+M12+J13-K13)>0,(L12+M12+J13-K13),0) -> 69450 | M13: =IF((L12+M12+J13-K13)<0,(L12+M12+J13-K13),0) -> 0 | Q13: Personal | S13: Rep Center
A14: 45133 | B14: =MONTH(A14) -> 7 | C14: =YEAR(A14) -> 2023 | D14: Ingreso a Caja grande | E14: Taller | F14: cierre caja | K14: 64500 | L14: =IF((L13+M13+J14-K14)>0,(L13+M13+J14-K14),0) -> 4950 | M14: =IF((L13+M13+J14-K14)<0,(L13+M13+J14-K14),0) -> 0 | Q14: Gastos generales | S14: RC distribuciones
A15: 45134 | B15: =MONTH(A15) -> 7 | C15: =YEAR(A15) -> 2023 | D15: Pago cliente | E15: Taller | J15: 25000 | L15: =IF((L14+M14+J15-K15)>0,(L14+M14+J15-K15),0) -> 29950 | M15: =IF((L14+M14+J15-K15)<0,(L14+M14+J15-K15),0) -> 0 | Q15: Comisiones | S15: Rectificadora Debernardi
A16: 45134 | B16: =MONTH(A16) -> 7 | C16: =YEAR(A16) -> 2023 | D16: Pago cliente | E16: Taller | J16: =49960+4340 -> 54300 | L16: =IF((L15+M15+J16-K16)>0,(L15+M15+J16-K16),0) -> 84250 | M16: =IF((L15+M15+J16-K16)<0,(L15+M15+J16-K16),0) -> 0 | Q16: Vuelto cliente | S16: TDI
A17: 45134 | B17: =MONTH(A17) -> 7 | C17: =YEAR(A17) -> 2023 | D17: Ingreso a Caja grande | E17: Taller | F17: 100 dolares | K17: 54300 | L17: =IF((L16+M16+J17-K17)>0,(L16+M16+J17-K17),0) -> 29950 | M17: =IF((L16+M16+J17-K17)<0,(L16+M16+J17-K17),0) -> 0 | Q17: Servicios | S17: Forcor
A18: 45134 | B18: =MONTH(A18) -> 7 | C18: =YEAR(A18) -> 2023 | D18: Pago cliente | E18: Taller | F18: vuelto | K18: 4340 | L18: =IF((L17+M17+J18-K18)>0,(L17+M17+J18-K18),0) -> 25610 | M18: =IF((L17+M17+J18-K18)<0,(L17+M17+J18-K18),0) -> 0 | Q18: Sueldos | S18: Shell Bata
A19: 45134 | B19: =MONTH(A19) -> 7 | C19: =YEAR(A19) -> 2023 | D19: Ingreso a Caja chica | E19: Taller | F19: caja grande | J19: 25000 | L19: =IF((L18+M18+J19-K19)>0,(L18+M18+J19-K19),0) -> 50610 | M19: =IF((L18+M18+J19-K19)<0,(L18+M18+J19-K19),0) -> 0 | Q19: Honorarios | S19: Mundo Chevrolet
A20: 45134 | B20: =MONTH(A20) -> 7 | C20: =YEAR(A20) -> 2023 | D20: Gastos generales | E20: Taller | F20: leña | K20: 25000 | L20: =IF((L19+M19+J20-K20)>0,(L19+M19+J20-K20),0) -> 25610 | M20: =IF((L19+M19+J20-K20)<0,(L19+M19+J20-K20),0) -> 0 | Q20: Sueldo administrativo | S20: Alarmas
A21: 45134 | B21: =MONTH(A21) -> 7 | C21: =YEAR(A21) -> 2023 | D21: Ingreso a Caja chica | E21: Taller | F21: caja grande | J21: 2000 | L21: =IF((L20+M20+J21-K21)>0,(L20+M20+J21-K21),0) -> 27610 | M21: =IF((L20+M20+J21-K21)<0,(L20+M20+J21-K21),0) -> 0 | Q21: Sueldo mecánicos | S21: Atilio Lucero
A22: 45134 | B22: =MONTH(A22) -> 7 | C22: =YEAR(A22) -> 2023 | D22: Personal | E22: Personal | F22: analisis | K22: 1380 | L22: =IF((L21+M21+J22-K22)>0,(L21+M21+J22-K22),0) -> 26230 | M22: =IF((L21+M21+J22-K22)<0,(L21+M21+J22-K22),0) -> 0 | Q22: Herramientas / bienes de uso | S22: Rio Rep
A23: 45134 | B23: =MONTH(A23) -> 7 | C23: =YEAR(A23) -> 2023 | D23: Comisiones | E23: Taller | F23: comisionista | K23: 2000 | L23: =IF((L22+M22+J23-K23)>0,(L22+M22+J23-K23),0) -> 24230 | M23: =IF((L22+M22+J23-K23)<0,(L22+M22+J23-K23),0) -> 0 | Q23: Servicios de terceros | S23: Sabaini Ignacio
A24: 45134 | B24: =MONTH(A24) -> 7 | C24: =YEAR(A24) -> 2023 | D24: Ingreso a Caja grande | E24: Taller | F24: cierre caja | K24: =22280-3000 -> 19280 | L24: =IF((L23+M23+J24-K24)>0,(L23+M23+J24-K24),0) -> 4950 | M24: =IF((L23+M23+J24-K24)<0,(L23+M23+J24-K24),0) -> 0 | Q24: Calcomanias | S24: Rolando Juan
A25: 45135 | B25: =MONTH(A25) -> 7 | C25: =YEAR(A25) -> 2023 | D25: Ingreso a Caja chica | E25: Taller | J25: 19200 | L25: =IF((L24+M24+J25-K25)>0,(L24+M24+J25-K25),0) -> 24150 | M25: =IF((L24+M24+J25-K25)<0,(L24+M24+J25-K25),0) -> 0 | Q25: Monotributo | S25: Bertea
A26: 45135 | B26: =MONTH(A26) -> 7 | C26: =YEAR(A26) -> 2023 | D26: Pago proveedor | E26: Taller | G26: Ferrando | K26: 19280 | L26: =IF((L25+M25+J26-K26)>0,(L25+M25+J26-K26),0) -> 4870 | M26: =IF((L25+M25+J26-K26)<0,(L25+M25+J26-K26),0) -> 0 | Q26: Publicidad | S26: Chemical
A27: 45135 | B27: =MONTH(A27) -> 7 | C27: =YEAR(A27) -> 2023 | D27: Ingreso a Caja chica | E27: Taller | J27: 25000 | L27: =IF((L26+M26+J27-K27)>0,(L26+M26+J27-K27),0) -> 29870 | M27: =IF((L26+M26+J27-K27)<0,(L26+M26+J27-K27),0) -> 0 | Q27: Ropa | S27: Mansilla
A28: 45135 | B28: =MONTH(A28) -> 7 | C28: =YEAR(A28) -> 2023 | D28: Gastos generales | E28: Taller | F28: leña | K28: 25000 | L28: =IF((L27+M27+J28-K28)>0,(L27+M27+J28-K28),0) -> 4870 | M28: =IF((L27+M27+J28-K28)<0,(L27+M27+J28-K28),0) -> 0 | Q28: Impuestos AFIP | S28: Pablo Fenoglio
A29: 45135 | B29: =MONTH(A29) -> 7 | C29: =YEAR(A29) -> 2023 | D29: Ingreso a Caja chica | E29: Personal | J29: 22500 | L29: =IF((L28+M28+J29-K29)>0,(L28+M28+J29-K29),0) -> 27370 | M29: =IF((L28+M28+J29-K29)<0,(L28+M28+J29-K29),0) -> 0 | S29: Sthil Gutierrez
A30: 45135 | B30: =MONTH(A30) -> 7 | C30: =YEAR(A30) -> 2023 | D30: Personal | E30: Personal | F30: fumigador | K30: 22500 | L30: =IF((L29+M29+J30-K30)>0,(L29+M29+J30-K30),0) -> 4870 | M30: =IF((L29+M29+J30-K30)<0,(L29+M29+J30-K30),0) -> 0
A31: 45135 | B31: =MONTH(A31) -> 7 | C31: =YEAR(A31) -> 2023 | D31: Ingreso a Caja chica | E31: Taller | J31: 2600 | L31: =IF((L30+M30+J31-K31)>0,(L30+M30+J31-K31),0) -> 7470 | M31: =IF((L30+M30+J31-K31)<0,(L30+M30+J31-K31),0) -> 0
A32: 45135 | B32: =MONTH(A32) -> 7 | C32: =YEAR(A32) -> 2023 | D32: Gastos generales | E32: Taller | F32: gas | K32: 2600 | L32: =IF((L31+M31+J32-K32)>0,(L31+M31+J32-K32),0) -> 4870 | M32: =IF((L31+M31+J32-K32)<0,(L31+M31+J32-K32),0) -> 0
A33: 45135 | B33: =MONTH(A33) -> 7 | C33: =YEAR(A33) -> 2023 | D33: Pago cliente | E33: Taller | F33: Service Palloni | J33: 4500 | L33: =IF((L32+M32+J33-K33)>0,(L32+M32+J33-K33),0) -> 9370 | M33: =IF((L32+M32+J33-K33)<0,(L32+M32+J33-K33),0) -> 0
A34: 45135 | B34: =MONTH(A34) -> 7 | C34: =YEAR(A34) -> 2023 | D34: Pago cliente | E34: Taller | J34: 223820 | L34: =IF((L33+M33+J34-K34)>0,(L33+M33+J34-K34),0) -> 233190 | M34: =IF((L33+M33+J34-K34)<0,(L33+M33+J34-K34),0) -> 0
A35: 45135 | B35: =MONTH(A35) -> 7 | C35: =YEAR(A35) -> 2023 | D35: Ingreso a Caja grande | E35: Taller | F35: cierre caja | K35: 230190 | L35: =IF((L34+M34+J35-K35)>0,(L34+M34+J35-K35),0) -> 3000 | M35: =IF((L34+M34+J35-K35)<0,(L34+M34+J35-K35),0) -> 0
A36: 45136 | B36: =MONTH(A36) -> 7 | C36: =YEAR(A36) -> 2023 | D36: Pago cliente casual | E36: Taller | J36: 3000 | L36: =IF((L35+M35+J36-K36)>0,(L35+M35+J36-K36),0) -> 6000 | M36: =IF((L35+M35+J36-K36)<0,(L35+M35+J36-K36),0) -> 0
A37: 45136 | B37: =MONTH(A37) -> 7 | C37: =YEAR(A37) -> 2023 | D37: Gastos generales | E37: Taller | F37: publicidad web | K37: 3000 | L37: =IF((L36+M36+J37-K37)>0,(L36+M36+J37-K37),0) -> 3000 | M37: =IF((L36+M36+J37-K37)<0,(L36+M36+J37-K37),0) -> 0
A38: 45136 | B38: =MONTH(A38) -> 7 | C38: =YEAR(A38) -> 2023 | D38: Pago cliente | E38: Taller | J38: 70000 | L38: =IF((L37+M37+J38-K38)>0,(L37+M37+J38-K38),0) -> 73000 | M38: =IF((L37+M37+J38-K38)<0,(L37+M37+J38-K38),0) -> 0
A39: 45136 | B39: =MONTH(A39) -> 7 | C39: =YEAR(A39) -> 2023 | D39: Ingreso a Caja grande | E39: Taller | K39: 70000 | L39: =IF((L38+M38+J39-K39)>0,(L38+M38+J39-K39),0) -> 3000 | M39: =IF((L38+M38+J39-K39)<0,(L38+M38+J39-K39),0) -> 0
A40: 45138 | B40: =MONTH(A40) -> 7 | C40: =YEAR(A40) -> 2023 | D40: Pago cliente | E40: Taller | J40: 86850 | L40: =IF((L39+M39+J40-K40)>0,(L39+M39+J40-K40),0) -> 89850 | M40: =IF((L39+M39+J40-K40)<0,(L39+M39+J40-K40),0) -> 0
A41: 45138 | B41: =MONTH(A41) -> 7 | C41: =YEAR(A41) -> 2023 | D41: Pago cliente | E41: Taller | J41: 70000 | L41: =IF((L40+M40+J41-K41)>0,(L40+M40+J41-K41),0) -> 159850 | M41: =IF((L40+M40+J41-K41)<0,(L40+M40+J41-K41),0) -> 0
A42: 45138 | B42: =MONTH(A42) -> 7 | C42: =YEAR(A42) -> 2023 | D42: Pago cliente | E42: Taller | J42: 13800 | L42: =IF((L41+M41+J42-K42)>0,(L41+M41+J42-K42),0) -> 173650 | M42: =IF((L41+M41+J42-K42)<0,(L41+M41+J42-K42),0) -> 0
A43: 45138 | B43: =MONTH(A43) -> 7 | C43: =YEAR(A43) -> 2023 | D43: Combustible | E43: Taller | K43: 3500 | L43: =IF((L42+M42+J43-K43)>0,(L42+M42+J43-K43),0) -> 170150 | M43: =IF((L42+M42+J43-K43)<0,(L42+M42+J43-K43),0) -> 0
A44: 45138 | B44: =MONTH(A44) -> 7 | C44: =YEAR(A44) -> 2023 | D44: Ingreso a Caja grande | E44: Taller | K44: 170150 | L44: =IF((L43+M43+J44-K44)>0,(L43+M43+J44-K44),0) -> 0 | M44: =IF((L43+M43+J44-K44)<0,(L43+M43+J44-K44),0) -> 0
A45: 45139 | B45: =MONTH(A45) -> 8 | C45: =YEAR(A45) -> 2023 | D45: Ingreso a Caja chica | E45: Taller | J45: 3000 | L45: =IF((L44+M44+J45-K45)>0,(L44+M44+J45-K45),0) -> 3000 | M45: =IF((L44+M44+J45-K45)<0,(L44+M44+J45-K45),0) -> 0
A46: 45139 | B46: =MONTH(A46) -> 8 | C46: =YEAR(A46) -> 2023 | D46: Comisiones | E46: Taller | K46: 3000 | L46: =IF((L45+M45+J46-K46)>0,(L45+M45+J46-K46),0) -> 0 | M46: =IF((L45+M45+J46-K46)<0,(L45+M45+J46-K46),0) -> 0
A47: 45139 | B47: =MONTH(A47) -> 8 | C47: =YEAR(A47) -> 2023 | D47: Ingreso a Caja chica | E47: Taller | J47: 17520 | L47: =IF((L46+M46+J47-K47)>0,(L46+M46+J47-K47),0) -> 17520 | M47: =IF((L46+M46+J47-K47)<0,(L46+M46+J47-K47),0) -> 0
A48: 45139 | B48: =MONTH(A48) -> 8 | C48: =YEAR(A48) -> 2023 | D48: Gastos generales | E48: Taller | F48: panaderia | K48: 17520 | L48: =IF((L47+M47+J48-K48)>0,(L47+M47+J48-K48),0) -> 0 | M48: =IF((L47+M47+J48-K48)<0,(L47+M47+J48-K48),0) -> 0
A49: 45139 | B49: =MONTH(A49) -> 8 | C49: =YEAR(A49) -> 2023 | D49: Ingreso a Caja chica | E49: Taller | J49: 46000 | L49: =IF((L48+M48+J49-K49)>0,(L48+M48+J49-K49),0) -> 46000 | M49: =IF((L48+M48+J49-K49)<0,(L48+M48+J49-K49),0) -> 0
A50: 45139 | B50: =MONTH(A50) -> 8 | C50: =YEAR(A50) -> 2023 | D50: Vuelto cliente | E50: Taller | K50: 46000 | L50: =IF((L49+M49+J50-K50)>0,(L49+M49+J50-K50),0) -> 0 | M50: =IF((L49+M49+J50-K50)<0,(L49+M49+J50-K50),0) -> 0
A51: 45139 | B51: =MONTH(A51) -> 8 | C51: =YEAR(A51) -> 2023 | D51: Pago cliente | E51: Taller | F51: municipalidad | J51: 51000 | L51: =IF((L50+M50+J51-K51)>0,(L50+M50+J51-K51),0) -> 51000 | M51: =IF((L50+M50+J51-K51)<0,(L50+M50+J51-K51),0) -> 0
A52: 45139 | B52: =MONTH(A52) -> 8 | C52: =YEAR(A52) -> 2023 | D52: Impuestos Municipales | E52: Taller | K52: 11444.71 | L52: =IF((L51+M51+J52-K52)>0,(L51+M51+J52-K52),0) -> 39555.29 | M52: =IF((L51+M51+J52-K52)<0,(L51+M51+J52-K52),0) -> 0
A53: 45139 | B53: =MONTH(A53) -> 8 | C53: =YEAR(A53) -> 2023 | D53: Impuestos Municipales | E53: Personal | K53: 44834.14 | L53: =IF((L52+M52+J53-K53)>0,(L52+M52+J53-K53),0) -> 0 | M53: =IF((L52+M52+J53-K53)<0,(L52+M52+J53-K53),0) -> -5278.85
A54: 45139 | B54: =MONTH(A54) -> 8 | C54: =YEAR(A54) -> 2023 | D54: Ingreso a Caja chica | E54: Taller | J54: 100000 | L54: =IF((L53+M53+J54-K54)>0,(L53+M53+J54-K54),0) -> 94721.15 | M54: =IF((L53+M53+J54-K54)<0,(L53+M53+J54-K54),0) -> 0
A55: 45139 | B55: =MONTH(A55) -> 8 | C55: =YEAR(A55) -> 2023 | D55: Gastos generales | E55: Taller | F55: honorarios | K55: 100000 | L55: =IF((L54+M54+J55-K55)>0,(L54+M54+J55-K55),0) -> 0 | M55: =IF((L54+M54+J55-K55)<0,(L54+M54+J55-K55),0) -> -5278.85
A56: 45139 | B56: =MONTH(A56) -> 8 | C56: =YEAR(A56) -> 2023 | D56: Ingreso a Caja chica | E56: Taller | J56: 5000 | L56: =IF((L55+M55+J56-K56)>0,(L55+M55+J56-K56),0) -> 0 | M56: =IF((L55+M55+J56-K56)<0,(L55+M55+J56-K56),0) -> -278.85
A57: 45139 | B57: =MONTH(A57) -> 8 | C57: =YEAR(A57) -> 2023 | D57: Comisiones | E57: Taller | K57: 5000 | L57: =IF((L56+M56+J57-K57)>0,(L56+M56+J57-K57),0) -> 0 | M57: =IF((L56+M56+J57-K57)<0,(L56+M56+J57-K57),0) -> -5278.85
A58: 45139 | B58: =MONTH(A58) -> 8 | C58: =YEAR(A58) -> 2023 | D58: Pago cliente | E58: Taller | F58: cane | J58: 2610 | L58: =IF((L57+M57+J58-K58)>0,(L57+M57+J58-K58),0) -> 0 | M58: =IF((L57+M57+J58-K58)<0,(L57+M57+J58-K58),0) -> -2668.85
A59: 45139 | B59: =MONTH(A59) -> 8 | C59: =YEAR(A59) -> 2023 | D59: Pago cliente | E59: Taller | J59: 58800 | L59: =IF((L58+M58+J59-K59)>0,(L58+M58+J59-K59),0) -> 56131.15 | M59: =IF((L58+M58+J59-K59)<0,(L58+M58+J59-K59),0) -> 0
A60: 45139 | B60: =MONTH(A60) -> 8 | C60: =YEAR(A60) -> 2023 | D60: Ingreso a Caja grande | E60: Taller | K60: 56131.15 | L60: =IF((L59+M59+J60-K60)>0,(L59+M59+J60-K60),0) -> 0 | M60: =IF((L59+M59+J60-K60)<0,(L59+M59+J60-K60),0) -> -7.2759576e-12
A61: 45140 | B61: =MONTH(A61) -> 8 | C61: =YEAR(A61) -> 2023 | D61: Pago cliente | E61: Taller | F61: Teresa Merlo | J61: 52862.5 | L61: =IF((L60+M60+J61-K61)>0,(L60+M60+J61-K61),0) -> 52862.5 | M61: =IF((L60+M60+J61-K61)<0,(L60+M60+J61-K61),0) -> 0
A62: 45140 | B62: =MONTH(A62) -> 8 | C62: =YEAR(A62) -> 2023 | D62: Pago proveedor | E62: Taller | K62: 3860 | L62: =IF((L61+M61+J62-K62)>0,(L61+M61+J62-K62),0) -> 49002.5 | M62: =IF((L61+M61+J62-K62)<0,(L61+M61+J62-K62),0) -> 0
A63: 45140 | B63: =MONTH(A63) -> 8 | C63: =YEAR(A63) -> 2023 | D63: Combustible | E63: Taller | K63: 3000 | L63: =IF((L62+M62+J63-K63)>0,(L62+M62+J63-K63),0) -> 46002.5 | M63: =IF((L62+M62+J63-K63)<0,(L62+M62+J63-K63),0) -> 0
A64: 45140 | B64: =MONTH(A64) -> 8 | C64: =YEAR(A64) -> 2023 | D64: Ingreso a Caja grande | E64: Taller | K64: 46002.5 | L64: =IF((L63+M63+J64-K64)>0,(L63+M63+J64-K64),0) -> 0 | M64: =IF((L63+M63+J64-K64)<0,(L63+M63+J64-K64),0) -> -7.2759576e-12
A65: 45141 | B65: =MONTH(A65) -> 8 | C65: =YEAR(A65) -> 2023 | D65: Ingreso a Caja chica | E65: Taller | J65: 60000 | L65: =IF((L64+M64+J65-K65)>0,(L64+M64+J65-K65),0) -> 60000 | M65: =IF((L64+M64+J65-K65)<0,(L64+M64+J65-K65),0) -> 0
A66: 37471 | B66: =MONTH(A66) -> 8 | C66: =YEAR(A66) -> 2002 | D66: Gastos generales | E66: Taller | F66: caballetes | K66: 60000 | L66: =IF((L65+M65+J66-K66)>0,(L65+M65+J66-K66),0) -> 0 | M66: =IF((L65+M65+J66-K66)<0,(L65+M65+J66-K66),0) -> -7.2759576e-12
A67: 45141 | B67: =MONTH(A67) -> 8 | C67: =YEAR(A67) -> 2023 | D67: Ingreso a Caja chica | E67: Taller | J67: 78300 | L67: =IF((L66+M66+J67-K67)>0,(L66+M66+J67-K67),0) -> 78300 | M67: =IF((L66+M66+J67-K67)<0,(L66+M66+J67-K67),0) -> 0
A68: 45141 | B68: =MONTH(A68) -> 8 | C68: =YEAR(A68) -> 2023 | D68: Gastos generales | E68: Taller | F68: herramientas | K68: 78300 | L68: =IF((L67+M67+J68-K68)>0,(L67+M67+J68-K68),0) -> 0 | M68: =IF((L67+M67+J68-K68)<0,(L67+M67+J68-K68),0) -> 0
A69: 45141 | B69: =MONTH(A69) -> 8 | C69: =YEAR(A69) -> 2023 | D69: Ingreso a Caja chica | E69: Taller | J69: 30000 | L69: =IF((L68+M68+J69-K69)>0,(L68+M68+J69-K69),0) -> 30000 | M69: =IF((L68+M68+J69-K69)<0,(L68+M68+J69-K69),0) -> 0
A70: 45141 | B70: =MONTH(A70) -> 8 | C70: =YEAR(A70) -> 2023 | D70: Gastos generales | E70: Taller | F70: bobinas de papel | K70: 10300 | L70: =IF((L69+M69+J70-K70)>0,(L69+M69+J70-K70),0) -> 19700 | M70: =IF((L69+M69+J70-K70)<0,(L69+M69+J70-K70),0) -> 0
A71: 45141 | B71: =MONTH(A71) -> 8 | C71: =YEAR(A71) -> 2023 | D71: Gastos generales | E71: Taller | F71: rifa perros | K71: 1500 | L71: =IF((L70+M70+J71-K71)>0,(L70+M70+J71-K71),0) -> 18200 | M71: =IF((L70+M70+J71-K71)<0,(L70+M70+J71-K71),0) -> 0
A72: 45141 | B72: =MONTH(A72) -> 8 | C72: =YEAR(A72) -> 2023 | D72: Pago cliente | E72: Taller | F72: Cane Mauri | J72: 134500 | L72: =IF((L71+M71+J72-K72)>0,(L71+M71+J72-K72),0) -> 152700 | M72: =IF((L71+M71+J72-K72)<0,(L71+M71+J72-K72),0) -> 0
A73: 45141 | B73: =MONTH(A73) -> 8 | C73: =YEAR(A73) -> 2023 | D73: Pago cliente | E73: Taller | F73: toyos | J73: 28000 | L73: =IF((L72+M72+J73-K73)>0,(L72+M72+J73-K73),0) -> 180700 | M73: =IF((L72+M72+J73-K73)<0,(L72+M72+J73-K73),0) -> 0
A74: 45141 | B74: =MONTH(A74) -> 8 | C74: =YEAR(A74) -> 2023 | D74: Pago cliente | E74: Taller | F74: Adelanto x trabajo Ricchi | J74: 45000 | L74: =IF((L73+M73+J74-K74)>0,(L73+M73+J74-K74),0) -> 225700 | M74: =IF((L73+M73+J74-K74)<0,(L73+M73+J74-K74),0) -> 0
A75: 45141 | B75: =MONTH(A75) -> 8 | C75: =YEAR(A75) -> 2023 | D75: Ingreso a Caja grande | E75: Taller | K75: 225700 | L75: =IF((L74+M74+J75-K75)>0,(L74+M74+J75-K75),0) -> 0 | M75: =IF((L74+M74+J75-K75)<0,(L74+M74+J75-K75),0) -> 0
A76: 45142 | B76: =MONTH(A76) -> 8 | C76: =YEAR(A76) -> 2023 | D76: Ingreso a Caja chica | E76: Taller | J76: 30000 | L76: =IF((L75+M75+J76-K76)>0,(L75+M75+J76-K76),0) -> 30000 | M76: =IF((L75+M75+J76-K76)<0,(L75+M75+J76-K76),0) -> 0
A77: 45142 | B77: =MONTH(A77) -> 8 | C77: =YEAR(A77) -> 2023 | D77: Gastos generales | E77: Taller | F77: color plus | K77: 4030 | L77: =IF((L76+M76+J77-K77)>0,(L76+M76+J77-K77),0) -> 25970 | M77: =IF((L76+M76+J77-K77)<0,(L76+M76+J77-K77),0) -> 0
A78: 45142 | B78: =MONTH(A78) -> 8 | C78: =YEAR(A78) -> 2023 | D78: Gastos generales | E78: Taller | F78: comision x cheque | K78: 2000 | L78: =IF((L77+M77+J78-K78)>0,(L77+M77+J78-K78),0) -> 23970 | M78: =IF((L77+M77+J78-K78)<0,(L77+M77+J78-K78),0) -> 0
A79: 45142 | B79: =MONTH(A79) -> 8 | C79: =YEAR(A79) -> 2023 | D79: Pago cliente | E79: Taller | J79: 23800 | L79: =IF((L78+M78+J79-K79)>0,(L78+M78+J79-K79),0) -> 47770 | M79: =IF((L78+M78+J79-K79)<0,(L78+M78+J79-K79),0) -> 0
A80: 45142 | B80: =MONTH(A80) -> 8 | C80: =YEAR(A80) -> 2023 | D80: Pago cliente casual | E80: Taller | F80: foco | J80: 2000 | L80: =IF((L79+M79+J80-K80)>0,(L79+M79+J80-K80),0) -> 49770 | M80: =IF((L79+M79+J80-K80)<0,(L79+M79+J80-K80),0) -> 0
A81: 45142 | B81: =MONTH(A81) -> 8 | C81: =YEAR(A81) -> 2023 | D81: Pago cliente | E81: Taller | F81: creativity | J81: 89400 | L81: =IF((L80+M80+J81-K81)>0,(L80+M80+J81-K81),0) -> 139170 | M81: =IF((L80+M80+J81-K81)<0,(L80+M80+J81-K81),0) -> 0
A82: 45142 | B82: =MONTH(A82) -> 8 | C82: =YEAR(A82) -> 2023 | D82: Pago proveedor | E82: Taller | G82: Barotto | K82: 89400 | L82: =IF((L81+M81+J82-K82)>0,(L81+M81+J82-K82),0) -> 49770 | M82: =IF((L81+M81+J82-K82)<0,(L81+M81+J82-K82),0) -> 0
A83: 45142 | B83: =MONTH(A83) -> 8 | C83: =YEAR(A83) -> 2023 | D83: Pago cliente | E83: Taller | J83: 10000 | L83: =IF((L82+M82+J83-K83)>0,(L82+M82+J83-K83),0) -> 59770 | M83: =IF((L82+M82+J83-K83)<0,(L82+M82+J83-K83),0) -> 0
A84: 45142 | B84: =MONTH(A84) -> 8 | C84: =YEAR(A84) -> 2023 | D84: Ingreso a Caja grande | E84: Taller | K84: 59770 | L84: =IF((L83+M83+J84-K84)>0,(L83+M83+J84-K84),0) -> 0 | M84: =IF((L83+M83+J84-K84)<0,(L83+M83+J84-K84),0) -> 0
A85: 45145 | B85: =MONTH(A85) -> 8 | C85: =YEAR(A85) -> 2023 | D85: Ingreso a Caja chica | E85: Taller | J85: 30000 | L85: =IF((L84+M84+J85-K85)>0,(L84+M84+J85-K85),0) -> 30000 | M85: =IF((L84+M84+J85-K85)<0,(L84+M84+J85-K85),0) -> 0
A86: 45145 | B86: =MONTH(A86) -> 8 | C86: =YEAR(A86) -> 2023 | D86: Pago cliente casual | E86: Taller | F86: pablo | J86: 750 | L86: =IF((L85+M85+J86-K86)>0,(L85+M85+J86-K86),0) -> 30750 | M86: =IF((L85+M85+J86-K86)<0,(L85+M85+J86-K86),0) -> 0
A87: 45145 | B87: =MONTH(A87) -> 8 | C87: =YEAR(A87) -> 2023 | D87: Ingreso a Caja chica | E87: Taller | J87: 170000 | L87: =IF((L86+M86+J87-K87)>0,(L86+M86+J87-K87),0) -> 200750 | M87: =IF((L86+M86+J87-K87)<0,(L86+M86+J87-K87),0) -> 0
A88: 45145 | B88: =MONTH(A88) -> 8 | C88: =YEAR(A88) -> 2023 | D88: Personal | E88: Taller | F88: pago semana empleados | K88: 170000 | L88: =IF((L87+M87+J88-K88)>0,(L87+M87+J88-K88),0) -> 30750 | M88: =IF((L87+M87+J88-K88)<0,(L87+M87+J88-K88),0) -> 0
A89: 45145 | B89: =MONTH(A89) -> 8 | C89: =YEAR(A89) -> 2023 | D89: Pago cliente | E89: Taller | F89: di genaro | J89: 63000 | L89: =IF((L88+M88+J89-K89)>0,(L88+M88+J89-K89),0) -> 93750 | M89: =IF((L88+M88+J89-K89)<0,(L88+M88+J89-K89),0) -> 0
A90: 45145 | B90: =MONTH(A90) -> 8 | C90: =YEAR(A90) -> 2023 | D90: Pago proveedor | E90: Taller | G90: Barotto | K90: 63000 | L90: =IF((L89+M89+J90-K90)>0,(L89+M89+J90-K90),0) -> 30750 | M90: =IF((L89+M89+J90-K90)<0,(L89+M89+J90-K90),0) -> 0
A91: 45145 | B91: =MONTH(A91) -> 8 | C91: =YEAR(A91) -> 2023 | D91: Ingreso a Caja chica | E91: Taller | J91: 60000 | L91: =IF((L90+M90+J91-K91)>0,(L90+M90+J91-K91),0) -> 90750 | M91: =IF((L90+M90+J91-K91)<0,(L90+M90+J91-K91),0) -> 0
A92: 45145 | B92: =MONTH(A92) -> 8 | C92: =YEAR(A92) -> 2023 | D92: Servicios | E92: Taller | F92: luz | K92: 21868.79 | L92: =IF((L91+M91+J92-K92)>0,(L91+M91+J92-K92),0) -> 68881.21 | M92: =IF((L91+M91+J92-K92)<0,(L91+M91+J92-K92),0) -> 0
A93: 45145 | B93: =MONTH(A93) -> 8 | C93: =YEAR(A93) -> 2023 | D93: Servicios | E93: Personal | F93: claro | K93: 3741.52 | L93: =IF((L92+M92+J93-K93)>0,(L92+M92+J93-K93),0) -> 65139.69 | M93: =IF((L92+M92+J93-K93)<0,(L92+M92+J93-K93),0) -> 0
A94: 45145 | B94: =MONTH(A94) -> 8 | C94: =YEAR(A94) -> 2023 | D94: Servicios | E94: Personal | F94: telecom | K94: 7839.96 | L94: =IF((L93+M93+J94-K94)>0,(L93+M93+J94-K94),0) -> 57299.73 | M94: =IF((L93+M93+J94-K94)<0,(L93+M93+J94-K94),0) -> 0
A95: 45145 | B95: =MONTH(A95) -> 8 | C95: =YEAR(A95) -> 2023 | D95: Servicios | E95: Personal | F95: luz y gas | K95: 20573 | L95: =IF((L94+M94+J95-K95)>0,(L94+M94+J95-K95),0) -> 36726.73 | M95: =IF((L94+M94+J95-K95)<0,(L94+M94+J95-K95),0) -> 0
A96: 45145 | B96: =MONTH(A96) -> 8 | C96: =YEAR(A96) -> 2023 | D96: Servicios | E96: Taller | F96: camaras | K96: 6000 | L96: =IF((L95+M95+J96-K96)>0,(L95+M95+J96-K96),0) -> 30726.73 | M96: =IF((L95+M95+J96-K96)<0,(L95+M95+J96-K96),0) -> 0
A97: 45145 | B97: =MONTH(A97) -> 8 | C97: =YEAR(A97) -> 2023 | D97: Ingreso a Caja grande | E97: Taller | K97: 30726.73 | L97: =IF((L96+M96+J97-K97)>0,(L96+M96+J97-K97),0) -> 0 | M97: =IF((L96+M96+J97-K97)<0,(L96+M96+J97-K97),0) -> -3.6379788e-12
A98: 45146 | B98: =MONTH(A98) -> 8 | C98: =YEAR(A98) -> 2023 | D98: Pago cliente | E98: Taller | F98: Barroso | J98: 50000 | L98: =IF((L97+M97+J98-K98)>0,(L97+M97+J98-K98),0) -> 50000 | M98: =IF((L97+M97+J98-K98)<0,(L97+M97+J98-K98),0) -> 0
A99: 45146 | B99: =MONTH(A99) -> 8 | C99: =YEAR(A99) -> 2023 | D99: Ingreso a Caja grande | E99: Taller | K99: 50000 | L99: =IF((L98+M98+J99-K99)>0,(L98+M98+J99-K99),0) -> 0 | M99: =IF((L98+M98+J99-K99)<0,(L98+M98+J99-K99),0) -> 0
A100: 45147 | B100: =MONTH(A100) -> 8 | C100: =YEAR(A100) -> 2023 | D100: Ingreso a Caja chica | E100: Taller | J100: 2000 | L100: =IF((L99+M99+J100-K100)>0,(L99+M99+J100-K100),0) -> 2000 | M100: =IF((L99+M99+J100-K100)<0,(L99+M99+J100-K100),0) -> 0
A101: 45147 | B101: =MONTH(A101) -> 8 | C101: =YEAR(A101) -> 2023 | D101: Combustible | E101: Taller | K101: 2000 | L101: =IF((L100+M100+J101-K101)>0,(L100+M100+J101-K101),0) -> 0 | M101: =IF((L100+M100+J101-K101)<0,(L100+M100+J101-K101),0) -> 0
...

Sheet G. personales
A2: UNIDAD DE NEGOCIO | B2: Personal
A3: AÑO | B3: (Varios elementos)
A5: Etiquetas de fila | B5: Suma de HABER (EGRESO)
A6: 9 | B6: 4034580
A7: 8 | B7: 5330103.4
A8: 10 | B8: 5431354.7
A9: 11 | B9: 4648613.7
A10: 1 | B10: 2703737.3
A11: 2 | B11: 1363366.4
A12: 3 | B12: 2019494.7
A13: 4 | B13: 2283356.5
A14: 5 | B14: 1623467.8
A15: 6 | B15: 2329229.6
A16: 7 | B16: 3337950.8
A17: Total general | B17: 35105255

Sheet Indic 2019
A3: Sale | B3: Contabilidad | E3: =2400000/12 -> 200000
A5: Rótulos de fila | B5: Suma de Total 19
A6: Egreso | B6: 2387026.8 | C6: % total Egr | D6: % total Ing | G6: 0.082 | H6: 1.2 | I6: Debito/credito | J6: 0.85
A7: Bancario | B7: 452108.35 | C7: =B7/$B$6 -> 0.1894023 | D7: =B7/$B$16 -> 0.16003946 | H7: 2.26 | I7: Funcionamiento general
A8: Comisiones | B8: 92120 | C8: =B8/$B$6 -> 0.038591943 | D8: =B8/$B$16 -> 0.032609074 | H8: 0.34 | I8: Ing brutos
A9: Funcionamiento | B9: 82164.97 | C9: =B9/$B$6 -> 0.03442147 | D9: =B9/$B$16 -> 0.029085145 | H9: 3.9 | I9: Sueldos
A10: Honorarios | B10: 330039.09 | C10: =B10/$B$6 -> 0.13826367 | D10: =B10/$B$16 -> 0.1168288 | H10: 0.3 | I10: Gastos bancarios
A11: Impuestos y servicios | B11: 122288.53 | C11: =B11/$B$6 -> 0.051230481 | D11: =B11/$B$16 -> 0.043288273 | G11: 0.016 | H11: 0.9 | I11: Plazo fijo | J11: 0.15
A12: Ingresos brutos | B12: 101008.74 | C12: =B12/$B$6 -> 0.042315713 | D12: =B12/$B$16 -> 0.035755552 | H12: 0.6 | I12: Sobrante
A13: Limpieza | B13: 13300 | C13: =B13/$B$6 -> 0.005571785 | D13: =B13/$B$16 -> 0.004707997
A14: Papeleria | B14: 38790.92 | C14: =B14/$B$6 -> 0.016250727 | D14: =B14/$B$16 -> 0.013731394
A15: Sueldos | B15: 1155206.2 | C15: =B15/$B$6 -> 0.48395191 | D15: =B15/$B$16 -> 0.40892535 | G15: El total de ingresos podemos decir que es un 9,8 % de la liquidación. El 85% , que equivale a 8,2 puntos se utiliza para pagar gastos de funcionamiento de la estructura y 15% que equivale al 1,6 se utiliza para "ahorro". 1 punto aproximadamente hoy es lo que se tiene en plazo fijo. Con estos datos vemos que lo que se podría reducir es 1 punto en general que sería el 0,6 de sobrante + 0,34 de ingresos brutos que descontaba Osde y ya no lo descuenta más.
A16: Ingreso | B16: 2824980.5
A17: Alquiler | B17: 94800 | C17: =B17/$B$16 -> 0.033557753
A18: Cuota Colegio | B18: 441059 | C18: =B18/$B$16 -> 0.15612815
A19: Gtos adm Colegio Médico | B19: 2289121.5 | C19: =B19/$B$16 -> 0.81031409
A20: Total general | B20: 5212007.3
C24: 2300000 | D24: 8 | G24: Galvez - Propall plantea abonar al Colegio Médico un 3% sobre facturación. Los servicios que si o si debería abonar son 2,26 de funcionamiento general + 0,3 de gastos bancarios . realizar la parte operativa de facturación y liquidación en sus oficinas propias y utilizar el servicio de negociación de aranceles y gestión de pagos del Colegio Médico. También que la OS abone las facturas directamente a Propall para evitar el 1,2 de débito/crédito y abonar en lugar
C25: 95000 | D25: =C25*D24/C24 -> 0.33043478 | E25: 1.5
E26: 0.33
A28: FIESTA DÍA DEL MÉDICO 2019
A30: CONCEPTO | B30: ENTRADA | C30: SALIDA
A31: Tarjeta socio | B31: 87000
A32: Hotel colonial menu | C32: 82500
A33: Música carranza mauro | C33: 7000
A34: Muñiz musica | C34: 6000
A35: Cotillon cotimundo | C35: 1550
A36: Mercado libre copa copon cristal | C36: 12599.93
A37: Mercado libre cotillon | C37: 2204
A38: Mercado libre minipimer | C38: 6396
A39: Mercado libre plancha vapor | C39: 9897.36
A40: Mercado libre secador pelo | C40: 8394
A41: Camoati moños y bolsas regalos cena medico | C41: 1023.07
A42: Arredo regalos cena medicos | C42: 18053.2
A43: TOTAL | B43: =SUM(B31:B42) -> 87000 | C43: =SUM(C31:C42) -> 155617.56
A44: RESULTADO | B44: =B43-C43 -> -68617.56
B54: Valores
A55: Egresos | B55: Enero | C55: Febrero | D55: Marzo | E55: Abril | F55: Mayo
A56: Bancario | B56: 55283.44 | C56: 48533.96 | D56: 40335.89 | E56: 43719.99 | F56: 48791.16
A57: Comisiones | B57: 11600 | C57: 5200.02 | D57: 9030.01 | E57: 12090.02 | F57: 8070.02
A58: Funcionamiento | B58: 29599.63 | C58: 9962.8 | D58: 7493.67 | E58: 2829 | F58: 3210.65
A59: Honorarios | B59: 35000 | C59: 30000 | D59: 30000 | E59: 30000 | F59: 30000
A60: Impuestos y servicios | B60: 12921.59 | C60: 10591.32 | D60: 10673.1 | E60: 10941.22 | F60: 11585.73
A61: Limpieza | B61: 1200 | C61: 1200 | D61: 600 | E61: 1200 | F61: 1750.8
A62: Papelería | B62: 4339.86 | D62: 3736.23 | F62: 644.5
A63: Sueldos | B63: 69368.32 | C63: 214404.58 | D63: 195918.21 | E63: 103356.49 | F63: 146023.08
A64: Total general | B64: 219312.84 | C64: 319892.68 | D64: 297787.11 | E64: 204136.72 | F64: 250075.94

Sheet Resumen 2020
A1: Concepto | B1: Detalle | C1: Moviemieto | D1: 1 | E1: 2 | F1: 3 | G1: 4 | H1: 5 | I1: 6
A2: Sueldos | B2: Sueldos | C2: Egreso | D2: 69368.32 | E2: 108847.36 | F2: 139394.1 | G2: 74097.12 | H2: 77205.39
A3: Sueldos | B3: Pago electrónico de aportes y cargas sociales | C3: Egreso | E3: 105557.22 | F3: 56524.11 | G3: 29259.37 | H3: 68817.69
A4: Bancario | B4: Impuesto débito/crédito | C4: Egreso | D4: 38484.97 | E4: 32276.01 | F4: 32543.08 | G4: 35102.71 | H4: 39779.21
A5: Honorarios | B5: Honorarios | C5: Egreso | D5: 35000 | E5: 30000 | F5: 30000 | G5: 30000 | H5: 30000
A6: Funcionamiento | B6: Gastos varios caja chica | C6: Egreso | D6: 10000 | E6: 2350 | F6: 3200
A7: Impuestos y servicios | B7: Pago electrónico Impuestos | C7: Egreso | D7: 3319.46 | E7: 10591.32 | F7: 8856.69 | G7: 10941.22 | H7: 7567.06
A8: Bancario | B8: Comisión canje Bp | C8: Egreso | D8: 11992.99 | E8: 11648.26 | F8: 4821.85 | G8: 5285.87 | H8: 5543.06
A9: Comisiones | B9: Comisionistas | C9: Egreso | D9: 7550 | E9: 300 | F9: 6300 | G9: 7600 | H9: 4900
A10: Funcionamiento | B10: Mantenimiento VCL | C10: Egreso | D10: 16335.03 | E10: 1500
A11: Bancario | B11: IVA 21% comisiones | C11: Egreso | D11: 2915.48 | E11: 2719.69 | F11: 1080.96 | G11: 1441.41 | H11: 1578.89
A12: Bancario | B12: Gastos mantenimiento /comisiones varias | C12: Egreso | D12: 1890 | E12: 1890 | F12: 1890 | G12: 1890 | H12: 1890
A13: Papelería | B13: Librería | C13: Egreso | D13: 3999.86 | F13: 3736.23
A14: Funcionamiento | B14: Publicidad | C14: Egreso | E14: 800
A15: Bancario | B15: cheque anulado | C15: Egreso | F15: 0
A16: Comisiones | B16: Gasto franqueo | C16: Egreso | D16: 4050 | E16: 4900.02 | F16: 1940.01 | G16: 4490.02 | H16: 3170.02 | I16: 4240.01
A17: Impuestos y servicios | B17: Impuestos y servicios | C17: Egreso | D17: 9602.13 | F17: 1816.41 | H17: 4018.67 | I17: 1318.28
A18: Funcionamiento | B18: Gastos Varios | C18: Egreso | D18: 1520 | E18: 2802 | F18: 2119.47 | G18: 1229 | H18: 2410.65 | I18: 2593.2
A19: Limpieza | B19: Servicio de limpieza | C19: Egreso | D19: 1200 | E19: 1200 | F19: 600 | G19: 1200 | H19: 1380 | I19: 1200
A20: Funcionamiento | B20: Gasto administrativo alquiler Rotary | C20: Egreso | D20: 800 | E20: 800 | F20: 800 | G20: 800 | H20: 800 | I20: 800
A21: Funcionamiento | B21: Supermercado | C21: Egreso | D21: 944.6 | E21: 546.8 | F21: 1374.2
A22: Funcionamiento | B22: Gastos de mantenimiento | C22: Egreso | E22: 1164 | I22: 500
A23: Funcionamiento | B23: Reuniones | C23: Egreso | G23: 800
A24: Comisiones | B24: Certificación de firma | C24: Egreso | F24: 790
A25: Papelería | B25: Librería | C25: Egreso | H25: 644.5
A26: Limpieza | B26: Insumos limpieza | C26: Egreso | H26: 370.8
A27: Papelería | B27: Imprenta | C27: Egreso | D27: 340
