Workbook

Sheet Carga Presup.
D2: PRESUPUESTOS
A3: Nro comp. | B3: contador | C3: Fecha | D3: Cliente | F3: Dominio | G3: Vehículo | H3: Diagnóstico | J3: Código | K3: Repuesto | L3: Proveedor | M3: Costo | N3: Comisionista | O3: % ganancia | P3: Cantidad | Q3: Precio repuesto | R3: Total | S3: MO tiempo | T3: MO precio | U3: MO | V3: MO Acumulado
A4: 9 | B4: 1 | C4: 45131 | D4: Saturnino Santa Cruz | E4: =CONCATENATE(A4,D4,B4) -> 9Saturnino Santa Cruz1 | G4: Voyage | H4: Service y Distribución. | I4: =H4 -> Service y Distribución. | K4: Aceite motor | P4: 1 | Q4: 22000 | R4: =Q4*P4 -> 22000 | S4: 1 | T4: 60000 | U4: =+T4*S4 -> 60000 | V4: =U4 -> 60000
A5: 10 | B5: =IF(A5=A4,B4+1,1) -> 1 | C5: =IF(A5=A4,C4,"") | D5: =IF(A5=A4,D4,"") | E5: =CONCATENATE(A5,D5,B5) -> 101 | I5: =IF(A5=A4,CONCATENATE(I4," ",H5),H5) -> 0 | K5: Filtros | P5: 1 | Q5: 14520 | R5: =Q5*P5 -> 14520 | U5: =+T5*S5 -> 0 | V5: =IF(A5=A4,V4+U5,U5) -> 0
A6: 10 | B6: =IF(A6=A5,B5+1,1) -> 2 | C6: =IF(A6=A5,C5,"") | D6: =IF(A6=A5,D5,"") | E6: =CONCATENATE(A6,D6,B6) -> 102 | I6: =IF(A6=A5,CONCATENATE(I5," ",H6),H6) -> 0 | K6: Kit distribución | P6: 1 | Q6: 63800 | R6: =Q6*P6 -> 63800 | U6: =+T6*S6 -> 0 | V6: =IF(A6=A5,V5+U6,U6) -> 0
A7: 10 | B7: =IF(A7=A6,B6+1,1) -> 3 | C7: =IF(A7=A6,C6,"") | D7: =IF(A7=A6,D6,"") | E7: =CONCATENATE(A7,D7,B7) -> 103 | I7: =IF(A7=A6,CONCATENATE(I6," ",H7),H7) -> 0 | K7: Refrigerante + Destilada | P7: 1 | Q7: 7000 | R7: =Q7*P7 -> 7000 | U7: =+T7*S7 -> 0 | V7: =IF(A7=A6,V6+U7,U7) -> 0
A8: 11 | B8: =IF(A8=A7,B7+1,1) -> 1 | C8: 45132 | D8: OCA LOG S.A | E8: =CONCATENATE(A8,D8,B8) -> 11OCA LOG S.A1 | F8: 297 | G8: Ford Ranger | H8: Limpieza circuito refrigeración. | I8: =IF(A8=A7,CONCATENATE(I7," ",H8),H8) -> Limpieza circuito refrigeración. | K8: Liquido desincrustante | P8: 1 | Q8: 4000 | R8: =Q8*P8 -> 4000 | U8: =+T8*S8 -> 0 | V8: =IF(A8=A7,V7+U8,U8) -> 0
A9: 11 | B9: =IF(A9=A8,B8+1,1) -> 2 | C9: =IF(A9=A8,C8,"") -> 45132 | D9: =IF(A9=A8,D8,"") -> OCA LOG S.A | E9: =CONCATENATE(A9,D9,B9) -> 11OCA LOG S.A2 | H9: Cambio refrigerante y purgado del circuito. | I9: =IF(A9=A8,CONCATENATE(I8," ",H9),H9) -> Limpieza circuito refrigeración. Cambio refrigerante y purgado del circuito. | K9: Liquido refrigerante + destilada | P9: 1 | Q9: 7000 | R9: =Q9*P9 -> 7000 | S9: 1 | T9: 10000 | U9: =+T9*S9 -> 10000 | V9: =IF(A9=A8,V8+U9,U9) -> 10000
A10: 11 | B10: =IF(A10=A9,B9+1,1) -> 3 | C10: =IF(A10=A9,C9,"") -> 45132 | D10: =IF(A10=A9,D9,"") -> OCA LOG S.A | E10: =CONCATENATE(A10,D10,B10) -> 11OCA LOG S.A3 | H10: Lavado interior del block. | I10: =IF(A10=A9,CONCATENATE(I9," ",H10),H10) -> Limpieza circuito refrigeración. Cambio refrigerante y purgado del circuito. Lavado interior del block. | R10: =Q10*P10 -> 0 | U10: =+T10*S10 -> 0 | V10: =IF(A10=A9,V9+U10,U10) -> 10000
A11: 12 | B11: =IF(A11=A10,B10+1,1) -> 1 | C11: 45133 | D11: Bastianelli | E11: =CONCATENATE(A11,D11,B11) -> 12Bastianelli1 | G11: Peugeot 206 | H11: Cambiar kit de distribución. | I11: =IF(A11=A10,CONCATENATE(I10," ",H11),H11) -> Cambiar kit de distribución. | K11: Kit distribución | P11: 1 | Q11: 28000 | R11: =Q11*P11 -> 28000 | U11: =+T11*S11 -> 0 | V11: =IF(A11=A10,V10+U11,U11) -> 0
A12: 12 | B12: =IF(A12=A11,B11+1,1) -> 2 | C12: =IF(A12=A11,C11,"") -> 45133 | D12: =IF(A12=A11,D11,"") -> Bastianelli | E12: =CONCATENATE(A12,D12,B12) -> 12Bastianelli2 | H12: Cambiar correa poliv. | I12: =IF(A12=A11,CONCATENATE(I11," ",H12),H12) -> Cambiar kit de distribución. Cambiar correa poliv. | K12: Correa poliv | P12: 1 | Q12: 9000 | R12: =Q12*P12 -> 9000 | U12: =+T12*S12 -> 0 | V12: =IF(A12=A11,V11+U12,U12) -> 0
A13: 12 | B13: =IF(A13=A12,B12+1,1) -> 3 | C13: =IF(A13=A12,C12,"") -> 45133 | D13: =IF(A13=A12,D12,"") -> Bastianelli | E13: =CONCATENATE(A13,D13,B13) -> 12Bastianelli3 | H13: Cambiar bomba de agua. | I13: =IF(A13=A12,CONCATENATE(I12," ",H13),H13) -> Cambiar kit de distribución. Cambiar correa poliv. Cambiar bomba de agua. | K13: Bomba de agua | P13: 1 | Q13: 15800 | R13: =Q13*P13 -> 15800 | U13: =+T13*S13 -> 0 | V13: =IF(A13=A12,V12+U13,U13) -> 0
A14: 12 | B14: =IF(A14=A13,B13+1,1) -> 4 | C14: =IF(A14=A13,C13,"") -> 45133 | D14: =IF(A14=A13,D13,"") -> Bastianelli | E14: =CONCATENATE(A14,D14,B14) -> 12Bastianelli4 | I14: =IF(A14=A13,CONCATENATE(I13," ",H14),H14) -> Cambiar kit de distribución. Cambiar correa poliv. Cambiar bomba de agua. | K14: Liquido refrigerante + | P14: 1 | Q14: 7000 | R14: =Q14*P14 -> 7000 | S14: 1 | T14: 38000 | U14: =+T14*S14 -> 38000 | V14: =IF(A14=A13,V13+U14,U14) -> 38000
A15: 12 | B15: =IF(A15=A14,B14+1,1) -> 5 | C15: =IF(A15=A14,C14,"") -> 45133 | D15: =IF(A15=A14,D14,"") -> Bastianelli | E15: =CONCATENATE(A15,D15,B15) -> 12Bastianelli5 | I15: =IF(A15=A14,CONCATENATE(I14," ",H15),H15) -> Cambiar kit de distribución. Cambiar correa poliv. Cambiar bomba de agua. | K15: agua destilada. | R15: =Q15*P15 -> 0 | U15: =+T15*S15 -> 0 | V15: =IF(A15=A14,V14+U15,U15) -> 38000
A16: 13 | B16: =IF(A16=A15,B15+1,1) -> 1 | C16: 45139 | D16: OCA LOG S.A | E16: =CONCATENATE(A18,D16,B16) -> 13OCA LOG S.A1 | F16: 297 | G16: Ford Ranger | H16: Sacar turbo multiple de escape. | I16: =IF(A18=A15,CONCATENATE(I15," ",H16),H16) -> Sacar turbo multiple de escape. | R16: =Q16*P16 -> 0 | S16: 1 | T16: 35000 | U16: =+T16*S16 -> 35000 | V16: =IF(A18=A15,V15+U16,U16) -> 35000
A17: 13 | B17: =IF(A17=A16,B16+1,1) -> 2 | C17: 45139 | D17: OCA LOG S.A | E17: =CONCATENATE(A17,D17,B17) -> 13OCA LOG S.A2 | H17: Cambiar tapones de block lado izquierdo. Armado total. | I17: =IF(A17=A18,CONCATENATE(I16," ",H17),H17) -> Sacar turbo multiple de escape. Cambiar tapones de block lado izquierdo. Armado total. | R17: =Q17*P17 -> 0 | U17: =+T17*S17 -> 0 | V17: =IF(A17=A18,V16+U17,U17) -> 35000
A18: 13 | B18: =IF(A18=A17,B17+1,1) -> 3 | C18: 45139 | D18: OCA LOG S.A | E18: =CONCATENATE(A18,D18,B18) -> 13OCA LOG S.A3 | I18: =IF(#REF!=A17,CONCATENATE(I17," ",H18),H18) -> #REF! | R18: =Q18*P18 -> 0 | U18: =+T18*S18 -> 0 | V18: =IF(#REF!=A17,V17+U18,U18) -> #REF!
A19: 14 | B19: =IF(A19=A18,B18+1,1) -> 1 | C19: 45140 | D19: Moreno Orlando | E19: =CONCATENATE(A19,D19,B19) -> 14Moreno Orlando1 | G19: Amarok | H19: Cambiar kit distribución con bomba de agua. | I19: =IF(A19=#REF!,CONCATENATE(I18," ",H19),H19) -> #REF! | K19: Kit distribución con bomba de agua. | P19: 1 | Q19: 170000 | R19: =Q19*P19 -> 170000 | S19: 1 | T19: 40000 | U19: =+T19*S19 -> 40000 | V19: =IF(A19=#REF!,V18+U19,U19) -> #REF!
A20: 14 | B20: =IF(A20=A19,B19+1,1) -> 2 | C20: =IF(A20=A19,C19,"") -> 45140 | D20: =IF(A20=A19,D19,"") -> Moreno Orlando | E20: =CONCATENATE(A20,D20,B20) -> 14Moreno Orlando2 | H20: con polea de dirección hidraulica y correa poliv. | I20: =IF(A20=A19,CONCATENATE(I19," ",H20),H20) -> #REF! | K20: Polea de dirección hidráulica. | P20: 1 | Q20: 8000 | R20: =Q20*P20 -> 8000 | U20: =+T20*S20 -> 0 | V20: =IF(A20=A19,V19+U20,U20) -> #REF!
A21: 14 | B21: =IF(A21=A20,B20+1,1) -> 3 | C21: =IF(A21=A20,C20,"") -> 45140 | D21: =IF(A21=A20,D20,"") -> Moreno Orlando | E21: =CONCATENATE(A21,D21,B21) -> 14Moreno Orlando3 | I21: =IF(A21=A20,CONCATENATE(I20," ",H21),H21) -> #REF! | K21: Correa poliv. | P21: 1 | Q21: 9800 | R21: =Q21*P21 -> 9800 | U21: =+T21*S21 -> 0 | V21: =IF(A21=A20,V20+U21,U21) -> #REF!
A22: 14 | B22: =IF(A22=A21,B21+1,1) -> 4 | C22: =IF(A22=A21,C21,"") -> 45140 | D22: =IF(A22=A21,D21,"") -> Moreno Orlando | E22: =CONCATENATE(A22,D22,B22) -> 14Moreno Orlando4 | H22: Service cambio de aceite y filtros. | I22: =IF(A22=A21,CONCATENATE(I21," ",H22),H22) -> #REF! | K22: Aceite motor 5w30. | P22: 6 | Q22: 6500 | R22: =Q22*P22 -> 39000 | S22: 1 | T22: 30000 | U22: =+T22*S22 -> 30000 | V22: =IF(A22=A21,V21+U22,U22) -> #REF!
A23: 14 | B23: =IF(A23=A22,B22+1,1) -> 5 | C23: =IF(A23=A22,C22,"") -> 45140 | D23: =IF(A23=A22,D22,"") -> Moreno Orlando | E23: =CONCATENATE(A23,D23,B23) -> 14Moreno Orlando5 | I23: =IF(A23=A22,CONCATENATE(I22," ",H23),H23) -> #REF! | K23: Kit de filtros. | P23: 1 | Q23: 39000 | R23: =Q23*P23 -> 39000 | U23: =+T23*S23 -> 0 | V23: =IF(A23=A22,V22+U23,U23) -> #REF!
A24: 15 | B24: =IF(A24=A23,B23+1,1) -> 1 | C24: 45140 | D24: Beriani Nazarena | E24: =CONCATENATE(A24,D24,B24) -> 15Beriani Nazarena1 | G24: Kangoo | H24: Reparar eje trasero y engrasar | I24: =IF(A24=A23,CONCATENATE(I23," ",H24),H24) -> Reparar eje trasero y engrasar | K24: Juego de orring eje trasero | P24: 1 | Q24: 9800 | R24: =Q24*P24 -> 9800 | S24: 1 | T24: 35000 | U24: =+T24*S24 -> 35000 | V24: =IF(A24=A23,V23+U24,U24) -> 35000
A25: 16 | B25: =IF(A25=A24,B24+1,1) -> 1 | C25: 45140 | D25: Moreno Orlando | E25: =CONCATENATE(A25,D25,B25) -> 16Moreno Orlando1 | G25: Amarok | H25: Cambiar kit distribución con bomba de agua. | I25: =IF(A25=A24,CONCATENATE(I24," ",H25),H25) -> Cambiar kit distribución con bomba de agua. | K25: Kit distribución con bomba de agua. | P25: 1 | Q25: 170000 | R25: =Q25*P25 -> 170000 | S25: 1 | T25: 40000 | U25: =+T25*S25 -> 40000 | V25: =IF(A25=A24,V24+U25,U25) -> 40000
A26: 16 | B26: =IF(A26=A25,B25+1,1) -> 2 | C26: =IF(A26=A25,C25,"") -> 45140 | D26: =IF(A26=A25,D25,"") -> Moreno Orlando | E26: =CONCATENATE(A26,D26,B26) -> 16Moreno Orlando2 | H26: Polea de dirección hidráulica y correa poliv. | I26: =IF(A26=A25,CONCATENATE(I25," ",H26),H26) -> Cambiar kit distribución con bomba de agua. Polea de dirección hidráulica y correa poliv. | K26: Polea de dirección hidraulica | P26: 1 | Q26: 8200 | R26: =Q26*P26 -> 8200 | U26: =+T26*S26 -> 0 | V26: =IF(A26=A25,V25+U26,U26) -> 40000
A27: 16 | B27: =IF(A27=A26,B26+1,1) -> 3 | C27: =IF(A27=A26,C26,"") -> 45140 | D27: =IF(A27=A26,D26,"") -> Moreno Orlando | E27: =CONCATENATE(A27,D27,B27) -> 16Moreno Orlando3 | I27: =IF(A27=A26,CONCATENATE(I26," ",H27),H27) -> Cambiar kit distribución con bomba de agua. Polea de dirección hidráulica y correa poliv. | K27: Correa poliv. | P27: 1 | Q27: 9800 | R27: =Q27*P27 -> 9800 | U27: =+T27*S27 -> 0 | V27: =IF(A27=A26,V26+U27,U27) -> 40000
A28: 16 | B28: =IF(A28=A27,B27+1,1) -> 4 | C28: =IF(A28=A27,C27,"") -> 45140 | D28: =IF(A28=A27,D27,"") -> Moreno Orlando | E28: =CONCATENATE(A28,D28,B28) -> 16Moreno Orlando4 | I28: =IF(A28=A27,CONCATENATE(I27," ",H28),H28) -> Cambiar kit distribución con bomba de agua. Polea de dirección hidráulica y correa poliv. | U28: =+T28*S28 -> 0 | V28: =IF(A28=A27,V27+U28,U28) -> 40000
A29: 16 | B29: =IF(A29=A28,B28+1,1) -> 5 | C29: =IF(A29=A28,C28,"") -> 45140 | D29: =IF(A29=A28,D28,"") -> Moreno Orlando | E29: =CONCATENATE(A29,D29,B29) -> 16Moreno Orlando5 | I29: =IF(A29=A28,CONCATENATE(I28," ",H29),H29) -> Cambiar kit distribución con bomba de agua. Polea de dirección hidráulica y correa poliv. | U29: =+T29*S29 -> 0 | V29: =IF(A29=A28,V28+U29,U29) -> 40000
A30: 17 | B30: =IF(A30=A29,B29+1,1) -> 1 | C30: 45140 | D30: 8925 | E30: =CONCATENATE(A30,D30,B30) -> 1789251 | G30: Amarok | H30: Service cambio de aceite y filtros. | I30: =IF(A30=A29,CONCATENATE(I29," ",H30),H30) -> Service cambio de aceite y filtros. | K30: Aceite motor 5w30 | P30: 6 | Q30: 6500 | R30: =Q30*P30 -> 39000 | U30: =+T30*S30 -> 0 | V30: =IF(A30=A29,V29+U30,U30) -> 0
A31: 17 | B31: =IF(A31=A30,B30+1,1) -> 2 | C31: =IF(A31=A30,C30,"") -> 45140 | D31: =IF(A31=A30,D30,"") -> 8925 | E31: =CONCATENATE(A31,D31,B31) -> 1789252 | I31: =IF(A31=A30,CONCATENATE(I30," ",H31),H31) -> Service cambio de aceite y filtros. | K31: Kit de filtros | P31: 1 | Q31: 39000 | R31: =Q31*P31 -> 39000 | S31: 1 | T31: 30000 | U31: =+T31*S31 -> 30000 | V31: =IF(A31=A30,V30+U31,U31) -> 30000
A32: 18 | B32: =IF(A32=A31,B31+1,1) -> 1 | C32: 45140 | D32: Martina Nilda | E32: =CONCATENATE(A32,D32,B32) -> 18Martina Nilda1 | I32: =IF(A32=A31,CONCATENATE(I31," ",H32),H32) -> 0 | K32: Radiador de agua | P32: 1 | Q32: 79800 | R32: =Q32*P32 -> 79800 | U32: =+T32*S32 -> 0 | V32: =IF(A32=A31,V31+U32,U32) -> 0
A33: 18 | B33: =IF(A33=A32,B32+1,1) -> 2 | C33: =IF(A33=A32,C32,"") -> 45140 | D33: =IF(A33=A32,D32,"") -> Martina Nilda | E33: =CONCATENATE(A33,D33,B33) -> 18Martina Nilda2 | I33: =IF(A33=A32,CONCATENATE(I32," ",H33),H33) -> 0 | K33: Radiador de aire acondicionado | P33: 1 | Q33: 85500 | R33: =Q33*P33 -> 85500 | U33: =+T33*S33 -> 0 | V33: =IF(A33=A32,V32+U33,U33) -> 0
A34: 18 | B34: =IF(A34=A33,B33+1,1) -> 3 | C34: =IF(A34=A33,C33,"") -> 45140 | D34: =IF(A34=A33,D33,"") -> Martina Nilda | E34: =CONCATENATE(A34,D34,B34) -> 18Martina Nilda3 | I34: =IF(A34=A33,CONCATENATE(I33," ",H34),H34) -> 0 | K34: Electro de aire acondicionado | P34: 1 | Q34: 39900 | R34: =Q34*P34 -> 39900 | U34: =+T34*S34 -> 0 | V34: =IF(A34=A33,V33+U34,U34) -> 0
A35: 18 | B35: =IF(A35=A34,B34+1,1) -> 4 | C35: =IF(A35=A34,C34,"") -> 45140 | D35: =IF(A35=A34,D34,"") -> Martina Nilda | E35: =CONCATENATE(A35,D35,B35) -> 18Martina Nilda4 | I35: =IF(A35=A34,CONCATENATE(I34," ",H35),H35) -> 0 | K35: Electro de radiador de agua | P35: 1 | Q35: 39900 | R35: =Q35*P35 -> 39900 | S35: 1 | T35: 57000 | U35: =+T35*S35 -> 57000 | V35: =IF(A35=A34,V34+U35,U35) -> 57000
A36: 18 | B36: =IF(A36=A35,B35+1,1) -> 5 | C36: =IF(A36=A35,C35,"") -> 45140 | D36: =IF(A36=A35,D35,"") -> Martina Nilda | E36: =CONCATENATE(A36,D36,B36) -> 18Martina Nilda5 | I36: =IF(A36=A35,CONCATENATE(I35," ",H36),H36) -> 0 | K36: refrigerante + agua destilada | P36: 1 | Q36: 7000 | R36: =Q36*P36 -> 7000 | U36: =+T36*S36 -> 0 | V36: =IF(A36=A35,V35+U36,U36) -> 57000
A37: 18 | B37: =IF(A37=A36,B36+1,1) -> 6 | C37: =IF(A37=A36,C36,"") -> 45140 | D37: =IF(A37=A36,D36,"") -> Martina Nilda | E37: =CONCATENATE(A37,D37,B37) -> 18Martina Nilda6 | I37: =IF(A37=A36,CONCATENATE(I36," ",H37),H37) -> 0 | K37: carga de aire acondicionado | P37: 1 | Q37: 39900 | R37: =Q37*P37 -> 39900 | U37: =+T37*S37 -> 0 | V37: =IF(A37=A36,V36+U37,U37) -> 57000
A38: 19 | B38: =IF(A38=A37,B37+1,1) -> 1 | C38: 45146 | D38: Calderon Daniel | E38: =CONCATENATE(A38,D38,B38) -> 19Calderon Daniel1 | H38: Cambiar ambos amortiguadores. | I38: =IF(A38=A37,CONCATENATE(I37," ",H38),H38) -> Cambiar ambos amortiguadores. | K38: Amortiguadores delanteros | P38: 2 | Q38: 32000 | R38: =Q38*P38 -> 64000 | S38: 1 | T38: 23000 | U38: =+T38*S38 -> 23000 | V38: =IF(A38=A37,V37+U38,U38) -> 23000
A39: 19 | B39: =IF(A39=A38,B38+1,1) -> 2 | C39: =IF(A39=A38,C38,"") -> 45146 | D39: =IF(A39=A38,D38,"") -> Calderon Daniel | E39: =CONCATENATE(A39,D39,B39) -> 19Calderon Daniel2 | H39: Cambiar caño de agua. | I39: =IF(A39=A38,CONCATENATE(I38," ",H39),H39) -> Cambiar ambos amortiguadores. Cambiar caño de agua. | K39: Casoletas suspensión completa | P39: 2 | Q39: 14500 | R39: =Q39*P39 -> 29000 | U39: =+T39*S39 -> 0 | V39: =IF(A39=A38,V38+U39,U39) -> 23000
A40: 19 | B40: =IF(A40=A39,B39+1,1) -> 3 | C40: =IF(A40=A39,C39,"") -> 45146 | D40: =IF(A40=A39,D39,"") -> Calderon Daniel | E40: =CONCATENATE(A40,D40,B40) -> 19Calderon Daniel3 | I40: =IF(A40=A39,CONCATENATE(I39," ",H40),H40) -> Cambiar ambos amortiguadores. Cambiar caño de agua. | K40: Caño de agua | P40: 1 | Q40: 8000 | R40: =Q40*P40 -> 8000 | U40: =+T40*S40 -> 0 | V40: =IF(A40=A39,V39+U40,U40) -> 23000
A41: 20 | B41: =IF(A41=A40,B40+1,1) -> 1 | C41: 45152 | D41: Creativity S.A.S | E41: =CONCATENATE(A41,D41,B41) -> 20Creativity S.A.S1 | G41: Fiorino | H41: Service cambio de aceite y filtros. | I41: =IF(A41=A40,CONCATENATE(I40," ",H41),H41) -> Service cambio de aceite y filtros. | K41: Aceite motor 10w40 | P41: 4 | Q41: 3575 | R41: =Q41*P41 -> 14300 | U41: =+T41*S41 -> 0 | V41: =IF(A41=A40,V40+U41,U41) -> 0
A42: 20 | B42: =IF(A42=A41,B41+1,1) -> 2 | C42: =IF(A42=A41,C41,"") -> 45152 | D42: =IF(A42=A41,D41,"") -> Creativity S.A.S | E42: =CONCATENATE(A42,D42,B42) -> 20Creativity S.A.S2 | H42: Control del vehículo. | I42: =IF(A42=A41,CONCATENATE(I41," ",H42),H42) -> Service cambio de aceite y filtros. Control del vehículo. | K42: Filtro aceite | P42: 1 | Q42: 2800 | R42: =Q42*P42 -> 2800 | U42: =+T42*S42 -> 0 | V42: =IF(A42=A41,V41+U42,U42) -> 0
A43: 20 | B43: =IF(A43=A42,B42+1,1) -> 3 | C43: =IF(A43=A42,C42,"") -> 45152 | D43: =IF(A43=A42,D42,"") -> Creativity S.A.S | E43: =CONCATENATE(A43,D43,B43) -> 20Creativity S.A.S3 | I43: =IF(A43=A42,CONCATENATE(I42," ",H43),H43) -> Service cambio de aceite y filtros. Control del vehículo. | K43: Filtro aire | P43: 1 | Q43: 3900 | R43: =Q43*P43 -> 3900 | S43: 1 | T43: 25000 | U43: =+T43*S43 -> 25000 | V43: =IF(A43=A42,V42+U43,U43) -> 25000
A44: 20 | B44: =IF(A44=A43,B43+1,1) -> 4 | C44: =IF(A44=A43,C43,"") -> 45152 | D44: =IF(A44=A43,D43,"") -> Creativity S.A.S | E44: =CONCATENATE(A44,D44,B44) -> 20Creativity S.A.S4 | I44: =IF(A44=A43,CONCATENATE(I43," ",H44),H44) -> Service cambio de aceite y filtros. Control del vehículo. | K44: Filtro nafta | P44: 1 | Q44: 3400 | R44: =Q44*P44 -> 3400 | U44: =+T44*S44 -> 0 | V44: =IF(A44=A43,V43+U44,U44) -> 25000
A45: 20 | B45: =IF(A45=A44,B44+1,1) -> 5 | C45: =IF(A45=A44,C44,"") -> 45152 | D45: =IF(A45=A44,D44,"") -> Creativity S.A.S | E45: =CONCATENATE(A45,D45,B45) -> 20Creativity S.A.S5 | I45: =IF(A45=A44,CONCATENATE(I44," ",H45),H45) -> Service cambio de aceite y filtros. Control del vehículo. | K45: Filtro pólen | P45: 1 | Q45: 3000 | R45: =Q45*P45 -> 3000 | U45: =+T45*S45 -> 0 | V45: =IF(A45=A44,V44+U45,U45) -> 25000
A46: 21 | B46: =IF(A46=A45,B45+1,1) -> 1 | C46: 45152 | D46: OCA LOG S.A | E46: =CONCATENATE(A46,D46,B46) -> 21OCA LOG S.A1 | I46: =IF(A46=A45,CONCATENATE(I45," ",H46),H46) -> 0 | K46: Block tapón 36MM | P46: 3 | Q46: 570 | R46: =Q46*P46 -> 1710 | U46: =+T46*S46 -> 0 | V46: =IF(A46=A45,V45+U46,U46) -> 0
A47: 21 | B47: =IF(A47=A46,B46+1,1) -> 2 | C47: =IF(A47=A46,C46,"") -> 45152 | D47: =IF(A47=A46,D46,"") -> OCA LOG S.A | E47: =CONCATENATE(A47,D47,B47) -> 21OCA LOG S.A2 | F47: 297 | G47: Ford Ranger | I47: =IF(A47=A46,CONCATENATE(I46," ",H47),H47) -> 0 | K47: Junta múltiple | P47: 1 | Q47: 14701.5 | R47: =Q47*P47 -> 14701.5 | U47: =+T47*S47 -> 0 | V47: =IF(A47=A46,V46+U47,U47) -> 0
A48: 22 | B48: =IF(A48=A47,B47+1,1) -> 1 | C48: 45153 | D48: OCA LOG S.A | E48: =CONCATENATE(A48,D48,B48) -> 22OCA LOG S.A1 | F48: 297 | G48: Ford Ranger | H48: Sacar radiador hacer destapar. Armado total | I48: =IF(A48=A47,CONCATENATE(I47," ",H48),H48) -> Sacar radiador hacer destapar. Armado total | K48: Termostato | P48: 1 | Q48: 60000 | R48: =Q48*P48 -> 60000 | S48: 1 | T48: 43000 | U48: =+T48*S48 -> 43000 | V48: =IF(A48=A47,V47+U48,U48) -> 43000
A49: 22 | B49: =IF(A49=A48,B48+1,1) -> 2 | C49: =IF(A49=A48,C48,"") -> 45153 | D49: =IF(A49=A48,D48,"") -> OCA LOG S.A | E49: =CONCATENATE(A49,D49,B49) -> 22OCA LOG S.A2 | H49: Sacar termostato control del funcionamiento del mismo, armado total. | I49: =IF(A49=A48,CONCATENATE(I48," ",H49),H49) -> Sacar radiador hacer destapar. Armado total Sacar termostato control del funcionamiento del mismo, armado total. | R49: =Q49*P49 -> 0 | U49: =+T49*S49 -> 0 | V49: =IF(A49=A48,V48+U49,U49) -> 43000
A50: 22 | B50: =IF(A50=A49,B49+1,1) -> 3 | C50: =IF(A50=A49,C49,"") -> 45153 | D50: =IF(A50=A49,D49,"") -> OCA LOG S.A | E50: =CONCATENATE(A50,D50,B50) -> 22OCA LOG S.A3 | H50: Trasbazado líquido refrigerante, purgado del circuito de refrigeración. | I50: =IF(A50=A49,CONCATENATE(I49," ",H50),H50) -> Sacar radiador hacer destapar. Armado total Sacar termostato control del funcionamiento del mismo, armado total. Trasbazado líquido refrigerante, purgado del circuito de refrigeración. | R50: =Q50*P50 -> 0 | U50: =+T50*S50 -> 0 | V50: =IF(A50=A49,V49+U50,U50) -> 43000
A51: 22 | B51: =IF(A51=A50,B50+1,1) -> 4 | C51: =IF(A51=A50,C50,"") -> 45153 | D51: =IF(A51=A50,D50,"") -> OCA LOG S.A | E51: =CONCATENATE(A51,D51,B51) -> 22OCA LOG S.A4 | H51: Ajustar soporte de bomba de agua en block de motor. | I51: =IF(A51=A50,CONCATENATE(I50," ",H51),H51) -> Sacar radiador hacer destapar. Armado total Sacar termostato control del funcionamiento del mismo, armado total. Trasbazado líquido refrigerante, purgado del circuito de refrigeración. Ajustar soporte de bomba de agua en block de motor. | R51: =Q51*P51 -> 0 | U51: =+T51*S51 -> 0 | V51: =IF(A51=A50,V50+U51,U51) -> 43000
A52: 22 | B52: =IF(A52=A51,B51+1,1) -> 5 | C52: =IF(A52=A51,C51,"") -> 45153 | D52: =IF(A52=A51,D51,"") -> OCA LOG S.A | E52: =CONCATENATE(A52,D52,B52) -> 22OCA LOG S.A5 | H52: (Va el precio del termostato por si hay que cambiarlo) | I52: =IF(A52=A51,CONCATENATE(I51," ",H52),H52) -> Sacar radiador hacer destapar. Armado total Sacar termostato control del funcionamiento del mismo, armado total. Trasbazado líquido refrigerante, purgado del circuito de refrigeración. Ajustar soporte de bomba de agua en block de motor. (Va el precio del termostato por si hay que cambiarlo) | R52: =Q52*P52 -> 0 | U52: =+T52*S52 -> 0 | V52: =IF(A52=A51,V51+U52,U52) -> 43000
A53: 23 | B53: =IF(A53=A52,B52+1,1) -> 1 | C53: 45154 | D53: Ventura Marcelo | E53: =CONCATENATE(A53,D53,B53) -> 23Ventura Marcelo1 | G53: Vento TFSI | H53: Service cambio de aceite y filtros. | I53: =IF(A53=A52,CONCATENATE(I52," ",H53),H53) -> Service cambio de aceite y filtros. | K53: Aceite motor 5w30 | P53: 5 | Q53: 9000 | R53: =Q53*P53 -> 45000 | U53: =+T53*S53 -> 0 | V53: =IF(A53=A52,V52+U53,U53) -> 0
A54: 23 | B54: =IF(A54=A53,B53+1,1) -> 2 | C54: =IF(A54=A53,C53,"") -> 45154 | D54: =IF(A54=A53,D53,"") -> Ventura Marcelo | E54: =CONCATENATE(A54,D54,B54) -> 23Ventura Marcelo2 | I54: =IF(A54=A53,CONCATENATE(I53," ",H54),H54) -> Service cambio de aceite y filtros. | K54: Filtro aceite | P54: 1 | Q54: 12560 | R54: =Q54*P54 -> 12560 | U54: =+T54*S54 -> 0 | V54: =IF(A54=A53,V53+U54,U54) -> 0
A55: 23 | B55: =IF(A55=A54,B54+1,1) -> 3 | C55: =IF(A55=A54,C54,"") -> 45154 | D55: =IF(A55=A54,D54,"") -> Ventura Marcelo | E55: =CONCATENATE(A55,D55,B55) -> 23Ventura Marcelo3 | I55: =IF(A55=A54,CONCATENATE(I54," ",H55),H55) -> Service cambio de aceite y filtros. | K55: Filtro de aire | P55: 1 | Q55: 11360 | R55: =Q55*P55 -> 11360 | U55: =+T55*S55 -> 0 | V55: =IF(A55=A54,V54+U55,U55) -> 0
A56: 23 | B56: =IF(A56=A55,B55+1,1) -> 4 | C56: =IF(A56=A55,C55,"") -> 45154 | D56: =IF(A56=A55,D55,"") -> Ventura Marcelo | E56: =CONCATENATE(A56,D56,B56) -> 23Ventura Marcelo4 | I56: =IF(A56=A55,CONCATENATE(I55," ",H56),H56) -> Service cambio de aceite y filtros. | K56: Filtro de nafta | P56: 1 | Q56: 24960 | R56: =Q56*P56 -> 24960 | U56: =+T56*S56 -> 0 | V56: =IF(A56=A55,V55+U56,U56) -> 0
A57: 23 | B57: =IF(A57=A56,B56+1,1) -> 5 | C57: =IF(A57=A56,C56,"") -> 45154 | D57: =IF(A57=A56,D56,"") -> Ventura Marcelo | E57: =CONCATENATE(A57,D57,B57) -> 23Ventura Marcelo5 | I57: =IF(A57=A56,CONCATENATE(I56," ",H57),H57) -> Service cambio de aceite y filtros. | K57: Filtro de pólen | P57: 1 | Q57: 12600 | R57: =Q57*P57 -> 12600 | U57: =+T57*S57 -> 0 | V57: =IF(A57=A56,V56+U57,U57) -> 0
A58: 24 | B58: =IF(A58=A57,B57+1,1) -> 1 | C58: 45155 | D58: Chumbita Juan | E58: =CONCATENATE(A58,D58,B58) -> 24Chumbita Juan1 | G58: Ford Focus Sigma 1,6 | H58: Desarmar distribución , cambiar kit con bomba de agua y correas poliv. | I58: =IF(A58=A57,CONCATENATE(I57," ",H58),H58) -> Desarmar distribución , cambiar kit con bomba de agua y correas poliv. | K58: kit distribución | P58: 1 | Q58: 78000 | R58: =Q58*P58 -> 78000 | S58: 1 | T58: 50000 | U58: =+T58*S58 -> 50000 | V58: =IF(A58=A57,V57+U58,U58) -> 50000
A59: 24 | B59: =IF(A59=A58,B58+1,1) -> 2 | C59: =IF(A59=A58,C58,"") -> 45155 | D59: =IF(A59=A58,D58,"") -> Chumbita Juan | E59: =CONCATENATE(A59,D59,B59) -> 24Chumbita Juan2 | H59: Cambiar líquido refrigerante. Puesta a punto. | I59: =IF(A59=A58,CONCATENATE(I58," ",H59),H59) -> Desarmar distribución , cambiar kit con bomba de agua y correas poliv. Cambiar líquido refrigerante. Puesta a punto. | K59: bomba de agua | P59: 1 | Q59: 43200 | R59: =Q59*P59 -> 43200 | U59: =+T59*S59 -> 0 | V59: =IF(A59=A58,V58+U59,U59) -> 50000
A60: 24 | B60: =IF(A60=A59,B59+1,1) -> 3 | C60: =IF(A60=A59,C59,"") -> 45155 | D60: =IF(A60=A59,D59,"") -> Chumbita Juan | E60: =CONCATENATE(A60,D60,B60) -> 24Chumbita Juan3 | I60: =IF(A60=A59,CONCATENATE(I59," ",H60),H60) -> Desarmar distribución , cambiar kit con bomba de agua y correas poliv. Cambiar líquido refrigerante. Puesta a punto. | K60: correas poliv | P60: 1 | Q60: 45360 | R60: =Q60*P60 -> 45360 | U60: =+T60*S60 -> 0 | V60: =IF(A60=A59,V59+U60,U60) -> 50000
A61: 24 | B61: =IF(A61=A60,B60+1,1) -> 4 | C61: =IF(A61=A60,C60,"") -> 45155 | D61: =IF(A61=A60,D60,"") -> Chumbita Juan | E61: =CONCATENATE(A61,D61,B61) -> 24Chumbita Juan4 | I61: =IF(A61=A60,CONCATENATE(I60," ",H61),H61) -> Desarmar distribución , cambiar kit con bomba de agua y correas poliv. Cambiar líquido refrigerante. Puesta a punto. | K61: liquido refrigerante + agua destilada | P61: 1 | Q61: 8400 | R61: =Q61*P61 -> 8400 | U61: =+T61*S61 -> 0 | V61: =IF(A61=A60,V60+U61,U61) -> 50000
A62: 25 | B62: =IF(A62=A61,B61+1,1) -> 1 | C62: 45155 | D62: Chumbita Juan | E62: =CONCATENATE(A62,D62,B62) -> 25Chumbita Juan1 | G62: Ford Focus Sigma 1,6 | H62: Sacar y colocar caja de velocidad. | I62: =IF(A62=A61,CONCATENATE(I61," ",H62),H62) -> Sacar y colocar caja de velocidad. | K62: Kit embrague con crapo hidraulic | P62: 1 | Q62: 172000 | R62: =Q62*P62 -> 172000 | U62: =+T62*S62 -> 0 | V62: =IF(A62=A61,V61+U62,U62) -> 0
A63: 25 | B63: =IF(A63=A62,B62+1,1) -> 2 | C63: =IF(A63=A62,C62,"") -> 45155 | D63: =IF(A63=A62,D62,"") -> Chumbita Juan | E63: =CONCATENATE(A63,D63,B63) -> 25Chumbita Juan2 | H63: Cambiar kit de embrague completo. | I63: =IF(A63=A62,CONCATENATE(I62," ",H63),H63) -> Sacar y colocar caja de velocidad. Cambiar kit de embrague completo. | R63: =Q63*P63 -> 0 | S63: 1 | T63: 80000 | U63: =+T63*S63 -> 80000 | V63: =IF(A63=A62,V62+U63,U63) -> 80000
A64: 25 | B64: =IF(A64=A63,B63+1,1) -> 3 | C64: =IF(A64=A63,C63,"") -> 45155 | D64: =IF(A64=A63,D63,"") -> Chumbita Juan | E64: =CONCATENATE(A64,D64,B64) -> 25Chumbita Juan3 | H64: Regular convergencia. Puesta a punto. | I64: =IF(A64=A63,CONCATENATE(I63," ",H64),H64) -> Sacar y colocar caja de velocidad. Cambiar kit de embrague completo. Regular convergencia. Puesta a punto. | R64: =Q64*P64 -> 0 | U64: =+T64*S64 -> 0 | V64: =IF(A64=A63,V63+U64,U64) -> 80000
A65: 25 | B65: =IF(A65=A64,B64+1,1) -> 4 | C65: =IF(A65=A64,C64,"") -> 45155 | D65: =IF(A65=A64,D64,"") -> Chumbita Juan | E65: =CONCATENATE(A65,D65,B65) -> 25Chumbita Juan4 | H65: Armado total. | I65: =IF(A65=A64,CONCATENATE(I64," ",H65),H65) -> Sacar y colocar caja de velocidad. Cambiar kit de embrague completo. Regular convergencia. Puesta a punto. Armado total. | R65: =Q65*P65 -> 0 | U65: =+T65*S65 -> 0 | V65: =IF(A65=A64,V64+U65,U65) -> 80000
A66: 26 | B66: =IF(A66=A65,B65+1,1) -> 1 | C66: 45160 | D66: Salgado Victor | E66: =CONCATENATE(A66,D66,B66) -> 26Salgado Victor1 | G66: Kangoo | H66: Cambiar ambos amortiguadores. | I66: =IF(A66=A65,CONCATENATE(I65," ",H66),H66) -> Cambiar ambos amortiguadores. | K66: Fuelles | P66: 2 | Q66: 2250 | R66: =Q66*P66 -> 4500 | U66: =+T66*S66 -> 0 | V66: =IF(A66=A65,V65+U66,U66) -> 0
A67: 26 | B67: =IF(A67=A66,B66+1,1) -> 2 | C67: 45160 | D67: =IF(A67=A66,D66,"") -> Salgado Victor | E67: =CONCATENATE(A67,D67,B67) -> 26Salgado Victor2 | H67: Cambiar ambas cazoletas. | I67: =IF(A67=A66,CONCATENATE(I66," ",H67),H67) -> Cambiar ambos amortiguadores. Cambiar ambas cazoletas. | K67: Cazoletas sin crapodina | P67: 2 | Q67: 10931.25 | R67: =Q67*P67 -> 21862.5 | S67: 1 | T67: 30000 | U67: =+T67*S67 -> 30000 | V67: =IF(A67=A66,V66+U67,U67) -> 30000
A68: 26 | B68: =IF(A68=A67,B67+1,1) -> 3 | C68: 45160 | D68: =IF(A68=A67,D67,"") -> Salgado Victor | E68: =CONCATENATE(A68,D68,B68) -> 26Salgado Victor3 | H68: Regular topes, regular convergencia. | I68: =IF(A68=A67,CONCATENATE(I67," ",H68),H68) -> Cambiar ambos amortiguadores. Cambiar ambas cazoletas. Regular topes, regular convergencia. | K68: Amortiguaderos delanteros | P68: 2 | Q68: 37329 | R68: =Q68*P68 -> 74658 | U68: =+T68*S68 -> 0 | V68: =IF(A68=A67,V67+U68,U68) -> 30000
A69: 26 | B69: =IF(A69=A68,B68+1,1) -> 4 | C69: 45160 | D69: =IF(A69=A68,D68,"") -> Salgado Victor | E69: =CONCATENATE(A69,D69,B69) -> 26Salgado Victor4 | I69: =IF(A69=A68,CONCATENATE(I68," ",H69),H69) -> Cambiar ambos amortiguadores. Cambiar ambas cazoletas. Regular topes, regular convergencia. | R69: =Q69*P69 -> 0 | U69: =+T69*S69 -> 0 | V69: =IF(A69=A68,V68+U69,U69) -> 30000
A70: 27 | B70: =IF(A70=A69,B69+1,1) -> 1 | C70: 45160 | D70: Albarracin German | E70: =CONCATENATE(A70,D70,B70) -> 27Albarracin German1 | G70: Kangoo K4M | H70: Service cambio de aceite y filtros. | I70: =IF(A70=A69,CONCATENATE(I69," ",H70),H70) -> Service cambio de aceite y filtros. | K70: Aceite 10w40 Castrol | P70: 5 | Q70: 7865 | R70: =Q70*P70 -> 39325 | U70: =+T70*S70 -> 0 | V70: =IF(A70=A69,V69+U70,U70) -> 0
A71: 27 | B71: =IF(A71=A70,B70+1,1) -> 2 | C71: 45160 | D71: =IF(A71=A70,D70,"") -> Albarracin German | E71: =CONCATENATE(A71,D71,B71) -> 27Albarracin German2 | H71: Rotación. Control del vehículo. | I71: =IF(A71=A70,CONCATENATE(I70," ",H71),H71) -> Service cambio de aceite y filtros. Rotación. Control del vehículo. | K71: Filtro aceite | P71: 1 | Q71: 3000 | R71: =Q71*P71 -> 3000 | S71: 1 | T71: 30500 | U71: =+T71*S71 -> 30500 | V71: =IF(A71=A70,V70+U71,U71) -> 30500
A72: 27 | B72: =IF(A72=A71,B71+1,1) -> 3 | C72: 45160 | D72: =IF(A72=A71,D71,"") -> Albarracin German | E72: =CONCATENATE(A72,D72,B72) -> 27Albarracin German3 | I72: =IF(A72=A71,CONCATENATE(I71," ",H72),H72) -> Service cambio de aceite y filtros. Rotación. Control del vehículo. | K72: Filtro aire | P72: 1 | Q72: 4200 | R72: =Q72*P72 -> 4200 | U72: =+T72*S72 -> 0 | V72: =IF(A72=A71,V71+U72,U72) -> 30500
A73: 27 | B73: =IF(A73=A72,B72+1,1) -> 4 | C73: 45160 | D73: =IF(A73=A72,D72,"") -> Albarracin German | E73: =CONCATENATE(A73,D73,B73) -> 27Albarracin German4 | I73: =IF(A73=A72,CONCATENATE(I72," ",H73),H73) -> Service cambio de aceite y filtros. Rotación. Control del vehículo. | K73: Filtro nafta | P73: 1 | Q73: 3400 | R73: =Q73*P73 -> 3400 | U73: =+T73*S73 -> 0 | V73: =IF(A73=A72,V72+U73,U73) -> 30500
A74: 27 | B74: =IF(A74=A73,B73+1,1) -> 5 | C74: 45160 | D74: =IF(A74=A73,D73,"") -> Albarracin German | E74: =CONCATENATE(A74,D74,B74) -> 27Albarracin German5 | I74: =IF(A74=A73,CONCATENATE(I73," ",H74),H74) -> Service cambio de aceite y filtros. Rotación. Control del vehículo. | K74: Filtro pólen | P74: 1 | Q74: 3000 | R74: =Q74*P74 -> 3000 | U74: =+T74*S74 -> 0 | V74: =IF(A74=A73,V73+U74,U74) -> 30500
A75: 28 | B75: =IF(A75=A74,B74+1,1) -> 1 | C75: 45160 | D75: Albarracin German | E75: =CONCATENATE(A75,D75,B75) -> 28Albarracin German1 | G75: S10 2016 | H75: Service cambio de aceite y filtros. | I75: =IF(A75=A74,CONCATENATE(I74," ",H75),H75) -> Service cambio de aceite y filtros. | K75: Aceite 5w30 | P75: 7.5 | Q75: 8000 | R75: =Q75*P75 -> 60000 | U75: =+T75*S75 -> 0 | V75: =IF(A75=A74,V74+U75,U75) -> 0
A76: 28 | B76: =IF(A76=A75,B75+1,1) -> 2 | C76: =IF(A76=A75,C75,"") -> 45160 | D76: =IF(A76=A75,D75,"") -> Albarracin German | E76: =CONCATENATE(A76,D76,B76) -> 28Albarracin German2 | H76: Control del vehículo. | I76: =IF(A76=A75,CONCATENATE(I75," ",H76),H76) -> Service cambio de aceite y filtros. Control del vehículo. | K76: Filtro aceite | P76: 1 | Q76: 8900 | R76: =Q76*P76 -> 8900 | U76: =+T76*S76 -> 0 | V76: =IF(A76=A75,V75+U76,U76) -> 0
A77: 28 | B77: =IF(A77=A76,B76+1,1) -> 3 | C77: =IF(A77=A76,C76,"") -> 45160 | D77: =IF(A77=A76,D76,"") -> Albarracin German | E77: =CONCATENATE(A77,D77,B77) -> 28Albarracin German3 | I77: =IF(A77=A76,CONCATENATE(I76," ",H77),H77) -> Service cambio de aceite y filtros. Control del vehículo. | K77: Filtro aire | P77: 1 | Q77: 9000 | R77: =Q77*P77 -> 9000 | U77: =+T77*S77 -> 0 | V77: =IF(A77=A76,V76+U77,U77) -> 0
A78: 28 | B78: =IF(A78=A77,B77+1,1) -> 4 | C78: =IF(A78=A77,C77,"") -> 45160 | D78: =IF(A78=A77,D77,"") -> Albarracin German | E78: =CONCATENATE(A78,D78,B78) -> 28Albarracin German4 | I78: =IF(A78=A77,CONCATENATE(I77," ",H78),H78) -> Service cambio de aceite y filtros. Control del vehículo. | K78: Filtro combustible | P78: 2 | Q78: 9400 | R78: 18800 | S78: 1 | T78: 40000 | U78: =+T78*S78 -> 40000 | V78: =IF(A78=A77,V77+U78,U78) -> 40000
A79: 28 | B79: =IF(A79=A78,B78+1,1) -> 5 | C79: =IF(A79=A78,C78,"") -> 45160 | D79: =IF(A79=A78,D78,"") -> Albarracin German | E79: =CONCATENATE(A79,D79,B79) -> 28Albarracin German5 | I79: =IF(A79=A78,CONCATENATE(I78," ",H79),H79) -> Service cambio de aceite y filtros. Control del vehículo. | K79: Filtro polen | P79: 1 | Q79: 8000 | R79: =Q79*P79 -> 8000 | U79: =+T79*S79 -> 0 | V79: =IF(A79=A78,V78+U79,U79) -> 40000
A80: 29 | B80: =IF(A80=A79,B79+1,1) -> 1 | C80: 45160 | D80: Giordano Hugo | E80: =CONCATENATE(A80,D80,B80) -> 29Giordano Hugo1 | G80: Logan | H80: Service cambio de aceite y filtros. | I80: =IF(A80=A79,CONCATENATE(I79," ",H80),H80) -> Service cambio de aceite y filtros. | K80: Aceite motor 10w40 | P80: 4.5 | Q80: 4290 | R80: =Q80*P80 -> 19305 | U80: =+T80*S80 -> 0 | V80: =IF(A80=A79,V79+U80,U80) -> 0
A81: 29 | B81: =IF(A81=A80,B80+1,1) -> 2 | C81: =IF(A81=A80,C80,"") -> 45160 | D81: =IF(A81=A80,D80,"") -> Giordano Hugo | E81: =CONCATENATE(A81,D81,B81) -> 29Giordano Hugo2 | H81: Rotación. Control del vehículo. | I81: =IF(A81=A80,CONCATENATE(I80," ",H81),H81) -> Service cambio de aceite y filtros. Rotación. Control del vehículo. | K81: Filtro aceite | P81: 1 | Q81: 3200 | R81: =Q81*P81 -> 3200 | S81: 1 | T81: 30500 | U81: =+T81*S81 -> 30500 | V81: =IF(A81=A80,V80+U81,U81) -> 30500
A82: 29 | B82: =IF(A82=A81,B81+1,1) -> 3 | C82: =IF(A82=A81,C81,"") -> 45160 | D82: =IF(A82=A81,D81,"") -> Giordano Hugo | E82: =CONCATENATE(A82,D82,B82) -> 29Giordano Hugo3 | I82: =IF(A82=A81,CONCATENATE(I81," ",H82),H82) -> Service cambio de aceite y filtros. Rotación. Control del vehículo. | K82: Filtro aire | P82: 1 | Q82: 4800 | R82: =Q82*P82 -> 4800 | U82: =+T82*S82 -> 0 | V82: =IF(A82=A81,V81+U82,U82) -> 30500
A83: 29 | B83: =IF(A83=A82,B82+1,1) -> 4 | C83: =IF(A83=A82,C82,"") -> 45160 | D83: =IF(A83=A82,D82,"") -> Giordano Hugo | E83: =CONCATENATE(A83,D83,B83) -> 29Giordano Hugo4 | I83: =IF(A83=A82,CONCATENATE(I82," ",H83),H83) -> Service cambio de aceite y filtros. Rotación. Control del vehículo. | K83: Filtro nafta | P83: 1 | Q83: 3400 | R83: =Q83*P83 -> 3400 | U83: =+T83*S83 -> 0 | V83: =IF(A83=A82,V82+U83,U83) -> 30500
A84: 29 | B84: =IF(A84=A83,B83+1,1) -> 5 | C84: =IF(A84=A83,C83,"") -> 45160 | D84: =IF(A84=A83,D83,"") -> Giordano Hugo | E84: =CONCATENATE(A84,D84,B84) -> 29Giordano Hugo5 | I84: =IF(A84=A83,CONCATENATE(I83," ",H84),H84) -> Service cambio de aceite y filtros. Rotación. Control del vehículo. | K84: Filtro pólen | P84: 1 | Q84: 3000 | R84: =Q84*P84 -> 3000 | U84: =+T84*S84 -> 0 | V84: =IF(A84=A83,V83+U84,U84) -> 30500
A85: 30 | B85: =IF(A85=A84,B84+1,1) -> 1 | C85: 45161 | D85: Manaceno Fany | E85: =CONCATENATE(A85,D85,B85) -> 30Manaceno Fany1 | G85: Peugeot 207 | H85: Service cambio de aceite y filtros. | I85: =IF(A85=A84,CONCATENATE(I84," ",H85),H85) -> Service cambio de aceite y filtros. | K85: Aceite 10w40 | P85: 4 | Q85: 4290 | R85: =Q85*P85 -> 17160 | S85: 1 | T85: 25000 | U85: =+T85*S85 -> 25000 | V85: =IF(A85=A84,V84+U85,U85) -> 25000
A86: 30 | B86: =IF(A86=A85,B85+1,1) -> 2 | C86: =IF(A86=A85,C85,"") -> 45161 | D86: =IF(A86=A85,D85,"") -> Manaceno Fany | E86: =CONCATENATE(A86,D86,B86) -> 30Manaceno Fany2 | H86: Rotación. Control del vehículo. | I86: =IF(A86=A85,CONCATENATE(I85," ",H86),H86) -> Service cambio de aceite y filtros. Rotación. Control del vehículo. | K86: Filtro aceite | P86: 1 | Q86: 4200 | R86: =Q86*P86 -> 4200 | U86: =+T86*S86 -> 0 | V86: =IF(A86=A85,V85+U86,U86) -> 25000
A87: 30 | B87: =IF(A87=A86,B86+1,1) -> 3 | C87: =IF(A87=A86,C86,"") -> 45161 | D87: =IF(A87=A86,D86,"") -> Manaceno Fany | E87: =CONCATENATE(A87,D87,B87) -> 30Manaceno Fany3 | I87: =IF(A87=A86,CONCATENATE(I86," ",H87),H87) -> Service cambio de aceite y filtros. Rotación. Control del vehículo. | K87: Filtro aire | P87: 1 | Q87: 5200 | R87: =Q87*P87 -> 5200 | U87: =+T87*S87 -> 0 | V87: =IF(A87=A86,V86+U87,U87) -> 25000
A88: 30 | B88: =IF(A88=A87,B87+1,1) -> 4 | C88: =IF(A88=A87,C87,"") -> 45161 | D88: =IF(A88=A87,D87,"") -> Manaceno Fany | E88: =CONCATENATE(A88,D88,B88) -> 30Manaceno Fany4 | I88: =IF(A88=A87,CONCATENATE(I87," ",H88),H88) -> Service cambio de aceite y filtros. Rotación. Control del vehículo. | K88: Filtro nafta | P88: 1 | Q88: 3400 | R88: =Q88*P88 -> 3400 | U88: =+T88*S88 -> 0 | V88: =IF(A88=A87,V87+U88,U88) -> 25000
A89: 31 | B89: =IF(A89=A88,B88+1,1) -> 1 | C89: 45166 | D89: PAMI | E89: =CONCATENATE(A89,D89,B89) -> 31PAMI1 | G89: Berlingo HDI | H89: Desarmar tren delantero lado derecho. Cambiar parrilla de suspension. Cambiar portamasa. Cambiar extremo de direccion. Cambiar precap de direccion. Sacar semieje y reparar con trinseta nueva. Engrase. Armado total. Cambiar llanta y cubierta. Balanceo de las mismas. Alineado del tren delantero. Presupuesto sujeto a cambios si es necesario emplear repuestos inesperados. | I89: =IF(A89=A88,CONCATENATE(I88," ",H89),H89) -> Desarmar tren delantero lado derecho. Cambiar parrilla de suspension. Cambiar portamasa. Cambiar extremo de direccion. Cambiar precap de direccion. Sacar semieje y reparar con trinseta nueva. Engrase. Armado total. Cambiar llanta y cubierta. Balanceo de las mismas. Alineado del tren delantero. Presupuesto sujeto a cambios si es necesario emplear repuestos inesperados. | P89: 1 | R89: =Q89*P89 -> 0 | S89: 1 | T89: 200000 | U89: =+T89*S89 -> 200000 | V89: =IF(A89=A88,V88+U89,U89) -> 200000
A90: 31 | B90: =IF(A90=A89,B89+1,1) -> 2 | C90: =IF(A90=A89,C89,"") -> 45166 | D90: =IF(A90=A89,D89,"") -> PAMI | E90: =CONCATENATE(A90,D90,B90) -> 31PAMI2 | I90: =IF(A90=A89,CONCATENATE(I89," ",H90),H90) -> Desarmar tren delantero lado derecho. Cambiar parrilla de suspension. Cambiar portamasa. Cambiar extremo de direccion. Cambiar precap de direccion. Sacar semieje y reparar con trinseta nueva. Engrase. Armado total. Cambiar llanta y cubierta. Balanceo de las mismas. Alineado del tren delantero. Presupuesto sujeto a cambios si es necesario emplear repuestos inesperados. | P90: 1 | R90: =Q90*P90 -> 0 | U90: =+T90*S90 -> 0 | V90: =IF(A90=A89,V89+U90,U90) -> 200000
A91: 31 | B91: =IF(A91=A90,B90+1,1) -> 3 | C91: =IF(A91=A90,C90,"") -> 45166 | D91: =IF(A91=A90,D90,"") -> PAMI | E91: =CONCATENATE(A91,D91,B91) -> 31PAMI3 | I91: =IF(A91=A90,CONCATENATE(I90," ",H91),H91) -> Desarmar tren delantero lado derecho. Cambiar parrilla de suspension. Cambiar portamasa. Cambiar extremo de direccion. Cambiar precap de direccion. Sacar semieje y reparar con trinseta nueva. Engrase. Armado total. Cambiar llanta y cubierta. Balanceo de las mismas. Alineado del tren delantero. Presupuesto sujeto a cambios si es necesario emplear repuestos inesperados. | P91: 1 | R91: =Q91*P91 -> 0 | U91: =+T91*S91 -> 0 | V91: =IF(A91=A90,V90+U91,U91) -> 200000
A92: 31 | B92: =IF(A92=A91,B91+1,1) -> 4 | C92: =IF(A92=A91,C91,"") -> 45166 | D92: =IF(A92=A91,D91,"") -> PAMI | E92: =CONCATENATE(A92,D92,B92) -> 31PAMI4 | I92: =IF(A92=A91,CONCATENATE(I91," ",H92),H92) -> Desarmar tren delantero lado derecho. Cambiar parrilla de suspension. Cambiar portamasa. Cambiar extremo de direccion. Cambiar precap de direccion. Sacar semieje y reparar con trinseta nueva. Engrase. Armado total. Cambiar llanta y cubierta. Balanceo de las mismas. Alineado del tren delantero. Presupuesto sujeto a cambios si es necesario emplear repuestos inesperados. | P92: 1 | R92: =Q92*P92 -> 0 | U92: =+T92*S92 -> 0 | V92: =IF(A92=A91,V91+U92,U92) -> 200000
A93: 31 | B93: =IF(A93=A92,B92+1,1) -> 5 | C93: =IF(A93=A92,C92,"") -> 45166 | D93: =IF(A93=A92,D92,"") -> PAMI | E93: =CONCATENATE(A93,D93,B93) -> 31PAMI5 | I93: =IF(A93=A92,CONCATENATE(I92," ",H93),H93) -> Desarmar tren delantero lado derecho. Cambiar parrilla de suspension. Cambiar portamasa. Cambiar extremo de direccion. Cambiar precap de direccion. Sacar semieje y reparar con trinseta nueva. Engrase. Armado total. Cambiar llanta y cubierta. Balanceo de las mismas. Alineado del tren delantero. Presupuesto sujeto a cambios si es necesario emplear repuestos inesperados. | P93: 1 | R93: =Q93*P93 -> 0 | U93: =+T93*S93 -> 0 | V93: =IF(A93=A92,V92+U93,U93) -> 200000
A94: 31 | B94: =IF(A94=A93,B93+1,1) -> 6 | C94: =IF(A94=A93,C93,"") -> 45166 | D94: =IF(A94=A93,D93,"") -> PAMI | E94: =CONCATENATE(A94,D94,B94) -> 31PAMI6 | I94: =IF(A94=A93,CONCATENATE(I93," ",H94),H94) -> Desarmar tren delantero lado derecho. Cambiar parrilla de suspension. Cambiar portamasa. Cambiar extremo de direccion. Cambiar precap de direccion. Sacar semieje y reparar con trinseta nueva. Engrase. Armado total. Cambiar llanta y cubierta. Balanceo de las mismas. Alineado del tren delantero. Presupuesto sujeto a cambios si es necesario emplear repuestos inesperados. | P94: 1 | R94: =Q94*P94 -> 0 | U94: =+T94*S94 -> 0 | V94: =IF(A94=A93,V93+U94,U94) -> 200000
A95: 31 | B95: =IF(A95=A94,B94+1,1) -> 7 | C95: =IF(A95=A94,C94,"") -> 45166 | D95: =IF(A95=A94,D94,"") -> PAMI | E95: =CONCATENATE(A95,D95,B95) -> 31PAMI7 | I95: =IF(A95=A94,CONCATENATE(I94," ",H95),H95) -> Desarmar tren delantero lado derecho. Cambiar parrilla de suspension. Cambiar portamasa. Cambiar extremo de direccion. Cambiar precap de direccion. Sacar semieje y reparar con trinseta nueva. Engrase. Armado total. Cambiar llanta y cubierta. Balanceo de las mismas. Alineado del tren delantero. Presupuesto sujeto a cambios si es necesario emplear repuestos inesperados. | P95: 1 | R95: =Q95*P95 -> 0 | U95: =+T95*S95 -> 0 | V95: =IF(A95=A94,V94+U95,U95) -> 200000
A96: 31 | B96: =IF(A96=A95,B95+1,1) -> 8 | C96: =IF(A96=A95,C95,"") -> 45166 | D96: =IF(A96=A95,D95,"") -> PAMI | E96: =CONCATENATE(A96,D96,B96) -> 31PAMI8 | I96: =IF(A96=A95,CONCATENATE(I95," ",H96),H96) -> Desarmar tren delantero lado derecho. Cambiar parrilla de suspension. Cambiar portamasa. Cambiar extremo de direccion. Cambiar precap de direccion. Sacar semieje y reparar con trinseta nueva. Engrase. Armado total. Cambiar llanta y cubierta. Balanceo de las mismas. Alineado del tren delantero. Presupuesto sujeto a cambios si es necesario emplear repuestos inesperados. | P96: 1 | R96: =Q96*P96 -> 0 | U96: =+T96*S96 -> 0 | V96: =IF(A96=A95,V95+U96,U96) -> 200000
A97: 31 | B97: =IF(A97=A96,B96+1,1) -> 9 | C97: =IF(A97=A96,C96,"") -> 45166 | D97: =IF(A97=A96,D96,"") -> PAMI | E97: =CONCATENATE(A97,D97,B97) -> 31PAMI9 | I97: =IF(A97=A96,CONCATENATE(I96," ",H97),H97) -> Desarmar tren delantero lado derecho. Cambiar parrilla de suspension. Cambiar portamasa. Cambiar extremo de direccion. Cambiar precap de direccion. Sacar semieje y reparar con trinseta nueva. Engrase. Armado total. Cambiar llanta y cubierta. Balanceo de las mismas. Alineado del tren delantero. Presupuesto sujeto a cambios si es necesario emplear repuestos inesperados. | P97: 1 | R97: =Q97*P97 -> 0 | U97: =+T97*S97 -> 0 | V97: =IF(A97=A96,V96+U97,U97) -> 200000
A98: 31 | B98: =IF(A98=A97,B97+1,1) -> 10 | C98: =IF(A98=A97,C97,"") -> 45166 | D98: =IF(A98=A97,D97,"") -> PAMI | E98: =CONCATENATE(A98,D98,B98) -> 31PAMI10 | I98: =IF(A98=A97,CONCATENATE(I97," ",H98),H98) -> Desarmar tren delantero lado derecho. Cambiar parrilla de suspension. Cambiar portamasa. Cambiar extremo de direccion. Cambiar precap de direccion. Sacar semieje y reparar con trinseta nueva. Engrase. Armado total. Cambiar llanta y cubierta. Balanceo de las mismas. Alineado del tren delantero. Presupuesto sujeto a cambios si es necesario emplear repuestos inesperados. | P98: 1 | R98: =Q98*P98 -> 0 | U98: =+T98*S98 -> 0 | V98: =IF(A98=A97,V97+U98,U98) -> 200000
A99: 31 | B99: =IF(A99=A98,B98+1,1) -> 11 | C99: =IF(A99=A98,C98,"") -> 45166 | D99: =IF(A99=A98,D98,"") -> PAMI | E99: =CONCATENATE(A99,D99,B99) -> 31PAMI11 | I99: =IF(A99=A98,CONCATENATE(I98," ",H99),H99) -> Desarmar tren delantero lado derecho. Cambiar parrilla de suspension. Cambiar portamasa. Cambiar extremo de direccion. Cambiar precap de direccion. Sacar semieje y reparar con trinseta nueva. Engrase. Armado total. Cambiar llanta y cubierta. Balanceo de las mismas. Alineado del tren delantero. Presupuesto sujeto a cambios si es necesario emplear repuestos inesperados. | P99: 1 | R99: =Q99*P99 -> 0 | U99: =+T99*S99 -> 0 | V99: =IF(A99=A98,V98+U99,U99) -> 200000
A100: 32 | B100: =IF(A100=A99,B99+1,1) -> 1 | C100: 45166 | D100: Ricardo Fiore | E100: =CONCATENATE(A100,D100,B100) -> 32Ricardo Fiore1 | G100: TOYOTA | H100: Sacar caja de velocidad, placa de disco de embrague, limpieza. | I100: =IF(A100=A99,CONCATENATE(I99," ",H100),H100) -> Sacar caja de velocidad, placa de disco de embrague, limpieza. | K100: Crapodina embrague toyota china | P100: 1 | Q100: 47000 | R100: =Q100*P100 -> 47000 | U100: =+T100*S100 -> 0 | V100: =IF(A100=A99,V99+U100,U100) -> 0
A101: 32 | B101: =IF(A101=A100,B100+1,1) -> 2 | C101: =IF(A101=A100,C100,"") -> 45166 | D101: =IF(A101=A100,D100,"") -> Ricardo Fiore | E101: =CONCATENATE(A101,D101,B101) -> 32Ricardo Fiore2 | H101: Sopletear. Armado total con crapodina nueva. | I101: =IF(A101=A100,CONCATENATE(I100," ",H101),H101) -> Sacar caja de velocidad, placa de disco de embrague, limpieza. Sopletear. Armado total con crapodina nueva. | K101: Crapodina NSK Original | P101: 1 | Q101: 59000 | R101: =Q101*P101 -> 59000 | S101: 1 | T101: 120000 | U101: =+T101*S101 -> 120000 | V101: =IF(A101=A100,V100+U101,U101) -> 120000
...

Sheet Presupuesto
A1: PRESUPUESTO
A3: De Cristian Bongiovanni | C3: Comprob: | D3: 224
A4: Domicilio: Gral. Deheza 191 (6120) Laboulaye | C4: Fecha: | D4: =VLOOKUP(D3,'Carga Presup.'!A5:U664,3,0) -> #N/A
A7: Razón social: | B7: =VLOOKUP(D3,'Carga Presup.'!A5:U7262,4,0) -> Luciano Napoli
A8: Vehiculo: | B8: =VLOOKUP(D3,'Carga Presup.'!A5:U7262,7,0) -> Peugeot 307 | C8: Dominio: | D8: =VLOOKUP(D3,'Carga Presup.'!A5:V7261,6,0) -> 0
A11: Diagnóstico: | B11: =VLOOKUP(CONCATENATE(D3,B7,COUNT(A18:A39)),'Carga Presup.'!E5:V69261,5,0) -> Desarmar suspension de ambos lados. Sacar ambos amortiguadores completos. Reparar con cazoletas nuevas. Armado total. Regulacion de convergencia.
A16: Producto/servicio | C16: Cant. | D16: Precio Unit. | E16: Importe
A17: 5 | B17: Mano de obra | C17: 1 | D17: =VLOOKUP(CONCATENATE(D3,B7,COUNT(A18:A39)),'Carga Presup.'!E5:V69261,18,0) -> 150000 | E17: =IFERROR(D17*C17,"") -> 150000
A18: =IFERROR(VLOOKUP(CONCATENATE(D3,B7,1),'Carga Presup.'!E5:V69261,6,0),"") -> 0 | B18: =IFERROR(VLOOKUP(CONCATENATE(D3,B7,1),'Carga Presup.'!E5:V69261,7,0),"") -> Cazoletas | C18: =IFERROR(VLOOKUP(CONCATENATE(D3,B7,1),'Carga Presup.'!E5:V69261,12,0),"") -> 2 | D18: =IFERROR(VLOOKUP(CONCATENATE(D3,B7,1),'Carga Presup.'!E5:V69261,13,0),"") -> 43000 | E18: =IFERROR(D18*C18,"") -> 86000
A19: =IFERROR(VLOOKUP(CONCATENATE(D3,B7,2),'Carga Presup.'!E5:V69261,6,0),"") -> 0 | B19: =IFERROR(VLOOKUP(CONCATENATE(D3,B7,2),'Carga Presup.'!E5:V69261,7,0),"") -> 0 | C19: =IFERROR(VLOOKUP(CONCATENATE(D3,B7,2),'Carga Presup.'!E5:V69261,12,0),"") -> 0 | D19: =IFERROR(VLOOKUP(CONCATENATE(D3,B7,2),'Carga Presup.'!E5:V69261,13,0),"") -> 0 | E19: =IFERROR(D19*C19,"") -> 0
A20: =IFERROR(VLOOKUP(CONCATENATE($D$3,$B$7,3),'Carga Presup.'!$E$5:$V$69261,6,0),"") | B20: =IFERROR(VLOOKUP(CONCATENATE(D3,B7,3),'Carga Presup.'!E6:V69262,7,0),"") | C20: =IFERROR(VLOOKUP(CONCATENATE(D3,B7,3),'Carga Presup.'!E5:V69261,12,0),"") | D20: =IFERROR(VLOOKUP(CONCATENATE($D$3,$B$7,3),'Carga Presup.'!$E$5:$V$69261,13,0),"") | E20: =IFERROR(D20*C20,"")
A21: =IFERROR(VLOOKUP(CONCATENATE($D$3,$B$7,4),'Carga Presup.'!$E$5:$V$69261,6,0),"") | B21: =IFERROR(VLOOKUP(CONCATENATE($D$3,$B$7,4),'Carga Presup.'!$E$5:$V$69261,7,0),"") | C21: =IFERROR(VLOOKUP(CONCATENATE($D$3,$B$7,4),'Carga Presup.'!$E$5:$V$69261,12,0),"") | D21: =IFERROR(VLOOKUP(CONCATENATE($D$3,$B$7,4),'Carga Presup.'!$E$5:$V$69261,13,0),"") | E21: =IFERROR(D21*C21,"")
A22: =IFERROR(VLOOKUP(CONCATENATE($D$3,$B$7,5),'Carga Presup.'!$E$5:$V$69261,6,0),"") | B22: =IFERROR(VLOOKUP(CONCATENATE($D$3,$B$7,5),'Carga Presup.'!$E$5:$V$69261,7,0),"") | C22: =IFERROR(VLOOKUP(CONCATENATE($D$3,$B$7,5),'Carga Presup.'!$E$5:$V$69261,12,0),"") | D22: =IFERROR(VLOOKUP(CONCATENATE($D$3,$B$7,5),'Carga Presup.'!$E$5:$V$69261,13,0),"") | E22: =IFERROR(D22*C22,"")
A23: =IFERROR(VLOOKUP(CONCATENATE($D$3,$B$7,6),'Carga Presup.'!$E$5:$V$69261,6,0),"") | B23: =IFERROR(VLOOKUP(CONCATENATE($D$3,$B$7,6),'Carga Presup.'!$E$5:$V$69261,7,0),"") | C23: =IFERROR(VLOOKUP(CONCATENATE($D$3,$B$7,6),'Carga Presup.'!$E$5:$V$69261,12,0),"") | D23: =IFERROR(VLOOKUP(CONCATENATE($D$3,$B$7,6),'Carga Presup.'!$E$5:$V$69261,13,0),"") | E23: =IFERROR(D23*C23,"")
A24: =IFERROR(VLOOKUP(CONCATENATE($D$3,$B$7,7),'Carga Presup.'!$E$5:$V$69261,6,0),"") | B24: =IFERROR(VLOOKUP(CONCATENATE($D$3,$B$7,7),'Carga Presup.'!$E$5:$V$69261,7,0),"") | C24: =IFERROR(VLOOKUP(CONCATENATE($D$3,$B$7,7),'Carga Presup.'!$E$5:$V$69261,12,0),"") | D24: =IFERROR(VLOOKUP(CONCATENATE($D$3,$B$7,7),'Carga Presup.'!$E$5:$V$69261,13,0),"") | E24: =IFERROR(D24*C24,"")
A25: =IFERROR(VLOOKUP(CONCATENATE($D$3,$B$7,8),'Carga Presup.'!$E$5:$V$69261,6,0),"") | B25: =IFERROR(VLOOKUP(CONCATENATE($D$3,$B$7,8),'Carga Presup.'!$E$5:$V$69261,7,0),"") | C25: =IFERROR(VLOOKUP(CONCATENATE($D$3,$B$7,8),'Carga Presup.'!$E$5:$V$69261,12,0),"") | D25: =IFERROR(VLOOKUP(CONCATENATE($D$3,$B$7,8),'Carga Presup.'!$E$5:$V$69261,13,0),"") | E25: =IFERROR(D25*C25,"")
A26: =IFERROR(VLOOKUP(CONCATENATE($D$3,$B$7,9),'Carga Presup.'!$E$5:$V$69261,6,0),"") | B26: =IFERROR(VLOOKUP(CONCATENATE($D$3,$B$7,9),'Carga Presup.'!$E$5:$V$69261,7,0),"") | C26: =IFERROR(VLOOKUP(CONCATENATE($D$3,$B$7,9),'Carga Presup.'!$E$5:$V$69261,12,0),"") | D26: =IFERROR(VLOOKUP(CONCATENATE($D$3,$B$7,9),'Carga Presup.'!$E$5:$V$69261,13,0),"") | E26: =IFERROR(D26*C26,"")
A27: =IFERROR(VLOOKUP(CONCATENATE($D$3,$B$7,10),'Carga Presup.'!$E$5:$V$69261,6,0),"") | C27: =IFERROR(VLOOKUP(CONCATENATE($D$3,$B$7,10),'Carga Presup.'!$E$5:$V$69261,12,0),"") | D27: =IFERROR(VLOOKUP(CONCATENATE($D$3,$B$7,10),'Carga Presup.'!$E$5:$V$69261,13,0),"") | E27: =IFERROR(D27*C27,"")
B28: =IFERROR(VLOOKUP(CONCATENATE($D$3,$B$7,11),'Carga Presup.'!$E$5:$V$69261,7,0),"") | C28: =IFERROR(VLOOKUP(CONCATENATE($D$3,$B$7,11),'Carga Presup.'!$E$5:$V$69261,12,0),"") | D28: =IFERROR(VLOOKUP(CONCATENATE($D$3,$B$7,11),'Carga Presup.'!$E$5:$V$69261,13,0),"") | E28: =IFERROR(D28*C28,"")
C29: =IFERROR(VLOOKUP(CONCATENATE($D$3,$B$7,12),'Carga Presup.'!$E$5:$V$69261,12,0),"") | D29: =IFERROR(VLOOKUP(CONCATENATE($D$3,$B$7,12),'Carga Presup.'!$E$5:$V$69261,13,0),"") | E29: =IFERROR(D29*C29,"")
A30: =IFERROR(VLOOKUP(CONCATENATE($D$3,$B$7,13),'Carga Presup.'!$E$5:$V$69261,6,0),"") | B30: =IFERROR(VLOOKUP(CONCATENATE($D$3,$B$7,13),'Carga Presup.'!$E$5:$V$69261,7,0),"") | C30: =IFERROR(VLOOKUP(CONCATENATE($D$3,$B$7,13),'Carga Presup.'!$E$5:$V$69261,12,0),"") | D30: =IFERROR(VLOOKUP(CONCATENATE($D$3,$B$7,13),'Carga Presup.'!$E$5:$V$69261,13,0),"") | E30: =IFERROR(D30*C30,"")
A31: =IFERROR(VLOOKUP(CONCATENATE($D$3,$B$7,14),'Carga Presup.'!$E$5:$V$69261,6,0),"") | B31: =IFERROR(VLOOKUP(CONCATENATE($D$3,$B$7,14),'Carga Presup.'!$E$5:$V$69261,7,0),"") | C31: =IFERROR(VLOOKUP(CONCATENATE($D$3,$B$7,14),'Carga Presup.'!$E$5:$V$69261,12,0),"") | D31: =IFERROR(VLOOKUP(CONCATENATE($D$3,$B$7,14),'Carga Presup.'!$E$5:$V$69261,13,0),"") | E31: =IFERROR(D31*C31,"")
A32: =IFERROR(VLOOKUP(CONCATENATE($D$3,$B$7,15),'Carga Presup.'!$E$5:$V$69261,6,0),"") | B32: =IFERROR(VLOOKUP(CONCATENATE($D$3,$B$7,15),'Carga Presup.'!$E$5:$V$69261,7,0),"") | C32: =IFERROR(VLOOKUP(CONCATENATE($D$3,$B$7,15),'Carga Presup.'!$E$5:$V$69261,12,0),"") | D32: =IFERROR(VLOOKUP(CONCATENATE($D$3,$B$7,15),'Carga Presup.'!$E$5:$V$69261,13,0),"") | E32: =IFERROR(D32*C32,"")
A33: =IFERROR(VLOOKUP(CONCATENATE($D$3,$B$7,16),'Carga Presup.'!$E$5:$V$69261,6,0),"") | B33: =IFERROR(VLOOKUP(CONCATENATE($D$3,$B$7,16),'Carga Presup.'!$E$5:$V$69261,7,0),"") | C33: =IFERROR(VLOOKUP(CONCATENATE($D$3,$B$7,16),'Carga Presup.'!$E$5:$V$69261,12,0),"") | D33: =IFERROR(VLOOKUP(CONCATENATE($D$3,$B$7,16),'Carga Presup.'!$E$5:$V$69261,13,0),"") | E33: =IFERROR(D33*C33,"")
A34: =IFERROR(VLOOKUP(CONCATENATE($D$3,$B$7,17),'Carga Presup.'!$E$5:$V$69261,6,0),"") | B34: =IFERROR(VLOOKUP(CONCATENATE($D$3,$B$7,17),'Carga Presup.'!$E$5:$V$69261,7,0),"") | C34: =IFERROR(VLOOKUP(CONCATENATE($D$3,$B$7,17),'Carga Presup.'!$E$5:$V$69261,12,0),"") | D34: =IFERROR(VLOOKUP(CONCATENATE($D$3,$B$7,17),'Carga Presup.'!$E$5:$V$69261,13,0),"") | E34: =IFERROR(D34*C34,"")
B35: =IFERROR(VLOOKUP(CONCATENATE($D$3,$B$7,18),'Carga Presup.'!$E$5:$V$69261,7,0),"") | C35: =IFERROR(VLOOKUP(CONCATENATE($D$3,$B$7,18),'Carga Presup.'!$E$5:$V$69261,12,0),"") | D35: =IFERROR(VLOOKUP(CONCATENATE($D$3,$B$7,18),'Carga Presup.'!$E$5:$V$69261,13,0),"") | E35: =IFERROR(D35*C35,"")
A36: =IFERROR(VLOOKUP(CONCATENATE($D$3,$B$7,19),'Carga Presup.'!$E$5:$V$69261,6,0),"") | B36: =IFERROR(VLOOKUP(CONCATENATE($D$3,$B$7,19),'Carga Presup.'!$E$5:$V$69261,7,0),"") | C36: =IFERROR(VLOOKUP(CONCATENATE($D$3,$B$7,19),'Carga Presup.'!$E$5:$V$69261,12,0),"") | D36: =IFERROR(VLOOKUP(CONCATENATE($D$3,$B$7,19),'Carga Presup.'!$E$5:$V$69261,13,0),"") | E36: =IFERROR(D36*C36,"")
A37: =IFERROR(VLOOKUP(CONCATENATE($D$3,$B$7,20),'Carga Presup.'!$E$5:$V$69261,6,0),"") | B37: =IFERROR(VLOOKUP(CONCATENATE($D$3,$B$7,20),'Carga Presup.'!$E$5:$V$69261,7,0),"") | C37: =IFERROR(VLOOKUP(CONCATENATE($D$3,$B$7,20),'Carga Presup.'!$E$5:$V$69261,12,0),"") | D37: =IFERROR(VLOOKUP(CONCATENATE($D$3,$B$7,20),'Carga Presup.'!$E$5:$V$69261,13,0),"") | E37: =IFERROR(D37*C37,"")
A38: =IFERROR(VLOOKUP(CONCATENATE($D$3,$B$7,21),'Carga Presup.'!$E$5:$V$69261,6,0),"") | B38: =IFERROR(VLOOKUP(CONCATENATE($D$3,$B$7,21),'Carga Presup.'!$E$5:$V$69261,7,0),"") | C38: =IFERROR(VLOOKUP(CONCATENATE($D$3,$B$7,21),'Carga Presup.'!$E$5:$V$69261,12,0),"") | D38: =IFERROR(VLOOKUP(CONCATENATE($D$3,$B$7,21),'Carga Presup.'!$E$5:$V$69261,13,0),"") | E38: =IFERROR(D38*C38,"")
A41: Este presupuesto tiene validez por 15 días. | E41: TOTAL
E42: =SUM(E17:E39) -> 236000
H209: Service completo del vehiculo. El valor del servicio abarca el control de mas de 50 puntos del automovil.
A215: 64 | C215: 45231 | D215: Boschiaso Antonella | F215: JWE950 | G215: VW Vento 2.5 | H215: Service completo del vehiculo. El valor del servicio abarca el control de mas de 50 puntos del automovil. | K215: Kit de filtros | P215: 1 | Q215: 59000 | S215: 1 | T215: 41400
A216: 64 | K216: Aceite motor 5w40 | P216: 6 | Q216: 6950
M1791: taller
AB3599: 200000

Sheet % recargo
A1: PORCENTAJES DE REFERENCIA | D1: REFERENCIA MO
A2: REPUESTO | B2: % | D2: TRABAJO | E2: COSTO
A3: TODOS LOS REPUESTOS | B3: 0.2 | D3: HORA | E3: 4500
D4: SERVICE AUTO | E4: 5600
D5: SERVICE CAMIONETA | E5: 6500
D6: DIAGNÓSTICO (conectar scaner) | E6: 0

Sheet Base rep.
A1: CÓDIGO | B1: DESCRIPCIÓN
A2: 1 | B2: ALINEACION Y BALANCEO
A3: 2 | B3: SERVICE
A4: 3 | B4: TREN DELANTERO
A5: 4 | B5: SERVICIO TERCERO
A6: 5 | B6: MANO DE OBRA
