Workbook

Sheet Pagos clientes
D2: PAGOS DE CLIENTES
G3: =MATCH(G4,'Carga Remito.'!A3:AQ3,0) -> 37
A4: Nro comp. | B4: Fecha | C4: Meses de deuda | D4: Cliente | E4: Dominio | F4: Vehículo | G4: Total trabajo | H4: Fecha final pago | I4: Método pago | J4: Deuda | K4: Entrega 1 | L4: Fecha 1 | M4: Nº recibo | N4: Entrega 2 | O4: Fecha 2 | P4: Nº recibo | Q4: Entrega 3 | R4: Fecha 3 | S4: Nº recibo | T4: Entrega 4 | U4: Fecha 4 | V4: Nº recibo | W4: Entrega 5 | X4: Fecha 5 | Y4: Nº recibo | Z4: Entrega 6 | AA4: Fecha 6 | AB4: Nº recibo | AC4: Comentraio
A5: 1111 | B5: =VLOOKUP(A5,'Carga Remito.'!A$4:AK$16957,3,0) -> 45111 | C5: =ROUNDUP(IF((TODAY()-B5)<30,0,(TODAY()-B5)/30),0) -> 18 | D5: =VLOOKUP(A5,'Carga Remito.'!A$4:AK$15957,4,0) -> Gonzalez Alberto | E5: =VLOOKUP(A5,'Carga Remito.'!A$4:AK$2258,6,0) -> 0 | F5: =VLOOKUP(A5,'Carga Remito.'!A$4:AK$1858,7,0) -> Cronos | G5: =VLOOKUP(A5,'Carga Remito.'!A$4:AK$20957,MATCH(G$4,'Carga Remito.'!A$3:AQ$3,0),0) -> 64450 | I5: Efectivo | J5: =+G5-K5-N5-Q5-T5-W5-Z5 -> 0 | K5: 64450 | L5: 45112
A6: 1114 | B6: =VLOOKUP(A6,'Carga Remito.'!A$4:AK$16957,3,0) -> 45112 | C6: =ROUNDUP(IF((TODAY()-B6)<30,0,(TODAY()-B6)/30),0) -> 18 | D6: =VLOOKUP(A6,'Carga Remito.'!A$4:AK$15957,4,0) -> Hoyos Pato | E6: =VLOOKUP(A6,'Carga Remito.'!A$4:AK$2258,6,0) -> 0 | F6: =VLOOKUP(A6,'Carga Remito.'!A$4:AK$1858,7,0) -> Partner | G6: =VLOOKUP(A6,'Carga Remito.'!A$4:AK$20957,MATCH(G$4,'Carga Remito.'!A$3:AQ$3,0),0) -> 28000 | I6: Efectivo | J6: =+G6-K6-N6-Q6-T6-W6-Z6 -> 0 | K6: 28000 | L6: 45141
A7: 1117 | B7: =VLOOKUP(A7,'Carga Remito.'!A$4:AK$16957,3,0) -> 45112 | C7: =ROUNDUP(IF((TODAY()-B7)<30,0,(TODAY()-B7)/30),0) -> 18 | D7: =VLOOKUP(A7,'Carga Remito.'!A$4:AK$15957,4,0) -> Pisani Nicolas | E7: =VLOOKUP(A7,'Carga Remito.'!A$4:AK$2258,6,0) -> 0 | F7: =VLOOKUP(A7,'Carga Remito.'!A$4:AK$1858,7,0) -> Megane | G7: =VLOOKUP(A7,'Carga Remito.'!A$4:AK$20957,MATCH(G$4,'Carga Remito.'!A$3:AQ$3,0),0) -> 51260 | I7: Efectivo | J7: =+G7-K7-N7-Q7-T7-W7-Z7 -> 0 | K7: 51260 | L7: 45134
A8: 1118 | B8: =VLOOKUP(A8,'Carga Remito.'!A$4:AK$16957,3,0) -> 45112 | C8: =ROUNDUP(IF((TODAY()-B8)<30,0,(TODAY()-B8)/30),0) -> 18 | D8: =VLOOKUP(A8,'Carga Remito.'!A$4:AK$15957,4,0) -> Acotto Jorge | E8: =VLOOKUP(A8,'Carga Remito.'!A$4:AK$2258,6,0) -> 0 | F8: =VLOOKUP(A8,'Carga Remito.'!A$4:AK$1858,7,0) -> 147 | G8: =VLOOKUP(A8,'Carga Remito.'!A$4:AK$20957,MATCH(G$4,'Carga Remito.'!A$3:AQ$3,0),0) -> 32040 | I8: Efectivo | J8: =+G8-K8-N8-Q8-T8-W8-Z8 -> 0 | K8: 32040 | L8: 45118
A9: 1119 | B9: =VLOOKUP(A9,'Carga Remito.'!A$4:AK$16957,3,0) -> 45113 | C9: =ROUNDUP(IF((TODAY()-B9)<30,0,(TODAY()-B9)/30),0) -> 18 | D9: =VLOOKUP(A9,'Carga Remito.'!A$4:AK$15957,4,0) -> Crocinelli Carlos | E9: =VLOOKUP(A9,'Carga Remito.'!A$4:AK$2258,6,0) -> FXU688 | F9: =VLOOKUP(A9,'Carga Remito.'!A$4:AK$1858,7,0) -> GolTrend | G9: =VLOOKUP(A9,'Carga Remito.'!A$4:AK$20957,MATCH(G$4,'Carga Remito.'!A$3:AQ$3,0),0) -> 53695 | J9: =+G9-K9-N9-Q9-T9-W9-Z9 -> 0 | K9: 53695 | L9: 45129
A10: 1120 | B10: =VLOOKUP(A10,'Carga Remito.'!A$4:AK$16957,3,0) -> 45114 | C10: =ROUNDUP(IF((TODAY()-B10)<30,0,(TODAY()-B10)/30),0) -> 18 | D10: =VLOOKUP(A10,'Carga Remito.'!A$4:AK$15957,4,0) -> Martin Jose | E10: =VLOOKUP(A10,'Carga Remito.'!A$4:AK$2258,6,0) -> AC369PI | F10: =VLOOKUP(A10,'Carga Remito.'!A$4:AK$1858,7,0) -> 0 | G10: =VLOOKUP(A10,'Carga Remito.'!A$4:AK$20957,MATCH(G$4,'Carga Remito.'!A$3:AQ$3,0),0) -> 102000 | I10: Efectivo | J10: =+G10-K10-N10-Q10-T10-W10-Z10 -> 0 | K10: 102000 | L10: 45114
A11: 1121 | B11: =VLOOKUP(A11,'Carga Remito.'!A$4:AK$16957,3,0) -> 45114 | C11: =ROUNDUP(IF((TODAY()-B11)<30,0,(TODAY()-B11)/30),0) -> 18 | D11: =VLOOKUP(A11,'Carga Remito.'!A$4:AK$15957,4,0) -> Formini Victor | E11: =VLOOKUP(A11,'Carga Remito.'!A$4:AK$2258,6,0) -> 0 | F11: =VLOOKUP(A11,'Carga Remito.'!A$4:AK$1858,7,0) -> 0 | G11: =VLOOKUP(A11,'Carga Remito.'!A$4:AK$20957,MATCH(G$4,'Carga Remito.'!A$3:AQ$3,0),0) -> 10900 | I11: Efectivo | J11: =+G11-K11-N11-Q11-T11-W11-Z11 -> 0 | K11: 10900 | L11: 45114
A12: 1122 | B12: =VLOOKUP(A12,'Carga Remito.'!A$4:AK$16957,3,0) -> 45114 | C12: =ROUNDUP(IF((TODAY()-B12)<30,0,(TODAY()-B12)/30),0) -> 18 | D12: =VLOOKUP(A12,'Carga Remito.'!A$4:AK$15957,4,0) -> Carrara Luis (bocha) | E12: =VLOOKUP(A12,'Carga Remito.'!A$4:AK$2258,6,0) -> AD225VD | F12: =VLOOKUP(A12,'Carga Remito.'!A$4:AK$1858,7,0) -> Citroen C4 LOUNGE | G12: =VLOOKUP(A12,'Carga Remito.'!A$4:AK$20957,MATCH(G$4,'Carga Remito.'!A$3:AQ$3,0),0) -> 46000 | J12: =+G12-K12-N12-Q12-T12-W12-Z12 -> 0 | K12: 21800 | L12: 45148 | N12: 4200 | O12: 45131 | Q12: 20000 | R12: 45227
A13: 1123 | B13: =VLOOKUP(A13,'Carga Remito.'!A$4:AK$16957,3,0) -> 45114 | C13: =ROUNDUP(IF((TODAY()-B13)<30,0,(TODAY()-B13)/30),0) -> 18 | D13: =VLOOKUP(A13,'Carga Remito.'!A$4:AK$15957,4,0) -> Muñoz | E13: =VLOOKUP(A13,'Carga Remito.'!A$4:AK$2258,6,0) -> AO556QH | F13: =VLOOKUP(A13,'Carga Remito.'!A$4:AK$1858,7,0) -> Fiat Movie | G13: =VLOOKUP(A13,'Carga Remito.'!A$4:AK$20957,MATCH(G$4,'Carga Remito.'!A$3:AQ$3,0),0) -> 56700 | I13: Efectivo | J13: =+G13-K13-N13-Q13-T13-W13-Z13 -> 0 | K13: 56700 | L13: 45117
A14: 1124 | B14: =VLOOKUP(A14,'Carga Remito.'!A$4:AK$16957,3,0) -> 45114 | C14: =ROUNDUP(IF((TODAY()-B14)<30,0,(TODAY()-B14)/30),0) -> 18 | D14: =VLOOKUP(A14,'Carga Remito.'!A$4:AK$15957,4,0) -> Barroso Ruben | E14: =VLOOKUP(A14,'Carga Remito.'!A$4:AK$2258,6,0) -> 0 | F14: =VLOOKUP(A14,'Carga Remito.'!A$4:AK$1858,7,0) -> Ford Ranger | G14: =VLOOKUP(A14,'Carga Remito.'!A$4:AK$20957,MATCH(G$4,'Carga Remito.'!A$3:AQ$3,0),0) -> 153300 | I14: Efectivo | J14: =+G14-K14-N14-Q14-T14-W14-Z14 -> 0 | K14: 50000 | L14: 45146 | N14: 50000 | O14: 45182 | Q14: 50000 | R14: 45208 | T14: 3300 | U14: 45243
A15: 1125 | B15: =VLOOKUP(A15,'Carga Remito.'!A$4:AK$16957,3,0) -> 45114 | C15: =ROUNDUP(IF((TODAY()-B15)<30,0,(TODAY()-B15)/30),0) -> 18 | D15: =VLOOKUP(A15,'Carga Remito.'!A$4:AK$15957,4,0) -> Barroso Willy | E15: =VLOOKUP(A15,'Carga Remito.'!A$4:AK$2258,6,0) -> AE154FT | F15: =VLOOKUP(A15,'Carga Remito.'!A$4:AK$1858,7,0) -> Chevrolet Prisma | G15: =VLOOKUP(A15,'Carga Remito.'!A$4:AK$20957,MATCH(G$4,'Carga Remito.'!A$3:AQ$3,0),0) -> 98000 | J15: =+G15-K15-N15-Q15-T15-W15-Z15 -> 0 | K15: 98000 | L15: 45248
A16: 1126 | B16: =VLOOKUP(A16,'Carga Remito.'!A$4:AK$16957,3,0) -> 45117 | C16: =ROUNDUP(IF((TODAY()-B16)<30,0,(TODAY()-B16)/30),0) -> 18 | D16: =VLOOKUP(A16,'Carga Remito.'!A$4:AK$15957,4,0) -> Barroso Willy | E16: =VLOOKUP(A16,'Carga Remito.'!A$4:AK$2258,6,0) -> AE154FT | F16: =VLOOKUP(A16,'Carga Remito.'!A$4:AK$1858,7,0) -> Chevrolet Prisma | G16: =VLOOKUP(A16,'Carga Remito.'!A$4:AK$20957,MATCH(G$4,'Carga Remito.'!A$3:AQ$3,0),0) -> 220800 | J16: =+G16-K16-N16-Q16-T16-W16-Z16 -> 0 | K16: 100000 | L16: 45248 | N16: 100000 | O16: 45299 | Q16: 20800 | R16: 45310
A17: 1127 | B17: =VLOOKUP(A17,'Carga Remito.'!A$4:AK$16957,3,0) -> 45117 | C17: =ROUNDUP(IF((TODAY()-B17)<30,0,(TODAY()-B17)/30),0) -> 18 | D17: =VLOOKUP(A17,'Carga Remito.'!A$4:AK$15957,4,0) -> Lucero Adrian | E17: =VLOOKUP(A17,'Carga Remito.'!A$4:AK$2258,6,0) -> EFR454 | F17: =VLOOKUP(A17,'Carga Remito.'!A$4:AK$1858,7,0) -> Palio | G17: =VLOOKUP(A17,'Carga Remito.'!A$4:AK$20957,MATCH(G$4,'Carga Remito.'!A$3:AQ$3,0),0) -> 59250 | J17: =+G17-K17-N17-Q17-T17-W17-Z17 -> 0 | K17: 59250 | L17: 45120 | AC17: se le descontó un 10%
A18: 1128 | B18: =VLOOKUP(A18,'Carga Remito.'!A$4:AK$16957,3,0) -> 45117 | C18: =ROUNDUP(IF((TODAY()-B18)<30,0,(TODAY()-B18)/30),0) -> 18 | D18: =VLOOKUP(A18,'Carga Remito.'!A$4:AK$15957,4,0) -> Rodriguez Jorge | E18: =VLOOKUP(A18,'Carga Remito.'!A$4:AK$2258,6,0) -> AA255TK | F18: =VLOOKUP(A18,'Carga Remito.'!A$4:AK$1858,7,0) -> Siena | G18: =VLOOKUP(A18,'Carga Remito.'!A$4:AK$20957,MATCH(G$4,'Carga Remito.'!A$3:AQ$3,0),0) -> 103355 | I18: Transferencia | J18: =+G18-K18-N18-Q18-T18-W18-Z18 -> 0 | K18: 103355 | L18: 45119
A19: 1130 | B19: =VLOOKUP(A19,'Carga Remito.'!A$4:AK$16957,3,0) -> 45118 | C19: =ROUNDUP(IF((TODAY()-B19)<30,0,(TODAY()-B19)/30),0) -> 18 | D19: =VLOOKUP(A19,'Carga Remito.'!A$4:AK$15957,4,0) -> Lang Juan Pablo | E19: =VLOOKUP(A19,'Carga Remito.'!A$4:AK$2258,6,0) -> 0 | F19: =VLOOKUP(A19,'Carga Remito.'!A$4:AK$1858,7,0) -> Toro | G19: =VLOOKUP(A19,'Carga Remito.'!A$4:AK$20957,MATCH(G$4,'Carga Remito.'!A$3:AQ$3,0),0) -> 214300 | I19: transferencia | J19: =+G19-K19-N19-Q19-T19-W19-Z19 -> 0 | K19: 114300 | L19: 45138 | N19: 100000 | O19: 45181
A20: 1131 | B20: =VLOOKUP(A20,'Carga Remito.'!A$4:AK$16957,3,0) -> 45117 | C20: =ROUNDUP(IF((TODAY()-B20)<30,0,(TODAY()-B20)/30),0) -> 18 | D20: =VLOOKUP(A20,'Carga Remito.'!A$4:AK$15957,4,0) -> Orsa Antonio | E20: =VLOOKUP(A20,'Carga Remito.'!A$4:AK$2258,6,0) -> 0 | F20: =VLOOKUP(A20,'Carga Remito.'!A$4:AK$1858,7,0) -> Palio Wekend | G20: =VLOOKUP(A20,'Carga Remito.'!A$4:AK$20957,MATCH(G$4,'Carga Remito.'!A$3:AQ$3,0),0) -> 0 | I20: Efectivo | J20: =+G20-K20-N20-Q20-T20-W20-Z20 -> 0 | L20: 45117
A21: 1132 | B21: =VLOOKUP(A21,'Carga Remito.'!A$4:AK$16957,3,0) -> 45119 | C21: =ROUNDUP(IF((TODAY()-B21)<30,0,(TODAY()-B21)/30),0) -> 18 | D21: =VLOOKUP(A21,'Carga Remito.'!A$4:AK$15957,4,0) -> Martinich Nahuel | E21: =VLOOKUP(A21,'Carga Remito.'!A$4:AK$2258,6,0) -> AB767DV | F21: =VLOOKUP(A21,'Carga Remito.'!A$4:AK$1858,7,0) -> Palio | G21: =VLOOKUP(A21,'Carga Remito.'!A$4:AK$20957,MATCH(G$4,'Carga Remito.'!A$3:AQ$3,0),0) -> 73155 | I21: Efectivo | J21: =+G21-K21-N21-Q21-T21-W21-Z21 -> 0 | K21: 73155 | L21: 45119
A22: 1133 | B22: =VLOOKUP(A22,'Carga Remito.'!A$4:AK$16957,3,0) -> 45119 | C22: =ROUNDUP(IF((TODAY()-B22)<30,0,(TODAY()-B22)/30),0) -> 18 | D22: =VLOOKUP(A22,'Carga Remito.'!A$4:AK$15957,4,0) -> Bertaina Damian | E22: =VLOOKUP(A22,'Carga Remito.'!A$4:AK$2258,6,0) -> 0 | F22: =VLOOKUP(A22,'Carga Remito.'!A$4:AK$1858,7,0) -> Fiat Strada | G22: =VLOOKUP(A22,'Carga Remito.'!A$4:AK$20957,MATCH(G$4,'Carga Remito.'!A$3:AQ$3,0),0) -> 6500 | J22: =+G22-K22-N22-Q22-T22-W22-Z22 -> 0 | K22: 6500 | L22: 45125
A23: 1134 | B23: =VLOOKUP(A23,'Carga Remito.'!A$4:AK$16957,3,0) -> 45119 | C23: =ROUNDUP(IF((TODAY()-B23)<30,0,(TODAY()-B23)/30),0) -> 18 | D23: =VLOOKUP(A23,'Carga Remito.'!A$4:AK$15957,4,0) -> Isasis Luciana | E23: =VLOOKUP(A23,'Carga Remito.'!A$4:AK$2258,6,0) -> 0 | F23: =VLOOKUP(A23,'Carga Remito.'!A$4:AK$1858,7,0) -> Clio | G23: =VLOOKUP(A23,'Carga Remito.'!A$4:AK$20957,MATCH(G$4,'Carga Remito.'!A$3:AQ$3,0),0) -> 22000 | I23: transferencia | J23: =+G23-K23-N23-Q23-T23-W23-Z23 -> 0 | K23: 22000 | L23: 45142
A24: 1135 | B24: =VLOOKUP(A24,'Carga Remito.'!A$4:AK$16957,3,0) -> 45119 | C24: =ROUNDUP(IF((TODAY()-B24)<30,0,(TODAY()-B24)/30),0) -> 18 | D24: =VLOOKUP(A24,'Carga Remito.'!A$4:AK$15957,4,0) -> Oviedo Jose Luis | E24: =VLOOKUP(A24,'Carga Remito.'!A$4:AK$2258,6,0) -> 0 | F24: =VLOOKUP(A24,'Carga Remito.'!A$4:AK$1858,7,0) -> Daster F4R 4X4 | G24: =VLOOKUP(A24,'Carga Remito.'!A$4:AK$20957,MATCH(G$4,'Carga Remito.'!A$3:AQ$3,0),0) -> 81800 | I24: Efectivo | J24: =+G24-K24-N24-Q24-T24-W24-Z24 -> 0 | K24: 55000 | L24: 45119 | N24: 26800 | O24: 45174
A25: 1136 | B25: =VLOOKUP(A25,'Carga Remito.'!A$4:AK$16957,3,0) -> 45119 | C25: =ROUNDUP(IF((TODAY()-B25)<30,0,(TODAY()-B25)/30),0) -> 18 | D25: =VLOOKUP(A25,'Carga Remito.'!A$4:AK$15957,4,0) -> Guerrieri Gladys | E25: =VLOOKUP(A25,'Carga Remito.'!A$4:AK$2258,6,0) -> AB744KG | F25: =VLOOKUP(A25,'Carga Remito.'!A$4:AK$1858,7,0) -> Traker | G25: =VLOOKUP(A25,'Carga Remito.'!A$4:AK$20957,MATCH(G$4,'Carga Remito.'!A$3:AQ$3,0),0) -> 51620 | I25: Transferencia | J25: =+G25-K25-N25-Q25-T25-W25-Z25 -> 0 | K25: 51620 | L25: 45120
A26: 1137 | B26: =VLOOKUP(A26,'Carga Remito.'!A$4:AK$16957,3,0) -> 45119 | C26: =ROUNDUP(IF((TODAY()-B26)<30,0,(TODAY()-B26)/30),0) -> 18 | D26: =VLOOKUP(A26,'Carga Remito.'!A$4:AK$15957,4,0) -> Verdus Silvio | E26: =VLOOKUP(A26,'Carga Remito.'!A$4:AK$2258,6,0) -> LRY221 | F26: =VLOOKUP(A26,'Carga Remito.'!A$4:AK$1858,7,0) -> Aveo | G26: =VLOOKUP(A26,'Carga Remito.'!A$4:AK$20957,MATCH(G$4,'Carga Remito.'!A$3:AQ$3,0),0) -> 313300 | I26: Efectivo | J26: =+G26-K26-N26-Q26-T26-W26-Z26 -> 0 | K26: 160000 | L26: 45121 | N26: 60000 | O26: 45131 | Q26: 80000 | R26: 45152 | T26: 13300 | U26: 45160
A27: 1138 | B27: =VLOOKUP(A27,'Carga Remito.'!A$4:AK$16957,3,0) -> 45119 | C27: =ROUNDUP(IF((TODAY()-B27)<30,0,(TODAY()-B27)/30),0) -> 18 | D27: =VLOOKUP(A27,'Carga Remito.'!A$4:AK$15957,4,0) -> Gigante Joni | E27: =VLOOKUP(A27,'Carga Remito.'!A$4:AK$2258,6,0) -> 0 | F27: =VLOOKUP(A27,'Carga Remito.'!A$4:AK$1858,7,0) -> Saveiro 1,9 Diesel | G27: =VLOOKUP(A27,'Carga Remito.'!A$4:AK$20957,MATCH(G$4,'Carga Remito.'!A$3:AQ$3,0),0) -> 45600 | J27: =+G27-K27-N27-Q27-T27-W27-Z27 -> 0 | K27: 45600 | L27: 45155
A28: 1139 | B28: =VLOOKUP(A28,'Carga Remito.'!A$4:AK$16957,3,0) -> 45119 | C28: =ROUNDUP(IF((TODAY()-B28)<30,0,(TODAY()-B28)/30),0) -> 18 | D28: =VLOOKUP(A28,'Carga Remito.'!A$4:AK$15957,4,0) -> Fernandez Gerardo | E28: =VLOOKUP(A28,'Carga Remito.'!A$4:AK$2258,6,0) -> 0 | F28: =VLOOKUP(A28,'Carga Remito.'!A$4:AK$1858,7,0) -> Voyage | G28: =VLOOKUP(A28,'Carga Remito.'!A$4:AK$20957,MATCH(G$4,'Carga Remito.'!A$3:AQ$3,0),0) -> 42187.5 | J28: =+G28-K28-N28-Q28-T28-W28-Z28 -> 0 | K28: 30000 | L28: 45131 | N28: 12187.5 | O28: 45160
A29: 1140 | B29: =VLOOKUP(A29,'Carga Remito.'!A$4:AK$16957,3,0) -> 45120 | C29: =ROUNDUP(IF((TODAY()-B29)<30,0,(TODAY()-B29)/30),0) -> 17 | D29: =VLOOKUP(A29,'Carga Remito.'!A$4:AK$15957,4,0) -> Baner Abu Grillo | E29: =VLOOKUP(A29,'Carga Remito.'!A$4:AK$2258,6,0) -> 0 | F29: =VLOOKUP(A29,'Carga Remito.'!A$4:AK$1858,7,0) -> Gol Trend | G29: =VLOOKUP(A29,'Carga Remito.'!A$4:AK$20957,MATCH(G$4,'Carga Remito.'!A$3:AQ$3,0),0) -> 80700 | I29: transferencia | J29: =+G29-K29-N29-Q29-T29-W29-Z29 -> 0 | K29: 80700 | L29: 45134
A30: 1141 | B30: =VLOOKUP(A30,'Carga Remito.'!A$4:AK$16957,3,0) -> 45120 | C30: =ROUNDUP(IF((TODAY()-B30)<30,0,(TODAY()-B30)/30),0) -> 17 | D30: =VLOOKUP(A30,'Carga Remito.'!A$4:AK$15957,4,0) -> Ocampo Manolo | E30: =VLOOKUP(A30,'Carga Remito.'!A$4:AK$2258,6,0) -> 0 | F30: =VLOOKUP(A30,'Carga Remito.'!A$4:AK$1858,7,0) -> 0 | G30: =VLOOKUP(A30,'Carga Remito.'!A$4:AK$20957,MATCH(G$4,'Carga Remito.'!A$3:AQ$3,0),0) -> 0 | J30: =+G30-K30-N30-Q30-T30-W30-Z30 -> 0
A31: 1142 | B31: =VLOOKUP(A31,'Carga Remito.'!A$4:AK$16957,3,0) -> 45120 | C31: =ROUNDUP(IF((TODAY()-B31)<30,0,(TODAY()-B31)/30),0) -> 17 | D31: =VLOOKUP(A31,'Carga Remito.'!A$4:AK$15957,4,0) -> Wesek Pini | E31: =VLOOKUP(A31,'Carga Remito.'!A$4:AK$2258,6,0) -> 0 | F31: =VLOOKUP(A31,'Carga Remito.'!A$4:AK$1858,7,0) -> Agile | G31: =VLOOKUP(A31,'Carga Remito.'!A$4:AK$20957,MATCH(G$4,'Carga Remito.'!A$3:AQ$3,0),0) -> 39100 | J31: =+G31-K31-N31-Q31-T31-W31-Z31 -> 0 | K31: 39100 | L31: 45114
A32: 1143 | B32: =VLOOKUP(A32,'Carga Remito.'!A$4:AK$16957,3,0) -> 45120 | C32: =ROUNDUP(IF((TODAY()-B32)<30,0,(TODAY()-B32)/30),0) -> 17 | D32: =VLOOKUP(A32,'Carga Remito.'!A$4:AK$15957,4,0) -> Beriani Nazarena | E32: =VLOOKUP(A32,'Carga Remito.'!A$4:AK$2258,6,0) -> NEN775 | F32: =VLOOKUP(A32,'Carga Remito.'!A$4:AK$1858,7,0) -> Kangoo | G32: =VLOOKUP(A32,'Carga Remito.'!A$4:AK$20957,MATCH(G$4,'Carga Remito.'!A$3:AQ$3,0),0) -> 11300 | J32: =+G32-K32-N32-Q32-T32-W32-Z32 -> 0 | K32: 11300 | L32: 45120
A33: 1145 | B33: =VLOOKUP(A33,'Carga Remito.'!A$4:AK$16957,3,0) -> 45120 | C33: =ROUNDUP(IF((TODAY()-B33)<30,0,(TODAY()-B33)/30),0) -> 17 | D33: =VLOOKUP(A33,'Carga Remito.'!A$4:AK$15957,4,0) -> Macagno Dante | E33: =VLOOKUP(A33,'Carga Remito.'!A$4:AK$2258,6,0) -> LUX908 | F33: =VLOOKUP(A33,'Carga Remito.'!A$4:AK$1858,7,0) -> SIMBOL | G33: =VLOOKUP(A33,'Carga Remito.'!A$4:AK$20957,MATCH(G$4,'Carga Remito.'!A$3:AQ$3,0),0) -> 12000 | J33: =+G33-K33-N33-Q33-T33-W33-Z33 -> 0 | K33: 12000 | L33: 45132
A34: 1146 | B34: =VLOOKUP(A34,'Carga Remito.'!A$4:AK$16957,3,0) -> 45120 | C34: =ROUNDUP(IF((TODAY()-B34)<30,0,(TODAY()-B34)/30),0) -> 17 | D34: =VLOOKUP(A34,'Carga Remito.'!A$4:AK$15957,4,0) -> Macagno Omar | E34: =VLOOKUP(A34,'Carga Remito.'!A$4:AK$2258,6,0) -> OHT863 | F34: =VLOOKUP(A34,'Carga Remito.'!A$4:AK$1858,7,0) -> PALIO | G34: =VLOOKUP(A34,'Carga Remito.'!A$4:AK$20957,MATCH(G$4,'Carga Remito.'!A$3:AQ$3,0),0) -> 10200 | J34: =+G34-K34-N34-Q34-T34-W34-Z34 -> 0 | K34: 10200 | L34: 45132
A35: 1147 | B35: =VLOOKUP(A35,'Carga Remito.'!A$4:AK$16957,3,0) -> 45120 | C35: =ROUNDUP(IF((TODAY()-B35)<30,0,(TODAY()-B35)/30),0) -> 17 | D35: =VLOOKUP(A35,'Carga Remito.'!A$4:AK$15957,4,0) -> Weizek Susana | E35: =VLOOKUP(A35,'Carga Remito.'!A$4:AK$2258,6,0) -> JNW454 | F35: =VLOOKUP(A35,'Carga Remito.'!A$4:AK$1858,7,0) -> FOX | G35: =VLOOKUP(A35,'Carga Remito.'!A$4:AK$20957,MATCH(G$4,'Carga Remito.'!A$3:AQ$3,0),0) -> 49500 | I35: transferencia | J35: =+G35-K35-N35-Q35-T35-W35-Z35 -> 0 | K35: 49500 | L35: 45120
A36: 1148 | B36: =VLOOKUP(A36,'Carga Remito.'!A$4:AK$16957,3,0) -> 45121 | C36: =ROUNDUP(IF((TODAY()-B36)<30,0,(TODAY()-B36)/30),0) -> 17 | D36: =VLOOKUP(A36,'Carga Remito.'!A$4:AK$15957,4,0) -> Pujol Jorge | E36: =VLOOKUP(A36,'Carga Remito.'!A$4:AK$2258,6,0) -> 0 | F36: =VLOOKUP(A36,'Carga Remito.'!A$4:AK$1858,7,0) -> 0 | G36: =VLOOKUP(A36,'Carga Remito.'!A$4:AK$20957,MATCH(G$4,'Carga Remito.'!A$3:AQ$3,0),0) -> 36400 | I36: Efectivo | J36: =+G36-K36-N36-Q36-T36-W36-Z36 -> 0 | K36: 36400 | L36: 45121
A37: 1149 | B37: =VLOOKUP(A37,'Carga Remito.'!A$4:AK$16957,3,0) -> 45121 | C37: =ROUNDUP(IF((TODAY()-B37)<30,0,(TODAY()-B37)/30),0) -> 17 | D37: =VLOOKUP(A37,'Carga Remito.'!A$4:AK$15957,4,0) -> Pasini Carolina | E37: =VLOOKUP(A37,'Carga Remito.'!A$4:AK$2258,6,0) -> 0 | F37: =VLOOKUP(A37,'Carga Remito.'!A$4:AK$1858,7,0) -> C3 croos 16v | G37: =VLOOKUP(A37,'Carga Remito.'!A$4:AK$20957,MATCH(G$4,'Carga Remito.'!A$3:AQ$3,0),0) -> 17000 | I37: Efectivo | J37: =+G37-K37-N37-Q37-T37-W37-Z37 -> 0 | K37: 17000 | L37: 45121
A38: 1150 | B38: =VLOOKUP(A38,'Carga Remito.'!A$4:AK$16957,3,0) -> 45121 | C38: =ROUNDUP(IF((TODAY()-B38)<30,0,(TODAY()-B38)/30),0) -> 17 | D38: =VLOOKUP(A38,'Carga Remito.'!A$4:AK$15957,4,0) -> Carrara Sandra | E38: =VLOOKUP(A38,'Carga Remito.'!A$4:AK$2258,6,0) -> 0 | F38: =VLOOKUP(A38,'Carga Remito.'!A$4:AK$1858,7,0) -> Saveiro | G38: =VLOOKUP(A38,'Carga Remito.'!A$4:AK$20957,MATCH(G$4,'Carga Remito.'!A$3:AQ$3,0),0) -> 69961 | I38: cheque | J38: =+G38-K38-N38-Q38-T38-W38-Z38 -> 0 | K38: 69961 | L38: 45134
A39: 1151 | B39: =VLOOKUP(A39,'Carga Remito.'!A$4:AK$16957,3,0) -> 45131 | C39: =ROUNDUP(IF((TODAY()-B39)<30,0,(TODAY()-B39)/30),0) -> 17 | D39: =VLOOKUP(A39,'Carga Remito.'!A$4:AK$15957,4,0) -> Cuevas Jorge | E39: =VLOOKUP(A39,'Carga Remito.'!A$4:AK$2258,6,0) -> 0 | F39: =VLOOKUP(A39,'Carga Remito.'!A$4:AK$1858,7,0) -> Prisma | G39: =VLOOKUP(A39,'Carga Remito.'!A$4:AK$20957,MATCH(G$4,'Carga Remito.'!A$3:AQ$3,0),0) -> 16500 | I39: Transferencia | J39: =+G39-K39-N39-Q39-T39-W39-Z39 -> 0 | K39: 16500 | L39: 45133
A40: 1152 | B40: =VLOOKUP(A40,'Carga Remito.'!A$4:AK$16957,3,0) -> 45131 | C40: =ROUNDUP(IF((TODAY()-B40)<30,0,(TODAY()-B40)/30),0) -> 17 | D40: =VLOOKUP(A40,'Carga Remito.'!A$4:AK$15957,4,0) -> Weizur | E40: =VLOOKUP(A40,'Carga Remito.'!A$4:AK$2258,6,0) -> 0 | F40: =VLOOKUP(A40,'Carga Remito.'!A$4:AK$1858,7,0) -> Oroch | G40: =VLOOKUP(A40,'Carga Remito.'!A$4:AK$20957,MATCH(G$4,'Carga Remito.'!A$3:AQ$3,0),0) -> 76800 | I40: transferencia | J40: =+G40-K40-N40-Q40-T40-W40-Z40 -> 0 | K40: 76800 | L40: 45180
A41: 1153 | B41: =VLOOKUP(A41,'Carga Remito.'!A$4:AK$16957,3,0) -> 45131 | C41: =ROUNDUP(IF((TODAY()-B41)<30,0,(TODAY()-B41)/30),0) -> 17 | D41: =VLOOKUP(A41,'Carga Remito.'!A$4:AK$15957,4,0) -> Alvarez Guillermo | E41: =VLOOKUP(A41,'Carga Remito.'!A$4:AK$2258,6,0) -> 0 | F41: =VLOOKUP(A41,'Carga Remito.'!A$4:AK$1858,7,0) -> Sandero stepway MK4M | G41: =VLOOKUP(A41,'Carga Remito.'!A$4:AK$20957,MATCH(G$4,'Carga Remito.'!A$3:AQ$3,0),0) -> 13800 | I41: Efectivo | J41: =+G41-K41-N41-Q41-T41-W41-Z41 -> 0 | K41: 13800
A42: 1154 | B42: =VLOOKUP(A42,'Carga Remito.'!A$4:AK$16957,3,0) -> 45131 | C42: =ROUNDUP(IF((TODAY()-B42)<30,0,(TODAY()-B42)/30),0) -> 17 | D42: =VLOOKUP(A42,'Carga Remito.'!A$4:AK$15957,4,0) -> Alemandi Vanina | E42: =VLOOKUP(A42,'Carga Remito.'!A$4:AK$2258,6,0) -> ORL424 | F42: =VLOOKUP(A42,'Carga Remito.'!A$4:AK$1858,7,0) -> Fiat Siena | G42: =VLOOKUP(A42,'Carga Remito.'!A$4:AK$20957,MATCH(G$4,'Carga Remito.'!A$3:AQ$3,0),0) -> 54400 | I42: Transferencia | J42: =+G42-K42-N42-Q42-T42-W42-Z42 -> 0 | K42: 54400 | L42: 45133
A43: 1155 | B43: =VLOOKUP(A43,'Carga Remito.'!A$4:AK$16957,3,0) -> 45132 | C43: =ROUNDUP(IF((TODAY()-B43)<30,0,(TODAY()-B43)/30),0) -> 17 | D43: =VLOOKUP(A43,'Carga Remito.'!A$4:AK$15957,4,0) -> Penocello Vanesa | E43: =VLOOKUP(A43,'Carga Remito.'!A$4:AK$2258,6,0) -> 0 | F43: =VLOOKUP(A43,'Carga Remito.'!A$4:AK$1858,7,0) -> Ecosport | G43: =VLOOKUP(A43,'Carga Remito.'!A$4:AK$20957,MATCH(G$4,'Carga Remito.'!A$3:AQ$3,0),0) -> 8000 | I43: efectivo | J43: =+G43-K43-N43-Q43-T43-W43-Z43 -> 0 | K43: 8000 | L43: 45133
A44: 1156 | B44: =VLOOKUP(A44,'Carga Remito.'!A$4:AK$16957,3,0) -> 45132 | C44: =ROUNDUP(IF((TODAY()-B44)<30,0,(TODAY()-B44)/30),0) -> 17 | D44: =VLOOKUP(A44,'Carga Remito.'!A$4:AK$15957,4,0) -> Pereyra Miguel | E44: =VLOOKUP(A44,'Carga Remito.'!A$4:AK$2258,6,0) -> AA464YE | F44: =VLOOKUP(A44,'Carga Remito.'!A$4:AK$1858,7,0) -> Peugeot 408 HDI | G44: =VLOOKUP(A44,'Carga Remito.'!A$4:AK$20957,MATCH(G$4,'Carga Remito.'!A$3:AQ$3,0),0) -> 83800 | I44: efectivo | J44: =+G44-K44-N44-Q44-T44-W44-Z44 -> 0 | K44: 60000 | L44: 45132 | N44: 23800 | O44: 45142
A45: 1157 | B45: =VLOOKUP(A45,'Carga Remito.'!A$4:AK$16957,3,0) -> 45132 | C45: =ROUNDUP(IF((TODAY()-B45)<30,0,(TODAY()-B45)/30),0) -> 17 | D45: =VLOOKUP(A45,'Carga Remito.'!A$4:AK$15957,4,0) -> Flores Juanis | E45: =VLOOKUP(A45,'Carga Remito.'!A$4:AK$2258,6,0) -> JPH200 | F45: =VLOOKUP(A45,'Carga Remito.'!A$4:AK$1858,7,0) -> Suran | G45: =VLOOKUP(A45,'Carga Remito.'!A$4:AK$20957,MATCH(G$4,'Carga Remito.'!A$3:AQ$3,0),0) -> 48900 | J45: =+G45-K45-N45-Q45-T45-W45-Z45 -> 0 | K45: 25000 | L45: 45127 | N45: 23900 | O45: 45148
A46: 1158 | B46: =VLOOKUP(A46,'Carga Remito.'!A$4:AK$16957,3,0) -> 45132 | C46: =ROUNDUP(IF((TODAY()-B46)<30,0,(TODAY()-B46)/30),0) -> 17 | D46: =VLOOKUP(A46,'Carga Remito.'!A$4:AK$15957,4,0) -> Beriani Nazarena | E46: =VLOOKUP(A46,'Carga Remito.'!A$4:AK$2258,6,0) -> NEN775 | F46: =VLOOKUP(A46,'Carga Remito.'!A$4:AK$1858,7,0) -> Kangoo | G46: =VLOOKUP(A46,'Carga Remito.'!A$4:AK$20957,MATCH(G$4,'Carga Remito.'!A$3:AQ$3,0),0) -> 223825 | J46: =+G46-K46-N46-Q46-T46-W46-Z46 -> 0 | K46: 223825 | L46: 45135
A47: 1159 | B47: =VLOOKUP(A47,'Carga Remito.'!A$4:AK$16957,3,0) -> 45133 | C47: =ROUNDUP(IF((TODAY()-B47)<30,0,(TODAY()-B47)/30),0) -> 17 | D47: =VLOOKUP(A47,'Carga Remito.'!A$4:AK$15957,4,0) -> Castro Martin | E47: =VLOOKUP(A47,'Carga Remito.'!A$4:AK$2258,6,0) -> 0 | F47: =VLOOKUP(A47,'Carga Remito.'!A$4:AK$1858,7,0) -> 0 | G47: =VLOOKUP(A47,'Carga Remito.'!A$4:AK$20957,MATCH(G$4,'Carga Remito.'!A$3:AQ$3,0),0) -> 50500 | J47: =+G47-K47-N47-Q47-T47-W47-Z47 -> 0 | K47: 50500 | L47: 45136
A48: 1160 | B48: =VLOOKUP(A48,'Carga Remito.'!A$4:AK$16957,3,0) -> 45133 | C48: =ROUNDUP(IF((TODAY()-B48)<30,0,(TODAY()-B48)/30),0) -> 17 | D48: =VLOOKUP(A48,'Carga Remito.'!A$4:AK$15957,4,0) -> Casas Juan Pablo | E48: =VLOOKUP(A48,'Carga Remito.'!A$4:AK$2258,6,0) -> NXQ974 | F48: =VLOOKUP(A48,'Carga Remito.'!A$4:AK$1858,7,0) -> Audi A4 | G48: =VLOOKUP(A48,'Carga Remito.'!A$4:AK$20957,MATCH(G$4,'Carga Remito.'!A$3:AQ$3,0),0) -> 86850 | J48: =+G48-K48-N48-Q48-T48-W48-Z48 -> 0 | K48: 86850 | L48: 45138
A49: 1161 | B49: =VLOOKUP(A49,'Carga Remito.'!A$4:AK$16957,3,0) -> 45133 | C49: =ROUNDUP(IF((TODAY()-B49)<30,0,(TODAY()-B49)/30),0) -> 17 | D49: =VLOOKUP(A49,'Carga Remito.'!A$4:AK$15957,4,0) -> Suarez Luchi | E49: =VLOOKUP(A49,'Carga Remito.'!A$4:AK$2258,6,0) -> AA887FX | F49: =VLOOKUP(A49,'Carga Remito.'!A$4:AK$1858,7,0) -> Ranger | G49: =VLOOKUP(A49,'Carga Remito.'!A$4:AK$20957,MATCH(G$4,'Carga Remito.'!A$3:AQ$3,0),0) -> 102615 | I49: cheque | J49: =+G49-K49-N49-Q49-T49-W49-Z49 -> 0 | K49: 102615 | L49: 45154
A50: 1162 | B50: =VLOOKUP(A50,'Carga Remito.'!A$4:AK$16957,3,0) -> 45133 | C50: =ROUNDUP(IF((TODAY()-B50)<30,0,(TODAY()-B50)/30),0) -> 17 | D50: =VLOOKUP(A50,'Carga Remito.'!A$4:AK$15957,4,0) -> Mendizabal Alicia | E50: =VLOOKUP(A50,'Carga Remito.'!A$4:AK$2258,6,0) -> IGI953 | F50: =VLOOKUP(A50,'Carga Remito.'!A$4:AK$1858,7,0) -> Gol | G50: =VLOOKUP(A50,'Carga Remito.'!A$4:AK$20957,MATCH(G$4,'Carga Remito.'!A$3:AQ$3,0),0) -> 25000 | I50: Efectivo | J50: =+G50-K50-N50-Q50-T50-W50-Z50 -> 0 | K50: 25000 | L50: 45134
A51: 1163 | B51: =VLOOKUP(A51,'Carga Remito.'!A$4:AK$16957,3,0) -> 45136 | C51: =ROUNDUP(IF((TODAY()-B51)<30,0,(TODAY()-B51)/30),0) -> 17 | D51: =VLOOKUP(A51,'Carga Remito.'!A$4:AK$15957,4,0) -> Transporte del Interior | E51: =VLOOKUP(A51,'Carga Remito.'!A$4:AK$2258,6,0) -> 553 | F51: =VLOOKUP(A51,'Carga Remito.'!A$4:AK$1858,7,0) -> 0 | G51: =VLOOKUP(A51,'Carga Remito.'!A$4:AK$20957,MATCH(G$4,'Carga Remito.'!A$3:AQ$3,0),0) -> 30000 | I51: cheque | J51: =+G51-K51-N51-Q51-T51-W51-Z51 -> 0 | K51: 30000
A52: 1164 | B52: =VLOOKUP(A52,'Carga Remito.'!A$4:AK$16957,3,0) -> 45136 | C52: =ROUNDUP(IF((TODAY()-B52)<30,0,(TODAY()-B52)/30),0) -> 17 | D52: =VLOOKUP(A52,'Carga Remito.'!A$4:AK$15957,4,0) -> Transporte del Interior | E52: =VLOOKUP(A52,'Carga Remito.'!A$4:AK$2258,6,0) -> 703 | F52: =VLOOKUP(A52,'Carga Remito.'!A$4:AK$1858,7,0) -> Kangoo | G52: =VLOOKUP(A52,'Carga Remito.'!A$4:AK$20957,MATCH(G$4,'Carga Remito.'!A$3:AQ$3,0),0) -> 100000 | I52: cheque | J52: =+G52-K52-N52-Q52-T52-W52-Z52 -> 0 | K52: 100000
A53: 1165 | B53: =VLOOKUP(A53,'Carga Remito.'!A$4:AK$16957,3,0) -> 45136 | C53: =ROUNDUP(IF((TODAY()-B53)<30,0,(TODAY()-B53)/30),0) -> 17 | D53: =VLOOKUP(A53,'Carga Remito.'!A$4:AK$15957,4,0) -> Transporte del Interior | E53: =VLOOKUP(A53,'Carga Remito.'!A$4:AK$2258,6,0) -> AE993CF | F53: =VLOOKUP(A53,'Carga Remito.'!A$4:AK$1858,7,0) -> Fiorino | G53: =VLOOKUP(A53,'Carga Remito.'!A$4:AK$20957,MATCH(G$4,'Carga Remito.'!A$3:AQ$3,0),0) -> 30000 | I53: cheque | J53: =+G53-K53-N53-Q53-T53-W53-Z53 -> 0 | K53: 30000
A54: 1166 | B54: =VLOOKUP(A54,'Carga Remito.'!A$4:AK$16957,3,0) -> 45136 | C54: =ROUNDUP(IF((TODAY()-B54)<30,0,(TODAY()-B54)/30),0) -> 17 | D54: =VLOOKUP(A54,'Carga Remito.'!A$4:AK$15957,4,0) -> Transporte del Interior | E54: =VLOOKUP(A54,'Carga Remito.'!A$4:AK$2258,6,0) -> AF044MU | F54: =VLOOKUP(A54,'Carga Remito.'!A$4:AK$1858,7,0) -> Fiorino | G54: =VLOOKUP(A54,'Carga Remito.'!A$4:AK$20957,MATCH(G$4,'Carga Remito.'!A$3:AQ$3,0),0) -> 28000 | I54: cheque | J54: =+G54-K54-N54-Q54-T54-W54-Z54 -> 0 | K54: 28000
A55: 1167 | B55: =VLOOKUP(A55,'Carga Remito.'!A$4:AK$16957,3,0) -> 45134 | C55: =ROUNDUP(IF((TODAY()-B55)<30,0,(TODAY()-B55)/30),0) -> 17 | D55: =VLOOKUP(A55,'Carga Remito.'!A$4:AK$15957,4,0) -> Transporte del Interior | E55: =VLOOKUP(A55,'Carga Remito.'!A$4:AK$2258,6,0) -> 0 | F55: =VLOOKUP(A55,'Carga Remito.'!A$4:AK$1858,7,0) -> 0 | G55: =VLOOKUP(A55,'Carga Remito.'!A$4:AK$20957,MATCH(G$4,'Carga Remito.'!A$3:AQ$3,0),0) -> 4500 | J55: =+G55-K55-N55-Q55-T55-W55-Z55 -> 0 | K55: 4500 | L55: 45120
A56: 1168 | B56: =VLOOKUP(A56,'Carga Remito.'!A$4:AK$16957,3,0) -> 45135 | C56: =ROUNDUP(IF((TODAY()-B56)<30,0,(TODAY()-B56)/30),0) -> 17 | D56: =VLOOKUP(A56,'Carga Remito.'!A$4:AK$15957,4,0) -> Transporte del Interior | E56: =VLOOKUP(A56,'Carga Remito.'!A$4:AK$2258,6,0) -> KVB553 | F56: =VLOOKUP(A56,'Carga Remito.'!A$4:AK$1858,7,0) -> Kangoo | G56: =VLOOKUP(A56,'Carga Remito.'!A$4:AK$20957,MATCH(G$4,'Carga Remito.'!A$3:AQ$3,0),0) -> 8000 | I56: cheque | J56: =+G56-K56-N56-Q56-T56-W56-Z56 -> 0 | K56: 8000
A57: 1169 | B57: =VLOOKUP(A57,'Carga Remito.'!A$4:AK$16957,3,0) -> 45135 | C57: =ROUNDUP(IF((TODAY()-B57)<30,0,(TODAY()-B57)/30),0) -> 17 | D57: =VLOOKUP(A57,'Carga Remito.'!A$4:AK$15957,4,0) -> Creativiti S.A.S | E57: =VLOOKUP(A57,'Carga Remito.'!A$4:AK$2258,6,0) -> AE573YM | F57: =VLOOKUP(A57,'Carga Remito.'!A$4:AK$1858,7,0) -> Fiorino | G57: =VLOOKUP(A57,'Carga Remito.'!A$4:AK$20957,MATCH(G$4,'Carga Remito.'!A$3:AQ$3,0),0) -> 89400 | J57: =+G57-K57-N57-Q57-T57-W57-Z57 -> 0 | K57: 89400 | L57: 45142
A58: 1170 | B58: =VLOOKUP(A58,'Carga Remito.'!A$4:AK$16957,3,0) -> 45135 | C58: =ROUNDUP(IF((TODAY()-B58)<30,0,(TODAY()-B58)/30),0) -> 17 | D58: =VLOOKUP(A58,'Carga Remito.'!A$4:AK$15957,4,0) -> Martin Jose | E58: =VLOOKUP(A58,'Carga Remito.'!A$4:AK$2258,6,0) -> AA641WW | F58: =VLOOKUP(A58,'Carga Remito.'!A$4:AK$1858,7,0) -> Tucson | G58: =VLOOKUP(A58,'Carga Remito.'!A$4:AK$20957,MATCH(G$4,'Carga Remito.'!A$3:AQ$3,0),0) -> 68150 | J58: =+G58-K58-N58-Q58-T58-W58-Z58 -> 0 | K58: 68150 | L58: 45135
A59: 1172 | B59: =VLOOKUP(A59,'Carga Remito.'!A$4:AK$16957,3,0) -> 45135 | C59: =ROUNDUP(IF((TODAY()-B59)<30,0,(TODAY()-B59)/30),0) -> 17 | D59: =VLOOKUP(A59,'Carga Remito.'!A$4:AK$15957,4,0) -> Di Genaro Julio | E59: =VLOOKUP(A59,'Carga Remito.'!A$4:AK$2258,6,0) -> ONT985 | F59: =VLOOKUP(A59,'Carga Remito.'!A$4:AK$1858,7,0) -> Focus Kinetic | G59: =VLOOKUP(A59,'Carga Remito.'!A$4:AK$20957,MATCH(G$4,'Carga Remito.'!A$3:AQ$3,0),0) -> 70600 | I59: Efectivo | J59: =+G59-K59-N59-Q59-T59-W59-Z59 -> 0 | K59: 70600 | L59: 45138
A60: 1173 | B60: =VLOOKUP(A60,'Carga Remito.'!A$4:AK$16957,3,0) -> 45135 | C60: =ROUNDUP(IF((TODAY()-B60)<30,0,(TODAY()-B60)/30),0) -> 17 | D60: =VLOOKUP(A60,'Carga Remito.'!A$4:AK$15957,4,0) -> Transporte del Interior | E60: =VLOOKUP(A60,'Carga Remito.'!A$4:AK$2258,6,0) -> KVB553 | F60: =VLOOKUP(A60,'Carga Remito.'!A$4:AK$1858,7,0) -> 0 | G60: =VLOOKUP(A60,'Carga Remito.'!A$4:AK$20957,MATCH(G$4,'Carga Remito.'!A$3:AQ$3,0),0) -> 4500 | I60: efectivo | J60: =+G60-K60-N60-Q60-T60-W60-Z60 -> 0 | K60: 4500
A61: 1174 | B61: =VLOOKUP(A61,'Carga Remito.'!A$4:AK$16957,3,0) -> 45136 | C61: =ROUNDUP(IF((TODAY()-B61)<30,0,(TODAY()-B61)/30),0) -> 17 | D61: =VLOOKUP(A61,'Carga Remito.'!A$4:AK$15957,4,0) -> Irouleguy Daniel | E61: =VLOOKUP(A61,'Carga Remito.'!A$4:AK$2258,6,0) -> 0 | F61: =VLOOKUP(A61,'Carga Remito.'!A$4:AK$1858,7,0) -> 147 | G61: =VLOOKUP(A61,'Carga Remito.'!A$4:AK$20957,MATCH(G$4,'Carga Remito.'!A$3:AQ$3,0),0) -> 36800 | I61: Efectivo | J61: =+G61-K61-N61-Q61-T61-W61-Z61 -> 0 | K61: 36800 | L61: 45153
A62: 1175 | B62: =VLOOKUP(A62,'Carga Remito.'!A$4:AK$16957,3,0) -> 45138 | C62: =ROUNDUP(IF((TODAY()-B62)<30,0,(TODAY()-B62)/30),0) -> 17 | D62: =VLOOKUP(A62,'Carga Remito.'!A$4:AK$15957,4,0) -> Vilares Roberto | E62: =VLOOKUP(A62,'Carga Remito.'!A$4:AK$2258,6,0) -> PDP290 | F62: =VLOOKUP(A62,'Carga Remito.'!A$4:AK$1858,7,0) -> Ecosport | G62: =VLOOKUP(A62,'Carga Remito.'!A$4:AK$20957,MATCH(G$4,'Carga Remito.'!A$3:AQ$3,0),0) -> 58800 | I62: Efectivo | J62: =+G62-K62-N62-Q62-T62-W62-Z62 -> 0 | K62: 58800 | L62: 45139
A63: 1176 | B63: =VLOOKUP(A63,'Carga Remito.'!A$4:AK$16957,3,0) -> 45138 | C63: =ROUNDUP(IF((TODAY()-B63)<30,0,(TODAY()-B63)/30),0) -> 17 | D63: =VLOOKUP(A63,'Carga Remito.'!A$4:AK$15957,4,0) -> Integral Agropecuaria | E63: =VLOOKUP(A63,'Carga Remito.'!A$4:AK$2258,6,0) -> AD813TG | F63: =VLOOKUP(A63,'Carga Remito.'!A$4:AK$1858,7,0) -> Toyota | G63: =VLOOKUP(A63,'Carga Remito.'!A$4:AK$20957,MATCH(G$4,'Carga Remito.'!A$3:AQ$3,0),0) -> 96500 | I63: transferencia | J63: =+G63-K63-N63-Q63-T63-W63-Z63 -> 0 | K63: 96500 | L63: 45177
A64: 1177 | B64: =VLOOKUP(A64,'Carga Remito.'!A$4:AK$16957,3,0) -> 45138 | C64: =ROUNDUP(IF((TODAY()-B64)<30,0,(TODAY()-B64)/30),0) -> 17 | D64: =VLOOKUP(A64,'Carga Remito.'!A$4:AK$15957,4,0) -> Municipalidad Laboulaye | E64: =VLOOKUP(A64,'Carga Remito.'!A$4:AK$2258,6,0) -> AD310CN | F64: =VLOOKUP(A64,'Carga Remito.'!A$4:AK$1858,7,0) -> Gol trend | G64: =VLOOKUP(A64,'Carga Remito.'!A$4:AK$20957,MATCH(G$4,'Carga Remito.'!A$3:AQ$3,0),0) -> 51000 | I64: Efectivo | J64: =+G64-K64-N64-Q64-T64-W64-Z64 -> 0 | K64: 51000 | L64: 45140
A65: 1178 | B65: =VLOOKUP(A65,'Carga Remito.'!A$4:AK$16957,3,0) -> 45138 | C65: =ROUNDUP(IF((TODAY()-B65)<30,0,(TODAY()-B65)/30),0) -> 17 | D65: =VLOOKUP(A65,'Carga Remito.'!A$4:AK$15957,4,0) -> Transporte del Interior | E65: =VLOOKUP(A65,'Carga Remito.'!A$4:AK$2258,6,0) -> 903 | F65: =VLOOKUP(A65,'Carga Remito.'!A$4:AK$1858,7,0) -> kangoo roja | G65: =VLOOKUP(A65,'Carga Remito.'!A$4:AK$20957,MATCH(G$4,'Carga Remito.'!A$3:AQ$3,0),0) -> 20000 | I65: cheque | J65: =+G65-K65-N65-Q65-T65-W65-Z65 -> 0 | K65: 20000
A66: 1179 | B66: =VLOOKUP(A66,'Carga Remito.'!A$4:AK$16957,3,0) -> 45139 | C66: =ROUNDUP(IF((TODAY()-B66)<30,0,(TODAY()-B66)/30),0) -> 17 | D66: =VLOOKUP(A66,'Carga Remito.'!A$4:AK$15957,4,0) -> Merlo Teresa | E66: =VLOOKUP(A66,'Carga Remito.'!A$4:AK$2258,6,0) -> GZC846 | F66: =VLOOKUP(A66,'Carga Remito.'!A$4:AK$1858,7,0) -> Peugeot 307 | G66: =VLOOKUP(A66,'Carga Remito.'!A$4:AK$20957,MATCH(G$4,'Carga Remito.'!A$3:AQ$3,0),0) -> 52862.5 | I66: Efectivo | J66: =+G66-K66-N66-Q66-T66-W66-Z66 -> 0 | K66: 52862.5 | L66: 45140
A67: 1180 | B67: =VLOOKUP(A67,'Carga Remito.'!A$4:AK$16957,3,0) -> 45139 | C67: =ROUNDUP(IF((TODAY()-B67)<30,0,(TODAY()-B67)/30),0) -> 17 | D67: =VLOOKUP(A67,'Carga Remito.'!A$4:AK$15957,4,0) -> Bertaina Jesica | E67: =VLOOKUP(A67,'Carga Remito.'!A$4:AK$2258,6,0) -> AC618TP | F67: =VLOOKUP(A67,'Carga Remito.'!A$4:AK$1858,7,0) -> Fiesta Kinetic | G67: =VLOOKUP(A67,'Carga Remito.'!A$4:AK$20957,MATCH(G$4,'Carga Remito.'!A$3:AQ$3,0),0) -> 53762.5 | J67: =+G67-K67-N67-Q67-T67-W67-Z67 -> 0 | K67: 53762.5 | L67: 45149
A68: 1181 | B68: =VLOOKUP(A68,'Carga Remito.'!A$4:AK$16957,3,0) -> 45140 | C68: =ROUNDUP(IF((TODAY()-B68)<30,0,(TODAY()-B68)/30),0) -> 17 | D68: =VLOOKUP(A68,'Carga Remito.'!A$4:AK$15957,4,0) -> Medic | E68: =VLOOKUP(A68,'Carga Remito.'!A$4:AK$2258,6,0) -> 0 | F68: =VLOOKUP(A68,'Carga Remito.'!A$4:AK$1858,7,0) -> Techo Alto | G68: =VLOOKUP(A68,'Carga Remito.'!A$4:AK$20957,MATCH(G$4,'Carga Remito.'!A$3:AQ$3,0),0) -> 20000 | I68: cheque | J68: =+G68-K68-N68-Q68-T68-W68-Z68 -> 0 | K68: 20000 | L68: 45160
A69: 1182 | B69: =VLOOKUP(A69,'Carga Remito.'!A$4:AK$16957,3,0) -> 45140 | C69: =ROUNDUP(IF((TODAY()-B69)<30,0,(TODAY()-B69)/30),0) -> 17 | D69: =VLOOKUP(A69,'Carga Remito.'!A$4:AK$15957,4,0) -> Medic | E69: =VLOOKUP(A69,'Carga Remito.'!A$4:AK$2258,6,0) -> 0 | F69: =VLOOKUP(A69,'Carga Remito.'!A$4:AK$1858,7,0) -> 0 | G69: =VLOOKUP(A69,'Carga Remito.'!A$4:AK$20957,MATCH(G$4,'Carga Remito.'!A$3:AQ$3,0),0) -> 108000 | J69: =+G69-K69-N69-Q69-T69-W69-Z69 -> 0 | K69: 32000 | L69: 45160 | N69: 76000 | O69: 45183
A70: 1183 | B70: =VLOOKUP(A70,'Carga Remito.'!A$4:AK$16957,3,0) -> 45140 | C70: =ROUNDUP(IF((TODAY()-B70)<30,0,(TODAY()-B70)/30),0) -> 17 | D70: =VLOOKUP(A70,'Carga Remito.'!A$4:AK$15957,4,0) -> Goico Ana Paula | E70: =VLOOKUP(A70,'Carga Remito.'!A$4:AK$2258,6,0) -> 0 | F70: =VLOOKUP(A70,'Carga Remito.'!A$4:AK$1858,7,0) -> Corsa | G70: =VLOOKUP(A70,'Carga Remito.'!A$4:AK$20957,MATCH(G$4,'Carga Remito.'!A$3:AQ$3,0),0) -> 50000 | I70: Transferencia | J70: =+G70-K70-N70-Q70-T70-W70-Z70 -> 0 | K70: 50000 | L70: 45110
A71: 1184 | B71: =VLOOKUP(A71,'Carga Remito.'!A$4:AK$16957,3,0) -> 45140 | C71: =ROUNDUP(IF((TODAY()-B71)<30,0,(TODAY()-B71)/30),0) -> 17 | D71: =VLOOKUP(A71,'Carga Remito.'!A$4:AK$15957,4,0) -> Mainero Rodolfo | E71: =VLOOKUP(A71,'Carga Remito.'!A$4:AK$2258,6,0) -> AA621YA | F71: =VLOOKUP(A71,'Carga Remito.'!A$4:AK$1858,7,0) -> Cruze | G71: =VLOOKUP(A71,'Carga Remito.'!A$4:AK$20957,MATCH(G$4,'Carga Remito.'!A$3:AQ$3,0),0) -> 76750 | I71: transferencia | J71: =+G71-K71-N71-Q71-T71-W71-Z71 -> 0 | K71: 76750 | L71: 45153
A72: 1185 | B72: =VLOOKUP(A72,'Carga Remito.'!A$4:AK$16957,3,0) -> 45140 | C72: =ROUNDUP(IF((TODAY()-B72)<30,0,(TODAY()-B72)/30),0) -> 17 | D72: =VLOOKUP(A72,'Carga Remito.'!A$4:AK$15957,4,0) -> Duran | E72: =VLOOKUP(A72,'Carga Remito.'!A$4:AK$2258,6,0) -> 0 | F72: =VLOOKUP(A72,'Carga Remito.'!A$4:AK$1858,7,0) -> Virtus | G72: =VLOOKUP(A72,'Carga Remito.'!A$4:AK$20957,MATCH(G$4,'Carga Remito.'!A$3:AQ$3,0),0) -> 51600 | I72: transferencia | J72: =+G72-K72-N72-Q72-T72-W72-Z72 -> 0 | K72: 51600 | L72: 45141
A73: 1186 | B73: =VLOOKUP(A73,'Carga Remito.'!A$4:AK$16957,3,0) -> 45140 | C73: =ROUNDUP(IF((TODAY()-B73)<30,0,(TODAY()-B73)/30),0) -> 17 | D73: =VLOOKUP(A73,'Carga Remito.'!A$4:AK$15957,4,0) -> Moretti Anabella | E73: =VLOOKUP(A73,'Carga Remito.'!A$4:AK$2258,6,0) -> KFX524 | F73: =VLOOKUP(A73,'Carga Remito.'!A$4:AK$1858,7,0) -> Toyota | G73: =VLOOKUP(A73,'Carga Remito.'!A$4:AK$20957,MATCH(G$4,'Carga Remito.'!A$3:AQ$3,0),0) -> 135925 | I73: cheque | J73: =+G73-K73-N73-Q73-T73-W73-Z73 -> 0 | K73: 135925 | L73: 45155
A74: 1187 | B74: =VLOOKUP(A74,'Carga Remito.'!A$4:AK$16957,3,0) -> 45141 | C74: =ROUNDUP(IF((TODAY()-B74)<30,0,(TODAY()-B74)/30),0) -> 17 | D74: =VLOOKUP(A74,'Carga Remito.'!A$4:AK$15957,4,0) -> Di Genaro Julio | E74: =VLOOKUP(A74,'Carga Remito.'!A$4:AK$2258,6,0) -> 0 | F74: =VLOOKUP(A74,'Carga Remito.'!A$4:AK$1858,7,0) -> 0 | G74: =VLOOKUP(A74,'Carga Remito.'!A$4:AK$20957,MATCH(G$4,'Carga Remito.'!A$3:AQ$3,0),0) -> 43700 | I74: Efectivo | J74: =+G74-K74-N74-Q74-T74-W74-Z74 -> 0 | K74: 43700 | L74: 45145
A75: 1188 | B75: =VLOOKUP(A75,'Carga Remito.'!A$4:AK$16957,3,0) -> 45141 | C75: =ROUNDUP(IF((TODAY()-B75)<30,0,(TODAY()-B75)/30),0) -> 17 | D75: =VLOOKUP(A75,'Carga Remito.'!A$4:AK$15957,4,0) -> Di Genaro Julio | E75: =VLOOKUP(A75,'Carga Remito.'!A$4:AK$2258,6,0) -> 0 | F75: =VLOOKUP(A75,'Carga Remito.'!A$4:AK$1858,7,0) -> 0 | G75: =VLOOKUP(A75,'Carga Remito.'!A$4:AK$20957,MATCH(G$4,'Carga Remito.'!A$3:AQ$3,0),0) -> 20160 | J75: =+G75-K75-N75-Q75-T75-W75-Z75 -> 0 | K75: 20160 | L75: 45145
A76: 1189 | B76: =VLOOKUP(A76,'Carga Remito.'!A$4:AK$16957,3,0) -> 45141 | C76: =ROUNDUP(IF((TODAY()-B76)<30,0,(TODAY()-B76)/30),0) -> 17 | D76: =VLOOKUP(A76,'Carga Remito.'!A$4:AK$15957,4,0) -> Gimenez Javier | E76: =VLOOKUP(A76,'Carga Remito.'!A$4:AK$2258,6,0) -> AC172QG | F76: =VLOOKUP(A76,'Carga Remito.'!A$4:AK$1858,7,0) -> Peugeot 208 | G76: =VLOOKUP(A76,'Carga Remito.'!A$4:AK$20957,MATCH(G$4,'Carga Remito.'!A$3:AQ$3,0),0) -> 30000 | I76: CHEQUE | J76: =+G76-K76-N76-Q76-T76-W76-Z76 -> 0 | K76: 30000 | L76: 45142
A77: 1190 | B77: =VLOOKUP(A77,'Carga Remito.'!A$4:AK$16957,3,0) -> 45142 | C77: =ROUNDUP(IF((TODAY()-B77)<30,0,(TODAY()-B77)/30),0) -> 17 | D77: =VLOOKUP(A77,'Carga Remito.'!A$4:AK$15957,4,0) -> Revol Juan | E77: =VLOOKUP(A77,'Carga Remito.'!A$4:AK$2258,6,0) -> 0 | F77: =VLOOKUP(A77,'Carga Remito.'!A$4:AK$1858,7,0) -> Fox | G77: =VLOOKUP(A77,'Carga Remito.'!A$4:AK$20957,MATCH(G$4,'Carga Remito.'!A$3:AQ$3,0),0) -> 75300 | J77: =+G77-K77-N77-Q77-T77-W77-Z77 -> 0 | K77: 45300 | L77: 45153 | N77: 25000 | O77: 45187 | Q77: 5000 | R77: 45189
A78: 1191 | B78: =VLOOKUP(A78,'Carga Remito.'!A$4:AK$16957,3,0) -> 45142 | C78: =ROUNDUP(IF((TODAY()-B78)<30,0,(TODAY()-B78)/30),0) -> 17 | D78: =VLOOKUP(A78,'Carga Remito.'!A$4:AK$15957,4,0) -> Guevara Mario | E78: =VLOOKUP(A78,'Carga Remito.'!A$4:AK$2258,6,0) -> 0 | F78: =VLOOKUP(A78,'Carga Remito.'!A$4:AK$1858,7,0) -> gol | G78: =VLOOKUP(A78,'Carga Remito.'!A$4:AK$20957,MATCH(G$4,'Carga Remito.'!A$3:AQ$3,0),0) -> 9600 | I78: efectivo | J78: =+G78-K78-N78-Q78-T78-W78-Z78 -> 0 | K78: 9600 | L78: 45142
A79: 1192 | B79: =VLOOKUP(A79,'Carga Remito.'!A$4:AK$16957,3,0) -> 45142 | C79: =ROUNDUP(IF((TODAY()-B79)<30,0,(TODAY()-B79)/30),0) -> 17 | D79: =VLOOKUP(A79,'Carga Remito.'!A$4:AK$15957,4,0) -> Rodriguez Jorge | E79: =VLOOKUP(A79,'Carga Remito.'!A$4:AK$2258,6,0) -> FCE245 | F79: =VLOOKUP(A79,'Carga Remito.'!A$4:AK$1858,7,0) -> Corsa | G79: =VLOOKUP(A79,'Carga Remito.'!A$4:AK$20957,MATCH(G$4,'Carga Remito.'!A$3:AQ$3,0),0) -> 121900 | J79: =+G79-K79-N79-Q79-T79-W79-Z79 -> 0 | K79: 121900 | L79: 45147
A80: 1193 | B80: =VLOOKUP(A80,'Carga Remito.'!A$4:AK$16957,3,0) -> 45136 | C80: =ROUNDUP(IF((TODAY()-B80)<30,0,(TODAY()-B80)/30),0) -> 17 | D80: =VLOOKUP(A80,'Carga Remito.'!A$4:AK$15957,4,0) -> Borzolino Celeste | E80: =VLOOKUP(A80,'Carga Remito.'!A$4:AK$2258,6,0) -> 53932 | F80: =VLOOKUP(A80,'Carga Remito.'!A$4:AK$1858,7,0) -> 208 | G80: =VLOOKUP(A80,'Carga Remito.'!A$4:AK$20957,MATCH(G$4,'Carga Remito.'!A$3:AQ$3,0),0) -> 73100 | J80: =+G80-K80-N80-Q80-T80-W80-Z80 -> 0 | K80: 73100 | L80: 45125
A81: 1194 | B81: =VLOOKUP(A81,'Carga Remito.'!A$4:AK$16957,3,0) -> 45143 | C81: =ROUNDUP(IF((TODAY()-B81)<30,0,(TODAY()-B81)/30),0) -> 17 | D81: =VLOOKUP(A81,'Carga Remito.'!A$4:AK$15957,4,0) -> Transporte del Interior | E81: =VLOOKUP(A81,'Carga Remito.'!A$4:AK$2258,6,0) -> 635 | F81: =VLOOKUP(A81,'Carga Remito.'!A$4:AK$1858,7,0) -> 0 | G81: =VLOOKUP(A81,'Carga Remito.'!A$4:AK$20957,MATCH(G$4,'Carga Remito.'!A$3:AQ$3,0),0) -> 7500 | J81: =+G81-K81-N81-Q81-T81-W81-Z81 -> 0 | K81: 7500 | L81: 45180
A82: 1195 | B82: =VLOOKUP(A82,'Carga Remito.'!A$4:AK$16957,3,0) -> 45145 | C82: =ROUNDUP(IF((TODAY()-B82)<30,0,(TODAY()-B82)/30),0) -> 17 | D82: =VLOOKUP(A82,'Carga Remito.'!A$4:AK$15957,4,0) -> Integral Agropecuaria | E82: =VLOOKUP(A82,'Carga Remito.'!A$4:AK$2258,6,0) -> AC890MO | F82: =VLOOKUP(A82,'Carga Remito.'!A$4:AK$1858,7,0) -> Amarok | G82: =VLOOKUP(A82,'Carga Remito.'!A$4:AK$20957,MATCH(G$4,'Carga Remito.'!A$3:AQ$3,0),0) -> 265200 | I82: transferencia | J82: =+G82-K82-N82-Q82-T82-W82-Z82 -> 0 | K82: 265200 | L82: 45177
A83: 1196 | B83: =VLOOKUP(A83,'Carga Remito.'!A$4:AK$16957,3,0) -> 45145 | C83: =ROUNDUP(IF((TODAY()-B83)<30,0,(TODAY()-B83)/30),0) -> 17 | D83: =VLOOKUP(A83,'Carga Remito.'!A$4:AK$15957,4,0) -> Borello Matias | E83: =VLOOKUP(A83,'Carga Remito.'!A$4:AK$2258,6,0) -> HDI107 | F83: =VLOOKUP(A83,'Carga Remito.'!A$4:AK$1858,7,0) -> Megane | G83: =VLOOKUP(A83,'Carga Remito.'!A$4:AK$20957,MATCH(G$4,'Carga Remito.'!A$3:AQ$3,0),0) -> 190050 | J83: =+G83-K83-N83-Q83-T83-W83-Z83 -> 0 | K83: 190050 | L83: 45154
A84: 1197 | B84: =VLOOKUP(A84,'Carga Remito.'!A$4:AK$16957,3,0) -> 45145 | C84: =ROUNDUP(IF((TODAY()-B84)<30,0,(TODAY()-B84)/30),0) -> 17 | D84: =VLOOKUP(A84,'Carga Remito.'!A$4:AK$15957,4,0) -> Mendizabal Alicia | E84: =VLOOKUP(A84,'Carga Remito.'!A$4:AK$2258,6,0) -> IGI953 | F84: =VLOOKUP(A84,'Carga Remito.'!A$4:AK$1858,7,0) -> 0 | G84: =VLOOKUP(A84,'Carga Remito.'!A$4:AK$20957,MATCH(G$4,'Carga Remito.'!A$3:AQ$3,0),0) -> 18800 | J84: =+G84-K84-N84-Q84-T84-W84-Z84 -> 0 | K84: 18800 | L84: 45156
A85: 1198 | B85: =VLOOKUP(A85,'Carga Remito.'!A$4:AK$16957,3,0) -> 45145 | C85: =ROUNDUP(IF((TODAY()-B85)<30,0,(TODAY()-B85)/30),0) -> 17 | D85: =VLOOKUP(A85,'Carga Remito.'!A$4:AK$15957,4,0) -> Cane Emiliano | E85: =VLOOKUP(A85,'Carga Remito.'!A$4:AK$2258,6,0) -> 0 | F85: =VLOOKUP(A85,'Carga Remito.'!A$4:AK$1858,7,0) -> 0 | G85: =VLOOKUP(A85,'Carga Remito.'!A$4:AK$20957,MATCH(G$4,'Carga Remito.'!A$3:AQ$3,0),0) -> 67559 | J85: =+G85-K85-N85-Q85-T85-W85-Z85 -> 0 | K85: 67559 | L85: 45153
A86: 1199 | B86: =VLOOKUP(A86,'Carga Remito.'!A$4:AK$16957,3,0) -> 45146 | C86: =ROUNDUP(IF((TODAY()-B86)<30,0,(TODAY()-B86)/30),0) -> 17 | D86: =VLOOKUP(A86,'Carga Remito.'!A$4:AK$15957,4,0) -> Oyola Alberto | E86: =VLOOKUP(A86,'Carga Remito.'!A$4:AK$2258,6,0) -> 0 | F86: =VLOOKUP(A86,'Carga Remito.'!A$4:AK$1858,7,0) -> Fluence | G86: =VLOOKUP(A86,'Carga Remito.'!A$4:AK$20957,MATCH(G$4,'Carga Remito.'!A$3:AQ$3,0),0) -> 0 | J86: =+G86-K86-N86-Q86-T86-W86-Z86 -> 0
A87: 1200 | B87: =VLOOKUP(A87,'Carga Remito.'!A$4:AK$16957,3,0) -> 45146 | C87: =ROUNDUP(IF((TODAY()-B87)<30,0,(TODAY()-B87)/30),0) -> 17 | D87: =VLOOKUP(A87,'Carga Remito.'!A$4:AK$15957,4,0) -> Moretti Renato | E87: =VLOOKUP(A87,'Carga Remito.'!A$4:AK$2258,6,0) -> 0 | F87: =VLOOKUP(A87,'Carga Remito.'!A$4:AK$1858,7,0) -> S10 | G87: =VLOOKUP(A87,'Carga Remito.'!A$4:AK$20957,MATCH(G$4,'Carga Remito.'!A$3:AQ$3,0),0) -> 363100 | J87: =+G87-K87-N87-Q87-T87-W87-Z87 -> 0 | K87: 150000 | L87: 45162 | N87: 213100 | O87: 45169
A88: 1201 | B88: =VLOOKUP(A88,'Carga Remito.'!A$4:AK$16957,3,0) -> 45146 | C88: =ROUNDUP(IF((TODAY()-B88)<30,0,(TODAY()-B88)/30),0) -> 17 | D88: =VLOOKUP(A88,'Carga Remito.'!A$4:AK$15957,4,0) -> Calderon Daniel | E88: =VLOOKUP(A88,'Carga Remito.'!A$4:AK$2258,6,0) -> 0 | F88: =VLOOKUP(A88,'Carga Remito.'!A$4:AK$1858,7,0) -> Palio | G88: =VLOOKUP(A88,'Carga Remito.'!A$4:AK$20957,MATCH(G$4,'Carga Remito.'!A$3:AQ$3,0),0) -> 16850 | J88: =+G88-K88-N88-Q88-T88-W88-Z88 -> 0 | K88: 16850 | L88: 45147
A89: 1202 | B89: =VLOOKUP(A89,'Carga Remito.'!A$4:AK$16957,3,0) -> 45146 | C89: =ROUNDUP(IF((TODAY()-B89)<30,0,(TODAY()-B89)/30),0) -> 17 | D89: =VLOOKUP(A89,'Carga Remito.'!A$4:AK$15957,4,0) -> Manitto Rosana | E89: =VLOOKUP(A89,'Carga Remito.'!A$4:AK$2258,6,0) -> AF064BA | F89: =VLOOKUP(A89,'Carga Remito.'!A$4:AK$1858,7,0) -> Gol trend | G89: =VLOOKUP(A89,'Carga Remito.'!A$4:AK$20957,MATCH(G$4,'Carga Remito.'!A$3:AQ$3,0),0) -> 52900 | I89: Transferencia | J89: =+G89-K89-N89-Q89-T89-W89-Z89 -> 0 | K89: 52900 | L89: 45148
A90: 1203 | B90: =VLOOKUP(A90,'Carga Remito.'!A$4:AK$16957,3,0) -> 45146 | C90: =ROUNDUP(IF((TODAY()-B90)<30,0,(TODAY()-B90)/30),0) -> 17 | D90: =VLOOKUP(A90,'Carga Remito.'!A$4:AK$15957,4,0) -> Borello Matias | E90: =VLOOKUP(A90,'Carga Remito.'!A$4:AK$2258,6,0) -> HDY107 | F90: =VLOOKUP(A90,'Carga Remito.'!A$4:AK$1858,7,0) -> Megane | G90: =VLOOKUP(A90,'Carga Remito.'!A$4:AK$20957,MATCH(G$4,'Carga Remito.'!A$3:AQ$3,0),0) -> 0 | J90: =+G90-K90-N90-Q90-T90-W90-Z90 -> 0
A91: 1204 | B91: =VLOOKUP(A91,'Carga Remito.'!A$4:AK$16957,3,0) -> 45147 | C91: =ROUNDUP(IF((TODAY()-B91)<30,0,(TODAY()-B91)/30),0) -> 17 | D91: =VLOOKUP(A91,'Carga Remito.'!A$4:AK$15957,4,0) -> Marciali Veronica | E91: =VLOOKUP(A91,'Carga Remito.'!A$4:AK$2258,6,0) -> JXH549 | F91: =VLOOKUP(A91,'Carga Remito.'!A$4:AK$1858,7,0) -> Fiesta | G91: =VLOOKUP(A91,'Carga Remito.'!A$4:AK$20957,MATCH(G$4,'Carga Remito.'!A$3:AQ$3,0),0) -> 63900 | I91: efectivo | J91: =+G91-K91-N91-Q91-T91-W91-Z91 -> 0 | K91: 33900 | L91: 45149 | N91: 30000 | O91: 45170
A92: 1205 | B92: =VLOOKUP(A92,'Carga Remito.'!A$4:AK$16957,3,0) -> 45147 | C92: =ROUNDUP(IF((TODAY()-B92)<30,0,(TODAY()-B92)/30),0) -> 17 | D92: =VLOOKUP(A92,'Carga Remito.'!A$4:AK$15957,4,0) -> Transporte del Interior | E92: =VLOOKUP(A92,'Carga Remito.'!A$4:AK$2258,6,0) -> 127 | F92: =VLOOKUP(A92,'Carga Remito.'!A$4:AK$1858,7,0) -> 0 | G92: =VLOOKUP(A92,'Carga Remito.'!A$4:AK$20957,MATCH(G$4,'Carga Remito.'!A$3:AQ$3,0),0) -> 15000 | J92: =+G92-K92-N92-Q92-T92-W92-Z92 -> 0 | K92: 15000 | L92: 45180
A93: 1206 | B93: =VLOOKUP(A93,'Carga Remito.'!A$4:AK$16957,3,0) -> 45147 | C93: =ROUNDUP(IF((TODAY()-B93)<30,0,(TODAY()-B93)/30),0) -> 17 | D93: =VLOOKUP(A93,'Carga Remito.'!A$4:AK$15957,4,0) -> Transporte del Interior | E93: =VLOOKUP(A93,'Carga Remito.'!A$4:AK$2258,6,0) -> 127 | F93: =VLOOKUP(A93,'Carga Remito.'!A$4:AK$1858,7,0) -> 0 | G93: =VLOOKUP(A93,'Carga Remito.'!A$4:AK$20957,MATCH(G$4,'Carga Remito.'!A$3:AQ$3,0),0) -> 0 | J93: =+G93-K93-N93-Q93-T93-W93-Z93 -> 0
A94: 1207 | B94: =VLOOKUP(A94,'Carga Remito.'!A$4:AK$16957,3,0) -> 45147 | C94: =ROUNDUP(IF((TODAY()-B94)<30,0,(TODAY()-B94)/30),0) -> 17 | D94: =VLOOKUP(A94,'Carga Remito.'!A$4:AK$15957,4,0) -> Transporte del Interior | E94: =VLOOKUP(A94,'Carga Remito.'!A$4:AK$2258,6,0) -> 703 | F94: =VLOOKUP(A94,'Carga Remito.'!A$4:AK$1858,7,0) -> 0 | G94: =VLOOKUP(A94,'Carga Remito.'!A$4:AK$20957,MATCH(G$4,'Carga Remito.'!A$3:AQ$3,0),0) -> 0 | J94: =+G94-K94-N94-Q94-T94-W94-Z94 -> 0
A95: 1208 | B95: =VLOOKUP(A95,'Carga Remito.'!A$4:AK$16957,3,0) -> 45147 | C95: =ROUNDUP(IF((TODAY()-B95)<30,0,(TODAY()-B95)/30),0) -> 17 | D95: =VLOOKUP(A95,'Carga Remito.'!A$4:AK$15957,4,0) -> Transporte del Interior | E95: =VLOOKUP(A95,'Carga Remito.'!A$4:AK$2258,6,0) -> 703 | F95: =VLOOKUP(A95,'Carga Remito.'!A$4:AK$1858,7,0) -> 0 | G95: =VLOOKUP(A95,'Carga Remito.'!A$4:AK$20957,MATCH(G$4,'Carga Remito.'!A$3:AQ$3,0),0) -> 52000 | J95: =+G95-K95-N95-Q95-T95-W95-Z95 -> 0 | K95: 5000 | N95: 47000
A96: 1209 | B96: =VLOOKUP(A96,'Carga Remito.'!A$4:AK$16957,3,0) -> 45147 | C96: =ROUNDUP(IF((TODAY()-B96)<30,0,(TODAY()-B96)/30),0) -> 17 | D96: =VLOOKUP(A96,'Carga Remito.'!A$4:AK$15957,4,0) -> Mansuino Alberto | E96: =VLOOKUP(A96,'Carga Remito.'!A$4:AK$2258,6,0) -> 0 | F96: =VLOOKUP(A96,'Carga Remito.'!A$4:AK$1858,7,0) -> gol trend | G96: =VLOOKUP(A96,'Carga Remito.'!A$4:AK$20957,MATCH(G$4,'Carga Remito.'!A$3:AQ$3,0),0) -> 10500 | I96: transferencia | J96: =+G96-K96-N96-Q96-T96-W96-Z96 -> 0 | K96: 10500 | L96: 45147
A97: 1210 | B97: =VLOOKUP(A97,'Carga Remito.'!A$4:AK$16957,3,0) -> 45148 | C97: =ROUNDUP(IF((TODAY()-B97)<30,0,(TODAY()-B97)/30),0) -> 17 | D97: =VLOOKUP(A97,'Carga Remito.'!A$4:AK$15957,4,0) -> Ricci Arturo | E97: =VLOOKUP(A97,'Carga Remito.'!A$4:AK$2258,6,0) -> PFH269 | F97: =VLOOKUP(A97,'Carga Remito.'!A$4:AK$1858,7,0) -> Gol trend | G97: =VLOOKUP(A97,'Carga Remito.'!A$4:AK$20957,MATCH(G$4,'Carga Remito.'!A$3:AQ$3,0),0) -> 100800 | I97: Efectivo | J97: =+G97-K97-N97-Q97-T97-W97-Z97 -> 0 | K97: 45000 | L97: 45148 | N97: 55800 | O97: 45148
A98: 1211 | B98: =VLOOKUP(A98,'Carga Remito.'!A$4:AK$16957,3,0) -> 45148 | C98: =ROUNDUP(IF((TODAY()-B98)<30,0,(TODAY()-B98)/30),0) -> 17 | D98: =VLOOKUP(A98,'Carga Remito.'!A$4:AK$15957,4,0) -> Sambruno Guillermo | E98: =VLOOKUP(A98,'Carga Remito.'!A$4:AK$2258,6,0) -> NLV585 | F98: =VLOOKUP(A98,'Carga Remito.'!A$4:AK$1858,7,0) -> Gol trend | G98: =VLOOKUP(A98,'Carga Remito.'!A$4:AK$20957,MATCH(G$4,'Carga Remito.'!A$3:AQ$3,0),0) -> 43175 | H98: =VLOOKUP(G98,'[1]Carga Remito.'!G$4:AH$16960,3,0) -> #N/A | I98: Efectivo | J98: =+G98-K98-N98-Q98-T98-W98-Z98 -> 0 | K98: 30000 | L98: 45162 | N98: 13175 | O98: 45170
A99: 1213 | B99: =VLOOKUP(A99,'Carga Remito.'!A$4:AK$16957,3,0) -> 45148 | C99: =ROUNDUP(IF((TODAY()-B99)<30,0,(TODAY()-B99)/30),0) -> 17 | D99: =VLOOKUP(A99,'Carga Remito.'!A$4:AK$15957,4,0) -> Gonzalez Gaston | E99: =VLOOKUP(A99,'Carga Remito.'!A$4:AK$2258,6,0) -> MYD516 | F99: =VLOOKUP(A99,'Carga Remito.'!A$4:AK$1858,7,0) -> Cruze | G99: =VLOOKUP(A99,'Carga Remito.'!A$4:AK$20957,MATCH(G$4,'Carga Remito.'!A$3:AQ$3,0),0) -> 186342.5 | I99: Efectivo | J99: =+G99-K99-N99-Q99-T99-W99-Z99 -> 0 | K99: 50000 | L99: 45148 | N99: 36300 | O99: 45154 | Q99: 40000 | R99: 45211 | T99: 30000 | U99: 45244 | W99: 30042.5
A100: 1214 | B100: =VLOOKUP(A100,'Carga Remito.'!A$4:AK$16957,3,0) -> 45104 | C100: =ROUNDUP(IF((TODAY()-B100)<30,0,(TODAY()-B100)/30),0) -> 18 | D100: =VLOOKUP(A100,'Carga Remito.'!A$4:AK$15957,4,0) -> Cabral Guillermo | E100: =VLOOKUP(A100,'Carga Remito.'!A$4:AK$2258,6,0) -> 0 | F100: =VLOOKUP(A100,'Carga Remito.'!A$4:AK$1858,7,0) -> Peugeot 308 | G100: =VLOOKUP(A100,'Carga Remito.'!A$4:AK$20957,MATCH(G$4,'Carga Remito.'!A$3:AQ$3,0),0) -> 60000 | J100: =+G100-K100-N100-Q100-T100-W100-Z100 -> 0 | K100: 60000 | L100: 45115
A101: 1215 | B101: =VLOOKUP(A101,'Carga Remito.'!A$4:AK$16957,3,0) -> 45104 | C101: =ROUNDUP(IF((TODAY()-B101)<30,0,(TODAY()-B101)/30),0) -> 18 | D101: =VLOOKUP(A101,'Carga Remito.'!A$4:AK$15957,4,0) -> Cane Emiliano | E101: =VLOOKUP(A101,'Carga Remito.'!A$4:AK$2258,6,0) -> 0 | F101: =VLOOKUP(A101,'Carga Remito.'!A$4:AK$1858,7,0) -> Ranger | G101: =VLOOKUP(A101,'Carga Remito.'!A$4:AK$20957,MATCH(G$4,'Carga Remito.'!A$3:AQ$3,0),0) -> 169250 | J101: =+G101-K101-N101-Q101-T101-W101-Z101 -> 0 | K101: 169250 | L101: 45112
...

Sheet Carga Remito.
A1: 1 | B1: 2 | C1: 3 | D1: 4 | E1: 5 | F1: 6 | G1: 7 | I1: 8 | J1: 9 | K1: 10 | M1: 11 | N1: 12 | Q1: 13 | R1: 14 | S1: 15 | T1: 16 | W1: 17 | X1: 18 | Y1: 19 | AB1: 20 | AC1: 21 | AD1: 22 | AE1: 23 | AF1: 24 | AG1: 25 | AH1: 26 | AK1: 27
G2: TRABAJOS REALIZADOS | S2: =(W2-Q2)/Q2 -> #DIV/0!
A3: Nro comp. | B3: contador | C3: Fecha | D3: Cliente | E3: Remito y cliente | F3: Dominio | G3: Vehículo | H3: Kilómetros | I3: Trabajo realizado | J3: CONCATENADO | K3: Responsable | L3: Codigo Repuesto | M3: Repuesto | N3: Proveedores | O3: Costo sin IVA | P3: IVA | Q3: Costo | R3: Tipo de trabajo | S3: % ganancia | T3: Cantidad | U3: Precio sin IVA | V3: IVA | W3: Precio final unitario repuesto | X3: Total | Y3: MO tiempo | Z3: Precio sin IVA | AA3: IVA | AB3: MO precio | AC3: MO | AD3: MO Acumulado | AE3: Costo repuestos | AF3: Total costo repuesto | AG3: Total precio repuesto | AH3: Total MO | AI3: Total trabajo sin IVA | AJ3: IVA | AK3: Total trabajo | AL3: NUMERO DE FACTURA | AN3: Responsable | AO3: Tipo de trabajo
A4: 1111 | B4: =IF(A4=A3,B3+1,1) -> 1 | C4: 45111 | D4: Gonzalez Alberto | E4: =CONCATENATE(A4,D4,B4) -> 1111Gonzalez Alberto1 | G4: Cronos | I4: Service cambio de aceite y filtro. | J4: =IF(A4=A3,CONCATENATE(J3," ",I4),I4) -> Service cambio de aceite y filtro. | L4: 1 | M4: Filtro aceite | N4: Taller | Q4: 1500 | R4: Service | S4: =+(W4-Q4)/Q4 -> 1.4 | T4: 1 | W4: 3600 | X4: =W4*T4 -> 3600 | AC4: =+AB4*Y4 -> 0 | AD4: =AC4 -> 0 | AE4: =+(Q4)*T4 -> 1500 | AF4: =SUM(AE4:AE8) -> 16672.411 | AG4: =SUM(X4:X8) -> 39450 | AH4: =AD8 -> 25000 | AK4: =AH4+AG4 -> 64450 | AN4: Emanuel | AO4: Service
A5: 1111 | B5: =IF(A5=A4,B4+1,1) -> 2 | C5: =IF(A5=A4,C4,"") -> 45111 | D5: =IF(A5=A4,D4,"") -> Gonzalez Alberto | E5: =CONCATENATE(A5,D5,B5) -> 1111Gonzalez Alberto2 | I5: Control general del vehículo. | J5: =IF(A5=A4,CONCATENATE(J4," ",I5),I5) -> Service cambio de aceite y filtro. Control general del vehículo. | L5: 1 | M5: Filtro aire | N5: Taller | Q5: 2000 | S5: =+(W5-Q5)/Q5 -> 1.4 | T5: 1 | W5: 4800 | X5: =W5*T5 -> 4800 | AC5: =+AB5*Y5 -> 0 | AD5: =IF(A5=A4,AD4+AC5,AC5) -> 0 | AE5: =+(Q5)*T5 -> 2000 | AF5: =IF(A5=A4,0,(SUMIF($A$3:$A$999956,A5,$Q$3:$Q$999956)))+IF(A5=A4,0,(SUMIF($A$3:$A$999956,A5,$R$3:$R$999956))) -> 0 | AG5: =IF(A5=A4,0,(SUMIF($A$3:$A$999956,A5,($X$3:$X$999956)))) -> 0 | AH5: =IF(A5=A4,0,(SUMIF($A$3:$A$999956,A5,($AC$3:$AC$999956)))) -> 0 | AK5: =AH5+AG5 -> 0 | AN5: Federico | AO5: Distribución
A6: 1111 | B6: =IF(A6=A5,B5+1,1) -> 3 | C6: =IF(A6=A5,C5,"") -> 45111 | D6: =IF(A6=A5,D5,"") -> Gonzalez Alberto | E6: =CONCATENATE(A6,D6,B6) -> 1111Gonzalez Alberto3 | I6: Lavado motor. | J6: =IF(A6=A5,CONCATENATE(J5," ",I6),I6) -> Service cambio de aceite y filtro. Control general del vehículo. Lavado motor. | L6: 1 | M6: Filtro nafta | N6: Taller | Q6: 2000 | S6: =+(W6-Q6)/Q6 -> 0.9 | T6: 1 | W6: 3800 | X6: =W6*T6 -> 3800 | AC6: =+AB6*Y6 -> 0 | AD6: =IF(A6=A5,AD5+AC6,AC6) -> 0 | AE6: =+(Q6)*T6 -> 2000 | AF6: =IF(A6=A5,0,(SUMIF($A$3:$A$999956,A6,$Q$3:$Q$999956)))+IF(A6=A5,0,(SUMIF($A$3:$A$999956,A6,$R$3:$R$999956))) -> 0 | AG6: =IF(A6=A5,0,(SUMIF($A$3:$A$999956,A6,($X$3:$X$999956)))) -> 0 | AH6: =IF(A6=A5,0,(SUMIF($A$3:$A$999956,A6,($AC$3:$AC$999956)))) -> 0 | AK6: =AH6+AG6 -> 0 | AN6: Cristian | AO6: Motor
A7: 1111 | B7: =IF(A7=A6,B6+1,1) -> 4 | C7: =IF(A7=A6,C6,"") -> 45111 | D7: =IF(A7=A6,D6,"") -> Gonzalez Alberto | E7: =CONCATENATE(A7,D7,B7) -> 1111Gonzalez Alberto4 | I7: Rotación de ruedas. | J7: =IF(A7=A6,CONCATENATE(J6," ",I7),I7) -> Service cambio de aceite y filtro. Control general del vehículo. Lavado motor. Rotación de ruedas. | L7: 1 | M7: Filtro pólen | N7: Taller | Q7: =+W7/(1+S7) -> 1666.6667 | S7: 0.5 | T7: 1 | W7: 2500 | X7: =W7*T7 -> 2500 | AC7: =+AB7*Y7 -> 0 | AD7: =IF(A7=A6,AD6+AC7,AC7) -> 0 | AE7: =+(Q7)*T7 -> 1666.6667 | AF7: =IF(A7=A6,0,(SUMIF($A$3:$A$999956,A7,$Q$3:$Q$999956)))+IF(A7=A6,0,(SUMIF($A$3:$A$999956,A7,$R$3:$R$999956))) -> 0 | AG7: =IF(A7=A6,0,(SUMIF($A$3:$A$999956,A7,($X$3:$X$999956)))) -> 0 | AH7: =IF(A7=A6,0,(SUMIF($A$3:$A$999956,A7,($AC$3:$AC$999956)))) -> 0 | AK7: =AH7+AG7 -> 0 | AN7: Juan Carlos | AO7: Otros
A8: 1111 | B8: =IF(A8=A7,B7+1,1) -> 5 | C8: =IF(A8=A7,C7,"") -> 45111 | D8: =IF(A8=A7,D7,"") -> Gonzalez Alberto | E8: =CONCATENATE(A8,D8,B8) -> 1111Gonzalez Alberto5 | J8: =IF(A8=A7,CONCATENATE(J7," ",I8),I8) -> Service cambio de aceite y filtro. Control general del vehículo. Lavado motor. Rotación de ruedas. | L8: 1 | M8: Aceite 5w30 | N8: Taller | Q8: =441489/209 -> 2112.3876 | S8: 1.6036889 | T8: 4.5 | W8: 5500 | X8: =W8*T8 -> 24750 | Y8: 1 | AB8: 25000 | AC8: =+AB8*Y8 -> 25000 | AD8: =IF(A8=A7,AD7+AC8,AC8) -> 25000 | AE8: =+(Q8)*T8 -> 9505.744 | AF8: =IF(A8=A7,0,(SUMIF($A$3:$A$999956,A8,$Q$3:$Q$999956)))+IF(A8=A7,0,(SUMIF($A$3:$A$999956,A8,$R$3:$R$999956))) -> 0 | AG8: =IF(A8=A7,0,(SUMIF($A$3:$A$999956,A8,($X$3:$X$999956)))) -> 0 | AH8: =IF(A8=A7,0,(SUMIF($A$3:$A$999956,A8,($AC$3:$AC$999956)))) -> 0 | AK8: =AH8+AG8 -> 0 | AN8: Emanuel/Cristian
A9: 1112 | B9: =IF(A9=A8,B8+1,1) -> 1 | C9: 45111 | D9: Transporte del Interior | E9: =CONCATENATE(A9,D9,B9) -> 1112Transporte del Interior1 | F9: 993CE | G9: Fiorino | I9: Cambiar cables de bujias y bujias. | J9: =IF(A9=A8,CONCATENATE(J8," ",I9),I9) -> Cambiar cables de bujias y bujias. | L9: 1 | R9: Otros | W9: 0 | X9: =W9*T9 -> 0 | Y9: 1 | AB9: 7000 | AC9: =+AB9*Y9 -> 7000 | AD9: =IF(A9=A8,AD8+AC9,AC9) -> 7000 | AE9: =+(Q9)*T9 -> 0 | AF9: =IF(A9=A8,0,(SUMIF($A$3:$A$999956,A9,$AE$3:$AE$999956))) -> 0 | AG9: =IF(A9=A8,0,(SUMIF($A$3:$A$999956,A9,($X$3:$X$999956)))) -> 0 | AH9: =IF(A9=A8,0,(SUMIF($A$3:$A$999956,A9,($AC$3:$AC$999956)))) -> 7000 | AK9: =AH9+AG9 -> 7000 | AN9: Federico/Cristian
A10: 1113 | B10: =IF(A10=A9,B9+1,1) -> 1 | C10: 45111 | D10: Transporte del Interior | E10: =CONCATENATE(A10,D10,B10) -> 1113Transporte del Interior1 | G10: Peugeot 208 | I10: Service cambio de aceite y filtros. | J10: =IF(A10=A9,CONCATENATE(J9," ",I10),I10) -> Service cambio de aceite y filtros. | L10: 1 | M10: Aceite 10w40 | N10: Taller | Q10: 1214.8325 | R10: Service | S10: 1.572371 | T10: 4 | W10: 3125 | X10: =W10*T10 -> 12500 | AC10: =+AB10*Y10 -> 0 | AD10: =IF(A10=A9,AD9+AC10,AC10) -> 0 | AE10: =+(Q10)*T10 -> 4859.3301 | AF10: =IF(A10=A9,0,(SUMIF($A$3:$A$999956,A10,$AE$3:$AE$999956))) -> 12025.997 | AG10: =IF(A10=A9,0,(SUMIF($A$3:$A$999956,A10,($X$3:$X$999956)))) -> 26400 | AH10: =IF(A10=A9,0,(SUMIF($A$3:$A$999956,A10,($AC$3:$AC$999956)))) -> 18000 | AK10: =AH10+AG10 -> 44400 | AN10: Juan Carlos/Cristian
A11: 1113 | B11: =IF(A11=A10,B10+1,1) -> 2 | C11: =IF(A11=A10,C10,"") -> 45111 | D11: Transporte del Interior | E11: =CONCATENATE(A11,D11,B11) -> 1113Transporte del Interior2 | I11: Control del vehículo. | J11: =IF(A11=A10,CONCATENATE(J10," ",I11),I11) -> Service cambio de aceite y filtros. Control del vehículo. | L11: 1 | M11: Filto aceite | N11: Taller | Q11: 1500 | S11: =+(W11-Q11)/Q11 -> 1.4 | T11: 1 | W11: 3600 | X11: =W11*T11 -> 3600 | AC11: =+AB11*Y11 -> 0 | AD11: =IF(A11=A10,AD10+AC11,AC11) -> 0 | AE11: =+(Q11)*T11 -> 1500 | AF11: =IF(A11=A10,0,(SUMIF($A$3:$A$999956,A11,$AE$3:$AE$999956))) -> 0 | AG11: =IF(A11=A10,0,(SUMIF($A$3:$A$999956,A11,($X$3:$X$999956)))) -> 0 | AH11: =IF(A11=A10,0,(SUMIF($A$3:$A$999956,A11,($AC$3:$AC$999956)))) -> 0 | AK11: =AH11+AG11 -> 0 | AN11: Emanuel/Federico
A12: 1113 | B12: =IF(A12=A11,B11+1,1) -> 3 | C12: =IF(A12=A11,C11,"") -> 45111 | D12: Transporte del Interior | E12: =CONCATENATE(A12,D12,B12) -> 1113Transporte del Interior3 | I12: Rotación de ruedas. | J12: =IF(A12=A11,CONCATENATE(J11," ",I12),I12) -> Service cambio de aceite y filtros. Control del vehículo. Rotación de ruedas. | L12: 1 | M12: Filtro aire | N12: Taller | Q12: 2000 | S12: =+(W12-Q12)/Q12 -> 1.4 | T12: 1 | W12: 4800 | X12: =W12*T12 -> 4800 | AC12: =+AB12*Y12 -> 0 | AD12: =IF(A12=A11,AD11+AC12,AC12) -> 0 | AE12: =+(Q12)*T12 -> 2000 | AF12: =IF(A12=A11,0,(SUMIF($A$3:$A$999956,A12,$AE$3:$AE$999956))) -> 0 | AG12: =IF(A12=A11,0,(SUMIF($A$3:$A$999956,A12,($X$3:$X$999956)))) -> 0 | AH12: =IF(A12=A11,0,(SUMIF($A$3:$A$999956,A12,($AC$3:$AC$999956)))) -> 0 | AK12: =AH12+AG12 -> 0
A13: 1113 | B13: =IF(A13=A12,B12+1,1) -> 4 | C13: =IF(A13=A12,C12,"") -> 45111 | D13: Transporte del Interior | E13: =CONCATENATE(A13,D13,B13) -> 1113Transporte del Interior4 | J13: =IF(A13=A12,CONCATENATE(J12," ",I13),I13) -> Service cambio de aceite y filtros. Control del vehículo. Rotación de ruedas. | L13: 1 | M13: Filtro nafta | N13: Taller | Q13: 2000 | S13: =+(W13-Q13)/Q13 -> 0.5 | T13: 1 | W13: 3000 | X13: =W13*T13 -> 3000 | AC13: =+AB13*Y13 -> 0 | AD13: =IF(A13=A12,AD12+AC13,AC13) -> 0 | AE13: =+(Q13)*T13 -> 2000 | AF13: =IF(A13=A12,0,(SUMIF($A$3:$A$999956,A13,$AE$3:$AE$999956))) -> 0 | AG13: =IF(A13=A12,0,(SUMIF($A$3:$A$999956,A13,($X$3:$X$999956)))) -> 0 | AH13: =IF(A13=A12,0,(SUMIF($A$3:$A$999956,A13,($AC$3:$AC$999956)))) -> 0 | AK13: =AH13+AG13 -> 0
A14: 1113 | B14: =IF(A14=A13,B13+1,1) -> 5 | C14: =IF(A14=A13,C13,"") -> 45111 | D14: Transporte del Interior | E14: =CONCATENATE(A14,D14,B14) -> 1113Transporte del Interior5 | J14: =IF(A14=A13,CONCATENATE(J13," ",I14),I14) -> Service cambio de aceite y filtros. Control del vehículo. Rotación de ruedas. | L14: 1 | M14: Filtro pólen | N14: Taller | Q14: =+W14/(1+S14) -> 1666.6667 | S14: 0.5 | T14: 1 | W14: 2500 | X14: =W14*T14 -> 2500 | Y14: 1 | AB14: 18000 | AC14: =+AB14*Y14 -> 18000 | AD14: =IF(A14=A13,AD13+AC14,AC14) -> 18000 | AE14: =+(Q14)*T14 -> 1666.6667 | AF14: =IF(A14=A13,0,(SUMIF($A$3:$A$999956,A14,$AE$3:$AE$999956))) -> 0 | AG14: =IF(A14=A13,0,(SUMIF($A$3:$A$999956,A14,($X$3:$X$999956)))) -> 0 | AH14: =IF(A14=A13,0,(SUMIF($A$3:$A$999956,A14,($AC$3:$AC$999956)))) -> 0 | AK14: =AH14+AG14 -> 0
A15: 1114 | B15: =IF(A15=A14,B14+1,1) -> 1 | C15: 45112 | D15: Hoyos Pato | E15: =CONCATENATE(A15,D15,B15) -> 1114Hoyos Pato1 | G15: Partner | I15: Scanear vehículo. | J15: =IF(A15=A14,CONCATENATE(J14," ",I15),I15) -> Scanear vehículo. | L15: 1 | M15: Bujia | N15: Taller | Q15: =+W15/(1+S15) -> 1666.6667 | R15: Otros | S15: 0.2 | T15: 4 | W15: 2000 | X15: =W15*T15 -> 8000 | Y15: 1 | AB15: 20000 | AC15: =+AB15*Y15 -> 20000 | AD15: =IF(A15=A14,AD14+AC15,AC15) -> 20000 | AE15: =+(Q15)*T15 -> 6666.6667 | AF15: =IF(A15=A14,0,(SUMIF($A$3:$A$999956,A15,$AE$3:$AE$999956))) -> 6666.6667 | AG15: =IF(A15=A14,0,(SUMIF($A$3:$A$999956,A15,($X$3:$X$999956)))) -> 8000 | AH15: =IF(A15=A14,0,(SUMIF($A$3:$A$999956,A15,($AC$3:$AC$999956)))) -> 20000 | AK15: =AH15+AG15 -> 28000
A16: 1114 | B16: =IF(A16=A15,B15+1,1) -> 2 | C16: =IF(A16=A15,C15,"") -> 45112 | D16: =IF(A16=A15,D15,"") -> Hoyos Pato | E16: =CONCATENATE(A16,D16,B16) -> 1114Hoyos Pato2 | I16: Limpieza del cuerpo mariposa. | J16: =IF(A16=A15,CONCATENATE(J15," ",I16),I16) -> Scanear vehículo. Limpieza del cuerpo mariposa. | L16: 1 | W16: 0 | X16: =W16*T16 -> 0 | AC16: =+AB16*Y16 -> 0 | AD16: =IF(A16=A15,AD15+AC16,AC16) -> 20000 | AE16: =+(Q16)*T16 -> 0 | AF16: =IF(A16=A15,0,(SUMIF($A$3:$A$999956,A16,$AE$3:$AE$999956))) -> 0 | AG16: =IF(A16=A15,0,(SUMIF($A$3:$A$999956,A16,($X$3:$X$999956)))) -> 0 | AH16: =IF(A16=A15,0,(SUMIF($A$3:$A$999956,A16,($AC$3:$AC$999956)))) -> 0 | AK16: =AH16+AG16 -> 0
A17: 1114 | B17: =IF(A17=A16,B16+1,1) -> 3 | C17: =IF(A17=A16,C16,"") -> 45112 | D17: =IF(A17=A16,D16,"") -> Hoyos Pato | E17: =CONCATENATE(A17,D17,B17) -> 1114Hoyos Pato3 | I17: Cambiar bujia de encendido. | J17: =IF(A17=A16,CONCATENATE(J16," ",I17),I17) -> Scanear vehículo. Limpieza del cuerpo mariposa. Cambiar bujia de encendido. | L17: 1 | W17: 0 | X17: =W17*T17 -> 0 | AC17: =+AB17*Y17 -> 0 | AD17: =IF(A17=A16,AD16+AC17,AC17) -> 20000 | AE17: =+(Q17)*T17 -> 0 | AF17: =IF(A17=A16,0,(SUMIF($A$3:$A$999956,A17,$AE$3:$AE$999956))) -> 0 | AG17: =IF(A17=A16,0,(SUMIF($A$3:$A$999956,A17,($X$3:$X$999956)))) -> 0 | AH17: =IF(A17=A16,0,(SUMIF($A$3:$A$999956,A17,($AC$3:$AC$999956)))) -> 0 | AK17: =AH17+AG17 -> 0
A18: 1115 | B18: =IF(A18=A17,B17+1,1) -> 1 | C18: 45112 | D18: Domanski Roberto | E18: =CONCATENATE(A18,D18,B18) -> 1115Domanski Roberto1 | F18: AE880MIT | G18: VW T CROOS | H18: 31686 | I18: Service cambio de aceite y filtro. | J18: =IF(A18=A17,CONCATENATE(J17," ",I18),I18) -> Service cambio de aceite y filtro. | L18: 1 | M18: Aceite motor 5w30 | N18: Taller | Q18: 2112 | R18: Service | S18: =+(W18-Q18)/Q18 -> 1.6041667 | T18: 4.5 | W18: 5500 | X18: =W18*T18 -> 24750 | AC18: =+AB18*Y18 -> 0 | AD18: =IF(A18=A17,AD17+AC18,AC18) -> 0 | AE18: =+(Q18)*T18 -> 9504 | AF18: =IF(A18=A17,0,(SUMIF($A$3:$A$999956,A18,$AE$3:$AE$999956))) -> 15004 | AG18: =IF(A18=A17,0,(SUMIF($A$3:$A$999956,A18,($X$3:$X$999956)))) -> 36350 | AH18: =IF(A18=A17,0,(SUMIF($A$3:$A$999956,A18,($AC$3:$AC$999956)))) -> 22000 | AK18: =AH18+AG18 -> 58350
A19: 1115 | B19: =IF(A19=A18,B18+1,1) -> 2 | C19: =IF(A19=A18,C18,"") -> 45112 | D19: =IF(A19=A18,D18,"") -> Domanski Roberto | E19: =CONCATENATE(A19,D19,B19) -> 1115Domanski Roberto2 | I19: Rotación de ruedas. | J19: =IF(A19=A18,CONCATENATE(J18," ",I19),I19) -> Service cambio de aceite y filtro. Rotación de ruedas. | L19: 1 | M19: Filtro aceite | N19: Taller | Q19: 1500 | S19: =+(W19-Q19)/Q19 -> 1.5333333 | T19: 1 | W19: 3800 | X19: =W19*T19 -> 3800 | AC19: =+AB19*Y19 -> 0 | AD19: =IF(A19=A18,AD18+AC19,AC19) -> 0 | AE19: =+(Q19)*T19 -> 1500 | AF19: =IF(A19=A18,0,(SUMIF($A$3:$A$999956,A19,$AE$3:$AE$999956))) -> 0 | AG19: =IF(A19=A18,0,(SUMIF($A$3:$A$999956,A19,($X$3:$X$999956)))) -> 0 | AH19: =IF(A19=A18,0,(SUMIF($A$3:$A$999956,A19,($AC$3:$AC$999956)))) -> 0 | AK19: =AH19+AG19 -> 0
A20: 1115 | B20: =IF(A20=A19,B19+1,1) -> 3 | C20: =IF(A20=A19,C19,"") -> 45112 | D20: =IF(A20=A19,D19,"") -> Domanski Roberto | E20: =CONCATENATE(A20,D20,B20) -> 1115Domanski Roberto3 | J20: =IF(A20=A19,CONCATENATE(J19," ",I20),I20) -> Service cambio de aceite y filtro. Rotación de ruedas. | L20: 1 | M20: Filtro aire | N20: Taller | Q20: 2000 | S20: =+(W20-Q20)/Q20 -> 1.4 | T20: 1 | W20: 4800 | X20: =W20*T20 -> 4800 | AC20: =+AB20*Y20 -> 0 | AD20: =IF(A20=A19,AD19+AC20,AC20) -> 0 | AE20: =+(Q20)*T20 -> 2000 | AF20: =IF(A20=A19,0,(SUMIF($A$3:$A$999956,A20,$AE$3:$AE$999956))) -> 0 | AG20: =IF(A20=A19,0,(SUMIF($A$3:$A$999956,A20,($X$3:$X$999956)))) -> 0 | AH20: =IF(A20=A19,0,(SUMIF($A$3:$A$999956,A20,($AC$3:$AC$999956)))) -> 0 | AK20: =AH20+AG20 -> 0
A21: 1115 | B21: =IF(A21=A20,B20+1,1) -> 4 | C21: =IF(A21=A20,C20,"") -> 45112 | D21: =IF(A21=A20,D20,"") -> Domanski Roberto | E21: =CONCATENATE(A21,D21,B21) -> 1115Domanski Roberto4 | J21: =IF(A21=A20,CONCATENATE(J20," ",I21),I21) -> Service cambio de aceite y filtro. Rotación de ruedas. | L21: 1 | M21: Filtro pólen | N21: Taller | Q21: =+W21/(1+S21) -> 2000 | S21: 0.5 | T21: 1 | W21: 3000 | X21: =W21*T21 -> 3000 | AC21: =+AB21*Y21 -> 0 | AD21: =IF(A21=A20,AD20+AC21,AC21) -> 0 | AE21: =+(Q21)*T21 -> 2000 | AF21: =IF(A21=A20,0,(SUMIF($A$3:$A$999956,A21,$AE$3:$AE$999956))) -> 0 | AG21: =IF(A21=A20,0,(SUMIF($A$3:$A$999956,A21,($X$3:$X$999956)))) -> 0 | AH21: =IF(A21=A20,0,(SUMIF($A$3:$A$999956,A21,($AC$3:$AC$999956)))) -> 0 | AK21: =AH21+AG21 -> 0
A22: 1115 | B22: =IF(A22=A21,B21+1,1) -> 5 | C22: =IF(A22=A21,C21,"") -> 45112 | D22: =IF(A22=A21,D21,"") -> Domanski Roberto | E22: =CONCATENATE(A22,D22,B22) -> 1115Domanski Roberto5 | J22: =IF(A22=A21,CONCATENATE(J21," ",I22),I22) -> Service cambio de aceite y filtro. Rotación de ruedas. | L22: 1 | W22: 0 | X22: =W22*T22 -> 0 | AC22: =+AB22*Y22 -> 0 | AD22: =IF(A22=A21,AD21+AC22,AC22) -> 0 | AE22: =+(Q22)*T22 -> 0 | AF22: =IF(A22=A21,0,(SUMIF($A$3:$A$999956,A22,$AE$3:$AE$999956))) -> 0 | AG22: =IF(A22=A21,0,(SUMIF($A$3:$A$999956,A22,($X$3:$X$999956)))) -> 0 | AH22: =IF(A22=A21,0,(SUMIF($A$3:$A$999956,A22,($AC$3:$AC$999956)))) -> 0 | AK22: =AH22+AG22 -> 0
A23: 1115 | B23: =IF(A23=A22,B22+1,1) -> 6 | C23: =IF(A23=A22,C22,"") -> 45112 | D23: =IF(A23=A22,D22,"") -> Domanski Roberto | E23: =CONCATENATE(A23,D23,B23) -> 1115Domanski Roberto6 | J23: =IF(A23=A22,CONCATENATE(J22," ",I23),I23) -> Service cambio de aceite y filtro. Rotación de ruedas. | L23: 1 | W23: 0 | X23: =W23*T23 -> 0 | Y23: 1 | AB23: 22000 | AC23: =+AB23*Y23 -> 22000 | AD23: =IF(A23=A22,AD22+AC23,AC23) -> 22000 | AE23: =+(Q23)*T23 -> 0 | AF23: =IF(A23=A22,0,(SUMIF($A$3:$A$999956,A23,$AE$3:$AE$999956))) -> 0 | AG23: =IF(A23=A22,0,(SUMIF($A$3:$A$999956,A23,($X$3:$X$999956)))) -> 0 | AH23: =IF(A23=A22,0,(SUMIF($A$3:$A$999956,A23,($AC$3:$AC$999956)))) -> 0 | AK23: =AH23+AG23 -> 0
A24: 1116 | B24: =IF(A24=A23,B23+1,1) -> 1 | C24: 45112 | D24: Quiroga Hector | E24: =CONCATENATE(A24,D24,B24) -> 1116Quiroga Hector1 | F24: AA914VK | G24: GolTrend | H24: 55440 | I24: Service cambio de aceite y filtro. | J24: =IF(A24=A23,CONCATENATE(J23," ",I24),I24) -> Service cambio de aceite y filtro. | L24: 1 | M24: Filtro aceite | N24: Taller | Q24: 3000 | R24: Service | S24: 1 | T24: 1 | W24: 3000 | X24: =W24*T24 -> 3000 | AC24: =+AB24*Y24 -> 0 | AD24: =IF(A24=A23,AD23+AC24,AC24) -> 0 | AE24: =+(Q24)*T24 -> 3000 | AF24: =IF(A24=A23,0,(SUMIF($A$3:$A$999956,A24,$AE$3:$AE$999956))) -> 59127.333 | AG24: =IF(A24=A23,0,(SUMIF($A$3:$A$999956,A24,($X$3:$X$999956)))) -> 77900 | AH24: =IF(A24=A23,0,(SUMIF($A$3:$A$999956,A24,($AC$3:$AC$999956)))) -> 50000 | AK24: =AH24+AG24 -> 127900
A25: 1116 | B25: =IF(A25=A24,B24+1,1) -> 2 | C25: =IF(A25=A24,C24,"") -> 45112 | D25: =IF(A25=A24,D24,"") -> Quiroga Hector | E25: =CONCATENATE(A25,D25,B25) -> 1116Quiroga Hector2 | I25: Control del véhiculo. | J25: =IF(A25=A24,CONCATENATE(J24," ",I25),I25) -> Service cambio de aceite y filtro. Control del véhiculo. | L25: 1 | M25: Filtro aire | N25: Taller | Q25: 2000 | S25: =+(W25-Q25)/Q25 -> 1 | T25: 1 | W25: 4000 | X25: =W25*T25 -> 4000 | AC25: =+AB25*Y25 -> 0 | AD25: =IF(A25=A24,AD24+AC25,AC25) -> 0 | AE25: =+(Q25)*T25 -> 2000 | AF25: =IF(A25=A24,0,(SUMIF($A$3:$A$999956,A25,$AE$3:$AE$999956))) -> 0 | AG25: =IF(A25=A24,0,(SUMIF($A$3:$A$999956,A25,($X$3:$X$999956)))) -> 0 | AH25: =IF(A25=A24,0,(SUMIF($A$3:$A$999956,A25,($AC$3:$AC$999956)))) -> 0 | AK25: =AH25+AG25 -> 0
A26: 1116 | B26: =IF(A26=A25,B25+1,1) -> 3 | C26: =IF(A26=A25,C25,"") -> 45112 | D26: =IF(A26=A25,D25,"") -> Quiroga Hector | E26: =CONCATENATE(A26,D26,B26) -> 1116Quiroga Hector3 | I26: Rotación de ruedas. | J26: =IF(A26=A25,CONCATENATE(J25," ",I26),I26) -> Service cambio de aceite y filtro. Control del véhiculo. Rotación de ruedas. | L26: 1 | M26: Filtro nafta | N26: Taller | Q26: 2000 | S26: =+(W26-Q26)/Q26 -> 0.6 | T26: 1 | W26: 3200 | X26: =W26*T26 -> 3200 | AC26: =+AB26*Y26 -> 0 | AD26: =IF(A26=A25,AD25+AC26,AC26) -> 0 | AE26: =+(Q26)*T26 -> 2000 | AF26: =IF(A26=A25,0,(SUMIF($A$3:$A$999956,A26,$AE$3:$AE$999956))) -> 0 | AG26: =IF(A26=A25,0,(SUMIF($A$3:$A$999956,A26,($X$3:$X$999956)))) -> 0 | AH26: =IF(A26=A25,0,(SUMIF($A$3:$A$999956,A26,($AC$3:$AC$999956)))) -> 0 | AK26: =AH26+AG26 -> 0
A27: 1116 | B27: =IF(A27=A26,B26+1,1) -> 4 | C27: =IF(A27=A26,C26,"") -> 45112 | D27: =IF(A27=A26,D26,"") -> Quiroga Hector | E27: =CONCATENATE(A27,D27,B27) -> 1116Quiroga Hector4 | I27: Cambio de kit completo de distribución y correa poliv. | J27: =IF(A27=A26,CONCATENATE(J26," ",I27),I27) -> Service cambio de aceite y filtro. Control del véhiculo. Rotación de ruedas. Cambio de kit completo de distribución y correa poliv. | L27: 1 | M27: Filtro pólen | N27: Taller | Q27: =+W27/(1+S27) -> 2000 | S27: 0.5 | T27: 1 | W27: 3000 | X27: =W27*T27 -> 3000 | AC27: =+AB27*Y27 -> 0 | AD27: =IF(A27=A26,AD26+AC27,AC27) -> 0 | AE27: =+(Q27)*T27 -> 2000 | AF27: =IF(A27=A26,0,(SUMIF($A$3:$A$999956,A27,$AE$3:$AE$999956))) -> 0 | AG27: =IF(A27=A26,0,(SUMIF($A$3:$A$999956,A27,($X$3:$X$999956)))) -> 0 | AH27: =IF(A27=A26,0,(SUMIF($A$3:$A$999956,A27,($AC$3:$AC$999956)))) -> 0 | AK27: =AH27+AG27 -> 0
A28: 1116 | B28: =IF(A28=A27,B27+1,1) -> 5 | C28: =IF(A28=A27,C27,"") -> 45112 | D28: =IF(A28=A27,D27,"") -> Quiroga Hector | E28: =CONCATENATE(A28,D28,B28) -> 1116Quiroga Hector5 | I28: Cambio de bomba de agua. | J28: =IF(A28=A27,CONCATENATE(J27," ",I28),I28) -> Service cambio de aceite y filtro. Control del véhiculo. Rotación de ruedas. Cambio de kit completo de distribución y correa poliv. Cambio de bomba de agua. | L28: 1 | M28: Kit distribución con bomba de agua y correa poliv. | N28: Taller | Q28: =+W28/(1+S28) -> 48333.333 | S28: 0.2 | T28: 1 | W28: 58000 | X28: =W28*T28 -> 58000 | AC28: =+AB28*Y28 -> 0 | AD28: =IF(A28=A27,AD27+AC28,AC28) -> 0 | AE28: =+(Q28)*T28 -> 48333.333 | AF28: =IF(A28=A27,0,(SUMIF($A$3:$A$999956,A28,$AE$3:$AE$999956))) -> 0 | AG28: =IF(A28=A27,0,(SUMIF($A$3:$A$999956,A28,($X$3:$X$999956)))) -> 0 | AH28: =IF(A28=A27,0,(SUMIF($A$3:$A$999956,A28,($AC$3:$AC$999956)))) -> 0 | AK28: =AH28+AG28 -> 0
A29: 1116 | B29: =IF(A29=A28,B28+1,1) -> 6 | C29: =IF(A29=A28,C28,"") -> 45112 | D29: =IF(A29=A28,D28,"") -> Quiroga Hector | E29: =CONCATENATE(A29,D29,B29) -> 1116Quiroga Hector6 | J29: =IF(A29=A28,CONCATENATE(J28," ",I29),I29) -> Service cambio de aceite y filtro. Control del véhiculo. Rotación de ruedas. Cambio de kit completo de distribución y correa poliv. Cambio de bomba de agua. | L29: 1 | M29: Liquido refrigerante + agua destilada | N29: Taller | Q29: 1794 | S29: =+(W29-Q29)/Q29 -> 2.7346711 | T29: 1 | W29: 6700 | X29: =W29*T29 -> 6700 | Y29: 1 | AB29: 50000 | AC29: =+AB29*Y29 -> 50000 | AD29: =IF(A29=A28,AD28+AC29,AC29) -> 50000 | AE29: =+(Q29)*T29 -> 1794 | AF29: =IF(A29=A28,0,(SUMIF($A$3:$A$999956,A29,$AE$3:$AE$999956))) -> 0 | AG29: =IF(A29=A28,0,(SUMIF($A$3:$A$999956,A29,($X$3:$X$999956)))) -> 0 | AH29: =IF(A29=A28,0,(SUMIF($A$3:$A$999956,A29,($AC$3:$AC$999956)))) -> 0 | AK29: =AH29+AG29 -> 0
A30: 1117 | B30: =IF(A30=A29,B29+1,1) -> 1 | C30: 45112 | D30: Pisani Nicolas | E30: =CONCATENATE(A30,D30,B30) -> 1117Pisani Nicolas1 | G30: Megane | I30: Sacar tapa válvula. | J30: =IF(A30=A29,CONCATENATE(J29," ",I30),I30) -> Sacar tapa válvula. | L30: 1 | M30: Retenes de arboles de leva | N30: Barotto | Q30: =3900*0.8 -> 3120 | R30: Otros | S30: =+(W30-Q30)/Q30 -> 0.25 | T30: 2 | W30: 3900 | X30: =W30*T30 -> 7800 | AC30: =+AB30*Y30 -> 0 | AD30: =IF(A30=A29,AD29+AC30,AC30) -> 0 | AE30: =+(Q30)*T30 -> 6240 | AF30: =IF(A30=A29,0,(SUMIF($A$3:$A$999956,A30,$AE$3:$AE$999956))) -> 13008 | AG30: =IF(A30=A29,0,(SUMIF($A$3:$A$999956,A30,($X$3:$X$999956)))) -> 16260 | AH30: =IF(A30=A29,0,(SUMIF($A$3:$A$999956,A30,($AC$3:$AC$999956)))) -> 35000 | AK30: =AH30+AG30 -> 51260
A31: 1117 | B31: =IF(A31=A30,B30+1,1) -> 2 | C31: =IF(A31=A30,C30,"") -> 45112 | D31: =IF(A31=A30,D30,"") -> Pisani Nicolas | E31: =CONCATENATE(A31,D31,B31) -> 1117Pisani Nicolas2 | I31: Limpieza y armado con sellador nuevo. | J31: =IF(A31=A30,CONCATENATE(J30," ",I31),I31) -> Sacar tapa válvula. Limpieza y armado con sellador nuevo. | L31: 1 | M31: Correa poliv | N31: Ferrando | Q31: =8460*0.8 -> 6768 | S31: =+(W31-Q31)/Q31 -> 0.25 | T31: 1 | W31: 8460 | X31: =W31*T31 -> 8460 | Y31: 1 | AB31: 35000 | AC31: =+AB31*Y31 -> 35000 | AD31: =IF(A31=A30,AD30+AC31,AC31) -> 35000 | AE31: =+(Q31)*T31 -> 6768 | AF31: =IF(A31=A30,0,(SUMIF($A$3:$A$999956,A31,$AE$3:$AE$999956))) -> 0 | AG31: =IF(A31=A30,0,(SUMIF($A$3:$A$999956,A31,($X$3:$X$999956)))) -> 0 | AH31: =IF(A31=A30,0,(SUMIF($A$3:$A$999956,A31,($AC$3:$AC$999956)))) -> 0 | AK31: =AH31+AG31 -> 0
A32: 1117 | B32: =IF(A32=A31,B31+1,1) -> 3 | C32: =IF(A32=A31,C31,"") -> 45112 | D32: =IF(A32=A31,D31,"") -> Pisani Nicolas | E32: =CONCATENATE(A32,D32,B32) -> 1117Pisani Nicolas3 | I32: Cambiar orring cuerpo mariposa. | J32: =IF(A32=A31,CONCATENATE(J31," ",I32),I32) -> Sacar tapa válvula. Limpieza y armado con sellador nuevo. Cambiar orring cuerpo mariposa. | L32: 1 | W32: 0 | X32: =W32*T32 -> 0 | AC32: =+AB32*Y32 -> 0 | AD32: =IF(A32=A31,AD31+AC32,AC32) -> 35000 | AE32: =+(Q32)*T32 -> 0 | AF32: =IF(A32=A31,0,(SUMIF($A$3:$A$999956,A32,$AE$3:$AE$999956))) -> 0 | AG32: =IF(A32=A31,0,(SUMIF($A$3:$A$999956,A32,($X$3:$X$999956)))) -> 0 | AH32: =IF(A32=A31,0,(SUMIF($A$3:$A$999956,A32,($AC$3:$AC$999956)))) -> 0 | AK32: =AH32+AG32 -> 0
A33: 1117 | B33: =IF(A33=A32,B32+1,1) -> 4 | C33: =IF(A33=A32,C32,"") -> 45112 | D33: =IF(A33=A32,D32,"") -> Pisani Nicolas | E33: =CONCATENATE(A33,D33,B33) -> 1117Pisani Nicolas4 | I33: Correa poliv. | J33: =IF(A33=A32,CONCATENATE(J32," ",I33),I33) -> Sacar tapa válvula. Limpieza y armado con sellador nuevo. Cambiar orring cuerpo mariposa. Correa poliv. | L33: 1 | W33: 0 | X33: =W33*T33 -> 0 | AC33: =+AB33*Y33 -> 0 | AD33: =IF(A33=A32,AD32+AC33,AC33) -> 35000 | AE33: =+(Q33)*T33 -> 0 | AF33: =IF(A33=A32,0,(SUMIF($A$3:$A$999956,A33,$AE$3:$AE$999956))) -> 0 | AG33: =IF(A33=A32,0,(SUMIF($A$3:$A$999956,A33,($X$3:$X$999956)))) -> 0 | AH33: =IF(A33=A32,0,(SUMIF($A$3:$A$999956,A33,($AC$3:$AC$999956)))) -> 0 | AK33: =AH33+AG33 -> 0
A34: 1117 | B34: =IF(A34=A33,B33+1,1) -> 5 | C34: =IF(A34=A33,C33,"") -> 45112 | D34: =IF(A34=A33,D33,"") -> Pisani Nicolas | E34: =CONCATENATE(A34,D34,B34) -> 1117Pisani Nicolas5 | I34: Retenes de árboles de leva. | J34: =IF(A34=A33,CONCATENATE(J33," ",I34),I34) -> Sacar tapa válvula. Limpieza y armado con sellador nuevo. Cambiar orring cuerpo mariposa. Correa poliv. Retenes de árboles de leva. | L34: 1 | W34: 0 | X34: =W34*T34 -> 0 | AC34: =+AB34*Y34 -> 0 | AD34: =IF(A34=A33,AD33+AC34,AC34) -> 35000 | AE34: =+(Q34)*T34 -> 0 | AF34: =IF(A34=A33,0,(SUMIF($A$3:$A$999956,A34,$AE$3:$AE$999956))) -> 0 | AG34: =IF(A34=A33,0,(SUMIF($A$3:$A$999956,A34,($X$3:$X$999956)))) -> 0 | AH34: =IF(A34=A33,0,(SUMIF($A$3:$A$999956,A34,($AC$3:$AC$999956)))) -> 0 | AK34: =AH34+AG34 -> 0
A35: 1117 | B35: =IF(A35=A34,B34+1,1) -> 6 | C35: =IF(A35=A34,C34,"") -> 45112 | D35: =IF(A35=A34,D34,"") -> Pisani Nicolas | E35: =CONCATENATE(A35,D35,B35) -> 1117Pisani Nicolas6 | I35: Puesta a punto. Armado total. | J35: =IF(A35=A34,CONCATENATE(J34," ",I35),I35) -> Sacar tapa válvula. Limpieza y armado con sellador nuevo. Cambiar orring cuerpo mariposa. Correa poliv. Retenes de árboles de leva. Puesta a punto. Armado total. | L35: 1 | W35: 0 | X35: =W35*T35 -> 0 | AC35: =+AB35*Y35 -> 0 | AD35: =IF(A35=A34,AD34+AC35,AC35) -> 35000 | AE35: =+(Q35)*T35 -> 0 | AF35: =IF(A35=A34,0,(SUMIF($A$3:$A$999956,A35,$AE$3:$AE$999956))) -> 0 | AG35: =IF(A35=A34,0,(SUMIF($A$3:$A$999956,A35,($X$3:$X$999956)))) -> 0 | AH35: =IF(A35=A34,0,(SUMIF($A$3:$A$999956,A35,($AC$3:$AC$999956)))) -> 0 | AK35: =AH35+AG35 -> 0
A36: 1118 | B36: =IF(A36=A35,B35+1,1) -> 1 | C36: 45112 | D36: Acotto Jorge | E36: =CONCATENATE(A36,D36,B36) -> 1118Acotto Jorge1 | G36: 147 | I36: Desarmar suspensión lado derecho. | J36: =IF(A36=A35,CONCATENATE(J35," ",I36),I36) -> Desarmar suspensión lado derecho. | L36: 1 | M36: Aceite caja velocidad | N36: Taller | Q36: =+W36/(1+S36) -> 3076.9231 | R36: Otros | S36: 1.6 | T36: 1 | W36: 8000 | X36: =W36*T36 -> 8000 | AC36: =+AB36*Y36 -> 0 | AD36: =IF(A36=A35,AD35+AC36,AC36) -> 0 | AE36: =+(Q36)*T36 -> 3076.9231 | AF36: =IF(A36=A35,0,(SUMIF($A$3:$A$999956,A36,$AE$3:$AE$999956))) -> 6308.9231 | AG36: =IF(A36=A35,0,(SUMIF($A$3:$A$999956,A36,($X$3:$X$999956)))) -> 12040 | AH36: =IF(A36=A35,0,(SUMIF($A$3:$A$999956,A36,($AC$3:$AC$999956)))) -> 20000 | AK36: =AH36+AG36 -> 32040
A37: 1118 | B37: =IF(A37=A36,B36+1,1) -> 2 | C37: =IF(A37=A36,C36,"") -> 45112 | D37: =IF(A37=A36,D36,"") -> Acotto Jorge | E37: =CONCATENATE(A37,D37,B37) -> 1118Acotto Jorge2 | I37: Colocar grasa y abrazaderas nuevas en fuelle de homocinética. | J37: =IF(A37=A36,CONCATENATE(J36," ",I37),I37) -> Desarmar suspensión lado derecho. Colocar grasa y abrazaderas nuevas en fuelle de homocinética. | L37: 1 | M37: Fuelle semi eje lado caja izquierdo | N37: Rep Serrano | Q37: =1830*0.8 -> 1464 | S37: =+(W37-Q37)/Q37 -> 0.25 | T37: 1 | W37: 1830 | X37: =W37*T37 -> 1830 | AC37: =+AB37*Y37 -> 0 | AD37: =IF(A37=A36,AD36+AC37,AC37) -> 0 | AE37: =+(Q37)*T37 -> 1464 | AF37: =IF(A37=A36,0,(SUMIF($A$3:$A$999956,A37,$AE$3:$AE$999956))) -> 0 | AG37: =IF(A37=A36,0,(SUMIF($A$3:$A$999956,A37,($X$3:$X$999956)))) -> 0 | AH37: =IF(A37=A36,0,(SUMIF($A$3:$A$999956,A37,($AC$3:$AC$999956)))) -> 0 | AK37: =AH37+AG37 -> 0
A38: 1118 | B38: =IF(A38=A37,B37+1,1) -> 3 | C38: =IF(A38=A37,C37,"") -> 45112 | D38: =IF(A38=A37,D37,"") -> Acotto Jorge | E38: =CONCATENATE(A38,D38,B38) -> 1118Acotto Jorge3 | I38: Desarmar suspensión lado izquierdo. | J38: =IF(A38=A37,CONCATENATE(J37," ",I38),I38) -> Desarmar suspensión lado derecho. Colocar grasa y abrazaderas nuevas en fuelle de homocinética. Desarmar suspensión lado izquierdo. | L38: 1 | M38: Reten eje selector | N38: Ferrando | Q38: =1000*0.8 -> 800 | S38: =+(W38-Q38)/Q38 -> 0.25 | T38: 1 | W38: 1000 | X38: =W38*T38 -> 1000 | AC38: =+AB38*Y38 -> 0 | AD38: =IF(A38=A37,AD37+AC38,AC38) -> 0 | AE38: =+(Q38)*T38 -> 800 | AF38: =IF(A38=A37,0,(SUMIF($A$3:$A$999956,A38,$AE$3:$AE$999956))) -> 0 | AG38: =IF(A38=A37,0,(SUMIF($A$3:$A$999956,A38,($X$3:$X$999956)))) -> 0 | AH38: =IF(A38=A37,0,(SUMIF($A$3:$A$999956,A38,($AC$3:$AC$999956)))) -> 0 | AK38: =AH38+AG38 -> 0
A39: 1118 | B39: =IF(A39=A38,B38+1,1) -> 4 | C39: =IF(A39=A38,C38,"") -> 45112 | D39: =IF(A39=A38,D38,"") -> Acotto Jorge | E39: =CONCATENATE(A39,D39,B39) -> 1118Acotto Jorge4 | I39: Sacar semi eje. | J39: =IF(A39=A38,CONCATENATE(J38," ",I39),I39) -> Desarmar suspensión lado derecho. Colocar grasa y abrazaderas nuevas en fuelle de homocinética. Desarmar suspensión lado izquierdo. Sacar semi eje. | L39: 1 | M39: Fuelle de reten de eje selector | N39: Rep Serrano | Q39: =1210*0.8 -> 968 | S39: =+(W39-Q39)/Q39 -> 0.25 | T39: 1 | W39: 1210 | X39: =W39*T39 -> 1210 | AC39: =+AB39*Y39 -> 0 | AD39: =IF(A39=A38,AD38+AC39,AC39) -> 0 | AE39: =+(Q39)*T39 -> 968 | AF39: =IF(A39=A38,0,(SUMIF($A$3:$A$999956,A39,$AE$3:$AE$999956))) -> 0 | AG39: =IF(A39=A38,0,(SUMIF($A$3:$A$999956,A39,($X$3:$X$999956)))) -> 0 | AH39: =IF(A39=A38,0,(SUMIF($A$3:$A$999956,A39,($AC$3:$AC$999956)))) -> 0 | AK39: =AH39+AG39 -> 0
A40: 1118 | B40: =IF(A40=A39,B39+1,1) -> 5 | C40: =IF(A40=A39,C39,"") -> 45112 | D40: =IF(A40=A39,D39,"") -> Acotto Jorge | E40: =CONCATENATE(A40,D40,B40) -> 1118Acotto Jorge5 | I40: Reparar con fuelle lado caja nueva. | J40: =IF(A40=A39,CONCATENATE(J39," ",I40),I40) -> Desarmar suspensión lado derecho. Colocar grasa y abrazaderas nuevas en fuelle de homocinética. Desarmar suspensión lado izquierdo. Sacar semi eje. Reparar con fuelle lado caja nueva. | L40: 1 | W40: 0 | X40: =W40*T40 -> 0 | Y40: 1 | AB40: 20000 | AC40: =+AB40*Y40 -> 20000 | AD40: =IF(A40=A39,AD39+AC40,AC40) -> 20000 | AE40: =+(Q40)*T40 -> 0 | AF40: =IF(A40=A39,0,(SUMIF($A$3:$A$999956,A40,$AE$3:$AE$999956))) -> 0 | AG40: =IF(A40=A39,0,(SUMIF($A$3:$A$999956,A40,($X$3:$X$999956)))) -> 0 | AH40: =IF(A40=A39,0,(SUMIF($A$3:$A$999956,A40,($AC$3:$AC$999956)))) -> 0 | AK40: =AH40+AG40 -> 0
A41: 1118 | B41: =IF(A41=A40,B40+1,1) -> 6 | C41: =IF(A41=A40,C40,"") -> 45112 | D41: =IF(A41=A40,D40,"") -> Acotto Jorge | E41: =CONCATENATE(A41,D41,B41) -> 1118Acotto Jorge6 | I41: Armado total, completar nivel de aceite caja velocidad. | J41: =IF(A41=A40,CONCATENATE(J40," ",I41),I41) -> Desarmar suspensión lado derecho. Colocar grasa y abrazaderas nuevas en fuelle de homocinética. Desarmar suspensión lado izquierdo. Sacar semi eje. Reparar con fuelle lado caja nueva. Armado total, completar nivel de aceite caja velocidad. | L41: 1 | W41: 0 | X41: =W41*T41 -> 0 | AC41: =+AB41*Y41 -> 0 | AD41: =IF(A41=A40,AD40+AC41,AC41) -> 20000 | AE41: =+(Q41)*T41 -> 0 | AF41: =IF(A41=A40,0,(SUMIF($A$3:$A$999956,A41,$AE$3:$AE$999956))) -> 0 | AG41: =IF(A41=A40,0,(SUMIF($A$3:$A$999956,A41,($X$3:$X$999956)))) -> 0 | AH41: =IF(A41=A40,0,(SUMIF($A$3:$A$999956,A41,($AC$3:$AC$999956)))) -> 0 | AK41: =AH41+AG41 -> 0
A42: 1118 | B42: =IF(A42=A41,B41+1,1) -> 7 | C42: =IF(A42=A41,C41,"") -> 45112 | D42: =IF(A42=A41,D41,"") -> Acotto Jorge | E42: =CONCATENATE(A42,D42,B42) -> 1118Acotto Jorge7 | I42: Cambiar reten de eje selector. | J42: =IF(A42=A41,CONCATENATE(J41," ",I42),I42) -> Desarmar suspensión lado derecho. Colocar grasa y abrazaderas nuevas en fuelle de homocinética. Desarmar suspensión lado izquierdo. Sacar semi eje. Reparar con fuelle lado caja nueva. Armado total, completar nivel de aceite caja velocidad. Cambiar reten de eje selector. | L42: 1 | W42: 0 | X42: =W42*T42 -> 0 | AC42: =+AB42*Y42 -> 0 | AD42: =IF(A42=A41,AD41+AC42,AC42) -> 20000 | AE42: =+(Q42)*T42 -> 0 | AF42: =IF(A42=A41,0,(SUMIF($A$3:$A$999956,A42,$AE$3:$AE$999956))) -> 0 | AG42: =IF(A42=A41,0,(SUMIF($A$3:$A$999956,A42,($X$3:$X$999956)))) -> 0 | AH42: =IF(A42=A41,0,(SUMIF($A$3:$A$999956,A42,($AC$3:$AC$999956)))) -> 0 | AK42: =AH42+AG42 -> 0
A43: 1118 | B43: =IF(A43=A42,B42+1,1) -> 8 | C43: =IF(A43=A42,C42,"") -> 45112 | D43: =IF(A43=A42,D42,"") -> Acotto Jorge | E43: =CONCATENATE(A43,D43,B43) -> 1118Acotto Jorge8 | I43: de cambio. Colocar tornillos y arandelas nuevas en amortiguador derecho. | J43: =IF(A43=A42,CONCATENATE(J42," ",I43),I43) -> Desarmar suspensión lado derecho. Colocar grasa y abrazaderas nuevas en fuelle de homocinética. Desarmar suspensión lado izquierdo. Sacar semi eje. Reparar con fuelle lado caja nueva. Armado total, completar nivel de aceite caja velocidad. Cambiar reten de eje selector. de cambio. Colocar tornillos y arandelas nuevas en amortiguador derecho. | L43: 1 | W43: 0 | X43: =W43*T43 -> 0 | AC43: =+AB43*Y43 -> 0 | AD43: =IF(A43=A42,AD42+AC43,AC43) -> 20000 | AE43: =+(Q43)*T43 -> 0 | AF43: =IF(A43=A42,0,(SUMIF($A$3:$A$999956,A43,$AE$3:$AE$999956))) -> 0 | AG43: =IF(A43=A42,0,(SUMIF($A$3:$A$999956,A43,($X$3:$X$999956)))) -> 0 | AH43: =IF(A43=A42,0,(SUMIF($A$3:$A$999956,A43,($AC$3:$AC$999956)))) -> 0 | AK43: =AH43+AG43 -> 0
A44: 1119 | B44: =IF(A44=A43,B43+1,1) -> 1 | C44: 45113 | D44: Crocinelli Carlos | E44: =CONCATENATE(A44,D44,B44) -> 1119Crocinelli Carlos1 | F44: FXU688 | G44: GolTrend | H44: 147891 | I44: Control parcial del vehiculo. | J44: =IF(A44=A43,CONCATENATE(J43," ",I44),I44) -> Control parcial del vehiculo. | L44: 1 | M44: Correa poliv 6SK | N44: Barotto | Q44: =+W44*0.8 -> 12100 | R44: Otros | S44: =+(W44-Q44)/Q44 -> 0.25 | T44: 1 | W44: 15125 | X44: =W44*T44 -> 15125 | AC44: =+AB44*Y44 -> 0 | AD44: =IF(A44=A43,AD43+AC44,AC44) -> 0 | AE44: =+(Q44)*T44 -> 12100 | AF44: =IF(A44=A43,0,(SUMIF($A$3:$A$999956,A44,$AE$3:$AE$999956))) -> 28846.4 | AG44: =IF(A44=A43,0,(SUMIF($A$3:$A$999956,A44,($X$3:$X$999956)))) -> 35695 | AH44: =IF(A44=A43,0,(SUMIF($A$3:$A$999956,A44,($AC$3:$AC$999956)))) -> 18000 | AK44: =AH44+AG44 -> 53695
A45: 1119 | B45: =IF(A45=A44,B44+1,1) -> 2 | C45: =IF(A45=A44,C44,"") -> 45113 | D45: =IF(A45=A44,D44,"") -> Crocinelli Carlos | E45: =CONCATENATE(A45,D45,B45) -> 1119Crocinelli Carlos2 | I45: Cambiar ambas correas poli V y polea tensora fija. | J45: =IF(A45=A44,CONCATENATE(J44," ",I45),I45) -> Control parcial del vehiculo. Cambiar ambas correas poli V y polea tensora fija. | L45: 1 | M45: Polea tensora de correa poliv | N45: Barotto | Q45: =+W45*0.8 -> 9486.4 | S45: =+(W45-Q45)/Q45 -> 0.25 | T45: 1 | W45: 11858 | X45: =W45*T45 -> 11858 | AC45: =+AB45*Y45 -> 0 | AD45: =IF(A45=A44,AD44+AC45,AC45) -> 0 | AE45: =+(Q45)*T45 -> 9486.4 | AF45: =IF(A45=A44,0,(SUMIF($A$3:$A$999956,A45,$AE$3:$AE$999956))) -> 0 | AG45: =IF(A45=A44,0,(SUMIF($A$3:$A$999956,A45,($X$3:$X$999956)))) -> 0 | AH45: =IF(A45=A44,0,(SUMIF($A$3:$A$999956,A45,($AC$3:$AC$999956)))) -> 0 | AK45: =AH45+AG45 -> 0
A46: 1119 | B46: =IF(A46=A45,B45+1,1) -> 3 | C46: =IF(A46=A45,C45,"") -> 45113 | D46: =IF(A46=A45,D45,"") -> Crocinelli Carlos | E46: =CONCATENATE(A46,D46,B46) -> 1119Crocinelli Carlos3 | J46: =IF(A46=A45,CONCATENATE(J45," ",I46),I46) -> Control parcial del vehiculo. Cambiar ambas correas poli V y polea tensora fija. | L46: 1 | M46: Correa poliv 3SK | N46: Taller | Q46: =+W46/(1+S46) -> 7260 | S46: 0.2 | T46: 1 | W46: 8712 | X46: =W46*T46 -> 8712 | Y46: 1 | AB46: 18000 | AC46: =+AB46*Y46 -> 18000 | AD46: =IF(A46=A45,AD45+AC46,AC46) -> 18000 | AE46: =+(Q46)*T46 -> 7260 | AF46: =IF(A46=A45,0,(SUMIF($A$3:$A$999956,A46,$AE$3:$AE$999956))) -> 0 | AG46: =IF(A46=A45,0,(SUMIF($A$3:$A$999956,A46,($X$3:$X$999956)))) -> 0 | AH46: =IF(A46=A45,0,(SUMIF($A$3:$A$999956,A46,($AC$3:$AC$999956)))) -> 0 | AK46: =AH46+AG46 -> 0
A47: 1120 | B47: =IF(A47=A46,B46+1,1) -> 1 | C47: 45114 | D47: Martin Jose | E47: =CONCATENATE(A47,D47,B47) -> 1120Martin Jose1 | F47: AC369PI | H47: 104003 | I47: Desarmar distribución completa. | J47: =IF(A47=A46,CONCATENATE(J46," ",I47),I47) -> Desarmar distribución completa. | L47: 1 | M47: Correa poliv | N47: Barotto | Q47: =+W47*0.8 -> 7040 | R47: Distribución | S47: =+(W47-Q47)/Q47 -> 0.25 | T47: 1 | W47: 8800 | X47: =W47*T47 -> 8800 | AC47: =+AB47*Y47 -> 0 | AD47: =IF(A47=A46,AD46+AC47,AC47) -> 0 | AE47: =+(Q47)*T47 -> 7040 | AF47: =IF(A47=A46,0,(SUMIF($A$3:$A$999956,A47,$AE$3:$AE$999956))) -> 51334 | AG47: =IF(A47=A46,0,(SUMIF($A$3:$A$999956,A47,($X$3:$X$999956)))) -> 67000 | AH47: =IF(A47=A46,0,(SUMIF($A$3:$A$999956,A47,($AC$3:$AC$999956)))) -> 35000 | AK47: =AH47+AG47 -> 102000
A48: 1120 | B48: =IF(A48=A47,B47+1,1) -> 2 | C48: =IF(A48=A47,C47,"") -> 45114 | D48: =IF(A48=A47,D47,"") -> Martin Jose | E48: =CONCATENATE(A48,D48,B48) -> 1120Martin Jose2 | I48: Cambiar kit de distribución con bomba de agua. | J48: =IF(A48=A47,CONCATENATE(J47," ",I48),I48) -> Desarmar distribución completa. Cambiar kit de distribución con bomba de agua. | L48: 1 | M48: Bomba de agua | N48: Taller | Q48: =+W48/(1+S48) -> 12500 | S48: 0.2 | T48: 1 | W48: 15000 | X48: =W48*T48 -> 15000 | AC48: =+AB48*Y48 -> 0 | AD48: =IF(A48=A47,AD47+AC48,AC48) -> 0 | AE48: =+(Q48)*T48 -> 12500 | AF48: =IF(A48=A47,0,(SUMIF($A$3:$A$999956,A48,$AE$3:$AE$999956))) -> 0 | AG48: =IF(A48=A47,0,(SUMIF($A$3:$A$999956,A48,($X$3:$X$999956)))) -> 0 | AH48: =IF(A48=A47,0,(SUMIF($A$3:$A$999956,A48,($AC$3:$AC$999956)))) -> 0 | AK48: =AH48+AG48 -> 0
A49: 1120 | B49: =IF(A49=A48,B48+1,1) -> 3 | C49: =IF(A49=A48,C48,"") -> 45114 | D49: =IF(A49=A48,D48,"") -> Martin Jose | E49: =CONCATENATE(A49,D49,B49) -> 1120Martin Jose3 | I49: Liquido refrigerante y correa poliv. | J49: =IF(A49=A48,CONCATENATE(J48," ",I49),I49) -> Desarmar distribución completa. Cambiar kit de distribución con bomba de agua. Liquido refrigerante y correa poliv. | L49: 1 | M49: Correa poliv 6SK | N49: Barotto | Q49: =+W49*0.8 -> 10000 | S49: =+(W49-Q49)/Q49 -> 0.25 | T49: 1 | W49: 12500 | X49: =W49*T49 -> 12500 | AC49: =+AB49*Y49 -> 0 | AD49: =IF(A49=A48,AD48+AC49,AC49) -> 0 | AE49: =+(Q49)*T49 -> 10000 | AF49: =IF(A49=A48,0,(SUMIF($A$3:$A$999956,A49,$AE$3:$AE$999956))) -> 0 | AG49: =IF(A49=A48,0,(SUMIF($A$3:$A$999956,A49,($X$3:$X$999956)))) -> 0 | AH49: =IF(A49=A48,0,(SUMIF($A$3:$A$999956,A49,($AC$3:$AC$999956)))) -> 0 | AK49: =AH49+AG49 -> 0
A50: 1120 | B50: =IF(A50=A49,B49+1,1) -> 4 | C50: =IF(A50=A49,C49,"") -> 45114 | D50: =IF(A50=A49,D49,"") -> Martin Jose | E50: =CONCATENATE(A50,D50,B50) -> 1120Martin Jose4 | J50: =IF(A50=A49,CONCATENATE(J49," ",I50),I50) -> Desarmar distribución completa. Cambiar kit de distribución con bomba de agua. Liquido refrigerante y correa poliv. | L50: 1 | M50: Kit distribución | N50: Taller | Q50: =+W50/(1+S50) -> 20000 | S50: 0.2 | T50: 1 | W50: 24000 | X50: =W50*T50 -> 24000 | Y50: 1 | AB50: 35000 | AC50: =+AB50*Y50 -> 35000 | AD50: =IF(A50=A49,AD49+AC50,AC50) -> 35000 | AE50: =+(Q50)*T50 -> 20000 | AF50: =IF(A50=A49,0,(SUMIF($A$3:$A$999956,A50,$AE$3:$AE$999956))) -> 0 | AG50: =IF(A50=A49,0,(SUMIF($A$3:$A$999956,A50,($X$3:$X$999956)))) -> 0 | AH50: =IF(A50=A49,0,(SUMIF($A$3:$A$999956,A50,($AC$3:$AC$999956)))) -> 0 | AK50: =AH50+AG50 -> 0
A51: 1120 | B51: =IF(A51=A50,B50+1,1) -> 5 | C51: =IF(A51=A50,C50,"") -> 45114 | D51: =IF(A51=A50,D50,"") -> Martin Jose | E51: =CONCATENATE(A51,D51,B51) -> 1120Martin Jose5 | J51: =IF(A51=A50,CONCATENATE(J50," ",I51),I51) -> Desarmar distribución completa. Cambiar kit de distribución con bomba de agua. Liquido refrigerante y correa poliv. | L51: 1 | M51: Liquido refrigerante + agua destilada | N51: Taller | Q51: 1794 | S51: =+(W51-Q51)/Q51 -> 2.7346711 | T51: 1 | W51: 6700 | X51: =W51*T51 -> 6700 | AC51: =+AB51*Y51 -> 0 | AD51: =IF(A51=A50,AD50+AC51,AC51) -> 35000 | AE51: =+(Q51)*T51 -> 1794 | AF51: =IF(A51=A50,0,(SUMIF($A$3:$A$999956,A51,$AE$3:$AE$999956))) -> 0 | AG51: =IF(A51=A50,0,(SUMIF($A$3:$A$999956,A51,($X$3:$X$999956)))) -> 0 | AH51: =IF(A51=A50,0,(SUMIF($A$3:$A$999956,A51,($AC$3:$AC$999956)))) -> 0 | AK51: =AH51+AG51 -> 0
A52: 1121 | B52: =IF(A52=A51,B51+1,1) -> 1 | C52: 45114 | D52: Formini Victor | E52: =CONCATENATE(A52,D52,B52) -> 1121Formini Victor1 | I52: Control tren delantero. | J52: =IF(A52=A51,CONCATENATE(J51," ",I52),I52) -> Control tren delantero. | L52: 1 | M52: Bieleta barra estabilizadora izquierda | N52: Ferrando | Q52: =+W52*0.8 -> 5520 | R52: Otros | S52: =+(W52-Q52)/Q52 -> 0.25 | T52: 1 | W52: 6900 | X52: =W52*T52 -> 6900 | Y52: 1 | AB52: 4000 | AC52: =+AB52*Y52 -> 4000 | AD52: =IF(A52=A51,AD51+AC52,AC52) -> 4000 | AE52: =+(Q52)*T52 -> 5520 | AF52: =IF(A52=A51,0,(SUMIF($A$3:$A$999956,A52,$AE$3:$AE$999956))) -> 5520 | AG52: =IF(A52=A51,0,(SUMIF($A$3:$A$999956,A52,($X$3:$X$999956)))) -> 6900 | AH52: =IF(A52=A51,0,(SUMIF($A$3:$A$999956,A52,($AC$3:$AC$999956)))) -> 4000 | AK52: =AH52+AG52 -> 10900
A53: 1121 | B53: =IF(A53=A52,B52+1,1) -> 2 | C53: =IF(A53=A52,C52,"") -> 45114 | D53: =IF(A53=A52,D52,"") -> Formini Victor | E53: =CONCATENATE(A53,D53,B53) -> 1121Formini Victor2 | I53: Cambiar bieleta barra estabilizadora lado izquierdo. | J53: =IF(A53=A52,CONCATENATE(J52," ",I53),I53) -> Control tren delantero. Cambiar bieleta barra estabilizadora lado izquierdo. | L53: 1 | W53: 0 | X53: =W53*T53 -> 0 | AC53: =+AB53*Y53 -> 0 | AD53: =IF(A53=A52,AD52+AC53,AC53) -> 4000 | AE53: =+(Q53)*T53 -> 0 | AF53: =IF(A53=A52,0,(SUMIF($A$3:$A$999956,A53,$AE$3:$AE$999956))) -> 0 | AG53: =IF(A53=A52,0,(SUMIF($A$3:$A$999956,A53,($X$3:$X$999956)))) -> 0 | AH53: =IF(A53=A52,0,(SUMIF($A$3:$A$999956,A53,($AC$3:$AC$999956)))) -> 0 | AK53: =AH53+AG53 -> 0
A54: 1122 | B54: =IF(A54=A53,B53+1,1) -> 1 | C54: 45114 | D54: Carrara Luis (bocha) | E54: =CONCATENATE(A54,D54,B54) -> 1122Carrara Luis (bocha)1 | F54: AD225VD | G54: Citroen C4 LOUNGE | I54: Auxilio. | J54: =IF(A54=A53,CONCATENATE(J53," ",I54),I54) -> Auxilio. | L54: 1 | M54: Bateria | N54: Atilio Lucero | Q54: =W54 -> 41000 | S54: =+(W54-Q54)/Q54 -> 0 | T54: 1 | W54: 41000 | X54: =W54*T54 -> 41000 | Y54: 1 | AB54: 5000 | AC54: =+AB54*Y54 -> 5000 | AD54: =IF(A54=A53,AD53+AC54,AC54) -> 5000 | AE54: =+(Q54)*T54 -> 41000 | AF54: =IF(A54=A53,0,(SUMIF($A$3:$A$999956,A54,$AE$3:$AE$999956))) -> 41000 | AG54: =IF(A54=A53,0,(SUMIF($A$3:$A$999956,A54,($X$3:$X$999956)))) -> 41000 | AH54: =IF(A54=A53,0,(SUMIF($A$3:$A$999956,A54,($AC$3:$AC$999956)))) -> 5000 | AK54: =AH54+AG54 -> 46000
A55: 1122 | B55: =IF(A55=A54,B54+1,1) -> 2 | C55: =IF(A55=A54,C54,"") -> 45114 | D55: =IF(A55=A54,D54,"") -> Carrara Luis (bocha) | E55: =CONCATENATE(A55,D55,B55) -> 1122Carrara Luis (bocha)2 | I55: Cambio Bateria | J55: =IF(A55=A54,CONCATENATE(J54," ",I55),I55) -> Auxilio. Cambio Bateria | L55: 1 | W55: 0 | X55: =W55*T55 -> 0 | AC55: =+AB55*Y55 -> 0 | AD55: =IF(A55=A54,AD54+AC55,AC55) -> 5000 | AE55: =+(Q55)*T55 -> 0 | AF55: =IF(A55=A54,0,(SUMIF($A$3:$A$999956,A55,$AE$3:$AE$999956))) -> 0 | AG55: =IF(A55=A54,0,(SUMIF($A$3:$A$999956,A55,($X$3:$X$999956)))) -> 0 | AH55: =IF(A55=A54,0,(SUMIF($A$3:$A$999956,A55,($AC$3:$AC$999956)))) -> 0 | AK55: =AH55+AG55 -> 0
A56: 1123 | B56: =IF(A56=A55,B55+1,1) -> 1 | C56: 45114 | D56: Muñoz | E56: =CONCATENATE(A56,D56,B56) -> 1123Muñoz1 | F56: AO556QH | G56: Fiat Movie | H56: 24808 | I56: Service cambio de aceite y filtros. | J56: =IF(A56=A55,CONCATENATE(J55," ",I56),I56) -> Service cambio de aceite y filtros. | L56: 1 | M56: Aceite 10w40 | N56: Taller | Q56: 1214.84 | R56: Service | S56: =+(W56-Q56)/Q56 -> 1.5723552 | T56: 4 | W56: 3125 | X56: =W56*T56 -> 12500 | AC56: =+AB56*Y56 -> 0 | AD56: =IF(A56=A55,AD55+AC56,AC56) -> 0 | AE56: =+(Q56)*T56 -> 4859.36 | AF56: =IF(A56=A55,0,(SUMIF($A$3:$A$999956,A56,$AE$3:$AE$999956))) -> 12512.36 | AG56: =IF(A56=A55,0,(SUMIF($A$3:$A$999956,A56,($X$3:$X$999956)))) -> 31700 | AH56: =IF(A56=A55,0,(SUMIF($A$3:$A$999956,A56,($AC$3:$AC$999956)))) -> 25000 | AK56: =AH56+AG56 -> 56700
A57: 1123 | B57: =IF(A57=A56,B56+1,1) -> 2 | C57: =IF(A57=A56,C56,"") -> 45114 | D57: =IF(A57=A56,D56,"") -> Muñoz | E57: =CONCATENATE(A57,D57,B57) -> 1123Muñoz2 | I57: Control del vehículo. | J57: =IF(A57=A56,CONCATENATE(J56," ",I57),I57) -> Service cambio de aceite y filtros. Control del vehículo. | L57: 1 | M57: Kit de Filtros | N57: Taller | Q57: 5500 | S57: =+(W57-Q57)/Q57 -> 1.2727273 | T57: 1 | W57: 12500 | X57: =W57*T57 -> 12500 | AC57: =+AB57*Y57 -> 0 | AD57: =IF(A57=A56,AD56+AC57,AC57) -> 0 | AE57: =+(Q57)*T57 -> 5500 | AF57: =IF(A57=A56,0,(SUMIF($A$3:$A$999956,A57,$AE$3:$AE$999956))) -> 0 | AG57: =IF(A57=A56,0,(SUMIF($A$3:$A$999956,A57,($X$3:$X$999956)))) -> 0 | AH57: =IF(A57=A56,0,(SUMIF($A$3:$A$999956,A57,($AC$3:$AC$999956)))) -> 0 | AK57: =AH57+AG57 -> 0
A58: 1123 | B58: =IF(A58=A57,B57+1,1) -> 3 | C58: =IF(A58=A57,C57,"") -> 45114 | D58: =IF(A58=A57,D57,"") -> Muñoz | E58: =CONCATENATE(A58,D58,B58) -> 1123Muñoz3 | I58: Lavado. Rotacion de ruedas. | J58: =IF(A58=A57,CONCATENATE(J57," ",I58),I58) -> Service cambio de aceite y filtros. Control del vehículo. Lavado. Rotacion de ruedas. | L58: 1 | M58: Liquido refrigerante + destilada | N58: Taller | Q58: 2153 | S58: =+(W58-Q58)/Q58 -> 2.1119368 | T58: 1 | W58: 6700 | X58: =W58*T58 -> 6700 | Y58: 1 | AB58: 25000 | AC58: =+AB58*Y58 -> 25000 | AD58: =IF(A58=A57,AD57+AC58,AC58) -> 25000 | AE58: =+(Q58)*T58 -> 2153 | AF58: =IF(A58=A57,0,(SUMIF($A$3:$A$999956,A58,$AE$3:$AE$999956))) -> 0 | AG58: =IF(A58=A57,0,(SUMIF($A$3:$A$999956,A58,($X$3:$X$999956)))) -> 0 | AH58: =IF(A58=A57,0,(SUMIF($A$3:$A$999956,A58,($AC$3:$AC$999956)))) -> 0 | AK58: =AH58+AG58 -> 0
A59: 1123 | B59: =IF(A59=A58,B58+1,1) -> 4 | C59: =IF(A59=A58,C58,"") -> 45114 | D59: =IF(A59=A58,D58,"") -> Muñoz | E59: =CONCATENATE(A59,D59,B59) -> 1123Muñoz4 | I59: Cambio liquido refrigerante. | J59: =IF(A59=A58,CONCATENATE(J58," ",I59),I59) -> Service cambio de aceite y filtros. Control del vehículo. Lavado. Rotacion de ruedas. Cambio liquido refrigerante. | L59: 1 | W59: 0 | X59: =W59*T59 -> 0 | AC59: =+AB59*Y59 -> 0 | AD59: =IF(A59=A58,AD58+AC59,AC59) -> 25000 | AE59: =+(Q59)*T59 -> 0 | AF59: =IF(A59=A58,0,(SUMIF($A$3:$A$999956,A59,$AE$3:$AE$999956))) -> 0 | AG59: =IF(A59=A58,0,(SUMIF($A$3:$A$999956,A59,($X$3:$X$999956)))) -> 0 | AH59: =IF(A59=A58,0,(SUMIF($A$3:$A$999956,A59,($AC$3:$AC$999956)))) -> 0 | AK59: =AH59+AG59 -> 0
A60: 1123 | B60: =IF(A60=A59,B59+1,1) -> 5 | C60: =IF(A60=A59,C59,"") -> 45114 | D60: =IF(A60=A59,D59,"") -> Muñoz | E60: =CONCATENATE(A60,D60,B60) -> 1123Muñoz5 | I60: Limpieza de déposito recuperador de agua y del circuito de refrigeración y purgado del mismo. | J60: =IF(A60=A59,CONCATENATE(J59," ",I60),I60) -> Service cambio de aceite y filtros. Control del vehículo. Lavado. Rotacion de ruedas. Cambio liquido refrigerante. Limpieza de déposito recuperador de agua y del circuito de refrigeración y purgado del mismo. | L60: 1 | W60: 0 | X60: =W60*T60 -> 0 | AC60: =+AB60*Y60 -> 0 | AD60: =IF(A60=A59,AD59+AC60,AC60) -> 25000 | AE60: =+(Q60)*T60 -> 0 | AF60: =IF(A60=A59,0,(SUMIF($A$3:$A$999956,A60,$AE$3:$AE$999956))) -> 0 | AG60: =IF(A60=A59,0,(SUMIF($A$3:$A$999956,A60,($X$3:$X$999956)))) -> 0 | AH60: =IF(A60=A59,0,(SUMIF($A$3:$A$999956,A60,($AC$3:$AC$999956)))) -> 0 | AK60: =AH60+AG60 -> 0
A61: 1124 | B61: =IF(A61=A60,B60+1,1) -> 1 | C61: 45114 | D61: Barroso Ruben | E61: =CONCATENATE(A61,D61,B61) -> 1124Barroso Ruben1 | G61: Ford Ranger | I61: Sacar tanque de combustible. | J61: =IF(A61=A60,CONCATENATE(J60," ",I61),I61) -> Sacar tanque de combustible. | L61: 1 | M61: Bomba de gasoil eléctrica | N61: Barotto | Q61: =+W61*0.8 -> 24000 | R61: Motor | S61: =+(W61-Q61)/Q61 -> 0.25 | T61: 1 | W61: 30000 | X61: =W61*T61 -> 30000 | AC61: =+AB61*Y61 -> 0 | AD61: =IF(A61=A60,AD60+AC61,AC61) -> 0 | AE61: =+(Q61)*T61 -> 24000 | AF61: =IF(A61=A60,0,(SUMIF($A$3:$A$999956,A61,$AE$3:$AE$999956))) -> 80610 | AG61: =IF(A61=A60,0,(SUMIF($A$3:$A$999956,A61,($X$3:$X$999956)))) -> 98300 | AH61: =IF(A61=A60,0,(SUMIF($A$3:$A$999956,A61,($AC$3:$AC$999956)))) -> 55000 | AK61: =AH61+AG61 -> 153300
A62: 1124 | B62: =IF(A62=A61,B61+1,1) -> 2 | C62: 45114 | D62: =IF(A62=A61,D61,"") -> Barroso Ruben | E62: =CONCATENATE(A62,D62,B62) -> 1124Barroso Ruben2 | I62: Limpieza y cambiar bomba eléctrica. | J62: =IF(A62=A61,CONCATENATE(J61," ",I62),I62) -> Sacar tanque de combustible. Limpieza y cambiar bomba eléctrica. | L62: 1 | M62: Filtro gasoil | N62: Ferrando | Q62: =+W62*0.8 -> 7360 | S62: =+(W62-Q62)/Q62 -> 0.25 | T62: 1 | W62: 9200 | X62: =W62*T62 -> 9200 | AC62: =+AB62*Y62 -> 0 | AD62: =IF(A62=A61,AD61+AC62,AC62) -> 0 | AE62: =+(Q62)*T62 -> 7360 | AF62: =IF(A62=A61,0,(SUMIF($A$3:$A$999956,A62,$AE$3:$AE$999956))) -> 0 | AG62: =IF(A62=A61,0,(SUMIF($A$3:$A$999956,A62,($X$3:$X$999956)))) -> 0 | AH62: =IF(A62=A61,0,(SUMIF($A$3:$A$999956,A62,($AC$3:$AC$999956)))) -> 0 | AK62: =AH62+AG62 -> 0
A63: 1124 | B63: =IF(A63=A62,B62+1,1) -> 3 | C63: =IF(A63=A62,C62,"") -> 45114 | D63: =IF(A63=A62,D62,"") -> Barroso Ruben | E63: =CONCATENATE(A63,D63,B63) -> 1124Barroso Ruben3 | I63: Desarmar frente de motor y cambiar retén de polea de cigüeñal, amortiguadores delanteros. | J63: =IF(A63=A62,CONCATENATE(J62," ",I63),I63) -> Sacar tanque de combustible. Limpieza y cambiar bomba eléctrica. Desarmar frente de motor y cambiar retén de polea de cigüeñal, amortiguadores delanteros. | L63: 1 | M63: Amortiguadores delanteros | N63: Taller | Q63: =+W63/(1+S63) -> 41333.333 | S63: 0.2 | T63: 1 | W63: 49600 | X63: =W63*T63 -> 49600 | AC63: =+AB63*Y63 -> 0 | AD63: =IF(A63=A62,AD62+AC63,AC63) -> 0 | AE63: =+(Q63)*T63 -> 41333.333 | AF63: =IF(A63=A62,0,(SUMIF($A$3:$A$999956,A63,$AE$3:$AE$999956))) -> 0 | AG63: =IF(A63=A62,0,(SUMIF($A$3:$A$999956,A63,($X$3:$X$999956)))) -> 0 | AH63: =IF(A63=A62,0,(SUMIF($A$3:$A$999956,A63,($AC$3:$AC$999956)))) -> 0 | AK63: =AH63+AG63 -> 0
A64: 1124 | B64: =IF(A64=A63,B63+1,1) -> 4 | C64: =IF(A64=A63,C63,"") -> 45114 | D64: =IF(A64=A63,D63,"") -> Barroso Ruben | E64: =CONCATENATE(A64,D64,B64) -> 1124Barroso Ruben4 | I64: Puesta en marcha. | J64: =IF(A64=A63,CONCATENATE(J63," ",I64),I64) -> Sacar tanque de combustible. Limpieza y cambiar bomba eléctrica. Desarmar frente de motor y cambiar retén de polea de cigüeñal, amortiguadores delanteros. Puesta en marcha. | L64: 1 | M64: Gasoil | N64: Taller | Q64: =+W64/(1+S64) -> 4166.6667 | S64: 0.2 | T64: 1 | W64: 5000 | X64: =W64*T64 -> 5000 | AC64: =+AB64*Y64 -> 0 | AD64: =IF(A64=A63,AD63+AC64,AC64) -> 0 | AE64: =+(Q64)*T64 -> 4166.6667 | AF64: =IF(A64=A63,0,(SUMIF($A$3:$A$999956,A64,$AE$3:$AE$999956))) -> 0 | AG64: =IF(A64=A63,0,(SUMIF($A$3:$A$999956,A64,($X$3:$X$999956)))) -> 0 | AH64: =IF(A64=A63,0,(SUMIF($A$3:$A$999956,A64,($AC$3:$AC$999956)))) -> 0 | AK64: =AH64+AG64 -> 0
A65: 1124 | B65: =IF(A65=A64,B64+1,1) -> 5 | C65: =IF(A65=A64,C64,"") -> 45114 | D65: =IF(A65=A64,D64,"") -> Barroso Ruben | E65: =CONCATENATE(A65,D65,B65) -> 1124Barroso Ruben5 | J65: =IF(A65=A64,CONCATENATE(J64," ",I65),I65) -> Sacar tanque de combustible. Limpieza y cambiar bomba eléctrica. Desarmar frente de motor y cambiar retén de polea de cigüeñal, amortiguadores delanteros. Puesta en marcha. | L65: 1 | M65: Retén de distribución 3.0 tapa | N65: Taller | Q65: =+W65/(1+S65) -> 3750 | S65: 0.2 | T65: 1 | W65: 4500 | X65: =W65*T65 -> 4500 | Y65: 1 | AB65: 55000 | AC65: =+AB65*Y65 -> 55000 | AD65: =IF(A65=A64,AD64+AC65,AC65) -> 55000 | AE65: =+(Q65)*T65 -> 3750 | AF65: =IF(A65=A64,0,(SUMIF($A$3:$A$999956,A65,$AE$3:$AE$999956))) -> 0 | AG65: =IF(A65=A64,0,(SUMIF($A$3:$A$999956,A65,($X$3:$X$999956)))) -> 0 | AH65: =IF(A65=A64,0,(SUMIF($A$3:$A$999956,A65,($AC$3:$AC$999956)))) -> 0 | AK65: =AH65+AG65 -> 0
A66: 1124 | B66: =IF(A66=A65,B65+1,1) -> 6 | C66: =IF(A66=A65,C65,"") -> 45114 | D66: =IF(A66=A65,D65,"") -> Barroso Ruben | E66: =CONCATENATE(A66,D66,B66) -> 1124Barroso Ruben6 | J66: =IF(A66=A65,CONCATENATE(J65," ",I66),I66) -> Sacar tanque de combustible. Limpieza y cambiar bomba eléctrica. Desarmar frente de motor y cambiar retén de polea de cigüeñal, amortiguadores delanteros. Puesta en marcha. | L66: 1 | W66: 0 | X66: =W66*T66 -> 0 | AC66: =+AB66*Y66 -> 0 | AD66: =IF(A66=A65,AD65+AC66,AC66) -> 55000 | AE66: =+(Q66)*T66 -> 0 | AF66: =IF(A66=A65,0,(SUMIF($A$3:$A$999956,A66,$AE$3:$AE$999956))) -> 0 | AG66: =IF(A66=A65,0,(SUMIF($A$3:$A$999956,A66,($X$3:$X$999956)))) -> 0 | AH66: =IF(A66=A65,0,(SUMIF($A$3:$A$999956,A66,($AC$3:$AC$999956)))) -> 0 | AK66: =AH66+AG66 -> 0
A67: 1125 | B67: =IF(A67=A66,B66+1,1) -> 1 | C67: 45114 | D67: Barroso Willy | E67: =CONCATENATE(A67,D67,B67) -> 1125Barroso Willy1 | F67: AE154FT | G67: Chevrolet Prisma | H67: 52989 | I67: Service cambio de aceite y filtros. Colocar liquido desencrustante para limpieza interior de block. Rotacion de ruedas. Cambio juego de bujias. | J67: =IF(A67=A66,CONCATENATE(J66," ",I67),I67) -> Service cambio de aceite y filtros. Colocar liquido desencrustante para limpieza interior de block. Rotacion de ruedas. Cambio juego de bujias. | K67: Cristian | L67: 1 | M67: Aceite 5w30 | N67: Taller | Q67: 2112 | R67: Service | S67: =+(W67-Q67)/Q67 -> 2.1723485 | T67: 4 | W67: 6700 | X67: =W67*T67 -> 26800 | Y67: 1 | AB67: 42000 | AC67: =+AB67*Y67 -> 42000 | AD67: =IF(A67=A66,AD66+AC67,AC67) -> 42000 | AE67: =+(Q67)*T67 -> 8448 | AF67: =IF(A67=A66,0,(SUMIF($A$3:$A$999956,A67,$AE$3:$AE$999956))) -> 26798 | AG67: =IF(A67=A66,0,(SUMIF($A$3:$A$999956,A67,($X$3:$X$999956)))) -> 56000 | AH67: =IF(A67=A66,0,(SUMIF($A$3:$A$999956,A67,($AC$3:$AC$999956)))) -> 42000 | AK67: =AH67+AG67 -> 98000
A68: 1125 | B68: =IF(A68=A67,B67+1,1) -> 2 | C68: =IF(A68=A67,C67,"") -> 45114 | D68: =IF(A68=A67,D67,"") -> Barroso Willy | E68: =CONCATENATE(A68,D68,B68) -> 1125Barroso Willy2 | J68: =IF(A68=A67,CONCATENATE(J67," ",I68),I68) -> Service cambio de aceite y filtros. Colocar liquido desencrustante para limpieza interior de block. Rotacion de ruedas. Cambio juego de bujias. | L68: 1 | M68: Juego de bujias | N68: Taller | Q68: =+W68/(1+S68) -> 2500 | S68: 0.2 | T68: 4 | W68: 3000 | X68: =W68*T68 -> 12000 | AC68: =+AB68*Y68 -> 0 | AD68: =IF(A68=A67,AD67+AC68,AC68) -> 42000 | AE68: =+(Q68)*T68 -> 10000 | AF68: =IF(A68=A67,0,(SUMIF($A$3:$A$999956,A68,$AE$3:$AE$999956))) -> 0 | AG68: =IF(A68=A67,0,(SUMIF($A$3:$A$999956,A68,($X$3:$X$999956)))) -> 0 | AH68: =IF(A68=A67,0,(SUMIF($A$3:$A$999956,A68,($AC$3:$AC$999956)))) -> 0 | AK68: =AH68+AG68 -> 0
A69: 1125 | B69: =IF(A69=A68,B68+1,1) -> 3 | C69: =IF(A69=A68,C68,"") -> 45114 | D69: =IF(A69=A68,D68,"") -> Barroso Willy | E69: =CONCATENATE(A69,D69,B69) -> 1125Barroso Willy3 | J69: =IF(A69=A68,CONCATENATE(J68," ",I69),I69) -> Service cambio de aceite y filtros. Colocar liquido desencrustante para limpieza interior de block. Rotacion de ruedas. Cambio juego de bujias. | L69: 1 | M69: Filtro aire | N69: Taller | Q69: 2000 | S69: =+(W69-Q69)/Q69 -> 2.45 | T69: 1 | W69: 6900 | X69: =W69*T69 -> 6900 | AC69: =+AB69*Y69 -> 0 | AD69: =IF(A69=A68,AD68+AC69,AC69) -> 42000 | AE69: =+(Q69)*T69 -> 2000 | AF69: =IF(A69=A68,0,(SUMIF($A$3:$A$999956,A69,$AE$3:$AE$999956))) -> 0 | AG69: =IF(A69=A68,0,(SUMIF($A$3:$A$999956,A69,($X$3:$X$999956)))) -> 0 | AH69: =IF(A69=A68,0,(SUMIF($A$3:$A$999956,A69,($AC$3:$AC$999956)))) -> 0 | AK69: =AH69+AG69 -> 0
A70: 1125 | B70: =IF(A70=A69,B69+1,1) -> 4 | C70: =IF(A70=A69,C69,"") -> 45114 | D70: =IF(A70=A69,D69,"") -> Barroso Willy | E70: =CONCATENATE(A70,D70,B70) -> 1125Barroso Willy4 | J70: =IF(A70=A69,CONCATENATE(J69," ",I70),I70) -> Service cambio de aceite y filtros. Colocar liquido desencrustante para limpieza interior de block. Rotacion de ruedas. Cambio juego de bujias. | L70: 1 | M70: Filtro Aceite | N70: Taller | Q70: 1500 | S70: =+(W70-Q70)/Q70 -> 1.4 | T70: 1 | W70: 3600 | X70: =W70*T70 -> 3600 | AC70: =+AB70*Y70 -> 0 | AD70: =IF(A70=A69,AD69+AC70,AC70) -> 42000 | AE70: =+(Q70)*T70 -> 1500 | AF70: =IF(A70=A69,0,(SUMIF($A$3:$A$999956,A70,$AE$3:$AE$999956))) -> 0 | AG70: =IF(A70=A69,0,(SUMIF($A$3:$A$999956,A70,($X$3:$X$999956)))) -> 0 | AH70: =IF(A70=A69,0,(SUMIF($A$3:$A$999956,A70,($AC$3:$AC$999956)))) -> 0 | AK70: =AH70+AG70 -> 0
A71: 1125 | B71: =IF(A71=A70,B70+1,1) -> 5 | C71: =IF(A71=A70,C70,"") -> 45114 | D71: =IF(A71=A70,D70,"") -> Barroso Willy | E71: =CONCATENATE(A71,D71,B71) -> 1125Barroso Willy5 | J71: =IF(A71=A70,CONCATENATE(J70," ",I71),I71) -> Service cambio de aceite y filtros. Colocar liquido desencrustante para limpieza interior de block. Rotacion de ruedas. Cambio juego de bujias. | L71: 1 | M71: Filtro pólen | N71: Taller | Q71: =+W71/(1+S71) -> 2933.3333 | S71: 0.5 | T71: 1 | W71: 4400 | X71: =W71*T71 -> 4400 | AC71: =+AB71*Y71 -> 0 | AD71: =IF(A71=A70,AD70+AC71,AC71) -> 42000 | AE71: =+(Q71)*T71 -> 2933.3333 | AF71: =IF(A71=A70,0,(SUMIF($A$3:$A$999956,A71,$AE$3:$AE$999956))) -> 0 | AG71: =IF(A71=A70,0,(SUMIF($A$3:$A$999956,A71,($X$3:$X$999956)))) -> 0 | AH71: =IF(A71=A70,0,(SUMIF($A$3:$A$999956,A71,($AC$3:$AC$999956)))) -> 0 | AK71: =AH71+AG71 -> 0
A72: 1125 | B72: =IF(A72=A71,B71+1,1) -> 6 | C72: =IF(A72=A71,C71,"") -> 45114 | D72: =IF(A72=A71,D71,"") -> Barroso Willy | E72: =CONCATENATE(A72,D72,B72) -> 1125Barroso Willy6 | J72: =IF(A72=A71,CONCATENATE(J71," ",I72),I72) -> Service cambio de aceite y filtros. Colocar liquido desencrustante para limpieza interior de block. Rotacion de ruedas. Cambio juego de bujias. | L72: 1 | M72: Liquido desencrustante | N72: Taller | Q72: =+W72/(1+S72) -> 1916.6667 | S72: 0.2 | T72: 1 | W72: 2300 | X72: =W72*T72 -> 2300 | AC72: =+AB72*Y72 -> 0 | AD72: =IF(A72=A71,AD71+AC72,AC72) -> 42000 | AE72: =+(Q72)*T72 -> 1916.6667 | AF72: =IF(A72=A71,0,(SUMIF($A$3:$A$999956,A72,$AE$3:$AE$999956))) -> 0 | AG72: =IF(A72=A71,0,(SUMIF($A$3:$A$999956,A72,($X$3:$X$999956)))) -> 0 | AH72: =IF(A72=A71,0,(SUMIF($A$3:$A$999956,A72,($AC$3:$AC$999956)))) -> 0 | AK72: =AH72+AG72 -> 0
A73: 1126 | B73: =IF(A73=A72,B72+1,1) -> 1 | C73: 45117 | D73: Barroso Willy | E73: =CONCATENATE(A73,D73,B73) -> 1126Barroso Willy1 | F73: AE154FT | G73: Chevrolet Prisma | H73: 52989 | I73: Desarmar distribución completa. Cambiar kit de distribucion. Cambiar termostato. Cambiar bomba de agua. Cambiar correa poly-v de alternador. Cambio de juego de pastillas de freno delateras. Limpieza de circuito de refrigeracion. Cambio de liquido refrigerante, purgado y puesta a punto. Armado total | J73: =IF(A73=A72,CONCATENATE(J72," ",I73),I73) -> Desarmar distribución completa. Cambiar kit de distribucion. Cambiar termostato. Cambiar bomba de agua. Cambiar correa poly-v de alternador. Cambio de juego de pastillas de freno delateras. Limpieza de circuito de refrigeracion. Cambio de liquido refrigerante, purgado y puesta a punto. Armado total | K73: Cristian | L73: 1 | M73: Kit distribucion | N73: Taller | Q73: =+W73/(1+S73) -> 28333.333 | R73: Distribución | S73: 0.2 | T73: 1 | W73: 34000 | X73: =W73*T73 -> 34000 | Y73: 1 | AB73: 103600 | AC73: =+AB73*Y73 -> 103600 | AD73: =IF(A73=A72,AD72+AC73,AC73) -> 103600 | AE73: =+(Q73)*T73 -> 28333.333 | AF73: =IF(A73=A72,0,(SUMIF($A$3:$A$999956,A73,$AE$3:$AE$999956))) -> 86460.667 | AG73: =IF(A73=A72,0,(SUMIF($A$3:$A$999956,A73,($X$3:$X$999956)))) -> 117200 | AH73: =IF(A73=A72,0,(SUMIF($A$3:$A$999956,A73,($AC$3:$AC$999956)))) -> 103600 | AK73: =AH73+AG73 -> 220800
A74: 1126 | B74: =IF(A74=A73,B73+1,1) -> 2 | C74: =IF(A74=A73,C73,"") -> 45117 | D74: =IF(A74=A73,D73,"") -> Barroso Willy | E74: =CONCATENATE(A74,D74,B74) -> 1126Barroso Willy2 | J74: =IF(A74=A73,CONCATENATE(J73," ",I74),I74) -> Desarmar distribución completa. Cambiar kit de distribucion. Cambiar termostato. Cambiar bomba de agua. Cambiar correa poly-v de alternador. Cambio de juego de pastillas de freno delateras. Limpieza de circuito de refrigeracion. Cambio de liquido refrigerante, purgado y puesta a punto. Armado total | L74: 1 | M74: Termostato | N74: Taller | Q74: =+W74/(1+S74) -> 14166.667 | S74: 0.2 | T74: 1 | W74: 17000 | X74: =W74*T74 -> 17000 | AC74: =+AB74*Y74 -> 0 | AD74: =IF(A74=A73,AD73+AC74,AC74) -> 103600 | AE74: =+(Q74)*T74 -> 14166.667 | AF74: =IF(A74=A73,0,(SUMIF($A$3:$A$999956,A74,$AE$3:$AE$999956))) -> 0 | AG74: =IF(A74=A73,0,(SUMIF($A$3:$A$999956,A74,($X$3:$X$999956)))) -> 0 | AH74: =IF(A74=A73,0,(SUMIF($A$3:$A$999956,A74,($AC$3:$AC$999956)))) -> 0 | AK74: =AH74+AG74 -> 0
A75: 1126 | B75: =IF(A75=A74,B74+1,1) -> 3 | C75: =IF(A75=A74,C74,"") -> 45117 | D75: =IF(A75=A74,D74,"") -> Barroso Willy | E75: =CONCATENATE(A75,D75,B75) -> 1126Barroso Willy3 | J75: =IF(A75=A74,CONCATENATE(J74," ",I75),I75) -> Desarmar distribución completa. Cambiar kit de distribucion. Cambiar termostato. Cambiar bomba de agua. Cambiar correa poly-v de alternador. Cambio de juego de pastillas de freno delateras. Limpieza de circuito de refrigeracion. Cambio de liquido refrigerante, purgado y puesta a punto. Armado total | L75: 1 | M75: Bomba de agua | N75: Taller | Q75: =+W75/(1+S75) -> 19000 | S75: 0.2 | T75: 1 | W75: 22800 | X75: =W75*T75 -> 22800 | AC75: =+AB75*Y75 -> 0 | AD75: =IF(A75=A74,AD74+AC75,AC75) -> 103600 | AE75: =+(Q75)*T75 -> 19000 | AF75: =IF(A75=A74,0,(SUMIF($A$3:$A$999956,A75,$AE$3:$AE$999956))) -> 0 | AG75: =IF(A75=A74,0,(SUMIF($A$3:$A$999956,A75,($X$3:$X$999956)))) -> 0 | AH75: =IF(A75=A74,0,(SUMIF($A$3:$A$999956,A75,($AC$3:$AC$999956)))) -> 0 | AK75: =AH75+AG75 -> 0
A76: 1126 | B76: =IF(A76=A75,B75+1,1) -> 4 | C76: =IF(A76=A75,C75,"") -> 45117 | D76: =IF(A76=A75,D75,"") -> Barroso Willy | E76: =CONCATENATE(A76,D76,B76) -> 1126Barroso Willy4 | J76: =IF(A76=A75,CONCATENATE(J75," ",I76),I76) -> Desarmar distribución completa. Cambiar kit de distribucion. Cambiar termostato. Cambiar bomba de agua. Cambiar correa poly-v de alternador. Cambio de juego de pastillas de freno delateras. Limpieza de circuito de refrigeracion. Cambio de liquido refrigerante, purgado y puesta a punto. Armado total | L76: 1 | M76: Correa poliv de alternador | N76: Taller | Q76: =+W76/(1+S76) -> 13333.333 | S76: 0.2 | T76: 1 | W76: 16000 | X76: =W76*T76 -> 16000 | AC76: =+AB76*Y76 -> 0 | AD76: =IF(A76=A75,AD75+AC76,AC76) -> 103600 | AE76: =+(Q76)*T76 -> 13333.333 | AF76: =IF(A76=A75,0,(SUMIF($A$3:$A$999956,A76,$AE$3:$AE$999956))) -> 0 | AG76: =IF(A76=A75,0,(SUMIF($A$3:$A$999956,A76,($X$3:$X$999956)))) -> 0 | AH76: =IF(A76=A75,0,(SUMIF($A$3:$A$999956,A76,($AC$3:$AC$999956)))) -> 0 | AK76: =AH76+AG76 -> 0
A77: 1126 | B77: =IF(A77=A76,B76+1,1) -> 5 | C77: =IF(A77=A76,C76,"") -> 45117 | D77: =IF(A77=A76,D76,"") -> Barroso Willy | E77: =CONCATENATE(A77,D77,B77) -> 1126Barroso Willy5 | J77: =IF(A77=A76,CONCATENATE(J76," ",I77),I77) -> Desarmar distribución completa. Cambiar kit de distribucion. Cambiar termostato. Cambiar bomba de agua. Cambiar correa poly-v de alternador. Cambio de juego de pastillas de freno delateras. Limpieza de circuito de refrigeracion. Cambio de liquido refrigerante, purgado y puesta a punto. Armado total | L77: 1 | M77: Juego de pastillas de freno delanteros | N77: Taller | Q77: =+W77/(1+S77) -> 9833.3333 | S77: 0.2 | T77: 1 | W77: 11800 | X77: =W77*T77 -> 11800 | AC77: =+AB77*Y77 -> 0 | AD77: =IF(A77=A76,AD76+AC77,AC77) -> 103600 | AE77: =+(Q77)*T77 -> 9833.3333 | AF77: =IF(A77=A76,0,(SUMIF($A$3:$A$999956,A77,$AE$3:$AE$999956))) -> 0 | AG77: =IF(A77=A76,0,(SUMIF($A$3:$A$999956,A77,($X$3:$X$999956)))) -> 0 | AH77: =IF(A77=A76,0,(SUMIF($A$3:$A$999956,A77,($AC$3:$AC$999956)))) -> 0 | AK77: =AH77+AG77 -> 0
A78: 1126 | B78: =IF(A78=A77,B77+1,1) -> 6 | C78: =IF(A78=A77,C77,"") -> 45117 | D78: =IF(A78=A77,D77,"") -> Barroso Willy | E78: =CONCATENATE(A78,D78,B78) -> 1126Barroso Willy6 | J78: =IF(A78=A77,CONCATENATE(J77," ",I78),I78) -> Desarmar distribución completa. Cambiar kit de distribucion. Cambiar termostato. Cambiar bomba de agua. Cambiar correa poly-v de alternador. Cambio de juego de pastillas de freno delateras. Limpieza de circuito de refrigeracion. Cambio de liquido refrigerante, purgado y puesta a punto. Armado total | L78: 1 | M78: Liquido refrigerante+agua destilada | N78: Taller | Q78: 1794 | S78: =+(W78-Q78)/Q78 -> 7.6956522 | T78: 1 | W78: 15600 | X78: =W78*T78 -> 15600 | AC78: =+AB78*Y78 -> 0 | AD78: =IF(A78=A77,AD77+AC78,AC78) -> 103600 | AE78: =+(Q78)*T78 -> 1794 | AF78: =IF(A78=A77,0,(SUMIF($A$3:$A$999956,A78,$AE$3:$AE$999956))) -> 0 | AG78: =IF(A78=A77,0,(SUMIF($A$3:$A$999956,A78,($X$3:$X$999956)))) -> 0 | AH78: =IF(A78=A77,0,(SUMIF($A$3:$A$999956,A78,($AC$3:$AC$999956)))) -> 0 | AK78: =AH78+AG78 -> 0
A79: 1127 | B79: =IF(A79=A78,B78+1,1) -> 1 | C79: 45117 | D79: Lucero Adrian | E79: =CONCATENATE(A79,D79,B79) -> 1127Lucero Adrian1 | F79: EFR454 | G79: Palio | I79: Auxilio y cambio de bateria. | J79: =IF(A79=A78,CONCATENATE(J78," ",I79),I79) -> Auxilio y cambio de bateria. | L79: 1 | M79: Bateria Moura | N79: Atilio Lucero | Q79: =W79 -> 56250 | R79: Otros | S79: =+(W79-Q79)/Q79 -> 0 | T79: 1 | W79: 56250 | X79: =W79*T79 -> 56250 | Y79: 1 | AB79: 3000 | AC79: =+AB79*Y79 -> 3000 | AD79: =IF(A79=A78,AD78+AC79,AC79) -> 3000 | AE79: =+(Q79)*T79 -> 56250 | AF79: =IF(A79=A78,0,(SUMIF($A$3:$A$999956,A79,$AE$3:$AE$999956))) -> 56250 | AG79: =IF(A79=A78,0,(SUMIF($A$3:$A$999956,A79,($X$3:$X$999956)))) -> 56250 | AH79: =IF(A79=A78,0,(SUMIF($A$3:$A$999956,A79,($AC$3:$AC$999956)))) -> 3000 | AK79: =AH79+AG79 -> 59250
A80: 1128 | B80: =IF(A80=A79,B79+1,1) -> 1 | C80: 45117 | D80: Rodriguez Jorge | E80: =CONCATENATE(A80,D80,B80) -> 1128Rodriguez Jorge1 | F80: AA255TK | G80: Siena | H80: 85848 | I80: Sacar tapa de cilindro desarmar integra. | J80: =IF(A80=A79,CONCATENATE(J79," ",I80),I80) -> Sacar tapa de cilindro desarmar integra. | L80: 1 | M80: Aceite motor 10w40 | N80: Taller | Q80: 1214.84 | R80: Motor | S80: =+(W80-Q80)/Q80 -> 1.5723552 | T80: 3 | W80: 3125 | X80: =W80*T80 -> 9375 | AC80: =+AB80*Y80 -> 0 | AD80: =IF(A80=A79,AD79+AC80,AC80) -> 0 | AE80: =+(Q80)*T80 -> 3644.52 | AF80: =IF(A80=A79,0,(SUMIF($A$3:$A$999956,A80,$AE$3:$AE$999956))) -> 26928.187 | AG80: =IF(A80=A79,0,(SUMIF($A$3:$A$999956,A80,($X$3:$X$999956)))) -> 43355 | AH80: =IF(A80=A79,0,(SUMIF($A$3:$A$999956,A80,($AC$3:$AC$999956)))) -> 60000 | AK80: =AH80+AG80 -> 103355
A81: 1128 | B81: =IF(A81=A80,B80+1,1) -> 2 | C81: =IF(A81=A80,C80,"") -> 45117 | D81: =IF(A81=A80,D80,"") -> Rodriguez Jorge | E81: =CONCATENATE(A81,D81,B81) -> 1128Rodriguez Jorge2 | I81: Limpieza y cambio de junta, tapa de cilindro y juego de juntas de descarbonizacion. | J81: =IF(A81=A80,CONCATENATE(J80," ",I81),I81) -> Sacar tapa de cilindro desarmar integra. Limpieza y cambio de junta, tapa de cilindro y juego de juntas de descarbonizacion. | L81: 1 | M81: Filtro aceite | N81: Taller | Q81: 1500 | S81: =+(W81-Q81)/Q81 -> 1 | T81: 1 | W81: 3000 | X81: =W81*T81 -> 3000 | AC81: =+AB81*Y81 -> 0 | AD81: =IF(A81=A80,AD80+AC81,AC81) -> 0 | AE81: =+(Q81)*T81 -> 1500 | AF81: =IF(A81=A80,0,(SUMIF($A$3:$A$999956,A81,$AE$3:$AE$999956))) -> 0 | AG81: =IF(A81=A80,0,(SUMIF($A$3:$A$999956,A81,($X$3:$X$999956)))) -> 0 | AH81: =IF(A81=A80,0,(SUMIF($A$3:$A$999956,A81,($AC$3:$AC$999956)))) -> 0 | AK81: =AH81+AG81 -> 0
A82: 1128 | B82: =IF(A82=A81,B81+1,1) -> 3 | C82: =IF(A82=A81,C81,"") -> 45117 | D82: =IF(A82=A81,D81,"") -> Rodriguez Jorge | E82: =CONCATENATE(A82,D82,B82) -> 1128Rodriguez Jorge3 | I82: Armado total puesta a punto cambiar aceite. Filtro de aceite, colocar líquido refrigerante. | J82: =IF(A82=A81,CONCATENATE(J81," ",I82),I82) -> Sacar tapa de cilindro desarmar integra. Limpieza y cambio de junta, tapa de cilindro y juego de juntas de descarbonizacion. Armado total puesta a punto cambiar aceite. Filtro de aceite, colocar líquido refrigerante. | L82: 1 | M82: Correa poliv 5PK | N82: Rep Serrano | Q82: =+W82*0.8 -> 6104 | S82: =+(W82-Q82)/Q82 -> 0.25 | T82: 1 | W82: 7630 | X82: =W82*T82 -> 7630 | AC82: =+AB82*Y82 -> 0 | AD82: =IF(A82=A81,AD81+AC82,AC82) -> 0 | AE82: =+(Q82)*T82 -> 6104 | AF82: =IF(A82=A81,0,(SUMIF($A$3:$A$999956,A82,$AE$3:$AE$999956))) -> 0 | AG82: =IF(A82=A81,0,(SUMIF($A$3:$A$999956,A82,($X$3:$X$999956)))) -> 0 | AH82: =IF(A82=A81,0,(SUMIF($A$3:$A$999956,A82,($AC$3:$AC$999956)))) -> 0 | AK82: =AH82+AG82 -> 0
A83: 1128 | B83: =IF(A83=A82,B82+1,1) -> 4 | C83: =IF(A83=A82,C82,"") -> 45117 | D83: =IF(A83=A82,D82,"") -> Rodriguez Jorge | E83: =CONCATENATE(A83,D83,B83) -> 1128Rodriguez Jorge4 | I83: Limpieza interior del circuito de refrigeración. | J83: =IF(A83=A82,CONCATENATE(J82," ",I83),I83) -> Sacar tapa de cilindro desarmar integra. Limpieza y cambio de junta, tapa de cilindro y juego de juntas de descarbonizacion. Armado total puesta a punto cambiar aceite. Filtro de aceite, colocar líquido refrigerante. Limpieza interior del circuito de refrigeración. | L83: 1 | M83: Correa poliv 3PK | N83: Rep Serrano | Q83: =+W83*0.8 -> 4360 | S83: =+(W83-Q83)/Q83 -> 0.25 | T83: 1 | W83: 5450 | X83: =W83*T83 -> 5450 | AC83: =+AB83*Y83 -> 0 | AD83: =IF(A83=A82,AD82+AC83,AC83) -> 0 | AE83: =+(Q83)*T83 -> 4360 | AF83: =IF(A83=A82,0,(SUMIF($A$3:$A$999956,A83,$AE$3:$AE$999956))) -> 0 | AG83: =IF(A83=A82,0,(SUMIF($A$3:$A$999956,A83,($X$3:$X$999956)))) -> 0 | AH83: =IF(A83=A82,0,(SUMIF($A$3:$A$999956,A83,($AC$3:$AC$999956)))) -> 0 | AK83: =AH83+AG83 -> 0
A84: 1128 | B84: =IF(A84=A83,B83+1,1) -> 5 | C84: =IF(A84=A83,C83,"") -> 45117 | D84: =IF(A84=A83,D83,"") -> Rodriguez Jorge | E84: =CONCATENATE(A84,D84,B84) -> 1128Rodriguez Jorge5 | J84: =IF(A84=A83,CONCATENATE(J83," ",I84),I84) -> Sacar tapa de cilindro desarmar integra. Limpieza y cambio de junta, tapa de cilindro y juego de juntas de descarbonizacion. Armado total puesta a punto cambiar aceite. Filtro de aceite, colocar líquido refrigerante. Limpieza interior del circuito de refrigeración. | L84: 1 | M84: Polea tensora | N84: Taller | Q84: =+W84/(1+S84) -> 5166.6667 | S84: 0.2 | T84: 1 | W84: 6200 | X84: =W84*T84 -> 6200 | AC84: =+AB84*Y84 -> 0 | AD84: =IF(A84=A83,AD83+AC84,AC84) -> 0 | AE84: =+(Q84)*T84 -> 5166.6667 | AF84: =IF(A84=A83,0,(SUMIF($A$3:$A$999956,A84,$AE$3:$AE$999956))) -> 0 | AG84: =IF(A84=A83,0,(SUMIF($A$3:$A$999956,A84,($X$3:$X$999956)))) -> 0 | AH84: =IF(A84=A83,0,(SUMIF($A$3:$A$999956,A84,($AC$3:$AC$999956)))) -> 0 | AK84: =AH84+AG84 -> 0
A85: 1128 | B85: =IF(A85=A84,B84+1,1) -> 6 | C85: =IF(A85=A84,C84,"") -> 45117 | D85: =IF(A85=A84,D84,"") -> Rodriguez Jorge | E85: =CONCATENATE(A85,D85,B85) -> 1128Rodriguez Jorge6 | J85: =IF(A85=A84,CONCATENATE(J84," ",I85),I85) -> Sacar tapa de cilindro desarmar integra. Limpieza y cambio de junta, tapa de cilindro y juego de juntas de descarbonizacion. Armado total puesta a punto cambiar aceite. Filtro de aceite, colocar líquido refrigerante. Limpieza interior del circuito de refrigeración. | L85: 1 | M85: Depósito de agua | N85: barotto | Q85: =+W85*0.8 -> 4000 | S85: =+(W85-Q85)/Q85 -> 0.25 | T85: 1 | W85: 5000 | X85: =W85*T85 -> 5000 | AC85: =+AB85*Y85 -> 0 | AD85: =IF(A85=A84,AD84+AC85,AC85) -> 0 | AE85: =+(Q85)*T85 -> 4000 | AF85: =IF(A85=A84,0,(SUMIF($A$3:$A$999956,A85,$AE$3:$AE$999956))) -> 0 | AG85: =IF(A85=A84,0,(SUMIF($A$3:$A$999956,A85,($X$3:$X$999956)))) -> 0 | AH85: =IF(A85=A84,0,(SUMIF($A$3:$A$999956,A85,($AC$3:$AC$999956)))) -> 0 | AK85: =AH85+AG85 -> 0
A86: 1128 | B86: =IF(A86=A85,B85+1,1) -> 7 | C86: =IF(A86=A85,C85,"") -> 45117 | D86: =IF(A86=A85,D85,"") -> Rodriguez Jorge | E86: =CONCATENATE(A86,D86,B86) -> 1128Rodriguez Jorge7 | J86: =IF(A86=A85,CONCATENATE(J85," ",I86),I86) -> Sacar tapa de cilindro desarmar integra. Limpieza y cambio de junta, tapa de cilindro y juego de juntas de descarbonizacion. Armado total puesta a punto cambiar aceite. Filtro de aceite, colocar líquido refrigerante. Limpieza interior del circuito de refrigeración. | L86: 1 | M86: Líquidio refrigerante + agua destilada | N86: Taller | Q86: 2153 | S86: =+(W86-Q86)/Q86 -> 2.1119368 | T86: 1 | W86: 6700 | X86: =W86*T86 -> 6700 | Y86: 1 | AB86: 60000 | AC86: =+AB86*Y86 -> 60000 | AD86: =IF(A86=A85,AD85+AC86,AC86) -> 60000 | AE86: =+(Q86)*T86 -> 2153 | AF86: =IF(A86=A85,0,(SUMIF($A$3:$A$999956,A86,$AE$3:$AE$999956))) -> 0 | AG86: =IF(A86=A85,0,(SUMIF($A$3:$A$999956,A86,($X$3:$X$999956)))) -> 0 | AH86: =IF(A86=A85,0,(SUMIF($A$3:$A$999956,A86,($AC$3:$AC$999956)))) -> 0 | AK86: =AH86+AG86 -> 0
A87: 1130 | B87: =IF(A87=A86,B86+1,1) -> 1 | C87: 45118 | D87: Lang Juan Pablo | E87: =CONCATENATE(A87,D87,B87) -> 1130Lang Juan Pablo1 | G87: Toro | H87: 120697 | I87: Desarmar distribución completa. | J87: =IF(A87=A86,CONCATENATE(J86," ",I87),I87) -> Desarmar distribución completa. | L87: 1 | M87: Kit distribución | N87: Rc distribuciones | Q87: 87000 | R87: Distribución | T87: 1 | W87: 87000 | X87: =W87*T87 -> 87000 | AC87: =+AB87*Y87 -> 0 | AD87: =IF(A87=A86,AD86+AC87,AC87) -> 0 | AE87: =+(Q87)*T87 -> 87000 | AF87: =IF(A87=A86,0,(SUMIF($A$3:$A$999956,A87,$AE$3:$AE$999956))) -> 142274 | AG87: =IF(A87=A86,0,(SUMIF($A$3:$A$999956,A87,($X$3:$X$999956)))) -> 159300 | AH87: =IF(A87=A86,0,(SUMIF($A$3:$A$999956,A87,($AC$3:$AC$999956)))) -> 55000 | AK87: =AH87+AG87 -> 214300
A88: 1130 | B88: =IF(A88=A87,B87+1,1) -> 2 | C88: =IF(A88=A87,C87,"") -> 45118 | D88: =IF(A88=A87,D87,"") -> Lang Juan Pablo | E88: =CONCATENATE(A88,D88,B88) -> 1130Lang Juan Pablo2 | I88: Cambiar kit de distribución. | J88: =IF(A88=A87,CONCATENATE(J87," ",I88),I88) -> Desarmar distribución completa. Cambiar kit de distribución. | L88: 1 | M88: Correa poliv | N88: Rc distribuciones | Q88: 5000 | T88: 1 | W88: 5000 | X88: =W88*T88 -> 5000 | AC88: =+AB88*Y88 -> 0 | AD88: =IF(A88=A87,AD87+AC88,AC88) -> 0 | AE88: =+(Q88)*T88 -> 5000 | AF88: =IF(A88=A87,0,(SUMIF($A$3:$A$999956,A88,$AE$3:$AE$999956))) -> 0 | AG88: =IF(A88=A87,0,(SUMIF($A$3:$A$999956,A88,($X$3:$X$999956)))) -> 0 | AH88: =IF(A88=A87,0,(SUMIF($A$3:$A$999956,A88,($AC$3:$AC$999956)))) -> 0 | AK88: =AH88+AG88 -> 0
A89: 1130 | B89: =IF(A89=A88,B88+1,1) -> 3 | C89: =IF(A89=A88,C88,"") -> 45118 | D89: =IF(A89=A88,D88,"") -> Lang Juan Pablo | E89: =CONCATENATE(A89,D89,B89) -> 1130Lang Juan Pablo3 | I89: Cambiar bomba de agua y poleas. | J89: =IF(A89=A88,CONCATENATE(J88," ",I89),I89) -> Desarmar distribución completa. Cambiar kit de distribución. Cambiar bomba de agua y poleas. | L89: 1 | M89: Bomba de agua | N89: barotto | Q89: =+W89*0.8 -> 31040 | S89: =+(W89-Q89)/Q89 -> 0.25 | T89: 1 | W89: 38800 | X89: =W89*T89 -> 38800 | AC89: =+AB89*Y89 -> 0 | AD89: =IF(A89=A88,AD88+AC89,AC89) -> 0 | AE89: =+(Q89)*T89 -> 31040 | AF89: =IF(A89=A88,0,(SUMIF($A$3:$A$999956,A89,$AE$3:$AE$999956))) -> 0 | AG89: =IF(A89=A88,0,(SUMIF($A$3:$A$999956,A89,($X$3:$X$999956)))) -> 0 | AH89: =IF(A89=A88,0,(SUMIF($A$3:$A$999956,A89,($AC$3:$AC$999956)))) -> 0 | AK89: =AH89+AG89 -> 0
A90: 1130 | B90: =IF(A90=A89,B89+1,1) -> 4 | C90: =IF(A90=A89,C89,"") -> 45118 | D90: =IF(A90=A89,D89,"") -> Lang Juan Pablo | E90: =CONCATENATE(A90,D90,B90) -> 1130Lang Juan Pablo4 | I90: Limpiar circuito refrigerante. | J90: =IF(A90=A89,CONCATENATE(J89," ",I90),I90) -> Desarmar distribución completa. Cambiar kit de distribución. Cambiar bomba de agua y poleas. Limpiar circuito refrigerante. | L90: 1 | M90: Polea acanalada | N90: barotto | Q90: =+W90*0.8 -> 10400 | S90: =+(W90-Q90)/Q90 -> 0.25 | T90: 1 | W90: 13000 | X90: =W90*T90 -> 13000 | AC90: =+AB90*Y90 -> 0 | AD90: =IF(A90=A89,AD89+AC90,AC90) -> 0 | AE90: =+(Q90)*T90 -> 10400 | AF90: =IF(A90=A89,0,(SUMIF($A$3:$A$999956,A90,$AE$3:$AE$999956))) -> 0 | AG90: =IF(A90=A89,0,(SUMIF($A$3:$A$999956,A90,($X$3:$X$999956)))) -> 0 | AH90: =IF(A90=A89,0,(SUMIF($A$3:$A$999956,A90,($AC$3:$AC$999956)))) -> 0 | AK90: =AH90+AG90 -> 0
A91: 1130 | B91: =IF(A91=A90,B90+1,1) -> 5 | C91: =IF(A91=A90,C90,"") -> 45118 | D91: =IF(A91=A90,D90,"") -> Lang Juan Pablo | E91: =CONCATENATE(A91,D91,B91) -> 1130Lang Juan Pablo5 | I91: Puesta a punto. Armado total. | J91: =IF(A91=A90,CONCATENATE(J90," ",I91),I91) -> Desarmar distribución completa. Cambiar kit de distribución. Cambiar bomba de agua y poleas. Limpiar circuito refrigerante. Puesta a punto. Armado total. | L91: 1 | M91: Polea lisa | N91: barotto | Q91: =+W91*0.8 -> 7040 | S91: =+(W91-Q91)/Q91 -> 0.25 | T91: 1 | W91: 8800 | X91: =W91*T91 -> 8800 | AC91: =+AB91*Y91 -> 0 | AD91: =IF(A91=A90,AD90+AC91,AC91) -> 0 | AE91: =+(Q91)*T91 -> 7040 | AF91: =IF(A91=A90,0,(SUMIF($A$3:$A$999956,A91,$AE$3:$AE$999956))) -> 0 | AG91: =IF(A91=A90,0,(SUMIF($A$3:$A$999956,A91,($X$3:$X$999956)))) -> 0 | AH91: =IF(A91=A90,0,(SUMIF($A$3:$A$999956,A91,($AC$3:$AC$999956)))) -> 0 | AK91: =AH91+AG91 -> 0
A92: 1130 | B92: =IF(A92=A91,B91+1,1) -> 6 | C92: =IF(A92=A91,C91,"") -> 45118 | D92: =IF(A92=A91,D91,"") -> Lang Juan Pablo | E92: =CONCATENATE(A92,D92,B92) -> 1130Lang Juan Pablo6 | J92: =IF(A92=A91,CONCATENATE(J91," ",I92),I92) -> Desarmar distribución completa. Cambiar kit de distribución. Cambiar bomba de agua y poleas. Limpiar circuito refrigerante. Puesta a punto. Armado total. | L92: 1 | M92: Liquido refrigerante + agua destilada | N92: Taller | Q92: 1794 | S92: =+(W92-Q92)/Q92 -> 2.7346711 | T92: 1 | W92: 6700 | X92: =W92*T92 -> 6700 | Y92: 1 | AB92: 55000 | AC92: =+AB92*Y92 -> 55000 | AD92: =IF(A92=A91,AD91+AC92,AC92) -> 55000 | AE92: =+(Q92)*T92 -> 1794 | AF92: =IF(A92=A91,0,(SUMIF($A$3:$A$999956,A92,$AE$3:$AE$999956))) -> 0 | AG92: =IF(A92=A91,0,(SUMIF($A$3:$A$999956,A92,($X$3:$X$999956)))) -> 0 | AH92: =IF(A92=A91,0,(SUMIF($A$3:$A$999956,A92,($AC$3:$AC$999956)))) -> 0 | AK92: =AH92+AG92 -> 0
A93: 1131 | B93: =IF(A93=A92,B92+1,1) -> 1 | C93: 45117 | D93: Orsa Antonio | G93: Palio Wekend | I93: Desarmar suspensión lado derecho. | L93: 1 | M93: Buje barra estabilizadora | N93: Rep Serrano | Q93: =+W93*0.8 -> 7008 | R93: Otros | S93: =+(W93-Q93)/Q93 -> 0.25 | T93: 1 | W93: 8760 | X93: =W93*T93 -> 8760 | AE93: =+(Q93)*T93 -> 7008
A94: 1131 | B94: =IF(A94=A93,B93+1,1) -> 2 | C94: =IF(A94=A93,C93,"") -> 45117 | D94: =IF(A94=A93,D93,"") -> Orsa Antonio | E94: =CONCATENATE(A94,D94,B94) -> 1131Orsa Antonio2 | I94: Sacar parrilla de suspensión mismo lado. | J94: =IF(A94=A93,CONCATENATE(J93," ",I94),I94) -> Sacar parrilla de suspensión mismo lado. | L94: 1 | M94: Buje de parrilla parte trasera lado derecho. | N94: Ferrando | Q94: =+W94*0.8 -> 2940 | S94: =+(W94-Q94)/Q94 -> 0.25 | T94: 1 | W94: 3675 | X94: =W94*T94 -> 3675 | AC94: =+AB94*Y94 -> 0 | AD94: =IF(A94=A93,AD93+AC94,AC94) -> 0 | AE94: =+(Q94)*T94 -> 2940 | AF94: =IF(A94=A93,0,(SUMIF($A$3:$A$999956,A94,$Q$3:$Q$999956)))+IF(A94=A93,0,(SUMIF($A$3:$A$999956,A94,$R$3:$R$999956))) -> 0 | AG94: =IF(A94=A93,0,(SUMIF($A$3:$A$999956,A94,($X$3:$X$999956)))) -> 0 | AH94: =IF(A94=A93,0,(SUMIF($A$3:$A$999956,A94,($AC$3:$AC$999956)))) -> 0 | AK94: =AH94+AG94 -> 0
A95: 1131 | B95: =IF(A95=A94,B94+1,1) -> 3 | C95: =IF(A95=A94,C94,"") -> 45117 | D95: =IF(A95=A94,D94,"") -> Orsa Antonio | E95: =CONCATENATE(A95,D95,B95) -> 1131Orsa Antonio3 | I95: Reparar co ambos bujes nuevos y cambiar bujes de barra de estabilizadora. | J95: =IF(A95=A94,CONCATENATE(J94," ",I95),I95) -> Sacar parrilla de suspensión mismo lado. Reparar co ambos bujes nuevos y cambiar bujes de barra de estabilizadora. | L95: 1 | M95: Buje de parrilla parte delantera lado derecho. | N95: Ferrando | Q95: =+W95*0.8 -> 2940 | S95: =+(W95-Q95)/Q95 -> 0.25 | T95: 1 | W95: 3675 | X95: =W95*T95 -> 3675 | Y95: 1 | AB95: 15000 | AC95: =+AB95*Y95 -> 15000 | AD95: =IF(A95=A94,AD94+AC95,AC95) -> 15000 | AE95: =+(Q95)*T95 -> 2940 | AF95: =IF(A95=A94,0,(SUMIF($A$3:$A$999956,A95,$Q$3:$Q$999956)))+IF(A95=A94,0,(SUMIF($A$3:$A$999956,A95,$R$3:$R$999956))) -> 0 | AG95: =IF(A95=A94,0,(SUMIF($A$3:$A$999956,A95,($X$3:$X$999956)))) -> 0 | AH95: =IF(A95=A94,0,(SUMIF($A$3:$A$999956,A95,($AC$3:$AC$999956)))) -> 0 | AK95: =AH95+AG95 -> 0
A96: 1131 | B96: =IF(A96=A95,B95+1,1) -> 4 | C96: =IF(A96=A95,C95,"") -> 45117 | D96: =IF(A96=A95,D95,"") -> Orsa Antonio | E96: =CONCATENATE(A96,D96,B96) -> 1131Orsa Antonio4 | I96: Regular convergencia. | J96: =IF(A96=A95,CONCATENATE(J95," ",I96),I96) -> Sacar parrilla de suspensión mismo lado. Reparar co ambos bujes nuevos y cambiar bujes de barra de estabilizadora. Regular convergencia. | L96: 1 | M96: Buje barra estabilizadora | N96: Rep Serrano | Q96: =+W96*0.8 -> 7008 | S96: =+(W96-Q96)/Q96 -> 0.25 | T96: 1 | W96: 8760 | X96: =W96*T96 -> 8760 | AC96: =+AB96*Y96 -> 0 | AD96: =IF(A96=A95,AD95+AC96,AC96) -> 15000 | AE96: =+(Q96)*T96 -> 7008 | AF96: =IF(A96=A95,0,(SUMIF($A$3:$A$999956,A96,$Q$3:$Q$999956)))+IF(A96=A95,0,(SUMIF($A$3:$A$999956,A96,$R$3:$R$999956))) -> 0 | AG96: =IF(A96=A95,0,(SUMIF($A$3:$A$999956,A96,($X$3:$X$999956)))) -> 0 | AH96: =IF(A96=A95,0,(SUMIF($A$3:$A$999956,A96,($AC$3:$AC$999956)))) -> 0 | AK96: =AH96+AG96 -> 0
A97: 1132 | B97: =IF(A97=A96,B96+1,1) -> 1 | C97: 45119 | D97: Martinich Nahuel | E97: =CONCATENATE(A97,D97,B97) -> 1132Martinich Nahuel1 | F97: AB767DV | G97: Palio | H97: 43403 | I97: Service cambio de aceite y filtro. | J97: =IF(A97=A96,CONCATENATE(J96," ",I97),I97) -> Service cambio de aceite y filtro. | L97: 1 | M97: Aceite 10w40 | N97: Taller | Q97: 1214.84 | R97: Service | S97: =+(W97-Q97)/Q97 -> 1.5723552 | T97: 1 | W97: 3125 | X97: =W97*T97 -> 3125 | AC97: =+AB97*Y97 -> 0 | AD97: =IF(A97=A96,AD96+AC97,AC97) -> 0 | AE97: =+(Q97)*T97 -> 1214.84 | AF97: =IF(A97=A96,0,(SUMIF($A$3:$A$999956,A97,$Q$3:$Q$999956)))+IF(A97=A96,0,(SUMIF($A$3:$A$999956,A97,$R$3:$R$999956))) -> 18159.507 | AG97: =IF(A97=A96,0,(SUMIF($A$3:$A$999956,A97,($X$3:$X$999956)))) -> 33155 | AH97: =IF(A97=A96,0,(SUMIF($A$3:$A$999956,A97,($AC$3:$AC$999956)))) -> 40000 | AK97: =AH97+AG97 -> 73155
A98: 1132 | B98: =IF(A98=A97,B97+1,1) -> 2 | C98: =IF(A98=A97,C97,"") -> 45119 | D98: =IF(A98=A97,D97,"") -> Martinich Nahuel | E98: =CONCATENATE(A98,D98,B98) -> 1132Martinich Nahuel2 | I98: Control general del vehículo. | J98: =IF(A98=A97,CONCATENATE(J97," ",I98),I98) -> Service cambio de aceite y filtro. Control general del vehículo. | L98: 1 | M98: Filtro aceite | N98: Taller | Q98: 1500 | S98: =+(W98-Q98)/Q98 -> 1 | T98: 1 | W98: 3000 | X98: =W98*T98 -> 3000 | AC98: =+AB98*Y98 -> 0 | AD98: =IF(A98=A97,AD97+AC98,AC98) -> 0 | AE98: =+(Q98)*T98 -> 1500 | AF98: =IF(A98=A97,0,(SUMIF($A$3:$A$999956,A98,$Q$3:$Q$999956)))+IF(A98=A97,0,(SUMIF($A$3:$A$999956,A98,$R$3:$R$999956))) -> 0 | AG98: =IF(A98=A97,0,(SUMIF($A$3:$A$999956,A98,($X$3:$X$999956)))) -> 0 | AH98: =IF(A98=A97,0,(SUMIF($A$3:$A$999956,A98,($AC$3:$AC$999956)))) -> 0 | AK98: =AH98+AG98 -> 0
A99: 1132 | B99: =IF(A99=A98,B98+1,1) -> 3 | C99: =IF(A99=A98,C98,"") -> 45119 | D99: =IF(A99=A98,D98,"") -> Martinich Nahuel | E99: =CONCATENATE(A99,D99,B99) -> 1132Martinich Nahuel3 | I99: Cambiar pastillas de freno delanteras. | J99: =IF(A99=A98,CONCATENATE(J98," ",I99),I99) -> Service cambio de aceite y filtro. Control general del vehículo. Cambiar pastillas de freno delanteras. | L99: 1 | M99: Filtro aire | N99: Taller | Q99: 2000 | S99: =+(W99-Q99)/Q99 -> 1.1 | T99: 1 | W99: 4200 | X99: =W99*T99 -> 4200 | AC99: =+AB99*Y99 -> 0 | AD99: =IF(A99=A98,AD98+AC99,AC99) -> 0 | AE99: =+(Q99)*T99 -> 2000 | AF99: =IF(A99=A98,0,(SUMIF($A$3:$A$999956,A99,$Q$3:$Q$999956)))+IF(A99=A98,0,(SUMIF($A$3:$A$999956,A99,$R$3:$R$999956))) -> 0 | AG99: =IF(A99=A98,0,(SUMIF($A$3:$A$999956,A99,($X$3:$X$999956)))) -> 0 | AH99: =IF(A99=A98,0,(SUMIF($A$3:$A$999956,A99,($AC$3:$AC$999956)))) -> 0 | AK99: =AH99+AG99 -> 0
A100: 1132 | B100: =IF(A100=A99,B99+1,1) -> 4 | C100: =IF(A100=A99,C99,"") -> 45119 | D100: =IF(A100=A99,D99,"") -> Martinich Nahuel | E100: =CONCATENATE(A100,D100,B100) -> 1132Martinich Nahuel4 | I100: Limpieza del circuito de refrigeración del depósito recuperador de agua. | J100: =IF(A100=A99,CONCATENATE(J99," ",I100),I100) -> Service cambio de aceite y filtro. Control general del vehículo. Cambiar pastillas de freno delanteras. Limpieza del circuito de refrigeración del depósito recuperador de agua. | L100: 1 | M100: Filtro nafta | N100: Taller | Q100: 2000 | S100: =+(W100-Q100)/Q100 -> 0.6 | T100: 1 | W100: 3200 | X100: =W100*T100 -> 3200 | AC100: =+AB100*Y100 -> 0 | AD100: =IF(A100=A99,AD99+AC100,AC100) -> 0 | AE100: =+(Q100)*T100 -> 2000 | AF100: =IF(A100=A99,0,(SUMIF($A$3:$A$999956,A100,$Q$3:$Q$999956)))+IF(A100=A99,0,(SUMIF($A$3:$A$999956,A100,$R$3:$R$999956))) -> 0 | AG100: =IF(A100=A99,0,(SUMIF($A$3:$A$999956,A100,($X$3:$X$999956)))) -> 0 | AH100: =IF(A100=A99,0,(SUMIF($A$3:$A$999956,A100,($AC$3:$AC$999956)))) -> 0 | AK100: =AH100+AG100 -> 0
...

Sheet Ficha
A1: Deuda por cliente | E1: Deuda cliente por fecha | H1: Cliente | I1: Transporte Palloni | Q1: Cliente | R1: Transporte Palloni
A2: Antes de analizar apretar click derecho sobre la tabla y luego "Actualizar" | E2: Antes de analizar apretar click derecho sobre la tabla y luego "Actualizar" | Q2: Fecha | R2: (Varios elementos)
E3: Están agrupados por cantidad de meses de deuda | H3: Etiquetas de fila | I3: Suma de Total trabajo | J3: Suma de Entrega 1 | K3: Suma de Fecha 1 | L3: Suma de Entrega 2 | M3: Suma de Fecha 2
H4: 1334 | I4: 25000 | J4: 25000 | K4: 45180 | O4: Dominio | P4: Vehículo | Q4: Etiquetas de fila | R4: Suma de Total precio repuesto | S4: Suma de Total MO | T4: Suma de Total trabajo
A5: Deuda | B5: (Varios elementos) | E5: Deuda | F5: (Varios elementos) | H5: 1336 | I5: 50000 | J5: 50000 | K5: 45180 | O5: =IFERROR(VLOOKUP(Q5,'Carga Remito.'!A$9:G$23287,6,0),"") -> 993CE | P5: =IFERROR(VLOOKUP(Q5,'Carga Remito.'!A$9:H$23287,7,0),"") -> Fiorino | Q5: 1112 | R5: 0 | S5: 7000 | T5: 7000
H6: 1341 | I6: 7000 | J6: 7000 | K6: 45180 | O6: =IFERROR(VLOOKUP(Q6,'Carga Remito.'!A$9:G$23287,6,0),"") | P6: =IFERROR(VLOOKUP(Q6,'Carga Remito.'!A$9:H$23287,7,0),"") | Q6: Cambiar cables de bujias y bujias. | R6: 0 | S6: 7000 | T6: 7000
A7: Etiquetas de fila | B7: Suma de Deuda | E7: Etiquetas de fila | F7: Suma de Deuda | H7: 1345 | I7: 0 | O7: =IFERROR(VLOOKUP(Q7,'Carga Remito.'!A$9:G$23287,6,0),"") -> 0 | P7: =IFERROR(VLOOKUP(Q7,'Carga Remito.'!A$9:H$23287,7,0),"") -> Peugeot 208 | Q7: 1113 | R7: 26400 | S7: 18000 | T7: 44400
A8: Acotto Jorge | B8: 0 | E8: 0 | F8: 11041240 | H8: 1349 | I8: 45000 | J8: 45000 | K8: 45180 | O8: =IFERROR(VLOOKUP(Q8,'Carga Remito.'!A$9:G$23287,6,0),"") | P8: =IFERROR(VLOOKUP(Q8,'Carga Remito.'!A$9:H$23287,7,0),"") | Q8: Control del vehículo. | R8: 0 | S8: 0 | T8: 0
A9: Antonio Orsa | B9: 0 | E9: Altamirano Alicia | F9: 270750 | H9: 1355 | I9: 0 | O9: =IFERROR(VLOOKUP(Q9,'Carga Remito.'!A$9:G$23287,6,0),"") | P9: =IFERROR(VLOOKUP(Q9,'Carga Remito.'!A$9:H$23287,7,0),"") | Q9: Rotación de ruedas. | R9: 0 | S9: 0 | T9: 0
A10: Baner Abu Grillo | B10: 0 | E10: Carranza Mauro | F10: 686000 | H10: 1360 | I10: 0 | O10: =IFERROR(VLOOKUP(Q10,'Carga Remito.'!A$9:G$23287,6,0),"") | P10: =IFERROR(VLOOKUP(Q10,'Carga Remito.'!A$9:H$23287,7,0),"") | Q10: Service cambio de aceite y filtros. | R10: 26400 | S10: 18000 | T10: 44400
A11: Beriani Nazarena | B11: 0 | E11: Cometto Julia | F11: 120000 | H11: 1369 | I11: 0 | O11: =IFERROR(VLOOKUP(Q11,'Carga Remito.'!A$9:G$23287,6,0),"") | P11: =IFERROR(VLOOKUP(Q11,'Carga Remito.'!A$9:H$23287,7,0),"") | Q11: (en blanco) | R11: 0 | S11: 0 | T11: 0
A12: Bertaina Damian | B12: 0 | E12: Cosaro Juan | F12: 186000 | H12: 1378 | I12: 4000 | J12: 4000 | O12: =IFERROR(VLOOKUP(Q12,'Carga Remito.'!A$9:G$23287,6,0),"") -> 553 | P12: =IFERROR(VLOOKUP(Q12,'Carga Remito.'!A$9:H$23287,7,0),"") -> 0 | Q12: 1163 | R12: 0 | S12: 30000 | T12: 30000
A13: Bustos Lolo | B13: 0 | E13: Dondena Cristian | F13: 149500 | H13: 1381 | I13: 30000 | J13: 30000 | O13: =IFERROR(VLOOKUP(Q13,'Carga Remito.'!A$9:G$23287,6,0),"") | P13: =IFERROR(VLOOKUP(Q13,'Carga Remito.'!A$9:H$23287,7,0),"") | Q13: Cambiar kit bomba de agua. | R13: 0 | S13: 0 | T13: 0
A14: Cabral Guillermo | B14: 0 | E14: Integral Agropecuaria | F14: 1019500 | H14: 1398 | I14: 6000 | J14: 6000 | K14: 45189 | O14: =IFERROR(VLOOKUP(Q14,'Carga Remito.'!A$9:G$23287,6,0),"") | P14: =IFERROR(VLOOKUP(Q14,'Carga Remito.'!A$9:H$23287,7,0),"") | Q14: Cambio de aceite y filtros. | R14: 0 | S14: 30000 | T14: 30000
A15: Fernandez Gerardo | B15: 0 | E15: Isasi Luciana | F15: 489500 | H15: 1402 | I15: 35000 | J15: 35000 | O15: =IFERROR(VLOOKUP(Q15,'Carga Remito.'!A$9:G$23287,6,0),"") | P15: =IFERROR(VLOOKUP(Q15,'Carga Remito.'!A$9:H$23287,7,0),"") | Q15: Desarmar distribución completa. | R15: 0 | S15: 0 | T15: 0
A16: Formini Victor | B16: 0 | E16: Maan constructora | F16: 300000 | H16: 1407 | I16: 8000 | J16: 8000 | O16: =IFERROR(VLOOKUP(Q16,'Carga Remito.'!A$9:G$23287,6,0),"") | P16: =IFERROR(VLOOKUP(Q16,'Carga Remito.'!A$9:H$23287,7,0),"") | Q16: Liquido refrigerante, purgado del circuito refrigerante y cambiar correa poliv. | R16: 0 | S16: 0 | T16: 0
A17: Gigante Joni | B17: 0 | E17: Medic | F17: 260000 | H17: 1418 | I17: 8000 | J17: 8000 | O17: =IFERROR(VLOOKUP(Q17,'Carga Remito.'!A$9:G$23287,6,0),"") -> 703 | P17: =IFERROR(VLOOKUP(Q17,'Carga Remito.'!A$9:H$23287,7,0),"") -> Kangoo | Q17: 1164 | R17: 0 | S17: 100000 | T17: 100000
A18: Gonzalez Alberto | B18: 0 | E18: Moretti Anabella | F18: 700500 | H18: 1419 | I18: 11000 | J18: 11000 | K18: 45196 | O18: =IFERROR(VLOOKUP(Q18,'Carga Remito.'!A$9:G$23287,6,0),"") | P18: =IFERROR(VLOOKUP(Q18,'Carga Remito.'!A$9:H$23287,7,0),"") | Q18: Armado total. Puesta a punto. | R18: 0 | S18: 0 | T18: 0
A19: Guerrieri Gladys | B19: 0 | E19: Moretti Renato | F19: 805000 | H19: 1422 | I19: 15000 | J19: 15000 | O19: =IFERROR(VLOOKUP(Q19,'Carga Remito.'!A$9:G$23287,6,0),"") | P19: =IFERROR(VLOOKUP(Q19,'Carga Remito.'!A$9:H$23287,7,0),"") | Q19: Bomba de agua. | R19: 0 | S19: 0 | T19: 0
A20: Toyos Pato | B20: 0 | E20: Municipalidad Laboulaye | F20: 733500 | H20: 1427 | I20: 15000 | J20: 15000 | O20: =IFERROR(VLOOKUP(Q20,'Carga Remito.'!A$9:G$23287,6,0),"") | P20: =IFERROR(VLOOKUP(Q20,'Carga Remito.'!A$9:H$23287,7,0),"") | Q20: Cambiar líquido refrigerante. | R20: 0 | S20: 0 | T20: 0
A21: Hoyos Pato | B21: 0 | E21: Paredes Juan | F21: 891150 | H21: 1438 | I21: 12000 | J21: 12000 | K21: 45244 | O21: =IFERROR(VLOOKUP(Q21,'Carga Remito.'!A$9:G$23287,6,0),"") | P21: =IFERROR(VLOOKUP(Q21,'Carga Remito.'!A$9:H$23287,7,0),"") | Q21: Limpieza, colocar tapa de cilindro reparada. | R21: 0 | S21: 0 | T21: 0
A22: Irouleguy Daniel | B22: 0 | E22: Paz Jose Maria | F22: 215000 | H22: 1464 | I22: 95325 | J22: 95325 | K22: 45244 | O22: =IFERROR(VLOOKUP(Q22,'Carga Remito.'!A$9:G$23287,6,0),"") | P22: =IFERROR(VLOOKUP(Q22,'Carga Remito.'!A$9:H$23287,7,0),"") | Q22: Sacar tapa de cilindro íntegra. | R22: 0 | S22: 100000 | T22: 100000
A23: Isasi Luciana | B23: 0 | E23: Rodriguez Osvaldo | F23: 108800 | H23: 1465 | I23: 15000 | J23: 15000 | K23: 45244 | O23: =IFERROR(VLOOKUP(Q23,'Carga Remito.'!A$9:G$23287,6,0),"") -> AE993CF | P23: =IFERROR(VLOOKUP(Q23,'Carga Remito.'!A$9:H$23287,7,0),"") -> Fiorino | Q23: 1165 | R23: 0 | S23: 30000 | T23: 30000
A24: Juan Achabal | B24: 0 | E24: Salas Jesus | F24: 484600 | H24: 1480 | I24: 29000 | J24: 29000 | K24: 45244 | O24: =IFERROR(VLOOKUP(Q24,'Carga Remito.'!A$9:G$23287,6,0),"") | P24: =IFERROR(VLOOKUP(Q24,'Carga Remito.'!A$9:H$23287,7,0),"") | Q24: Armado total. | R24: 0 | S24: 0 | T24: 0
A25: Lang Juan Pablo | B25: 0 | E25: Transporte Palloni | F25: 121000 | H25: 1483 | I25: 42000 | J25: 42000 | K25: 45244 | O25: =IFERROR(VLOOKUP(Q25,'Carga Remito.'!A$9:G$23287,6,0),"") | P25: =IFERROR(VLOOKUP(Q25,'Carga Remito.'!A$9:H$23287,7,0),"") | Q25: Bomba de agua. Cambiar líquido refrigerante, purgado. | R25: 0 | S25: 0 | T25: 0
A26: Llanos Raquel | B26: 0 | E26: Giorgis Juan Carlos | F26: 265000 | H26: 1493 | I26: 6000 | J26: 6000 | K26: 45244 | O26: =IFERROR(VLOOKUP(Q26,'Carga Remito.'!A$9:G$23287,6,0),"") | P26: =IFERROR(VLOOKUP(Q26,'Carga Remito.'!A$9:H$23287,7,0),"") | Q26: Cambiar correa poliv y correas tensoras de alternador. | R26: 0 | S26: 0 | T26: 0
A27: Lucero Adrian | B27: 0 | E27: Gutierrez Hnos | F27: 1668000 | H27: 1497 | I27: 7000 | J27: 7000 | O27: =IFERROR(VLOOKUP(Q27,'Carga Remito.'!A$9:G$23287,6,0),"") | P27: =IFERROR(VLOOKUP(Q27,'Carga Remito.'!A$9:H$23287,7,0),"") | Q27: Desarmar distribución completa. Cambiar. | R27: 0 | S27: 30000 | T27: 30000
A28: Macagno Dante | B28: 0 | E28: Palloni Sirley | F28: 408000 | H28: 1501 | I28: 8000 | J28: 8000 | K28: 45244 | O28: =IFERROR(VLOOKUP(Q28,'Carga Remito.'!A$9:G$23287,6,0),"") | P28: =IFERROR(VLOOKUP(Q28,'Carga Remito.'!A$9:H$23287,7,0),"") | Q28: Puesta a punto. Cambiar bujias y cable de bujías. | R28: 0 | S28: 0 | T28: 0
A29: Macagno Omar | B29: 0 | E29: Costa Laura | F29: 155000 | H29: 1503 | I29: 7500 | J29: 7500 | O29: =IFERROR(VLOOKUP(Q29,'Carga Remito.'!A$9:G$23287,6,0),"") -> AF044MU | P29: =IFERROR(VLOOKUP(Q29,'Carga Remito.'!A$9:H$23287,7,0),"") -> Fiorino | Q29: 1166 | R29: 0 | S29: 28000 | T29: 28000
A30: Martin Jose | B30: 0 | E30: Monasterio Paola | F30: 266000 | H30: 1512 | I30: 48000 | J30: 48000 | K30: 45274 | O30: =IFERROR(VLOOKUP(Q30,'Carga Remito.'!A$9:G$23287,6,0),"") | P30: =IFERROR(VLOOKUP(Q30,'Carga Remito.'!A$9:H$23287,7,0),"") | Q30: Cambiar bomba de agua. | R30: 0 | S30: 0 | T30: 0
A31: Martinich Nahuel | B31: 0 | E31: Giovanini Laura | F31: 488840 | H31: 1513 | I31: 13000 | J31: 13000 | K31: 45274 | O31: =IFERROR(VLOOKUP(Q31,'Carga Remito.'!A$9:G$23287,6,0),"") | P31: =IFERROR(VLOOKUP(Q31,'Carga Remito.'!A$9:H$23287,7,0),"") | Q31: Desarmar distribución completa. | R31: 0 | S31: 28000 | T31: 28000
A32: Medic | B32: 0 | E32: Napoli Luciano | F32: 249600 | H32: 1516 | I32: 35000 | J32: 35000 | K32: 45274 | O32: =IFERROR(VLOOKUP(Q32,'Carga Remito.'!A$9:G$23287,6,0),"") | P32: =IFERROR(VLOOKUP(Q32,'Carga Remito.'!A$9:H$23287,7,0),"") | Q32: Purgado circuito de refrigeración. | R32: 0 | S32: 0 | T32: 0
A33: Muñoz | B33: 0 | E33: 2 | F33: 4867870 | H33: 1522 | I33: 19000 | J33: 19000 | K33: 45274 | O33: =IFERROR(VLOOKUP(Q33,'Carga Remito.'!A$9:G$23287,6,0),"") | P33: =IFERROR(VLOOKUP(Q33,'Carga Remito.'!A$9:H$23287,7,0),"") | Q33: Pusta a punto. Armado total. | R33: 0 | S33: 0 | T33: 0
A34: Ocampo Manolo | B34: 0 | E34: Ferrando Elba | F34: 171500 | H34: 1523 | I34: 17000 | J34: 17000 | K34: 45274 | O34: =IFERROR(VLOOKUP(Q34,'Carga Remito.'!A$9:G$23287,6,0),"") | P34: =IFERROR(VLOOKUP(Q34,'Carga Remito.'!A$9:H$23287,7,0),"") | Q34: Trasbazado líquido refrigerante, completar nivel. | R34: 0 | S34: 0 | T34: 0
A35: Orsa Antonio | B35: 0 | E35: Mansuino Walter | F35: 200000 | H35: 1527 | I35: 23000 | J35: 23000 | K35: 45274 | O35: =IFERROR(VLOOKUP(Q35,'Carga Remito.'!A$9:G$23287,6,0),"") -> 0 | P35: =IFERROR(VLOOKUP(Q35,'Carga Remito.'!A$9:H$23287,7,0),"") -> 0 | Q35: 1167 | R35: 0 | S35: 4500 | T35: 4500
A36: Oviedo Jose Luis | B36: 0 | E36: Perviu Jorge | F36: 681800 | H36: 1528 | I36: 86400 | J36: 86400 | K36: 45274 | O36: =IFERROR(VLOOKUP(Q36,'Carga Remito.'!A$9:G$23287,6,0),"") | P36: =IFERROR(VLOOKUP(Q36,'Carga Remito.'!A$9:H$23287,7,0),"") | Q36: Cambio de aceite y filtros. | R36: 0 | S36: 0 | T36: 0
A37: Pelliza Kevin | B37: 0 | E37: Proietti Mariano | F37: 1.4551915e-11 | H37: 1555 | I37: 103250 | J37: 103250 | K37: 45274 | O37: =IFERROR(VLOOKUP(Q37,'Carga Remito.'!A$9:G$23287,6,0),"") | P37: =IFERROR(VLOOKUP(Q37,'Carga Remito.'!A$9:H$23287,7,0),"") | Q37: (en blanco) | R37: 0 | S37: 4500 | T37: 4500
A38: Pisani Nicolas | B38: 0 | E38: Transporte Palloni | F38: 3458270 | H38: 1576 | I38: 48000 | J38: 48000 | K38: 45274 | O38: =IFERROR(VLOOKUP(Q38,'Carga Remito.'!A$9:G$23287,6,0),"") -> KVB553 | P38: =IFERROR(VLOOKUP(Q38,'Carga Remito.'!A$9:H$23287,7,0),"") -> Kangoo | Q38: 1168 | R38: 0 | S38: 8000 | T38: 8000
A39: Revol Juan | B39: 0 | E39: Espinoza Javito | F39: 356300 | H39: 1577 | I39: 0 | O39: =IFERROR(VLOOKUP(Q39,'Carga Remito.'!A$9:G$23287,6,0),"") | P39: =IFERROR(VLOOKUP(Q39,'Carga Remito.'!A$9:H$23287,7,0),"") | Q39: Cambiar bujes de punta barra estabilizadora. | R39: 0 | S39: 0 | T39: 0
A40: Rodriguez Jorge | B40: 0 | E40: 3 | F40: 201500 | H40: 1592 | I40: 55000 | J40: 55000 | K40: 45310 | O40: =IFERROR(VLOOKUP(Q40,'Carga Remito.'!A$9:G$23287,6,0),"") | P40: =IFERROR(VLOOKUP(Q40,'Carga Remito.'!A$9:H$23287,7,0),"") | Q40: Control parcial del vehiculo. | R40: 0 | S40: 0 | T40: 0
A41: San Jose Agropecuaria | B41: 0 | E41: Bustos Lolo | F41: 201500 | H41: 1601 | I41: 20000 | J41: 20000 | K41: 45310 | O41: =IFERROR(VLOOKUP(Q41,'Carga Remito.'!A$9:G$23287,6,0),"") | P41: =IFERROR(VLOOKUP(Q41,'Carga Remito.'!A$9:H$23287,7,0),"") | Q41: Control tren delantero. | R41: 0 | S41: 8000 | T41: 8000
A42: Stap Carlos | B42: 0 | E42: 5 | F42: 980000 | H42: 1615 | I42: 100000 | J42: 100000 | K42: 45310 | O42: =IFERROR(VLOOKUP(Q42,'Carga Remito.'!A$9:G$23287,6,0),"") -> KVB553 | P42: =IFERROR(VLOOKUP(Q42,'Carga Remito.'!A$9:H$23287,7,0),"") -> 0 | Q42: 1173 | R42: 0 | S42: 4500 | T42: 4500
A43: Stap Nahuel | B43: 0 | E43: 8 | F43: 5.8207661e-11 | H43: 1620 | I43: 65000 | J43: 65000 | K43: 45310 | O43: =IFERROR(VLOOKUP(Q43,'Carga Remito.'!A$9:G$23287,6,0),"") | P43: =IFERROR(VLOOKUP(Q43,'Carga Remito.'!A$9:H$23287,7,0),"") | Q43: SERVICE | R43: 0 | S43: 4500 | T43: 4500
A44: Verdus Silvio | B44: 0 | E44: 12 | F44: 7.2759576e-12 | H44: 1627 | I44: 50000 | J44: 50000 | K44: 45310 | O44: =IFERROR(VLOOKUP(Q44,'Carga Remito.'!A$9:G$23287,6,0),"") -> 903 | P44: =IFERROR(VLOOKUP(Q44,'Carga Remito.'!A$9:H$23287,7,0),"") -> kangoo roja | Q44: 1178 | R44: 0 | S44: 20000 | T44: 20000
A45: Weizek Susana | B45: 0 | E45: Gonzalez Gaston | F45: 7.2759576e-12 | H45: 1639 | I45: 8000 | J45: 8000 | O45: =IFERROR(VLOOKUP(Q45,'Carga Remito.'!A$9:G$23287,6,0),"") | P45: =IFERROR(VLOOKUP(Q45,'Carga Remito.'!A$9:H$23287,7,0),"") | Q45: Cambiar ambos bujes de parrilla inferior y bujes de punta barra estabilizadora. | R45: 0 | S45: 0 | T45: 0
A46: Wesek Pini | B46: 0 | E46: Total general | F46: 17090610 | H46: 1640 | I46: 30000 | J46: 30000 | K46: 45310 | O46: =IFERROR(VLOOKUP(Q46,'Carga Remito.'!A$9:G$23287,6,0),"") | P46: =IFERROR(VLOOKUP(Q46,'Carga Remito.'!A$9:H$23287,7,0),"") | Q46: Cambiar soporte caja velocidad inferior. | R46: 0 | S46: 0 | T46: 0
A47: Pujol Jorge | B47: 0 | H47: 1645 | I47: 8000 | J47: 8000 | O47: =IFERROR(VLOOKUP(Q47,'Carga Remito.'!A$9:G$23287,6,0),"") | P47: =IFERROR(VLOOKUP(Q47,'Carga Remito.'!A$9:H$23287,7,0),"") | Q47: Control tren delantero. | R47: 0 | S47: 0 | T47: 0
A48: Rasini Carolina | B48: 0 | H48: 1647 | I48: 65000 | J48: 65000 | K48: 45310 | Q48: Desarmar suspensión lado izquierdo. | R48: 0 | S48: 20000 | T48: 20000
A49: Carrara Sandra | B49: 0 | H49: 1649 | I49: 160906.25 | J49: 160906.25 | K49: 45310 | Q49: Total general | R49: 26400 | S49: 250000 | T49: 276400
A50: Cuevas Jorge | B50: 0 | H50: 1650 | I50: 35000 | J50: 35000 | K50: 45310
A51: Weizur | B51: 0 | H51: 1662 | I51: 40000 | J51: 40000 | K51: 45336
A52: Alvarez Guillermo | B52: 0 | H52: 1663 | I52: 32000 | J52: 32000 | K52: 45336
A53: Alemandi Vanina | B53: 0 | H53: 1666 | I53: 65000 | J53: 65000 | K53: 45301
A54: Penocello Vanesa | B54: 0 | H54: 1678 | I54: 15000 | J54: 15000 | K54: 45336
A55: Pereyra Miguel | B55: 0 | H55: 1686 | I55: 100000 | J55: 100000 | K55: 45336
A56: Flores Juanis | B56: 0 | H56: 1708 | I56: 65000 | J56: 65000 | K56: 45336
A57: Castro Martin | B57: 0 | H57: 1709 | I57: 65000 | J57: 65000 | K57: 45336
A58: Casas Juan Pablo | B58: 0 | H58: 1715 | I58: 65000 | J58: 65000 | K58: 45336
A59: Suarez Luchi | B59: 0 | H59: 1738 | I59: 75000 | J59: 75000
A60: Mendizabal Alicia | B60: 0 | H60: 1747 | I60: 25000 | J60: 25000
A61: Transporte Palloni | B61: 0 | H61: 1767 | I61: 188500 | J61: 188500
A62: Borzolino Celeste | B62: 0 | H62: 1771 | I62: 25000 | J62: 25000
A63: Creativiti S.A.S | B63: 0 | H63: 1772 | I63: 78000 | J63: 78000
A64: Di Genaro Julio | B64: 0 | H64: 1776 | I64: 180000 | J64: 180000
A65: Vilares Roberto | B65: 0 | H65: 1780 | I65: 9500 | J65: 9500 | K65: 45355
A66: Integral Agropecuaria | B66: 0 | H66: 1789 | I66: 9500 | J66: 9500 | K66: 45355
A67: Municipalidad Laboulaye | B67: 0 | H67: 1792 | I67: 35000 | J67: 35000
A68: Merlo Teresa | B68: 0 | H68: 1819 | I68: 194300 | J68: 194300
A69: Bertaina Jesica | B69: 0 | H69: 1828 | I69: 75000 | J69: 9500 | K69: 45364 | L69: 65500
A70: Goico Ana Paula | B70: 0 | H70: 1832 | I70: 9500 | J70: 9500
A71: Mainero Rodolfo | B71: 0 | H71: 1838 | I71: 9500 | J71: 9500 | K71: 45366
A72: Duran | B72: 0 | H72: 1840 | I72: 70000 | J72: 70000
A73: Gimenez Javier | B73: 0 | H73: 1853 | I73: 150000 | J73: 150000
A74: Guevara Mario | B74: 0 | H74: 1855 | I74: 50000 | J74: 50000
A75: Borello Matias | B75: 0 | H75: 1866 | I75: 82000 | J75: 82000
A76: Cane Emiliano | B76: 0 | H76: 1874 | I76: 36000 | J76: 36000
A77: Oyola Alberto | B77: 0 | H77: 1898 | I77: 40000 | J77: 40000
A78: Moretti Renato | B78: 0 | H78: 1903 | I78: 60000 | J78: 60000
A79: Calderon Daniel | B79: 0 | H79: 1908 | I79: 100000 | J79: 100000
A80: Manitto Rosana | B80: 0 | H80: 1914 | I80: 65000 | J80: 65000
A81: Marciali Veronica | B81: 0 | H81: 1919 | I81: 92000 | J81: 92000
A82: Mansuino Alberto | B82: 0 | H82: 1925 | I82: 0
A83: Ricci Arturo | B83: 0 | H83: 1937 | I83: 65000 | J83: 65000
A84: Sambruno Guillermo | B84: 0 | H84: 1939 | I84: 40000 | J84: 40000
A85: Gonzalez Gaston | B85: 7.2759576e-12 | H85: 1941 | I85: 181500 | J85: 181500 | K85: 45468
A86: Domanski | B86: 0 | H86: 1954 | I86: 205700 | J86: 205700 | K86: 45468
A87: Silveira Pililo | B87: 0 | H87: 1959 | I87: 121000 | J87: 121000 | K87: 45468
A88: Oca Log S.A | B88: 0 | H88: 1974 | I88: 360580 | J88: 360580 | K88: 45468
A89: Chirino Roberto | B89: 0 | H89: 1986 | I89: 56870 | J89: 56870 | K89: 45468
A90: Urieltin | B90: 0 | H90: 1991 | I90: 113740 | J90: 113740 | K90: 45468
A91: Flores Carlos | B91: 0 | H91: 2000 | I91: 56870 | J91: 56870 | K91: 45468
A92: Wiesek Pini | B92: 0 | H92: 2017 | I92: 62920
A93: Saladino Guillermo | B93: 0 | H93: 2020 | I93: 145200
A94: Dutto Mariano | B94: 0 | H94: 2021 | I94: 102850
A95: Valdenbraben Pepe | B95: 0 | H95: 2036 | I95: 96800
A96: Andrada Horacio | B96: 0 | H96: 2043 | I96: 102850
A97: Molinari Luis | B97: 0 | H97: 2049 | I97: 170600
A98: Angeleri Monica | B98: 0 | H98: 2050 | I98: 140600
A99: Fiore Martin | B99: 0 | H99: 2057 | I99: 0
A100: Mainero Ariel | B100: 0 | H100: 2065 | I100: 254100
...

Sheet Remito
C3: Cristian Bongiovanni | D3: REMITO
C4: 03385 - 462399 | D4: Nro: | E4: 2392
C5: Gral. Deheza 191- Lbye | D5: Fecha: | E5: =VLOOKUP(E4,'Carga Remito.'!A4:AC62992,3,0) -> 45628
B8: Nombre: | C8: =VLOOKUP(E4,'Carga Remito.'!A4:AC72292,4,0) -> Altamirano Alicia | D8: Km: | E8: =IF(VLOOKUP(E4,'Carga Remito.'!A4:J14957,8,0)=0,"",VLOOKUP(E4,'Carga Remito.'!A4:J14957,8,0)) -> 95398
B9: Vehículo: | C9: =VLOOKUP(E4,'Carga Remito.'!A4:AC72292,7,0) -> Peugeot Partner | D9: Dominio: | E9: =VLOOKUP(E4,'Carga Remito.'!A4:AD72282,6,0) -> AA737HE
B12: Trabajo | C12: =VLOOKUP(CONCATENATE($E$4,$C$8,COUNT(B22:B43)),'Carga Remito.'!$E$4:$AD$69221,6,0) -> Service completo. Cambio de aceite y filtros. Control general del vehiculo.
B13: realizado:
B19: Codigo Repuesto | C19: Repuesto | D19: Cantidad | E19: MO Acumulado | F19: Precio final unitario repuesto
B20: Producto/servicio | D20: Cant. | E20: Precio Unit. | F20: Importe
B21: 5 | C21: Mano de obra | D21: 1 | E21: =IFERROR(VLOOKUP(CONCATENATE(E4,C8,COUNT(B22:B43)),'Carga Remito.'!E4:AD69220,MATCH(E19,'Carga Remito.'!E3:AK3,0),0),"") -> 100000 | F21: =IFERROR(E21*D21,"") -> 100000
B22: =IFERROR(VLOOKUP(CONCATENATE($E$4,$C$8,1),'Carga Remito.'!$E$4:$AD$69221,MATCH($B$19,'Carga Remito.'!$E$3:$AK$3,0),0),"") -> 1 | C22: =IFERROR(VLOOKUP(CONCATENATE($E$4,$C$8,1),'Carga Remito.'!$E$4:$AD$69221,MATCH($C$19,'Carga Remito.'!$E$3:$AK$3,0),0),"") -> Kit de filtros | D22: =IFERROR(VLOOKUP(CONCATENATE($E$4,$C$8,1),'Carga Remito.'!$E$4:$AD$69221,MATCH($D$19,'Carga Remito.'!$E$3:$AK$3,0),0),"") -> 1 | E22: =IFERROR(VLOOKUP(CONCATENATE($E$4,$C$8,1),'Carga Remito.'!$E$4:$AD$69221,MATCH($F$19,'Carga Remito.'!$E$3:$AK$3,0),0),"") -> 83000 | F22: =IFERROR(E22*D22,"") -> 83000
B23: =IFERROR(VLOOKUP(CONCATENATE($E$4,$C$8,2),'Carga Remito.'!$E$4:$AD$69221,MATCH($B$19,'Carga Remito.'!$E$3:$AK$3,0),0),"") -> 1 | C23: =IFERROR(VLOOKUP(CONCATENATE($E$4,$C$8,2),'Carga Remito.'!$E$4:$AD$69221,MATCH($C$19,'Carga Remito.'!$E$3:$AK$3,0),0),"") -> Aceite motor 10w40 | D23: =IFERROR(VLOOKUP(CONCATENATE($E$4,$C$8,2),'Carga Remito.'!$E$4:$AD$69221,MATCH($D$19,'Carga Remito.'!$E$3:$AK$3,0),0),"") -> 4.5 | E23: =IFERROR(VLOOKUP(CONCATENATE($E$4,$C$8,2),'Carga Remito.'!$E$4:$AD$69221,MATCH($F$19,'Carga Remito.'!$E$3:$AK$3,0),0),"") -> 14700 | F23: =IFERROR(E23*D23,"") -> 66150
B24: =IFERROR(VLOOKUP(CONCATENATE($E$4,$C$8,3),'Carga Remito.'!$E$4:$AD$69221,MATCH($B$19,'Carga Remito.'!$E$3:$AK$3,0),0),"") | C24: =IFERROR(VLOOKUP(CONCATENATE($E$4,$C$8,3),'Carga Remito.'!$E$4:$AD$69221,MATCH($C$19,'Carga Remito.'!$E$3:$AK$3,0),0),"") | D24: =IFERROR(VLOOKUP(CONCATENATE($E$4,$C$8,3),'Carga Remito.'!$E$4:$AD$69221,MATCH($D$19,'Carga Remito.'!$E$3:$AK$3,0),0),"") | E24: =IFERROR(VLOOKUP(CONCATENATE($E$4,$C$8,3),'Carga Remito.'!$E$4:$AD$69221,MATCH($F$19,'Carga Remito.'!$E$3:$AK$3,0),0),"") | F24: =IFERROR(E24*D24,"")
B25: =IFERROR(VLOOKUP(CONCATENATE($E$4,$C$8,4),'Carga Remito.'!$E$4:$AD$69221,MATCH($B$19,'Carga Remito.'!$E$3:$AK$3,0),0),"") | C25: =IFERROR(VLOOKUP(CONCATENATE($E$4,$C$8,4),'Carga Remito.'!$E$4:$AD$69221,MATCH($C$19,'Carga Remito.'!$E$3:$AK$3,0),0),"") | D25: =IFERROR(VLOOKUP(CONCATENATE($E$4,$C$8,4),'Carga Remito.'!$E$4:$AD$69221,MATCH($D$19,'Carga Remito.'!$E$3:$AK$3,0),0),"") | E25: =IFERROR(VLOOKUP(CONCATENATE($E$4,$C$8,4),'Carga Remito.'!$E$4:$AD$69221,MATCH($F$19,'Carga Remito.'!$E$3:$AK$3,0),0),"") | F25: =IFERROR(E25*D25,"")
B26: =IFERROR(VLOOKUP(CONCATENATE($E$4,$C$8,5),'Carga Remito.'!$E$4:$AD$69221,MATCH($B$19,'Carga Remito.'!$E$3:$AK$3,0),0),"") | C26: =IFERROR(VLOOKUP(CONCATENATE($E$4,$C$8,5),'Carga Remito.'!$E$4:$AD$69221,MATCH($C$19,'Carga Remito.'!$E$3:$AK$3,0),0),"") | D26: =IFERROR(VLOOKUP(CONCATENATE($E$4,$C$8,5),'Carga Remito.'!$E$4:$AD$69221,MATCH($D$19,'Carga Remito.'!$E$3:$AK$3,0),0),"") | E26: =IFERROR(VLOOKUP(CONCATENATE($E$4,$C$8,5),'Carga Remito.'!$E$4:$AD$69221,MATCH($F$19,'Carga Remito.'!$E$3:$AK$3,0),0),"") | F26: =IFERROR(E26*D26,"")
B27: =IFERROR(VLOOKUP(CONCATENATE($E$4,$C$8,6),'Carga Remito.'!$E$4:$AD$69221,MATCH($B$19,'Carga Remito.'!$E$3:$AK$3,0),0),"") | C27: =IFERROR(VLOOKUP(CONCATENATE($E$4,$C$8,6),'Carga Remito.'!$E$4:$AD$69221,MATCH($C$19,'Carga Remito.'!$E$3:$AK$3,0),0),"") | D27: =IFERROR(VLOOKUP(CONCATENATE($E$4,$C$8,6),'Carga Remito.'!$E$4:$AD$69221,MATCH($D$19,'Carga Remito.'!$E$3:$AK$3,0),0),"") | E27: =IFERROR(VLOOKUP(CONCATENATE($E$4,$C$8,6),'Carga Remito.'!$E$4:$AD$69221,MATCH($F$19,'Carga Remito.'!$E$3:$AK$3,0),0),"") | F27: =IFERROR(E27*D27,"")
B28: =IFERROR(VLOOKUP(CONCATENATE($E$4,$C$8,7),'Carga Remito.'!$E$4:$AD$69221,MATCH($B$19,'Carga Remito.'!$E$3:$AK$3,0),0),"") | C28: =IFERROR(VLOOKUP(CONCATENATE($E$4,$C$8,7),'Carga Remito.'!$E$4:$AD$69221,MATCH($C$19,'Carga Remito.'!$E$3:$AK$3,0),0),"") | D28: =IFERROR(VLOOKUP(CONCATENATE($E$4,$C$8,7),'Carga Remito.'!$E$4:$AD$69221,MATCH($D$19,'Carga Remito.'!$E$3:$AK$3,0),0),"") | E28: =IFERROR(VLOOKUP(CONCATENATE($E$4,$C$8,7),'Carga Remito.'!$E$4:$AD$69221,MATCH($F$19,'Carga Remito.'!$E$3:$AK$3,0),0),"") | F28: =IFERROR(E28*D28,"")
B29: =IFERROR(VLOOKUP(CONCATENATE($E$4,$C$8,8),'Carga Remito.'!$E$4:$AD$69221,MATCH($B$19,'Carga Remito.'!$E$3:$AK$3,0),0),"") | C29: =IFERROR(VLOOKUP(CONCATENATE($E$4,$C$8,8),'Carga Remito.'!$E$4:$AD$69221,MATCH($C$19,'Carga Remito.'!$E$3:$AK$3,0),0),"") | D29: =IFERROR(VLOOKUP(CONCATENATE($E$4,$C$8,8),'Carga Remito.'!$E$4:$AD$69221,MATCH($D$19,'Carga Remito.'!$E$3:$AK$3,0),0),"") | E29: =IFERROR(VLOOKUP(CONCATENATE($E$4,$C$8,8),'Carga Remito.'!$E$4:$AD$69221,MATCH($F$19,'Carga Remito.'!$E$3:$AK$3,0),0),"") | F29: =IFERROR(E29*D29,"")
B30: =IFERROR(VLOOKUP(CONCATENATE($E$4,$C$8,9),'Carga Remito.'!$E$4:$AD$69221,MATCH($B$19,'Carga Remito.'!$E$3:$AK$3,0),0),"") | C30: =IFERROR(VLOOKUP(CONCATENATE($E$4,$C$8,9),'Carga Remito.'!$E$4:$AD$69221,MATCH($C$19,'Carga Remito.'!$E$3:$AK$3,0),0),"") | D30: =IFERROR(VLOOKUP(CONCATENATE($E$4,$C$8,9),'Carga Remito.'!$E$4:$AD$69221,MATCH($D$19,'Carga Remito.'!$E$3:$AK$3,0),0),"") | E30: =IFERROR(VLOOKUP(CONCATENATE($E$4,$C$8,9),'Carga Remito.'!$E$4:$AD$69221,MATCH($F$19,'Carga Remito.'!$E$3:$AK$3,0),0),"") | F30: =IFERROR(E30*D30,"")
B31: =IFERROR(VLOOKUP(CONCATENATE($E$4,$C$8,10),'Carga Remito.'!$E$4:$AD$69221,MATCH($B$19,'Carga Remito.'!$E$3:$AK$3,0),0),"") | C31: =IFERROR(VLOOKUP(CONCATENATE($E$4,$C$8,10),'Carga Remito.'!$E$4:$AD$69221,MATCH($C$19,'Carga Remito.'!$E$3:$AK$3,0),0),"") | D31: =IFERROR(VLOOKUP(CONCATENATE($E$4,$C$8,10),'Carga Remito.'!$E$4:$AD$69221,MATCH($D$19,'Carga Remito.'!$E$3:$AK$3,0),0),"") | E31: =IFERROR(VLOOKUP(CONCATENATE($E$4,$C$8,10),'Carga Remito.'!$E$4:$AD$69221,MATCH($F$19,'Carga Remito.'!$E$3:$AK$3,0),0),"") | F31: =IFERROR(E31*D31,"")
B32: =IFERROR(VLOOKUP(CONCATENATE($E$4,$C$8,11),'Carga Remito.'!$E$4:$AD$69221,MATCH($B$19,'Carga Remito.'!$E$3:$AK$3,0),0),"") | C32: =IFERROR(VLOOKUP(CONCATENATE($E$4,$C$8,11),'Carga Remito.'!$E$4:$AD$69221,MATCH($C$19,'Carga Remito.'!$E$3:$AK$3,0),0),"") | D32: =IFERROR(VLOOKUP(CONCATENATE($E$4,$C$8,11),'Carga Remito.'!$E$4:$AD$69221,MATCH($D$19,'Carga Remito.'!$E$3:$AK$3,0),0),"") | E32: =IFERROR(VLOOKUP(CONCATENATE($E$4,$C$8,11),'Carga Remito.'!$E$4:$AD$69221,MATCH($F$19,'Carga Remito.'!$E$3:$AK$3,0),0),"") | F32: =IFERROR(E32*D32,"")
B33: =IFERROR(VLOOKUP(CONCATENATE($E$4,$C$8,12),'Carga Remito.'!$E$4:$AD$69221,MATCH($B$19,'Carga Remito.'!$E$3:$AK$3,0),0),"") | C33: =IFERROR(VLOOKUP(CONCATENATE($E$4,$C$8,12),'Carga Remito.'!$E$4:$AD$69221,MATCH($C$19,'Carga Remito.'!$E$3:$AK$3,0),0),"") | D33: =IFERROR(VLOOKUP(CONCATENATE($E$4,$C$8,12),'Carga Remito.'!$E$4:$AD$69221,MATCH($D$19,'Carga Remito.'!$E$3:$AK$3,0),0),"") | E33: =IFERROR(VLOOKUP(CONCATENATE($E$4,$C$8,12),'Carga Remito.'!$E$4:$AD$69221,MATCH($F$19,'Carga Remito.'!$E$3:$AK$3,0),0),"") | F33: =IFERROR(E33*D33,"")
B34: =IFERROR(VLOOKUP(CONCATENATE($E$4,$C$8,13),'Carga Remito.'!$E$4:$AD$69221,MATCH($B$19,'Carga Remito.'!$E$3:$AK$3,0),0),"") | C34: =IFERROR(VLOOKUP(CONCATENATE($E$4,$C$8,13),'Carga Remito.'!$E$4:$AD$69221,MATCH($C$19,'Carga Remito.'!$E$3:$AK$3,0),0),"") | D34: =IFERROR(VLOOKUP(CONCATENATE($E$4,$C$8,13),'Carga Remito.'!$E$4:$AD$69221,MATCH($D$19,'Carga Remito.'!$E$3:$AK$3,0),0),"") | E34: =IFERROR(VLOOKUP(CONCATENATE($E$4,$C$8,13),'Carga Remito.'!$E$4:$AD$69221,MATCH($F$19,'Carga Remito.'!$E$3:$AK$3,0),0),"") | F34: =IFERROR(E34*D34,"")
B35: =IFERROR(VLOOKUP(CONCATENATE($E$4,$C$8,14),'Carga Remito.'!$E$4:$AD$69221,MATCH($B$19,'Carga Remito.'!$E$3:$AK$3,0),0),"") | C35: =IFERROR(VLOOKUP(CONCATENATE($E$4,$C$8,14),'Carga Remito.'!$E$4:$AD$69221,MATCH($C$19,'Carga Remito.'!$E$3:$AK$3,0),0),"") | D35: =IFERROR(VLOOKUP(CONCATENATE($E$4,$C$8,14),'Carga Remito.'!$E$4:$AD$69221,MATCH($D$19,'Carga Remito.'!$E$3:$AK$3,0),0),"") | E35: =IFERROR(VLOOKUP(CONCATENATE($E$4,$C$8,14),'Carga Remito.'!$E$4:$AD$69221,MATCH($F$19,'Carga Remito.'!$E$3:$AK$3,0),0),"") | F35: =IFERROR(E35*D35,"")
B36: =IFERROR(VLOOKUP(CONCATENATE($E$4,$C$8,15),'Carga Remito.'!$E$4:$AD$69221,MATCH($B$19,'Carga Remito.'!$E$3:$AK$3,0),0),"") | C36: =IFERROR(VLOOKUP(CONCATENATE($E$4,$C$8,15),'Carga Remito.'!$E$4:$AD$69221,MATCH($C$19,'Carga Remito.'!$E$3:$AK$3,0),0),"") | D36: =IFERROR(VLOOKUP(CONCATENATE($E$4,$C$8,15),'Carga Remito.'!$E$4:$AD$69221,MATCH($D$19,'Carga Remito.'!$E$3:$AK$3,0),0),"") | E36: =IFERROR(VLOOKUP(CONCATENATE($E$4,$C$8,15),'Carga Remito.'!$E$4:$AD$69221,MATCH($F$19,'Carga Remito.'!$E$3:$AK$3,0),0),"") | F36: =IFERROR(E36*D36,"")
B37: =IFERROR(VLOOKUP(CONCATENATE($E$4,$C$8,16),'Carga Remito.'!$E$4:$AD$69221,MATCH($B$19,'Carga Remito.'!$E$3:$AK$3,0),0),"") | C37: =IFERROR(VLOOKUP(CONCATENATE($E$4,$C$8,16),'Carga Remito.'!$E$4:$AD$69221,MATCH($C$19,'Carga Remito.'!$E$3:$AK$3,0),0),"") | D37: =IFERROR(VLOOKUP(CONCATENATE($E$4,$C$8,16),'Carga Remito.'!$E$4:$AD$69221,MATCH($D$19,'Carga Remito.'!$E$3:$AK$3,0),0),"") | E37: =IFERROR(VLOOKUP(CONCATENATE($E$4,$C$8,16),'Carga Remito.'!$E$4:$AD$69221,MATCH($F$19,'Carga Remito.'!$E$3:$AK$3,0),0),"") | F37: =IFERROR(E37*D37,"")
B38: =IFERROR(VLOOKUP(CONCATENATE($E$4,$C$8,17),'Carga Remito.'!$E$4:$AD$69221,MATCH($B$19,'Carga Remito.'!$E$3:$AK$3,0),0),"") | C38: =IFERROR(VLOOKUP(CONCATENATE($E$4,$C$8,17),'Carga Remito.'!$E$4:$AD$69221,MATCH($C$19,'Carga Remito.'!$E$3:$AK$3,0),0),"") | D38: =IFERROR(VLOOKUP(CONCATENATE($E$4,$C$8,17),'Carga Remito.'!$E$4:$AD$69221,MATCH($D$19,'Carga Remito.'!$E$3:$AK$3,0),0),"") | E38: =IFERROR(VLOOKUP(CONCATENATE($E$4,$C$8,17),'Carga Remito.'!$E$4:$AD$69221,MATCH($F$19,'Carga Remito.'!$E$3:$AK$3,0),0),"") | F38: =IFERROR(E38*D38,"")
B39: =IFERROR(VLOOKUP(CONCATENATE($E$4,$C$8,18),'Carga Remito.'!$E$4:$AD$69221,MATCH($B$19,'Carga Remito.'!$E$3:$AK$3,0),0),"") | C39: =IFERROR(VLOOKUP(CONCATENATE($E$4,$C$8,18),'Carga Remito.'!$E$4:$AD$69221,MATCH($C$19,'Carga Remito.'!$E$3:$AK$3,0),0),"") | D39: =IFERROR(VLOOKUP(CONCATENATE($E$4,$C$8,18),'Carga Remito.'!$E$4:$AD$69221,MATCH($D$19,'Carga Remito.'!$E$3:$AK$3,0),0),"") | E39: =IFERROR(VLOOKUP(CONCATENATE($E$4,$C$8,18),'Carga Remito.'!$E$4:$AD$69221,MATCH($F$19,'Carga Remito.'!$E$3:$AK$3,0),0),"") | F39: =IFERROR(E39*D39,"")
B40: =IFERROR(VLOOKUP(CONCATENATE($E$4,$C$8,19),'Carga Remito.'!$E$4:$AD$69221,MATCH($B$19,'Carga Remito.'!$E$3:$AK$3,0),0),"") | C40: =IFERROR(VLOOKUP(CONCATENATE($E$4,$C$8,19),'Carga Remito.'!$E$4:$AD$69221,MATCH($C$19,'Carga Remito.'!$E$3:$AK$3,0),0),"") | D40: =IFERROR(VLOOKUP(CONCATENATE($E$4,$C$8,19),'Carga Remito.'!$E$4:$AD$69221,MATCH($D$19,'Carga Remito.'!$E$3:$AK$3,0),0),"") | E40: =IFERROR(VLOOKUP(CONCATENATE($E$4,$C$8,19),'Carga Remito.'!$E$4:$AD$69221,MATCH($F$19,'Carga Remito.'!$E$3:$AK$3,0),0),"") | F40: =IFERROR(E40*D40,"")
B41: =IFERROR(VLOOKUP(CONCATENATE($E$4,$C$8,20),'Carga Remito.'!$E$4:$AD$69221,MATCH($B$19,'Carga Remito.'!$E$3:$AK$3,0),0),"") | C41: =IFERROR(VLOOKUP(CONCATENATE($E$4,$C$8,20),'Carga Remito.'!$E$4:$AD$69221,MATCH($C$19,'Carga Remito.'!$E$3:$AK$3,0),0),"") | D41: =IFERROR(VLOOKUP(CONCATENATE($E$4,$C$8,20),'Carga Remito.'!$E$4:$AD$69221,MATCH($D$19,'Carga Remito.'!$E$3:$AK$3,0),0),"") | E41: =IFERROR(VLOOKUP(CONCATENATE($E$4,$C$8,20),'Carga Remito.'!$E$4:$AD$69221,MATCH($F$19,'Carga Remito.'!$E$3:$AK$3,0),0),"") | F41: =IFERROR(E41*D41,"")
B42: =IFERROR(VLOOKUP(CONCATENATE($E$4,$C$8,21),'Carga Remito.'!$E$4:$AD$69221,MATCH($B$19,'Carga Remito.'!$E$3:$AK$3,0),0),"") | C42: =IFERROR(VLOOKUP(CONCATENATE($E$4,$C$8,21),'Carga Remito.'!E24:AD69241,MATCH($C$19,'Carga Remito.'!$E$3:$AK$3,0),0),"") | D42: =IFERROR(VLOOKUP(CONCATENATE($E$4,$C$8,21),'Carga Remito.'!$E$4:$AD$69221,MATCH($D$19,'Carga Remito.'!$E$3:$AK$3,0),0),"") | E42: =IFERROR(VLOOKUP(CONCATENATE($E$4,$C$8,21),'Carga Remito.'!$E$4:$AD$69221,MATCH($F$19,'Carga Remito.'!$E$3:$AK$3,0),0),"") | F42: =IFERROR(E42*D42,"")
B44: Cuenta bancaria: LA NUEVA BOUTIQUE SAS (Bco Macro)
B45: - Alias: AVES.JOVIAL.PRIMO | F45: TOTAL
B46: Pago dentro de los 15 días. | F46: =SUM(F21:F43) -> 249150
B47: De lo contrario, obtendrá recargo según índice IPC.
E48: Gracias por elegirnos!
Q711: 180000
Q713: 20000
A1276: 1499

Sheet % recargo
A1: COSTOS
A2: REPUESTO
B3: promedio 15/7 | C3: 0.2 | D3: 0.12 | E3: 0.127 | F3: 0.2 | I3: 0.182
B4: 45108 | C4: 45139 | D4: 45170 | E4: 45200 | F4: 45231 | G4: 45261 | H4: 45292 | I4: 45323 | J4: 45352 | K4: 45383
A5: filtro de aceite - promedio | B5: 1500 | C5: =+B5*(1+C$3) -> 1800 | D5: =+C5*(1+D$3) -> 2016 | E5: =D5*(1+E$3) -> 2272.032 | F5: =E5*(1+F$3) -> 2726.4384 | G5: 5501.08 | H5: 6876.35 | I5: 8127.44 | J5: 5540 | K5: 5588
A6: filtro de aceite - max | B6: 4500 | C6: =+B6*(1+C$3) -> 5400 | D6: =+C6*(1+D$3) -> 6048 | E6: =D6*(1+E$3) -> 6816.096 | F6: =E6*(1+F$3) -> 8179.3152
A7: filtro de combustible - promedio | B7: 2000 | C7: =+B7*(1+C$3) -> 2400 | D7: =+C7*(1+D$3) -> 2688 | E7: =D7*(1+E$3) -> 3029.376 | F7: =E7*(1+F$3) -> 3635.2512 | G7: 7616.58 | H7: 9520.73 | I7: 11253.51 | J7: 9628 | K7: 9639
A8: filtro de combustible - max | B8: 6000 | C8: =+B8*(1+C$3) -> 7200 | D8: =+C8*(1+D$3) -> 8064 | E8: =D8*(1+E$3) -> 9088.128 | F8: =E8*(1+F$3) -> 10905.754
A9: filtro de aire motor - promedio | B9: 2000 | C9: =+B9*(1+C$3) -> 2400 | D9: =+C9*(1+D$3) -> 2688 | E9: =D9*(1+E$3) -> 3029.376 | F9: =E9*(1+F$3) -> 3635.2512 | G9: 6279.24 | H9: 7849.05 | I9: 8492.68 | J9: 7830 | K9: 7826
A10: filtro de aire motor - max | B10: 3500 | C10: =+B10*(1+C$3) -> 4200 | D10: =+C10*(1+D$3) -> 4704 | E10: =D10*(1+E$3) -> 5301.408 | F10: =E10*(1+F$3) -> 6361.6896
A11: filtro de polen - promedio | D11: 2427 | E11: =D11*(1+E$3) -> 2735.229 | F11: =E11*(1+F$3) -> 3282.2748 | G11: 4575.39 | H11: 5719.24 | I11: 6760.15 | J11: 5676 | K11: 5320
A12: filtro polen - max | D12: 17000 | E12: =D12*(1+E$3) -> 19159 | F12: =E12*(1+F$3) -> 22990.8
A13: kit promedio | B13: =+B5+B7+B9+B11 -> 5500 | C13: =+C5+C7+C9+C11 -> 6600 | D13: =+D5+D7+D9+D11 -> 9819 | E13: =D13*(1+E$3) -> 11066.013 | F13: =E13*(1+F$3) -> 13279.216
A14: kit max | B14: =+B6+B8+B10 -> 14000 | C14: =+B14*(1+C$3) -> 16800 | D14: =+C14*(1+D$3) -> 18816 | E14: =D14*(1+E$3) -> 21205.632 | F14: =E14*(1+F$3) -> 25446.758
B15: 45108 | C15: 45139 | D15: 45170 | E15: 45200 | F15: 45261 | G15: 45261 | H15: 45292 | I15: 45323 | J15: 45352 | K15: 45383 | L15: 45413 | M15: 45444 | N15: 45474 | O15: 45505 | P15: 45536
C16: Cálculo por IPC | D16: Real | E16: Real (27/11) | F16: Real (06/12) | G16: 10% (30/12) | H16: Real 03/01 | I16: Real | J16: Real | K16: Real | L16: Real | M16: Real | N16: Real | O16: Real | P16: Real
A17: ACEITE 5W30 | B17: 2112.3876 | C17: =441489/209*1.12 -> 2365.8741 | D17: =580900/209 -> 2779.4258 | E17: 3733.9522 | F17: 3959.44 | G17: ='[2]% recargo'!F17*1.1 -> 4355.384 | H17: 7292.46 | I17: 7614.26 | J17: 5741.63 | K17: 5741.63 | L17: 6401.92 | M17: 6914.08 | N17: 7100 | O17: 6430.63 | P17: 5741.63
A18: ACEITE 10W40 | B18: 1214.8325 | C18: =253900/209*1.12 -> 1360.6124 | D18: =319200/209 -> 1527.2727 | E18: 2145.8488 | F18: 2487.01 | G18: ='[2]% recargo'!F18*1.1 -> 2735.711 | H18: 4670.62 | I18: 4437.54 | J18: 3540.67 | K18: 3540.67 | L18: 4190 | M18: 4525 | N18: 4525 | O18: 3516.75 | P18: 3511.97
A19: ACEITE 15W40 | B19: 900.65072 | C19: =188236/209*1.12 -> 1008.7288 | D19: =275000/209 -> 1315.7895 | E19: 1600.934 | F19: 1921.12 | H19: 6517.2 | I19: 3926.56 | J19: 2955.88 | K19: 2955.88 | L19: 3420 | M19: 3693.6 | N19: 3740 | O19: 3244.02 | P19: 3231
A20: ACEITE 5W40 | B20: 3489 | C20: =C17 -> 2365.8741 | D20: =580900/209 -> 2779.4258 | E20: 3733.9522 | F20: 3959.44 | G20: ='[2]% recargo'!F20*1.1 -> 4355.384 | H20: 7292.46 | I20: 7614.26 | J20: 5741.63 | K20: 5741.63 | L20: 6401.63 | M20: 6914.08 | N20: 7100 | O20: 6947.37 | P20: 5588.52
A21: ACEITE 80W90 | D21: =355890/209 -> 1702.823 | E21: 1924.19 | F21: 2309.03 | G21: 3117.15 | H21: 5953.21 | I21: 4585.9 | J21: 5232.35 | K21: 5232.35 | L21: 5913 | M21: 6386.04 | N21: 6540 | O21: 6300 | P21: 6358.6
A22: LIQ. REFRIGERANTE | B22: 1394.2308 | C22: =+B22*1.2 -> 1673.0769 | D22: =+C22*(1+D$3) -> 1873.8462 | E22: 3733.9522 | F22: 4480.74 | G22: 5376 | H22: 6450.2 | I22: 7624.14 | J22: 7558 | K22: 7558 | L22: 8200 | M22: 8856 | N22: 9210 | O22: 9210 | P22: 9188.2
A23: AGUA DESTILADA | B23: 400 | C23: =+B23*1.2 -> 480 | D23: =+C23*(1+D$3) -> 537.6 | E23: 580 | F23: 600 | G23: 621 | H23: 621 | I23: 670 | J23: 670 | K23: 340 | L23: 380 | M23: 380 | N23: 395 | O23: 400 | P23: 380
A24: ACEITE 0W20 | J24: 5153.67 | K24: 5153.67 | L24: 6200.96 | M24: 6697.04 | N24: 7000 | O24: 6965 | P24: 6965
A25: ACEITE 5W30 CASTROL EDGE | L25: 14775 | M25: 15957 | N25: 16596 | O25: 16620
A26: DEXO 2 | M26: 14707 | N26: 15295 | O26: 15295 | P26: 14987.27
B27: 45200 | C27: 45231 | D27: 45261 | E27: 45292 | F27: 45323 | G27: 45352 | H27: 45383 | I27: 45413 | J27: 45444 | K27: 45474 | L27: 45505 | M27: 45536
B28: Real | C28: Real | D28: Real | E28: Real | F28: Real | G28: Real | H28: Real | I28: Real | J28: Real | K28: Real | L28: Real | M28: Real
A29: ACEITE 5W30 | B29: 6700 | C29: 8750 | D29: 13125 | E29: 15750 | F29: 15750 | G29: 16550 | H29: 16550 | I29: 16550 | J29: 16550 | K29: 17870 | L29: 18000 | M29: 18000
A30: ACEITE 10W40 | B30: 3700 | C30: 5950 | D30: 8925 | E30: 10710 | F30: 10710 | G30: 11250 | H30: 11250 | I30: 11250 | J30: 11250 | K30: 12200 | L30: 12500 | M30: 12500
A31: ACEITE 15W40 | B31: 3200 | C31: 4950 | D31: 7425 | E31: 8910 | F31: 8910 | G31: 9350 | H31: 9350 | I31: 9350 | J31: 9350 | K31: 10100 | L31: 11000 | M31: 11000
A32: ACEITE 5W40 | B32: 6950 | C32: 8750 | D32: 13125 | E32: 15750 | F32: 15750 | G32: 16550 | H32: 16550 | I32: 16550 | J32: 16550 | K32: 17870 | L32: 18000 | M32: 18000
A33: ACEITE 80W90 | B33: 3800 | C33: 6200 | D33: 9300 | E33: 11160 | F33: 11160 | G33: 15000 | H33: 15000 | I33: 15000 | J33: 15000 | K33: 16200 | L33: 17000 | M33: 17000
A34: LIQ. REFRIGERANTE | B34: 4800 | C34: 4800 | D34: 7200 | E34: 8640 | F34: 8640 | G34: 11500 | H34: 11500 | I34: 11500 | J34: 11500 | K34: 13500 | L34: 14000 | M34: 14000
A35: AGUA DESTILADA | B35: 1200 | C35: 1400 | D35: 2100 | E35: 2520 | F35: 2520 | G35: 4000 | H35: 4000 | I35: 4000 | J35: 4500 | K35: 4900 | L35: 5000 | M35: 5000
A36: ACEITE DIRECCION HIDRAULICA | B36: 3800 | C36: 6800 | D36: 10200 | E36: 12240 | F36: 12240 | G36: 15000 | H36: 15000 | I36: 15000 | J36: 15000 | K36: 16200 | L36: 17000 | M36: 17000
A37: ACEITE 5W30 CASTROL EDGE | B37: 9225 | C37: 13500 | D37: 20250 | E37: 24300 | F37: 24300 | G37: 24925 | H37: 20750 | I37: 20750 | J37: 20750 | K37: 22400 | L37: 22800 | M37: 22800
A38: ACEITE 0W20 | B38: 8450 | C38: 12250 | D38: 18375 | E38: 22050 | F38: 22050 | G38: 22750 | H38: 20000 | I38: 20000 | J38: 20000 | K38: 21600 | L38: 22000 | M38: 22000 | N38: 22500
A39: ACEITE 5W30 CASTROL DEXO 2 | B39: 8450 | C39: 11750 | D39: 17625 | E39: 21150 | F39: 21150 | G39: 22200 | H39: 19500 | I39: 19500 | J39: 19500 | K39: 21000 | L39: 22000 | M39: 22000
A40: ACEITE 75W80 | B40: 3450 | C40: 20000 | D40: 30000 | E40: 30000 | F40: 33000 | G40: 36000 | H40: 36000 | I40: 36000 | J40: 36000 | K40: 38800 | L40: 40000 | M40: 40000

Sheet Recibo
D3: De Cristian Bongiovanni | E3: RECIBO
D4: 03385 - 428467 | E4: Nro: | F4: 1
D5: Gral. Deheza 191- Lbye | E5: Fecha: | F5: 45624
B8: Nombre:
B9: Medio de pago: | D9: cpd
B14: PAGO: | D14: 157105
E17: SALDO DEUDOR
E18: 327895
B25: Gracias por elegirnos!

Sheet Análisis
A1: CÓDIGO | B1: CATEGORÍA
A2: Costo de filtros usé un promedio de todos los filtros
A3: El aumento fue por inflación
A4: Aceite en agosto aumenté por inflación y en septiembre pedí precios
A5: Estos precios están en % de recargo
A7: Agregué responsable para que comiencen a poner a partir de ahora
A8: Agregué tipo de trabajo en la primer fila de cada remito. (está en una columna desordenada porque si agrego me cambia el remito que sale automático
A9: En la hoja base cliente está el porcentaje de descuento que le hace cada casa de repuestos
A11: En algun lado mostraría todos los que dice taller y como no tenia el costo cristian me dijo que loe ponga l 20%. Muchos los compra en ML pero no nos anotan eso
A13: Controlar si esta bien 1 bidon de agua destilada + 1 l de liquido refri
A15: Controlar que lo que dice motor sea motor

Sheet Base Cliente
A1: CLIENTES | E1: PROVEEDORES
A2: Razón social | B2: CUIT | C2: Contacto | E2: Proveedores | F2: CUIT | G2: Contacto | H2: Producto | I2: Descuento
A3: Abbiatti | E3: Taller
A4: Accoto Carlos | E4: Barotto | F4: 20-25930182-4 | G4: 3385465075 | I4: 0.2
A5: Accotto Ariel | E5: Ferrando | G5: 3385521398 | I5: 0.2
A6: Acotto Jorge | E6: Rep Serrano | G6: 3385466887 | I6: 0.21
A7: Acuña Silvana | E7: Atilio Lucero | H7: Batería precio neto. | I7: 0.1
A8: AGD | B8: 30-50287435-3 | E8: Rc distribuciones | G8: 3584827949 | H8: Repuestos de distribución
A9: Aguilera Gustavo | E9: Bata rio 4 | H9: Shel-aceites | I9: 1.5
A10: Aimar Alberto | E10: Mercado Libre | I10: 0
A11: Aimar Julia | C11: 3385680000 | E11: Vetaro | F11: 30-56785933-5 | G11: 3534533698 | H11: Refrigerante, aceite | I11: 0.5
A12: Aimar Pablo | E12: Stabio | F12: 30-54011227-0 | G12: 3515297952 | H12: Rectificadora | I12: 0.1
A13: Airasca Gustavo | C13: 3385685474 | E13: Accotto Aldo | G13: 3385426517 | H13: Electricidad | I13: 0
A14: Airasca Victoria | E14: Color Plus | F14: 20-13498469-5 | G14: 3385425011 | H14: Insumos | I14: 0
A15: Alamo Susana | E15: Magliano Metal | F15: 27-14538668-9 | G15: 338528368 | H15: Insumos | I15: 0
A16: Alarcon Daniela | E16: Marglas S.A | F16: 30-62689508-1 | G16: 3385425585 | H16: Insumos | I16: 0
A17: Albarracin Ernesto | E17: Refiat | G17: 3584626133
A18: Albarracin German | E18: Rep Center | F18: 30-70831279-3 | G18: 3514516570
A19: Albarracin Mary | E19: Propio cliente | I19: 0
A20: Ale Gomez MEDIC | E20: Propio cliente | I20: 0
A21: Alemandi Vanina | E21: Rio Rep
A22: Alicia Altamirano | E22: Aldo Rep | I22: 0.2
A23: Allamandi Gustavo | E23: Hurtado | H23: Insumos | I23: 0
A24: Alonso Patricia | C24: 3385590040 | E24: TDI | H24: Repuestos | I24: 0.16
A25: Alonso Roberto | E25: Sergio Coria | H25: Reparación | I25: 0.1
A26: Alonso Roberto | E26: Weisek | H26: Soldadura | I26: 0.1
A27: Altamirano Alicia
A28: Alvarez Guillermo
A29: Alvarez Lautaro
A30: Alvarez Walter
A31: Ameri Roberta
A32: Ana Paula Fossano
A33: Anastasi Dario | C33: 3385592826
A34: Anchabal Juan | C34: 3385441956
A35: Anconetani Karina | C35: 3385404853
A36: Anconetani Teresa
A37: Andrada Horacio | C37: 3385437232
A38: Andres Antonella
A39: Anes Jorge | C39: 3385594450
A40: Angeleri Monica
A41: Aranda Pablo
A42: Arce Monica | C42: 3385042794
A43: Arguello Emanuel
A44: Armendari Martina
A45: Arregui Roberto
A46: Astesana
A47: Astezana Mirta
A48: Avila Edgardo
A49: Avila Leonardo
A50: Avila Micaela
A51: Ayraudo Alejandro
A52: Balario Paula
A53: Balestrelli Horacio
A54: Ballestrelli Horacio
... A78: Berdus Silvia
A79: Beriani Nazarena | C79: 3385436854
A80: Bernard Cristian
A81: Bertaina Damian
A82: Bertaina Jesica
A83: Bertania Mario
A84: Bertino Geno
A85: Bilinski
A86: Bilinski Miguel
A87: Biotti Claudia
A88: Birche Ariel | C88: 3385598619
A89: Blanco Carina
A90: Blanco Diego
A91: Blanco Maria Elena
A92: Blanco Paola
A93: Blanco Silvia
A94: Boiero
A95: Bolaños Alvaro
A96: Bomberos Voluntarios
A97: Bonava Eva
A98: Bonetto Diego
A99: Bonetto Gustavo
A100: Bongiorni Laura
... A105: Borzolino Celeste
A106: Boschiazo Antonella | C106: 3385508896
A107: Botasso Arley
A108: Boudoux Emanuel | C108: 3385504660
A109: Britos Silvia
A110: Brusco Paola
A111: Bueno Maria Elena
A112: Burgos Luis
A113: Bustos Churi
A114: Bustos Lolo | C114: 3385407074
A115: Caballero Jorge
A116: Cabral Guillermo | C116: 3385405601
A117: Cabral Guillermo
A118: Cabral Horacio
A119: Cabrero Marta
A120: Calderon (pini)
A121: Calderon Daniel
A122: Calleri Vanesa
A123: Canale Alejandra
A124: Canave Daniel
A125: Cane Emiliano
A126: Cane Mauricio
A127: Canepa Carlos
...
